Workbook

Sheet Eval Dataset
A1: query_id | B1: language | C1: region | D1: city_country | E1: scenario | F1: user_query | G1: constraints | H1: must_have | I1: must_not_have
A2: 1 | B2: en | C2: Europe | D2: Prague, Czechia | E2: Простой поиск мест | F2: Find cozy coffee shops in Prague Old Town. | G2: category: coffee shops; area: Old Town; atmosphere: cozy | H2: 2–5 реальных мест нужной категории; правильный город/район; краткое объяснение релевантности; соблюдение указанных предпочтений. | I2: Несуществующие места; другая категория; места вне указанной локации; неподтвержденные конкретные факты.
A3: 2 | B3: en | C3: Europe | D3: Berlin, Germany | E3: Простой поиск мест | F3: Recommend contemporary art museums in Berlin. | G3: category: contemporary art museums | H3: 2–5 реальных мест нужной категории; правильный город/район; краткое объяснение релевантности; соблюдение указанных предпочтений. | I3: Несуществующие места; другая категория; места вне указанной локации; неподтвержденные конкретные факты.
A4: 3 | B4: en | C4: Europe | D4: Lisbon, Portugal | E4: Простой поиск мест | F4: Find the best viewpoints in Lisbon for sunset. | G4: category: viewpoints; time: sunset | H4: 2–5 реальных мест нужной категории; правильный город/район; краткое объяснение релевантности; соблюдение указанных предпочтений. | I4: Несуществующие места; другая категория; места вне указанной локации; неподтвержденные конкретные факты.
A5: 4 | B5: en | C5: Europe | D5: Rome, Italy | E5: Простой поиск мест | F5: Suggest traditional trattorias in Trastevere. | G5: category: traditional trattorias; area: Trastevere | H5: 2–5 реальных мест нужной категории; правильный город/район; краткое объяснение релевантности; соблюдение указанных предпочтений. | I5: Несуществующие места; другая категория; места вне указанной локации; неподтвержденные конкретные факты.
A6: 5 | B6: en | C6: Europe | D6: Amsterdam, Netherlands | E6: Простой поиск мест | F6: Find quiet parks in Amsterdam for a relaxed afternoon. | G6: category: parks; atmosphere: quiet; time: afternoon | H6: 2–5 реальных мест нужной категории; правильный город/район; краткое объяснение релевантности; соблюдение указанных предпочтений. | I6: Несуществующие места; другая категория; места вне указанной локации; неподтвержденные конкретные факты.
A7: 6 | B7: en | C7: Europe | D7: Athens, Greece | E7: Простой поиск мест | F7: Recommend archaeological sites in central Athens. | G7: category: archaeological sites; area: city centre | H7: 2–5 реальных мест нужной категории; правильный город/район; краткое объяснение релевантности; соблюдение указанных предпочтений. | I7: Несуществующие места; другая категория; места вне указанной локации; неподтвержденные конкретные факты.
A8: 7 | B8: en | C8: Europe | D8: Copenhagen, Denmark | E8: Простой поиск мест | F8: Find independent Danish design shops in Copenhagen. | G8: category: design shops; independent/local | H8: 2–5 реальных мест нужной категории; правильный город/район; краткое объяснение релевантности; соблюдение указанных предпочтений. | I8: Несуществующие места; другая категория; места вне указанной локации; неподтвержденные конкретные факты.
A9: 8 | B9: ru | C9: Europe | D9: London, United Kingdom | E9: Простой поиск мест | F9: Порекомендуй бесплатные музеи в центре Лондона. | G9: категория: музеи; цена: бесплатно; район: центр | H9: 2–5 реальных мест нужной категории; правильный город/район; краткое объяснение релевантности; соблюдение указанных предпочтений. | I9: Несуществующие места; другая категория; места вне указанной локации; неподтвержденные конкретные факты.
A10: 9 | B10: ru | C10: Europe | D10: Barcelona, Spain | E10: Простой поиск мест | F10: Найди хорошие веганские кафе в Барселоне. | G10: категория: веганские кафе | H10: 2–5 реальных мест нужной категории; правильный город/район; краткое объяснение релевантности; соблюдение указанных предпочтений. | I10: Несуществующие места; другая категория; места вне указанной локации; неподтвержденные конкретные факты.
A11: 10 | B11: en | C11: CIS | D11: Almaty, Kazakhstan | E11: Простой поиск мест | F11: Find family-friendly parks in Almaty. | G11: category: parks; family-friendly | H11: 2–5 реальных мест нужной категории; правильный город/район; краткое объяснение релевантности; соблюдение указанных предпочтений. | I11: Несуществующие места; другая категория; места вне указанной локации; неподтвержденные конкретные факты.
A12: 11 | B12: en | C12: CIS | D12: Tbilisi, Georgia | E12: Простой поиск мест | F12: Suggest local bakeries in central Tbilisi. | G12: category: local bakeries; area: centre | H12: 2–5 реальных мест нужной категории; правильный город/район; краткое объяснение релевантности; соблюдение указанных предпочтений. | I12: Несуществующие места; другая категория; места вне указанной локации; неподтвержденные конкретные факты.
A13: 12 | B13: en | C13: CIS | D13: Baku, Azerbaijan | E13: Простой поиск мест | F13: Find historical museums in Baku. | G13: category: historical museums | H13: 2–5 реальных мест нужной категории; правильный город/район; краткое объяснение релевантности; соблюдение указанных предпочтений. | I13: Несуществующие места; другая категория; места вне указанной локации; неподтвержденные конкретные факты.
... A101: 100 | B101: en | C101: CIS | D101: Almaty, Kazakhstan | E101: Неполные / неоднозначные запросы | F101: I will be in Almaty for a while. Make me a plan. | G101: missing: exact duration, dates, interests, budget | H101: 1–3 точных уточняющих вопроса либо базовый вариант с явно обозначенными предположениями; указание, каких данных не хватает. | I101: Чрезмерно конкретный уверенный план без оснований; скрытые предположения; игнорирование неоднозначности запроса.

Sheet Results
A1: query_id | B1: language | C1: region | D1: city_country | E1: scenario | F1: user_query | G1: model | H1: prompt_version | I1: tool_outputs | J1: model_answer | K1: intent | L1: relevance | M1: factuality | N1: feasibility | O1: format | P1: critical_error | Q1: error_type | R1: overall_score | S1: evaluator_notes | T1: run_date
A2: 1 | B2: en | C2: Europe | D2: Prague, Czechia | E2: Простой поиск мест | F2: Find cozy coffee shops in Prague Old Town. | H2: geoagent v1 ( qwen3-8b) | K2: 0.8 | L2: 0.8 | M2: 0.4 | O2: 1 | R2: =IF(A2="","",IF(OR(E2="Маршрут на один день",E2="Планирование поездки на несколько дней"),IF(COUNT(K2:O2)<5,"",MIN(K2*0.2+L2*0.2+M2*0.25+N2*0.25+O2*0.1,IF(P2="Да",2,5))),IF(COUNT(K2:M2)+COUNT(O2)<4,"",MIN(K2*0.25+L2*0.25+M2*0.35+O2*0.15,IF(P2="Да",2,5))))) -> 0.69
A3: 2 | B3: en | C3: Europe | D3: Berlin, Germany | E3: Простой поиск мест | F3: Recommend contemporary art museums in Berlin. | H3: geoagent v1 ( qwen3-8b) | K3: 5 | L3: 4 | M3: 1 | O3: 5 | R3: =IF(A3="","",IF(OR(E3="Маршрут на один день",E3="Планирование поездки на несколько дней"),IF(COUNT(K3:O3)<5,"",MIN(K3*0.2+L3*0.2+M3*0.25+N3*0.25+O3*0.1,IF(P3="Да",2,5))),IF(COUNT(K3:M3)+COUNT(O3)<4,"",MIN(K3*0.25+L3*0.25+M3*0.35+O3*0.15,IF(P3="Да",2,5))))) -> 3.35
A4: 3 | B4: en | C4: Europe | D4: Lisbon, Portugal | E4: Простой поиск мест | F4: Find the best viewpoints in Lisbon for sunset. | H4: geoagent v1 ( qwen3-8b) | K4: 5 | L4: 4 | M4: 2 | O4: 5 | R4: =IF(A4="","",IF(OR(E4="Маршрут на один день",E4="Планирование поездки на несколько дней"),IF(COUNT(K4:O4)<5,"",MIN(K4*0.2+L4*0.2+M4*0.25+N4*0.25+O4*0.1,IF(P4="Да",2,5))),IF(COUNT(K4:M4)+COUNT(O4)<4,"",MIN(K4*0.25+L4*0.25+M4*0.35+O4*0.15,IF(P4="Да",2,5))))) -> 3.7
A5: 4 | B5: en | C5: Europe | D5: Rome, Italy | E5: Простой поиск мест | F5: Suggest traditional trattorias in Trastevere. | H5: geoagent v1 ( qwen3-8b) | K5: 5 | L5: 5 | M5: 3 | O5: 5 | R5: =IF(A5="","",IF(OR(E5="Маршрут на один день",E5="Планирование поездки на несколько дней"),IF(COUNT(K5:O5)<5,"",MIN(K5*0.2+L5*0.2+M5*0.25+N5*0.25+O5*0.1,IF(P5="Да",2,5))),IF(COUNT(K5:M5)+COUNT(O5)<4,"",MIN(K5*0.25+L5*0.25+M5*0.35+O5*0.15,IF(P5="Да",2,5))))) -> 4.3
A6: 5 | B6: en | C6: Europe | D6: Amsterdam, Netherlands | E6: Простой поиск мест | F6: Find quiet parks in Amsterdam for a relaxed afternoon. | H6: geoagent v1 ( qwen3-8b) | K6: 4 | L6: 3 | M6: 1 | O6: 5 | R6: =IF(A6="","",IF(OR(E6="Маршрут на один день",E6="Планирование поездки на несколько дней"),IF(COUNT(K6:O6)<5,"",MIN(K6*0.2+L6*0.2+M6*0.25+N6*0.25+O6*0.1,IF(P6="Да",2,5))),IF(COUNT(K6:M6)+COUNT(O6)<4,"",MIN(K6*0.25+L6*0.25+M6*0.35+O6*0.15,IF(P6="Да",2,5))))) -> 2.85
A7: 6 | B7: en | C7: Europe | D7: Athens, Greece | E7: Простой поиск мест | F7: Recommend archaeological sites in central Athens. | H7: geoagent v1 ( qwen3-8b) | K7: 5 | L7: 5 | M7: 2 | O7: 5 | R7: =IF(A7="","",IF(OR(E7="Маршрут на один день",E7="Планирование поездки на несколько дней"),IF(COUNT(K7:O7)<5,"",MIN(K7*0.2+L7*0.2+M7*0.25+N7*0.25+O7*0.1,IF(P7="Да",2,5))),IF(COUNT(K7:M7)+COUNT(O7)<4,"",MIN(K7*0.25+L7*0.25+M7*0.35+O7*0.15,IF(P7="Да",2,5))))) -> 3.95
A8: 7 | B8: en | C8: Europe | D8: Copenhagen, Denmark | E8: Простой поиск мест | F8: Find independent Danish design shops in Copenhagen. | H8: geoagent v1 ( qwen3-8b) | K8: 4 | L8: 2 | M8: 1 | O8: 4 | R8: =IF(A8="","",IF(OR(E8="Маршрут на один день",E8="Планирование поездки на несколько дней"),IF(COUNT(K8:O8)<5,"",MIN(K8*0.2+L8*0.2+M8*0.25+N8*0.25+O8*0.1,IF(P8="Да",2,5))),IF(COUNT(K8:M8)+COUNT(O8)<4,"",MIN(K8*0.25+L8*0.25+M8*0.35+O8*0.15,IF(P8="Да",2,5))))) -> 2.45
A9: 8 | B9: ru | C9: Europe | D9: London, United Kingdom | E9: Простой поиск мест | F9: Порекомендуй бесплатные музеи в центре Лондона. | H9: geoagent v1 ( qwen3-8b) | K9: 5 | L9: 4 | M9: 2 | O9: 4 | R9: =IF(A9="","",IF(OR(E9="Маршрут на один день",E9="Планирование поездки на несколько дней"),IF(COUNT(K9:O9)<5,"",MIN(K9*0.2+L9*0.2+M9*0.25+N9*0.25+O9*0.1,IF(P9="Да",2,5))),IF(COUNT(K9:M9)+COUNT(O9)<4,"",MIN(K9*0.25+L9*0.25+M9*0.35+O9*0.15,IF(P9="Да",2,5))))) -> 3.55
A10: 9 | B10: ru | C10: Europe | D10: Barcelona, Spain | E10: Простой поиск мест | F10: Найди хорошие веганские кафе в Барселоне. | H10: geoagent v1 ( qwen3-8b) | K10: 5 | L10: 4 | M10: 2 | O10: 5 | R10: =IF(A10="","",IF(OR(E10="Маршрут на один день",E10="Планирование поездки на несколько дней"),IF(COUNT(K10:O10)<5,"",MIN(K10*0.2+L10*0.2+M10*0.25+N10*0.25+O10*0.1,IF(P10="Да",2,5))),IF(COUNT(K10:M10)+COUNT(O10)<4,"",MIN(K10*0.25+L10*0.25+M10*0.35+O10*0.15,IF(P10="Да",2,5))))) -> 3.7
A11: 10 | B11: en | C11: CIS | D11: Almaty, Kazakhstan | E11: Простой поиск мест | F11: Find family-friendly parks in Almaty. | H11: geoagent v1 ( qwen3-8b) | K11: 2 | L11: 2 | M11: 1 | O11: 5 | R11: =IF(A11="","",IF(OR(E11="Маршрут на один день",E11="Планирование поездки на несколько дней"),IF(COUNT(K11:O11)<5,"",MIN(K11*0.2+L11*0.2+M11*0.25+N11*0.25+O11*0.1,IF(P11="Да",2,5))),IF(COUNT(K11:M11)+COUNT(O11)<4,"",MIN(K11*0.25+L11*0.25+M11*0.35+O11*0.15,IF(P11="Да",2,5))))) -> 2.1
A12: 11 | B12: en | C12: CIS | D12: Tbilisi, Georgia | E12: Простой поиск мест | F12: Suggest local bakeries in central Tbilisi. | H12: geoagent v1 ( qwen3-8b) | K12: 3 | L12: 3 | M12: 1 | O12: 3 | R12: =IF(A12="","",IF(OR(E12="Маршрут на один день",E12="Планирование поездки на несколько дней"),IF(COUNT(K12:O12)<5,"",MIN(K12*0.2+L12*0.2+M12*0.25+N12*0.25+O12*0.1,IF(P12="Да",2,5))),IF(COUNT(K12:M12)+COUNT(O12)<4,"",MIN(K12*0.25+L12*0.25+M12*0.35+O12*0.15,IF(P12="Да",2,5))))) -> 2.3
A13: 12 | B13: en | C13: CIS | D13: Baku, Azerbaijan | E13: Простой поиск мест | F13: Find historical museums in Baku. | H13: geoagent v1 ( qwen3-8b) | K13: 3 | L13: 3 | M13: 1 | O13: 4 | R13: =IF(A13="","",IF(OR(E13="Маршрут на один день",E13="Планирование поездки на несколько дней"),IF(COUNT(K13:O13)<5,"",MIN(K13*0.2+L13*0.2+M13*0.25+N13*0.25+O13*0.1,IF(P13="Да",2,5))),IF(COUNT(K13:M13)+COUNT(O13)<4,"",MIN(K13*0.25+L13*0.25+M13*0.35+O13*0.15,IF(P13="Да",2,5))))) -> 2.45
... A31: 30 | B31: ru | C31: CIS | D31: Almaty, Kazakhstan | E31: Проверка информации о конкретном месте | F31: Сколько стоит вход в Государственный музей искусств имени Кастеева и во сколько он закрывается? | H31: geoagent v1 ( qwen3-8b) | K31: 5 | L31: 4 | M31: 2 | O31: 5 | R31: =IF(A31="","",IF(OR(E31="Маршрут на один день",E31="Планирование поездки на несколько дней"),IF(COUNT(K31:O31)<5,"",MIN(K31*0.2+L31*0.2+M31*0.25+N31*0.25+O31*0.1,IF(P31="Да",2,5))),IF(COUNT(K31:M31)+COUNT(O31)<4,"",MIN(K31*0.25+L31*0.25+M31*0.35+O31*0.15,IF(P31="Да",2,5))))) -> 3.7
A32: 31 | B32: en | C32: Europe | D32: Prague, Czechia | E32: Поиск мест рядом с заданной точкой | F32: Find good cafes within 800 metres of Charles Bridge. | H32: geoagent v1 ( qwen3-8b) | K32: 5 | L32: 5 | M32: 4 | O32: 5 | R32: =IF(A32="","",IF(OR(E32="Маршрут на один день",E32="Планирование поездки на несколько дней"),IF(COUNT(K32:O32)<5,"",MIN(K32*0.2+L32*0.2+M32*0.25+N32*0.25+O32*0.1,IF(P32="Да",2,5))),IF(COUNT(K32:M32)+COUNT(O32)<4,"",MIN(K32*0.25+L32*0.25+M32*0.35+O32*0.15,IF(P32="Да",2,5))))) -> 4.65 | S32: Не удалось завершить запрос в отведённое число шагов.
A33: 32 | B33: en | C33: Europe | D33: Paris, France | E33: Поиск мест рядом с заданной точкой | F33: Find affordable restaurants within a 10-minute walk of Gare du Nord. | H33: geoagent v1 ( qwen3-8b) | K33: 5 | L33: 4 | M33: 3 | O33: 5 | R33: =IF(A33="","",IF(OR(E33="Маршрут на один день",E33="Планирование поездки на несколько дней"),IF(COUNT(K33:O33)<5,"",MIN(K33*0.2+L33*0.2+M33*0.25+N33*0.25+O33*0.1,IF(P33="Да",2,5))),IF(COUNT(K33:M33)+COUNT(O33)<4,"",MIN(K33*0.25+L33*0.25+M33*0.35+O33*0.15,IF(P33="Да",2,5))))) -> 4.05 | S33: Не удалось завершить запрос в отведённое число шагов.
A34: 33 | B34: en | C34: Europe | D34: Rome, Italy | E34: Поиск мест рядом с заданной точкой | F34: Recommend gelato shops within 1 km of the Colosseum. | H34: geoagent v1 ( qwen3-8b) | K34: 2 | L34: 2 | M34: 1 | O34: 4 | R34: =IF(A34="","",IF(OR(E34="Маршрут на один день",E34="Планирование поездки на несколько дней"),IF(COUNT(K34:O34)<5,"",MIN(K34*0.2+L34*0.2+M34*0.25+N34*0.25+O34*0.1,IF(P34="Да",2,5))),IF(COUNT(K34:M34)+COUNT(O34)<4,"",MIN(K34*0.25+L34*0.25+M34*0.35+O34*0.15,IF(P34="Да",2,5))))) -> 1.95
A35: 34 | B35: en | C35: Europe | D35: Vienna, Austria | E35: Поиск мест рядом с заданной точкой | F35: Find museums within 2 km of Vienna Hauptbahnhof. | H35: geoagent v1 ( qwen3-8b) | K35: 2 | L35: 2 | M35: 1 | O35: 5 | R35: =IF(A35="","",IF(OR(E35="Маршрут на один день",E35="Планирование поездки на несколько дней"),IF(COUNT(K35:O35)<5,"",MIN(K35*0.2+L35*0.2+M35*0.25+N35*0.25+O35*0.1,IF(P35="Да",2,5))),IF(COUNT(K35:M35)+COUNT(O35)<4,"",MIN(K35*0.25+L35*0.25+M35*0.35+O35*0.15,IF(P35="Да",2,5))))) -> 2.1
A36: 35 | B36: en | C36: Europe | D36: Barcelona, Spain | E36: Поиск мест рядом с заданной точкой | F36: Find breakfast places within a 15-minute walk of Plaça de Catalunya. | H36: geoagent v1 ( qwen3-8b) | K36: 2 | L36: 1 | M36: 1 | O36: 5 | R36: =IF(A36="","",IF(OR(E36="Маршрут на один день",E36="Планирование поездки на несколько дней"),IF(COUNT(K36:O36)<5,"",MIN(K36*0.2+L36*0.2+M36*0.25+N36*0.25+O36*0.1,IF(P36="Да",2,5))),IF(COUNT(K36:M36)+COUNT(O36)<4,"",MIN(K36*0.25+L36*0.25+M36*0.35+O36*0.15,IF(P36="Да",2,5))))) -> 1.85
A37: 36 | B37: en | C37: Europe | D37: London, United Kingdom | E37: Поиск мест рядом с заданной точкой | F37: Suggest quiet parks near the British Museum. | H37: geoagent v1 ( qwen3-8b) | K37: 4 | L37: 4 | M37: 2 | O37: 5 | R37: =IF(A37="","",IF(OR(E37="Маршрут на один день",E37="Планирование поездки на несколько дней"),IF(COUNT(K37:O37)<5,"",MIN(K37*0.2+L37*0.2+M37*0.25+N37*0.25+O37*0.1,IF(P37="Да",2,5))),IF(COUNT(K37:M37)+COUNT(O37)<4,"",MIN(K37*0.25+L37*0.25+M37*0.35+O37*0.15,IF(P37="Да",2,5))))) -> 3.45
A38: 37 | B38: ru | C38: Europe | D38: Paris, France | E38: Поиск мест рядом с заданной точкой | F38: Найди уютные кафе в радиусе километра от Лувра. | H38: geoagent v1 ( qwen3-8b) | K38: 4 | L38: 4 | M38: 3 | O38: 4 | R38: =IF(A38="","",IF(OR(E38="Маршрут на один день",E38="Планирование поездки на несколько дней"),IF(COUNT(K38:O38)<5,"",MIN(K38*0.2+L38*0.2+M38*0.25+N38*0.25+O38*0.1,IF(P38="Да",2,5))),IF(COUNT(K38:M38)+COUNT(O38)<4,"",MIN(K38*0.25+L38*0.25+M38*0.35+O38*0.15,IF(P38="Да",2,5))))) -> 3.65
A39: 38 | B39: ru | C39: Europe | D39: Berlin, Germany | E39: Поиск мест рядом с заданной точкой | F39: Порекомендуй вегетарианские рестораны в пределах 15 минут пешком от Бранденбургских ворот. | H39: geoagent v1 ( qwen3-8b) | K39: 2 | L39: 2 | M39: 1 | O39: 5 | R39: =IF(A39="","",IF(OR(E39="Маршрут на один день",E39="Планирование поездки на несколько дней"),IF(COUNT(K39:O39)<5,"",MIN(K39*0.2+L39*0.2+M39*0.25+N39*0.25+O39*0.1,IF(P39="Да",2,5))),IF(COUNT(K39:M39)+COUNT(O39)<4,"",MIN(K39*0.25+L39*0.25+M39*0.35+O39*0.15,IF(P39="Да",2,5))))) -> 2.1
A40: 39 | B40: ru | C40: Europe | D40: Amsterdam, Netherlands | E40: Поиск мест рядом с заданной точкой | F40: Найди небольшие музеи рядом с площадью Дам. | H40: geoagent v1 ( qwen3-8b) | K40: 3 | L40: 3 | M40: 1 | O40: 5 | R40: =IF(A40="","",IF(OR(E40="Маршрут на один день",E40="Планирование поездки на несколько дней"),IF(COUNT(K40:O40)<5,"",MIN(K40*0.2+L40*0.2+M40*0.25+N40*0.25+O40*0.1,IF(P40="Да",2,5))),IF(COUNT(K40:M40)+COUNT(O40)<4,"",MIN(K40*0.25+L40*0.25+M40*0.35+O40*0.15,IF(P40="Да",2,5))))) -> 2.6
A41: 40 | B41: en | C41: CIS | D41: Tbilisi, Georgia | E41: Поиск мест рядом с заданной точкой | F41: Find cafes within a 10-minute walk of Freedom Square in Tbilisi. | H41: geoagent v1 ( qwen3-8b) | K41: 3 | L41: 2 | M41: 1 | O41: 5 | R41: =IF(A41="","",IF(OR(E41="Маршрут на один день",E41="Планирование поездки на несколько дней"),IF(COUNT(K41:O41)<5,"",MIN(K41*0.2+L41*0.2+M41*0.25+N41*0.25+O41*0.1,IF(P41="Да",2,5))),IF(COUNT(K41:M41)+COUNT(O41)<4,"",MIN(K41*0.25+L41*0.25+M41*0.35+O41*0.15,IF(P41="Да",2,5))))) -> 2.35
A42: 41 | B42: en | C42: CIS | D42: Yerevan, Armenia | E42: Поиск мест рядом с заданной точкой | F42: Recommend Armenian restaurants near Republic Square in Yerevan. | H42: geoagent v1 ( qwen3-8b) | K42: 3 | L42: 2 | M42: 1 | O42: 5 | R42: =IF(A42="","",IF(OR(E42="Маршрут на один день",E42="Планирование поездки на несколько дней"),IF(COUNT(K42:O42)<5,"",MIN(K42*0.2+L42*0.2+M42*0.25+N42*0.25+O42*0.1,IF(P42="Да",2,5))),IF(COUNT(K42:M42)+COUNT(O42)<4,"",MIN(K42*0.25+L42*0.25+M42*0.35+O42*0.15,IF(P42="Да",2,5))))) -> 2.35
A43: 42 | B43: en | C43: CIS | D43: Moscow, Russia | E43: Поиск мест рядом с заданной точкой | F43: Find parks within 2 km of Red Square. | H43: geoagent v1 ( qwen3-8b) | K43: 3 | L43: 3 | M43: 3 | O43: 5 | R43: =IF(A43="","",IF(OR(E43="Маршрут на один день",E43="Планирование поездки на несколько дней"),IF(COUNT(K43:O43)<5,"",MIN(K43*0.2+L43*0.2+M43*0.25+N43*0.25+O43*0.1,IF(P43="Да",2,5))),IF(COUNT(K43:M43)+COUNT(O43)<4,"",MIN(K43*0.25+L43*0.25+M43*0.35+O43*0.15,IF(P43="Да",2,5))))) -> 3.3
A44: 43 | B44: en | C44: CIS | D44: Almaty, Kazakhstan | E44: Поиск мест рядом с заданной точкой | F44: Find coworking-friendly cafes near Abai Square in Almaty. | H44: geoagent v1 ( qwen3-8b) | K44: 3 | L44: 3 | M44: 2 | O44: 5 | R44: =IF(A44="","",IF(OR(E44="Маршрут на один день",E44="Планирование поездки на несколько дней"),IF(COUNT(K44:O44)<5,"",MIN(K44*0.2+L44*0.2+M44*0.25+N44*0.25+O44*0.1,IF(P44="Да",2,5))),IF(COUNT(K44:M44)+COUNT(O44)<4,"",MIN(K44*0.25+L44*0.25+M44*0.35+O44*0.15,IF(P44="Да",2,5))))) -> 2.95
A45: 44 | B45: ru | C45: CIS | D45: Saint Petersburg, Russia | E45: Поиск мест рядом с заданной точкой | F45: Найди рестораны русской кухни рядом с Дворцовой площадью. | H45: geoagent v1 ( qwen3-8b) | K45: 5 | L45: 4 | M45: 3 | O45: 5 | R45: =IF(A45="","",IF(OR(E45="Маршрут на один день",E45="Планирование поездки на несколько дней"),IF(COUNT(K45:O45)<5,"",MIN(K45*0.2+L45*0.2+M45*0.25+N45*0.25+O45*0.1,IF(P45="Да",2,5))),IF(COUNT(K45:M45)+COUNT(O45)<4,"",MIN(K45*0.25+L45*0.25+M45*0.35+O45*0.15,IF(P45="Да",2,5))))) -> 4.05
... A50: 49 | B50: en | C50: Europe | D50: Berlin, Germany | E50: Список мест для поездки | F50: Make a list of alternative culture spots, flea markets and inexpensive eateries in Berlin. | H50: geoagent v1 ( qwen3-8b) | K50: 5 | L50: 4 | M50: 2 | O50: 4 | R50: =IF(A50="","",IF(OR(E50="Маршрут на один день",E50="Планирование поездки на несколько дней"),IF(COUNT(K50:O50)<5,"",MIN(K50*0.2+L50*0.2+M50*0.25+N50*0.25+O50*0.1,IF(P50="Да",2,5))),IF(COUNT(K50:M50)+COUNT(O50)<4,"",MIN(K50*0.25+L50*0.25+M50*0.35+O50*0.15,IF(P50="Да",2,5))))) -> 3.55
A51: 50 | B51: en | C51: Europe | D51: Rome, Italy | E51: Список мест для поездки | F51: Suggest less crowded historical places and local restaurants in Rome. | G51: qwen/qwen3-30b-a3b-instruct-2507 | H51: geoagent v1 ( qwen3-8b) | I51: web_search(ok) | model_calls=2 tool_calls=1 grounded=true | J51: Here are some less crowded historical sites and authentic local restaurants in Rome, perfect for a more tranquil and immersive experience: --- ### 🏛️ **Less Crowded Historical Places in Rome** 1. **Clivus Scauri (Caelian Hill)** - *Location:* Between the Palatine and Caelian Hills - *Why visit:* This ancient Roman street is one of the best-preserved in the city, winding through a quiet, green area with a serene atmosphere. It’s far removed from the tourist crowds near the Colosseum and offers a peaceful journey through millennia of history. - *Highlights:* - The Basilica of Saints John and Paul - Roman Houses of the Caelian Hill (an archaeological complex with frescoes and layered history) - Panoramic views of Rome from the hilltop - *Tip:* Visit early in the morning to enjoy the tranquility and avoid midday heat. 2. **Villa Torlonia Museums and Park** - *Location:* Trastevere area, near the Janiculum Hill - *Why visit:* A hidden gem with a mix of ancient ruins, 19th-century architecture, and lush gardens. The park is expansive and rarely crowded, offering a peaceful escape. - *Highlights:* - The ruins of a Roman villa beneath the park - The elegant Villa Torlonia, once a residence of Mussolini - The Museum of the Italian Republic and the Museum of the 20th Century - *Tip:* Combine a visit with a walk along the Janiculum Hill for a stunning sunset view. 3. **Ostia Antica (Ancient Rome’s Port City)** - *Location:* 30 minutes by train from Rome (Porta San Paolo station) - *Why visit:* Often called “Rome’s Pompeii,” this well-preserved ancient city offers a quieter alternative to the crowded ruins in the city center. - *Highlights:* - Ancient streets, houses, baths, and mosaics - A peaceful atmosphere with fewer tourists - A perfect setting for a relaxed afternoon walk - *Tip:* Visit in the morning to avoid the midday heat and crowds. --- ### 🍝 **Authentic Local Restaurants in Rome** 1. **Ristorante Monumento dal 1884 (Ostia Antica)** - *Location:* Piazza Umberto I, 8, Ostia Antica - *Why go:* A century-old family-run restaurant that’s a local institution. It’s located right in the heart of Ostia Antica, making it ideal for a post-ruins seafood lunch. - *Must-try dishes:* - Linguine in bianco with clams, mussels, squid, and shrimp - Shrimp in brandy-lime sauce - Tiramisu (dense and rich, with a generous dusting of cacao) - *Atmosphere:* Sunny enclosed terrace, rustic charm, and warm hospitality. 2. **Trattoria da Enzo al 29** (Trastevere) - *Location:* Via dei Vascellari, 29, Trastevere - *Why go:* A beloved local favorite, tucked away in a quiet alley. It’s known for its traditional Roman cuisine and authentic atmosphere. - *Must-try dishes:* - Cacio e pepe (a classic Roman pasta) - Saltimbocca alla Romana (veal with prosciutto and sage) - Carciofi alla Romana (Roman-style artichokes) - *Tip:* Arrive early or make a reservation—this place is popular with locals and fills up quickly. 3. **La Montecarlo** (Testaccio) - *Location:* Via di Monte Testaccio, 10 - *Why go:* A no-frills, family-run spot known for its hearty Roman dishes and affordable prices. It’s a favorite among locals and foodies. - *Must-try dishes:* - Trippa alla Romana (Roman-style tripe) - Abbacchio alla scottadito (grilled lamb) - Pecorino cheese with honey - *Atmosphere:* Simple, rustic, and full of character. --- ### 🗺️ **Travel Tips** - **Best time to visit:** Early morning (before 10:00 AM) or late afternoon (after 4:00 PM) to avoid peak tourist hours. - **Transport:** Use the metro (Line A) to reach Ostia Antica and Trastevere. For the Caelian Hill and Villa Torlonia, a short walk or taxi is ideal. - **Dress code:** Comfortable walking shoes are essential—Rome is best explored on foot. Enjoy your journey through the quieter, more authentic side of Rome! 🇮🇹✨ | K51: 5 | L51: 4 | M51: 2 | O51: 5 | P51: Да | Q51: Wrong location within city; Hallucinated place; Unsupported factual claim | R51: =IF(A51="","",IF(OR(E51="Маршрут на один день",E51="Планирование поездки на несколько дней"),IF(COUNT(K51:O51)<5,"",MIN(K51*0.2+L51*0.2+M51*0.25+N51*0.25+O51*0.1,IF(P51="Да",2,5))),IF(COUNT(K51:M51)+COUNT(O51)<4,"",MIN(K51*0.25+L51*0.25+M51*0.35+O51*0.15,IF(P51="Да",2,5))))) -> 2 | S51: Формат строго списочный, обе категории покрыты, ставка на «нетуристическое» выдержана. Реальны и точны: Clivus Scauri с Римскими домами Целия и базиликой Сан-Джованни-э-Паоло, Остия-Антика, Trattoria da Enzo al 29 (Via dei Vascellari 29, Трастевере), Ristorante Monumento dal 1884 на Пьяцца Умберто I. Критично: вилла Торлония отнесена к Трастевере рядом с Яникулом — фактически Виа Номентана, северо-восток города; её музеи названы «Музей Итальянской Республики» и «Музей XX века» — таких там нет (Казино Нобиле, Казина делле Чиветте, Казино дей Принчипи), а под парком не «руины римской виллы», а еврейские катакомбы. La Montecarlo указана в Тестаччо (Via di Monte Testaccio 10) — реальная La Montecarlo это пиццерия у Пьяцца Навона. Совет ехать линией метро A в Остию-Антику и Трастевере неверен: Остия — линия Roma-Lido от Порта-Сан-Паоло. Подборка тонкая: по три позиции в каждой категории, две из шести привязаны к Остии. | T51: 46231
A52: 51 | B52: en | C52: Europe | D52: Vienna, Austria | E52: Список мест для поездки | F52: List places in Vienna for classical music, coffee culture and parks. | G52: qwen/qwen3-30b-a3b-instruct-2507 | H52: geoagent v1 ( qwen3-8b) | I52: web_search(ok); web_search(ok); web_search(ok) | model_calls=4 tool_calls=3 grounded=true | J52: Here is a curated list of the best places in Vienna for classical music, coffee culture, and parks, based on your interests: --- ### 🎻 **Classical Music Venues in Vienna** Vienna is renowned as the "City of Music," and its historic concert halls and churches offer world-class performances. 1. **The Musikverein** - One of the most prestigious concert halls in the world, home to the Vienna Philharmonic Orchestra. - Famous for the annual New Year’s Concert. - *Tip:* Book tickets in advance for performances of Mozart, Beethoven, and Strauss. 2. **Konzerthaus Wien** - A major venue for classical concerts, including symphonies, chamber music, and recitals. - Hosts the traditional **Christmas in Vienna** concert during the holiday season. 3. **Schönbrunn Palace Orangery** - A stunning setting for classical music concerts in a historic imperial garden. - Offers performances of works by Mozart, Haydn, and Vivaldi. 4. **Café Museum (Karlsplatz)** - A legendary coffee house with a long history of hosting live piano music (Fridays–Sundays, 4–7:30 PM). - Once frequented by Gustav Klimt and Adolf Loos. 5. **Konzert-Café Weimar (near Volksoper)** - Historic café with live piano music featuring operetta, jazz, and swing (Fri–Sun, 4–8 PM). --- ### ☕ **Iconic Coffee Houses for Viennese Coffee Culture** Vienna’s coffee house tradition is a UNESCO-recognized cultural heritage. These are the most authentic and beloved spots. 1. **Café Sacher Wien** - Famous for the **Original Sacher-Torte** and the **Sacher Coffee**. - Elegant, historic setting in the heart of Vienna. - A must-visit for a luxurious coffee and cake experience. 2. **Café Central** - A grand 19th-century café where Freud, Trotsky, and other intellectuals once gathered. - Known for its opulent interior and traditional Viennese pastries. 3. **Café Hawelka** - A legendary cultural hub with a bohemian atmosphere. - Famous for its **Buchteln** (jam-filled dough balls). - A favorite among artists and writers. 4. **Café Sperl** - One of the oldest coffee houses in Vienna (since 1880), with timeless decor. - Offers a genuine taste of old Vienna, including billiards and traditional cakes. 5. **Café Schwarzenberg** - A cozy, intimate spot with a literary vibe. - Known for its excellent coffee and relaxed ambiance. --- ### 🌳 **Top Parks in Vienna for Relaxation & Scenic Views** Vienna’s green spaces combine natural beauty with historical charm. 1. **Schloss Schönbrunn (Schönbrunn Palace Gardens)** - The imperial summer residence with magnificent baroque gardens. - Features fountains, a hedge maze, and the Gloriette (a triumphal arch with panoramic city views). - Ideal for a peaceful stroll or a picnic. 2. **Stadtpark (City Park)** - A serene green oasis near the Wien River, perfect for walking and cycling. - Home to a famous statue of Johann Strauss II. - Offers a tranquil escape from the city center. 3. **Prater Park** - Vienna’s largest public park, once a royal hunting ground. - Famous for the **Wiener Riesenrad (Vienna Ferris Wheel)**. - Great for picnics, cycling, and summer festivals. 4. **Lainzer Tiergarten** - A wild, forested park with free-roaming deer, boar, and birds. - A peaceful retreat for nature lovers and cross-country skiers in winter. 5. **Belvedere Palace Gardens** - Symmetrical French-style gardens between two grand palaces. - Features fountains, topiary, and stunning views of the palace and city skyline. --- ### ✅ **Recommended Experience Itinerary** - **Morning:** Start at **Café Sacher** for a traditional Viennese breakfast and a slice of Sacher-Torte. - **Afternoon:** Walk through **Stadtpark**, then visit **Café Central** for coffee and people-watching. - **Evening:** Attend a classical concert at **The Musikverein** or **Schönbrunn Orangery**. - **Optional:** End the day with a sunset stroll in **Schönbrunn Gardens**. Vienna beautifully blends music, coffee, and nature—perfect for a culturally rich and relaxing visit. | K52: 5 | L52: 4 | M52: 4 | O52: 5 | P52: Нет | Q52: Low relevance; Unsupported factual claim | R52: =IF(A52="","",IF(OR(E52="Маршрут на один день",E52="Планирование поездки на несколько дней"),IF(COUNT(K52:O52)<5,"",MIN(K52*0.2+L52*0.2+M52*0.25+N52*0.25+O52*0.1,IF(P52="Да",2,5))),IF(COUNT(K52:M52)+COUNT(O52)<4,"",MIN(K52*0.25+L52*0.25+M52*0.35+O52*0.15,IF(P52="Да",2,5))))) -> 4.4 | S52: Все три интереса покрыты реальными местами, формат списка. Кафе (Café Museum, Konzert-Café Weimar) отнесены в раздел классической музыки. Указаны конкретные часы живой музыки — не подтверждаются. В конце добавлен мини-маршрут, но список остаётся основным. | T52: 46231
A53: 52 | B53: en | C53: Europe | D53: Copenhagen, Denmark | E53: Список мест для поездки | F53: Suggest places in Copenhagen for design, modern architecture and food markets. | G53: qwen/qwen3-30b-a3b-instruct-2507 | H53: geoagent v1 ( qwen3-8b) | I53: web_search(ok) | model_calls=2 tool_calls=1 grounded=true | J53: Here are some top recommendations in Copenhagen for design, modern architecture, and food markets: --- ### 🏛️ **1. BLOX – Urban Life, Architecture & Sustainability** - **Why visit**: A striking example of modern architecture designed by renowned Dutch architects OMA. Located on Copenhagen’s central harbor front, BLOX is a hub for urban innovation, design, and sustainability. - **Highlights**: - **Danish Architecture Center (DAC)**: Hosts exhibitions on Danish and international architecture, design, and urban development. - **Design Shop**: Curated selection of Danish jewelry, watches, fashion, books, and design objects. - **BLOX EATS**: A vibrant café and restaurant with outdoor seating, perfect for a modern dining experience. - **Rental Apartments**: 22 stylish apartments with rooftop terraces (ideal for extended stays). - **Location**: Harbor front, Copenhagen. - **Website**: [www.blox.dk](https://www.blox.dk) --- ### 🍴 **2. Reffen – The Largest Street Food Market in the Nordics** - **Why visit**: A dynamic, waterfront food market that blends global street food with sustainable design and cultural events. - **Highlights**: - Over 50 food stalls offering cuisines from around the world (e.g., Thai, Mexican, Middle Eastern, and Nordic). - Unique architecture using repurposed shipping containers and reclaimed materials. - Regular live music, art installations, and seasonal events. - Open daily, making it a great spot for both lunch and evening outings. - **Location**: Former industrial harbor area, close to the city center. - **Website**: [reffen.dk](https://www.reffen.dk) --- ### 🏙️ **3. The Danish Architecture Center (DAC) – Inside BLOX** - **Why visit**: A must-visit for design and architecture enthusiasts. The center showcases the evolution of Danish design and urban planning. - **Highlights**: - **"So Danish!" Exhibition**: A sensory journey through 1,000 years of Danish architecture and design, featuring models, films, drawings, and installations. - **Events & Workshops**: Regular talks, lectures, and interactive sessions on architecture and sustainability. - **Café & Shop**: Relax with a coffee and browse unique design products. - **Location**: Inside BLOX, Copenhagen. - **Website**: [dac.dk](https://dac.dk) --- ### 🌿 **4. Superkilen Park – A Design-Driven Urban Space** - **Why visit**: A bold, colorful public park designed by the Danish firm BIG (Bjarke Ingels Group) in collaboration with Topotek 1 and Superflex. - **Highlights**: - A fusion of global cultures represented through architecture, art, and landscape design. - Features iconic elements like a red square, a black street, and a green park — each symbolizing a different cultural region. - A great place for a walk, photography, or simply experiencing innovative urban design. - **Location**: Nørrebro district, central Copenhagen. - **Website**: [superkilen.dk](https://www.superkilen.dk) --- ### 🍽️ **5. Torvehallerne (The Old Market Hall) – Modern Food Market with Design Flair** - **Why visit**: A beautifully restored 19th-century market hall now transformed into a modern food destination with a strong design focus. - **Highlights**: - Over 30 vendors offering artisanal food, organic produce, gourmet treats, and craft beverages. - Elegant interior with exposed brick, glass, and modern lighting — a blend of old and new. - Hosts pop-up events, cooking classes, and food festivals. - **Location**: Vesterbro, near the city center. - **Website**: [torvehallerne.dk](https://www.torvehallerne.dk) --- ### ✅ **Summary:** | Category | Recommended Place | |--------|-------------------| | **Modern Architecture** | BLOX, Superkilen Park | | **Design & Culture** | Danish Architecture Center (DAC), BLOX Design Shop | | **Food Markets** | Reffen, Torvehallerne | These locations offer a perfect blend of cutting-edge design, architectural innovation, and culinary experiences — all in the heart of Copenhagen. Let me know if you’d like a walking route or a day itinerary combining these spots! | K53: 5 | L53: 4 | M53: 4 | O53: 5 | P53: Нет | Q53: Unsupported factual claim; Too verbose | R53: =IF(A53="","",IF(OR(E53="Маршрут на один день",E53="Планирование поездки на несколько дней"),IF(COUNT(K53:O53)<5,"",MIN(K53*0.2+L53*0.2+M53*0.25+N53*0.25+O53*0.1,IF(P53="Да",2,5))),IF(COUNT(K53:M53)+COUNT(O53)<4,"",MIN(K53*0.25+L53*0.25+M53*0.35+O53*0.15,IF(P53="Да",2,5))))) -> 4.4 | S53: BLOX, Reffen, Superkilen, Torvehallerne, DAC — реальные, авторы (OMA, BIG) указаны верно. Torvehallerne отнесён к Vesterbro, фактически Indre By / Israels Plads. DAC и BLOX разнесены в два пункта, хотя это одно здание — дублирование сокращает реальную подборку. | T53: 46231
A54: 53 | B54: ru | C54: Europe | D54: Budapest, Hungary | E54: Список мест для поездки | F54: Составь список мест в Будапеште для терм, архитектуры и венгерской кухни. | G54: qwen/qwen3-30b-a3b-instruct-2507 | H54: geoagent v1 ( qwen3-8b) | I54: web_search(ok) | model_calls=2 tool_calls=1 grounded=true | J54: Вот подборка мест в Будапеште, которые идеально сочетают термальные источники, архитектурные достопримечательности и аутентичную венгерскую кухню: --- ### 🛁 **Термальные источники (термы)** 1. **Купальня Сечени (Széchenyi Gyógyfürdő)** - **Особенности**: Самая большая термальная баня в Европе, расположена на берегу Дуная. Включает 18 бассейнов, в том числе открытые, с термальной водой (36–40 °C). - **Атмосфера**: Оживлённая, популярна среди туристов и местных жителей. - **Совет**: Посетите вечером, чтобы насладиться видом на подсвеченный Парламент. - **Ссылка**: [Сечени — официальный сайт](https://www.szechenyygyogyfurdo.hu) 2. **Купальня Рудаш (Rudas Baths)** - **Особенности**: Историческая баня с османским наследием, построенная в XVI веке. Центральный восьмиугольный бассейн под рёбристым куполом с витражами — настоящий архитектурный шедевр. - **Атмосфера**: Тихая, созерцательная, идеальна для релаксации. - **Совет**: Посетите утром — свет, проникающий через витражи, особенно красив. - **Ссылка**: [Rudas Baths — официальный сайт](https://www.rudasbaths.hu) 3. **Купальня Геллерт (Gellért Baths)** - **Особенности**: Современный велнес-комплекс с историческим ядром. Включает бассейны, сауны, соляные пещеры и крытый бассейн с видом на Дунай. - **Важно**: В настоящее время закрыта на реконструкцию до 2028 года. - **Альтернатива**: Посетите **Купальню Лукач (Lukács Baths)** — более спокойная, с архитектурой в стиле модерн. --- ### 🏛️ **Архитектурные достопримечательности** 1. **Парламент Венгрии (Hungarian Parliament Building)** - **Особенности**: Неоготический шедевр на берегу Дуная. Внутри — великолепные залы, мозаики, башни. - **Совет**: Пройдитесь по балкону на верхнем этаже — панорама на Пешт и Дунай потрясающая. - **Экскурсии**: Доступны на нескольких языках. 2. **Замковый район и Рыбацкий бастион (Buda Castle & Fisherman’s Bastion)** - **Особенности**: Исторический холм с панорамными видами. - **Достопримечательности**: - Будайский замок (с музеями) - Церковь Святого Матяша - Лабиринт подземелий - **Совет**: Посетите вечером — виды на Пешт в свете особенно впечатляют. 3. **Проспект Андраши (Andrássy Avenue)** - **Особенности**: Пешеходный бульвар в стиле парижских проспектов. - **Достопримечательности**: - Площадь Героев (Hősök tere) - Театр оперы и балета - Архитектурные фасады в стиле неоклассицизма и модерна --- ### 🍽️ **Венгерская кухня** 1. **VakVarjú (на крыше Будайского замка)** - **Особенности**: Ресторан с панорамным видом на Пешт и Дунай. - **Кухня**: Современная венгерская с элементами фьюжн. - **Совет**: Закажите "гуляш с булочками" и венгерское вино. 2. **Bazár Várkert (у подножия Королевского дворца)** - **Особенности**: Рыночный комплекс с уличной едой и ресторанами. - **Рекомендации**: - "Гуляш" в традиционной керамической миске - "Палотас" — венгерский бутерброд с сыром и ветчиной - "Добош" — сладкий пирог с творогом 3. **Mézes Kör (Мёдовый круг)** - **Особенности**: Уютный ресторан в центре Пешта, известный своими традиционными блюдами. - **Рекомендации**: - "Суп из бобов с колбасой" - "Халаш" — венгерский хлеб с сыром - "Добош" с ванильным кремом --- ### 🗺️ **Совет по маршруту дня** 1. Утро: **Купальня Рудаш** (утренний свет в витражах) 2. День: **Замковый район + Рыбацкий бастион** (панорама + экскурсия) 3. Обед: **Bazár Várkерт** (вкусная уличная еда) 4. Вечер: **Парламент + круиз по Дунаю** (подсвеченный город) 5. Ужин: **VakVarjú** (панорама + венгерская кухня) --- Если хотите, могу составить **подробный маршрут на 1–3 дня** с учётом времени, транспорта и бронирования. | K54: 5 | L54: 4 | M54: 2 | O54: 4 | P54: Да | Q54: Hallucinated place; Unsupported factual claim; Wrong location within city | R54: =IF(A54="","",IF(OR(E54="Маршрут на один день",E54="Планирование поездки на несколько дней"),IF(COUNT(K54:O54)<5,"",MIN(K54*0.2+L54*0.2+M54*0.25+N54*0.25+O54*0.1,IF(P54="Да",2,5))),IF(COUNT(K54:M54)+COUNT(O54)<4,"",MIN(K54*0.25+L54*0.25+M54*0.35+O54*0.15,IF(P54="Да",2,5))))) -> 2 | S54: Термы и архитектура — реальные. Критично: ресторан «Mézes Kör» не идентифицируется; Сечени указана «на берегу Дуная» (фактически Варошлигет); ссылка szechenyygyogyfurdo.hu нерабочая; Várkert Bazár описан как рынок уличной еды; описания блюд неверны («Добош — пирог с творогом», «Халаш — хлеб с сыром», «Палотас»). Смешение кириллицы и латиницы в тексте. | T54: 46231
A55: 54 | B55: ru | C55: Europe | D55: Athens, Greece | E55: Список мест для поездки | F55: Порекомендуй места в Афинах для античной истории, видов на город и местной еды. | G55: qwen/qwen3-30b-a3b-instruct-2507 | H55: geoagent v1 ( qwen3-8b) | I55: web_search(ok) | model_calls=2 tool_calls=1 grounded=true | J55: Вот рекомендации по местам в Афинах, которые идеально сочетают античную историю, панорамные виды на город и возможность попробовать местную греческую кухню: --- ### 🏛️ **1. Акрополь Афин** - **Что посмотреть**: Главный символ древнегреческой цивилизации — храм Парфенон, Эрехтейон с портиком кариатид, храм Ники и Пропилеи. - **Виды**: Панорамный 360° вид на весь город с вершины холма. Особенно красив на закате. - **Местная еда**: Ресторан на вершине холма (часовня Святого Георгия) предлагает традиционные греческие блюда с видом на Акрополь. - **Совет**: Купите комбинированный билет (30 € на 5 дней) для посещения Акрополя и других музеев. - **Адрес**: Афинский Акрополь, Афины, Греция - **Ссылка**: [src_658dc90bf5](https://journest.app/athens-acropolis) --- ### 🏞️ **2. Холм Ликавитос** - **Что посмотреть**: Самая высокая точка Афин (277 м), с которой открывается великолепный вид на город, Акрополь и Средиземное море. - **Виды**: Панорама на 360° — идеально для фото и закатов. - **Местная еда**: На вершине — ресторан с традиционной греческой кухней (ламбаджия, мусака, тзазики). - **Доступ**: Подъём на фуникулёре или пешком по тропе. - **Адрес**: Улица Аристиппу, Колонаки, Афины - **Ссылка**: [src_f7567e59f4](https://journest.app/likavitos) --- ### 🏺 **3. Древняя Агора** - **Что посмотреть**: Сердце древнегреческой Афин — рынок, политический центр и место встреч. Здесь сохранился **Храм Гефеста** — один из лучших примеров древнегреческой архитектуры. - **Виды**: Вид на Акрополь с южной стороны. - **Местная еда**: Рядом — **Центральный рынок Варвакейос Агора**, где можно попробовать свежие продукты, сыр, оливки, фета и традиционные закуски. - **Совет**: Посетите **Стоа Аттала** — музей Агоры, где собраны археологические находки. - **Адрес**: Adrianou 24, Афины 105 55 - **Ссылка**: [src_78eb6bb418](https://journest.app/ancient-athens-agora) --- ### 🏺 **4. Национальный археологический музей** - **Что посмотреть**: Один из крупнейших археологических музеев мира. Здесь хранятся **золотая маска Агамемнона**, **Антикитерский механизм** и другие уникальные экспонаты. - **Виды**: Прекрасный вид на город с террасы музея. - **Местная еда**: Рядом — рестораны в районе Плака, где подают блюда в стиле «гриль» и традиционные греческие закуски. - **Адрес**: 28–30, Пирейская улица, Афины - **Ссылка**: [src_3f27b266f8](https://journest.app/national-archaeological-museum) --- ### 🍽️ **5. Район Плака (Plaka)** - **Что посмотреть**: Старый город, улочки с винтажными домами, лавки с сувенирами и ресторанами. - **Виды**: Виды на Акрополь с улиц и террас. - **Местная еда**: Множество ресторанов с традиционной греческой кухней: **Oinomageia**, **To Koutouki**, **Kostas** — здесь подают мусаку, салаты, кебабы и домашние десерты. - **Совет**: Посетите вечером — атмосфера особенно волшебная. - **Адрес**: Район Плака, Афины - **Ссылка**: [src_78eb6bb418](https://journest.app/ancient-athens-agora) --- ### ✅ **Итоговая рекомендация по маршруту**: 1. Утро: **Акрополь** (с посещением музея и храма Парфенон). 2. Обед: **Храм Гефеста** + прогулка по **Древней Агоре** + ужин в **Варвакейос Агора**. 3. Вечер: Подъём на **Ликавитос** на закат, ужин в ресторане на вершине. 4. Ночь: Прогулка по **Плаке** и дегустация местной еды. --- Если хотите, могу помочь составить **подробный маршрут на день** или **рекомендации по отелям** в этих районах. | K55: 5 | L55: 4 | M55: 2 | O55: 3 | P55: Да | Q55: Unsupported factual claim; Wrong location within city; Poor formatting | R55: =IF(A55="","",IF(OR(E55="Маршрут на один день",E55="Планирование поездки на несколько дней"),IF(COUNT(K55:O55)<5,"",MIN(K55*0.2+L55*0.2+M55*0.25+N55*0.25+O55*0.1,IF(P55="Да",2,5))),IF(COUNT(K55:M55)+COUNT(O55)<4,"",MIN(K55*0.25+L55*0.25+M55*0.35+O55*0.15,IF(P55="Да",2,5))))) -> 2 | S55: Акрополь, Агора, Ликавитос, Плака — реальные и покрывают запрос. Критично: часовня Св. Георгия и ресторан на вершине отнесены к Акрополю (это Ликавитос); адрес Национального археологического музея неверен (фактически ул. Патисион 44); блюдо «ламбаджия» выдумано. В текст утекли сырые id источников (src_...), ссылки journest.app нерабочие. | T55: 46231
A56: 55 | B56: en | C56: CIS | D56: Tbilisi, Georgia | E56: Список мест для поездки | F56: I am going to Tbilisi for four days. Suggest places for culture, Georgian food and panoramic views. | G56: qwen/qwen3-30b-a3b-instruct-2507 | H56: geoagent v1 ( qwen3-8b) | I56: web_search(ok); web_search(ok); web_search(ok) | model_calls=2 tool_calls=3 grounded=true | J56: Here’s a curated 4-day travel plan for your trip to **Tbilisi**, focusing on **culture**, **authentic Georgian cuisine**, and **panoramic views**. The recommendations are based on up-to-date information from trusted sources. --- ### 🌆 **Day 1: Explore Old Town & Cultural Heart** **Focus:** History, architecture, and iconic landmarks. - **Morning: Old Town Tbilisi** Start your journey in the historic **Old Town**, a maze of cobbled streets, 19th-century townhouses, and hidden courtyards. Wander through **Sololaki** and **Shardeni Street**, known for its charming alleys and vibrant café culture. - **Midday: Sioni Cathedral** Visit the **Sioni Cathedral** (6th century), the spiritual heart of Tbilisi. Admire its ancient architecture and view the **Cross of St. Nino**, Georgia’s holiest relic. - **Afternoon: Rustaveli Avenue & National Museum** Stroll down **Rustaveli Avenue**, Tbilisi’s grand boulevard. Stop by the **National Museum of Georgia** and the **Opera House**. The avenue is perfect for people-watching and soaking in the city’s energy. - **Evening: Sunset at Narikala Fortress** Head to **Narikala Fortress** (4th century) for panoramic views. Take the **cable car from Rike Park** (₾5) or hike up from **Abanotubani** (20 min). Best time: **one hour before sunset** for golden-hour photos. --- ### 🍽️ **Day 2: Georgian Food & Culinary Immersion** **Focus:** Authentic cuisine, traditional dining, and cultural experiences. - **Lunch: Ethno Tsiskvili (A. Beliashvili St. 99)** Dine at **Ethno Tsiskvili**, a cultural restaurant with a natural waterfall and traditional Georgian decor. Enjoy **khachapuri**, **khinkali**, and **barbecue**. Don’t miss the **live folk music and dance performances** (20:00–00:00). - **Afternoon: Vakhtanguri Restaurant (Old Town)** Visit **Vakhtanguri**, a beloved local institution since 1993. Try their famous **chebureki** (spiced meat turnovers) and other family-recipe dishes. The atmosphere is warm and nostalgic. - **Evening: Wine Tasting in the Old Town** Explore **wine bars** along **Shardeni Street** or **Tbilisi’s underground wine cellars** (like **Nikoloz’s Cellar**). Sample **Saperavi**, **Rkatsiteli**, and other local varietals. --- ### 🌄 **Day 3: Panoramic Views & Mountain Vibes** **Focus:** Elevated city views, parks, and relaxation. - **Morning: Mtatsminda Park & Funicular** Take the **funicular** from **Rustaveli Avenue** to **Mtatsminda Park**. Enjoy the ride and the **observation deck** with sweeping views of Tbilisi, the Kura River, and the Greater Caucasus Range. - **Midday: Ferris Wheel & Cafés** Ride the **Ferris wheel** for a 360° view. Grab a coffee at one of the park’s cafés and enjoy the mountain breeze. - **Afternoon: Bridge of Peace & Kura River Walk** Walk across the **Bridge of Peace**, a modern architectural gem. Stroll along the **Kura River** and enjoy views of the city skyline. - **Evening: Dinner at Tsiskvili Terrace (Z. Gamsakhurdia Embankment)** Dine with a view at **Tsiskvili Terrace**, a riverside restaurant offering panoramic city views and excellent Georgian cuisine. --- ### 🏛️ **Day 4: Museums, Monuments & Final Impressions** **Focus:** Culture, history, and memorable souvenirs. - **Morning: Chronicles of Georgia & Art Palace** Visit **Chronicles of Georgia**, a museum dedicated to Georgia’s history and national identity. Then explore the **Art Palace of Georgia – Museum of Cultural History** for insights into Georgian art and traditions. - **Midday: Rezo Gabriadze Marionette Theater** Watch a performance at the **Rezo Gabriadze Marionette Theater**, a unique cultural gem in the Old Town. The puppet shows are both artistic and deeply rooted in Georgian folklore. - **Afternoon: Final Walk & Souvenirs** Take a final walk through **Old Town**, pick up souvenirs like **Georgian wine**, **pomegranate molasses**, or **handmade ceramics** from local shops. - **Evening: Farewell Dinner at Wine Yard (A. Beliashvili St. 99)** End your trip with a relaxed dinner at **Wine Yard**, another gem in the Tsiskvili Group, known for its cozy atmosphere and excellent wine pairings. --- ### 📌 **Tips for Your Trip:** - **Best Time to Visit:** Spring (April–June) or early autumn (September–October) for pleasant weather. - **Transport:** Use the **funicular**, **cable car**, or **walk**—Tbilisi is very walkable. - **Currency:** Georgian Lari (GEL). ATMs are widely available. - **Travel Insurance:** Mandatory since 2026 (as per recent regulations). --- Enjoy your unforgettable journey through **Tbilisi**—a city where ancient history, vibrant culture, and breathtaking views come together in perfect harmony. 🇬🇪✨ | K56: 3 | L56: 3 | M56: 2 | O56: 4 | P56: Да | Q56: Low relevance; Unsupported factual claim; Hallucinated place | R56: =IF(A56="","",IF(OR(E56="Маршрут на один день",E56="Планирование поездки на несколько дней"),IF(COUNT(K56:O56)<5,"",MIN(K56*0.2+L56*0.2+M56*0.25+N56*0.25+O56*0.1,IF(P56="Да",2,5))),IF(COUNT(K56:M56)+COUNT(O56)<4,"",MIN(K56*0.25+L56*0.25+M56*0.35+O56*0.15,IF(P56="Да",2,5))))) -> 2 | S56: Пользователь просил список, агент выдал жёсткий маршрут по дням. Критично: утверждение «Travel Insurance: Mandatory since 2026» выдумано; цена канатной дороги ₾5 не соответствует действительности; заведения Vakhtanguri, Nikoloz's Cellar, Tsiskvili Terrace не подтверждаются. Нарикала, Сиони, Мтацминда, Мост Мира, Хроники Грузии — реальные. | T56: 46231
A57: 56 | B57: en | C57: CIS | D57: Yerevan, Armenia | E57: Список мест для поездки | F57: List places in Yerevan for history, Armenian cuisine and contemporary art. | G57: qwen/qwen3-30b-a3b-instruct-2507 | H57: geoagent v1 ( qwen3-8b) | I57: web_search(ok); web_search(ok); web_search(ok) | model_calls=4 tool_calls=3 grounded=true | J57: Here is a curated list of places in Yerevan that offer a rich experience in **history**, **Armenian cuisine**, and **contemporary art**, based on the latest available information: --- ### 🏺 **Historical Sites in Yerevan** 1. **Erebuni Fortress & Museum-Reserve** - **Location**: Southeastern suburbs of Yerevan - **Significance**: Founded in 782 BC by King Argishti I of Urartu, Erebuni is the oldest known foundation of Yerevan. The name "Yerevan" itself derives from "Erebuni." - **Highlights**: Ancient ruins, archaeological museum, panoramic views of the city. - **Visit Tip**: Combine with a visit to the adjacent **Erebuni Museum of History** (separate entry fee). - **Website**: [Erebuni Museum](https://en.wikipedia.org/wiki/Erebuni_Fortress) - **Address**: Erebuni District, Yerevan, Armenia 2. **Katoghike Church (Holy Mother of God Church)** - **Location**: Kentron District, central Yerevan - **Significance**: A 13th-century medieval church discovered during the demolition of a 17th-century basilica in 1936. It’s one of the oldest surviving churches in the city. - **Highlights**: Historical preservation, ancient khachkars (cross-stones), and architectural resilience. - **Address**: Kentron District, Yerevan, Armenia --- ### 🍽️ **Best Places for Armenian Cuisine** 1. **The Club** - **Location**: Tumanyan 40, Yerevan - **Cuisine**: Modern Armenian (New Armenian Cuisine) - **Highlights**: - Zero-waste restaurant using locally sourced ingredients. - Seasonal menu with innovative dishes inspired by Armenian highland traditions. - Wine cellar featuring wines from the Vayots Dzor region. - Hosts cultural events: concerts, lectures, book presentations. - **Ambience**: Intimate, artistic, and sustainable. - **Hours**: Daily 13:00–23:30 - **Contact**: +374 10 531361 | [Website](https://theclub.am) --- ### 🎨 **Contemporary Art Spaces in Yerevan** 1. **Cafesjian Center for the Arts (CCA)** - **Location**: The Cascade Complex, Yerevan - **Highlights**: - Dedicated to modern and contemporary art from Armenia and globally. - Features exhibitions from the **Cafesjian Art Trust**, including works by renowned artists. - Offers lectures, film screenings, concerts, and educational programs. - **Architecture**: Housed in the iconic **Cascade**, a monumental stairway complex designed by architect Alexander Tamanyan. - **Address**: Cascade Complex, Yerevan, Armenia - **Website**: [www.cmf.am](https://www.cmf.am) 2. **Esquisse Gallery** - **Location**: Sayat-Nova 5, Yerevan - **Focus**: International contemporary art and emerging Armenian artists. - **Highlights**: - Promotes cross-cultural dialogue through exhibitions. - Showcases artists with global recognition. - **Contact**: +374 95 555109 - **Website**: [esquissegallery.com](https://esquissegallery.com) 3. **Gala Art Gallery** - **Location**: Yerevan (exact address not specified, but active in the city center) - **Focus**: Modern and contemporary paintings, sculpture, and pottery by over 40 Armenian artists. - **Founded**: 2012 by Avetis Berberyan and Noushik Mikayelian. - **Website**: [gala-artgallery.am](https://gala-artgallery.am) 4. **Two Arcs Art Space** - **Location**: 5 Sayat-Nova Avenue, Yerevan - **Highlights**: A dynamic space for contemporary art exhibitions and artist residencies. - **Contact**: +374 43 490 490 | [Website](https://www.twoarcs.am) 5. **ARAR Gallery** - **Location**: Abovyan 13, Yerevan - **Focus**: Experimental and socially engaged contemporary art. - **Notable Projects**: Collaborations with the IPBA Foundation to bring art to public spaces. - **Website**: [arargallery.com](https://arargallery.com) --- ### ✅ **Suggested Itinerary for a Cultural Day in Yerevan** 1. **Morning**: Visit **Erebuni Fortress** and **Erebuni Museum** (history). 2. **Lunch**: Enjoy authentic Armenian cuisine at **The Club** (culinary experience). 3. **Afternoon**: Explore **Cafesjian Center for the Arts** (contemporary art). 4. **Evening**: Stroll through **The Cascade**, then visit **Esquisse Gallery** or **ARAR Gallery** for a night of art and culture. --- Let me know if you’d like help booking tickets, planning a multi-day trip, or finding accommodations near these sites! | K57: 5 | L57: 4 | M57: 4 | O57: 4 | P57: Нет | Q57: Missing important category; Unsupported factual claim | R57: =IF(A57="","",IF(OR(E57="Маршрут на один день",E57="Планирование поездки на несколько дней"),IF(COUNT(K57:O57)<5,"",MIN(K57*0.2+L57*0.2+M57*0.25+N57*0.25+O57*0.1,IF(P57="Да",2,5))),IF(COUNT(K57:M57)+COUNT(O57)<4,"",MIN(K57*0.25+L57*0.25+M57*0.35+O57*0.15,IF(P57="Да",2,5))))) -> 4.25 | S57: Все места реальные, история и современное искусство раскрыты хорошо (Эребуни, Катогике, Кафесчян, Esquisse, Two Arcs, ARAR). Кухня представлена одним заведением при пяти арт-площадках - категория недораскрыта. Часы работы и телефоны даны без подтверждения. Каскад приписан Таманяну - упрощение. | T57: 46231
A58: 57 | B58: en | C58: CIS | D58: Almaty, Kazakhstan | E58: Список мест для поездки | F58: Suggest places in Almaty for mountain views, local food and modern culture. | G58: qwen/qwen3-30b-a3b-instruct-2507 | H58: geoagent v1 ( qwen3-8b) | I58: web_search(ok) | model_calls=2 tool_calls=1 grounded=true | J58: Here are top recommendations in Almaty that combine **breathtaking mountain views**, **authentic local Kazakh cuisine**, and **modern cultural experiences**: --- ### 🏔️ 1. **Kok-Tobe Hill (Kok-Tobe)** - **Mountain Views**: Offers panoramic vistas of Almaty and the surrounding Tian Shan mountains. The cable car ride (6 minutes) from Dostyk Avenue provides a scenic ascent. - **Modern Culture**: Home to the **Almaty TV Tower (372m)**, a **Beatles monument**, a mini-zoo, amusement rides, and a vibrant promenade with cafes and shops. - **Local Food**: Try traditional Kazakh dishes like *beshbarmak*, *kumis*, and *samsa* at the hilltop restaurants. - **Best Time to Visit**: Sunset for stunning city lights and mountain silhouettes. - **Access**: Cable car (~2,000 KZT round-trip for adults). Open April–June and September–October for optimal weather. --- ### 🌲 2. **Big Almaty Lake (Bolshoy Almaty Lake)** - **Mountain Views**: Nestled in a high-altitude basin (2,500m), surrounded by snow-capped peaks. Ideal for hiking and photography. - **Local Food**: Nearby mountain lodges and picnic spots serve *kazy* (horse meat), *shashlik*, and homemade bread. - **Modern Culture**: Part of the city’s outdoor recreation network; increasingly popular with locals and tourists for weekend getaways. - **Access**: About 30 minutes from downtown by car. Road climbs steeply—best visited on weekdays to avoid weekend crowds. --- ### 🏞️ 3. **Medeu Skating Rink & Shymbulak Ski Resort** - **Mountain Views**: Medeu is a high-altitude ice rink (1,690m), with the Shymbulak cable car offering access to alpine trails and panoramic views. - **Local Food**: Cafés at Shymbulak serve hearty Kazakh meals and modern fusion dishes with mountain views. - **Modern Culture**: Shymbulak is a hub for winter sports and summer hiking. The resort hosts cultural events and music festivals in summer. - **Best Time to Visit**: Winter (Jan–Mar) for skiing; summer (June–Sept) for hiking and mountain biking. - **Access**: Public bus to Medeu (affordable and frequent), then cable car to Shymbulak. --- ### 🍽️ 4. **Green Market (Zelyony Bazaar) & Side Streets of Almaty** - **Local Food**: The heart of Almaty’s culinary scene. Sample *beshbarmak*, *kazy*, *kumis*, *baursaki*, and fresh fruit juices. - **Modern Culture**: Trendy cafés and street art blend traditional and contemporary styles. Great for people-watching and cultural immersion. - **Mountain Views**: While not directly mountain-facing, the market is located near the city’s edge, with distant views of the Tian Shan range. --- ### 🌆 5. **Panfilov Park & Central Almaty** - **Mountain Views**: Located on the city’s western edge, offering clear sightlines to the mountains. - **Modern Culture**: Hosts open-air concerts, art installations, and seasonal festivals. The park is a social hub with modern cafes and bookshops. - **Local Food**: Numerous restaurants serve modern Kazakh fusion cuisine, including innovative takes on traditional dishes. --- ### ✅ Summary: Best for Your Interests | Interest | Top Recommendation | |--------|-------------------| | Mountain Views | Kok-Tobe Hill & Big Almaty Lake | | Local Food | Green Market & Shymbulak cafés | | Modern Culture | Kok-Tobe promenade & Panfilov Park | For a full-day experience: **Start at Kok-Tobe for views and culture → Head to Big Almaty Lake for hiking and local food → End at Panfilov Park for a relaxed evening.** Let me know if you’d like help planning a route, booking a cable car ticket, or finding specific restaurants! | K58: 5 | L58: 3 | M58: 3 | O58: 5 | P58: Нет | Q58: Wrong location within city; Missing important category; Unsupported factual claim | R58: =IF(A58="","",IF(OR(E58="Маршрут на один день",E58="Планирование поездки на несколько дней"),IF(COUNT(K58:O58)<5,"",MIN(K58*0.2+L58*0.2+M58*0.25+N58*0.25+O58*0.1,IF(P58="Да",2,5))),IF(COUNT(K58:M58)+COUNT(O58)<4,"",MIN(K58*0.25+L58*0.25+M58*0.35+O58*0.15,IF(P58="Да",2,5))))) -> 3.8 | S58: Кок-Тобе, БАО, Медеу, Шымбулак, Зелёный базар - реальные, виды и еда покрыты. Парк Панфилова указан «на западной окраине» - фактически центр города. Время до Большого Алматинского озера занижено (30 мин вместо ~1 ч). Современная культура фактически не раскрыта: вместо площадок - променад и парк. | T58: 46231
A59: 58 | B59: en | C59: CIS | D59: Baku, Azerbaijan | E59: Список мест для поездки | F59: Make a list of places in Baku for architecture, Caspian Sea views and Azerbaijani cuisine. | G59: qwen/qwen3-30b-a3b-instruct-2507 | H59: geoagent v1 ( qwen3-8b) | I59: web_search(ok) | model_calls=2 tool_calls=1 grounded=true | J59: Here is a curated list of top places in Baku that combine **architecture**, **Caspian Sea views**, and **authentic Azerbaijani cuisine**, based on recent travel guides and local recommendations: --- ### 🏛️ **1. Baku Old City (İçərişəhər)** - **Architecture**: A UNESCO World Heritage Site, this medieval walled city features ancient caravanserais, mud-brick houses, and the iconic **Maiden Tower** (12th century), a symbol of Baku. - **Views**: While not directly on the Caspian Sea, the Old City offers panoramic views of the city skyline and the sea in the distance. - **Cuisine**: Explore traditional restaurants like **Məhəbbət** or **Khan’s Kitchen** for authentic Azerbaijani dishes such as *plov*, *dolma*, and *qutab*. --- ### 🌊 **2. Baku Boulevard (Neftchilar Avenue)** - **Architecture**: A modern waterfront promenade lined with striking contemporary buildings, including the **Flame Towers** and **Heydar Aliyev Center** (designed by Zaha Hadid). - **Views**: Direct, unobstructed views of the **Caspian Sea** — especially stunning at sunset when the Flame Towers glow behind the water. - **Cuisine**: - **SAHiL Restaurant** (on the boulevard): Renowned for its fresh **Caspian Sea fish**, traditional Azerbaijani dishes, and terrace seating with sea views. Ideal for lunch or dinner. --- ### 🏛️ **3. Heydar Aliyev Center** - **Architecture**: A masterpiece of modern architecture with flowing, futuristic curves. A cultural hub housing exhibitions, events, and art installations. - **Views**: Located near the Caspian Sea, offering sweeping views of the coastline and the Flame Towers. - **Cuisine**: Nearby cafes and restaurants like **Café 1900** (inside the complex) serve modern Azerbaijani fusion cuisine. --- ### 🏛️ **4. Carpet Museum (Baku)** - **Architecture**: Housed in a striking modern building on Baku Boulevard, designed with traditional Azerbaijani motifs. - **Views**: Direct access to the **Baku Boulevard** and the Caspian Sea. - **Cuisine**: Adjacent to **SAHiL Restaurant**, making it a perfect combo visit — enjoy a museum tour followed by a meal with sea views. --- ### 🍽️ **5. Qafqaz Restaurant (Old City)** - **Architecture**: Located in a restored 19th-century building within the Old City, blending historical charm with modern interiors. - **Views**: Offers a quiet, atmospheric setting with views of the city’s ancient rooftops and distant sea. - **Cuisine**: Specializes in **authentic Azerbaijani cuisine** — try *piti*, *dushbara*, and *shekerbura*. Known for its traditional recipes and warm hospitality. --- ### 🌅 **6. Flame Towers & Surrounding Areas** - **Architecture**: Iconic skyscrapers with dynamic LED lighting, representing Baku’s modern identity. - **Views**: Best at night when the towers light up and reflect on the Caspian Sea. - **Cuisine**: - **Café 1900** (inside the Flame Towers complex): Offers a refined dining experience with Azerbaijani and international dishes. - **Baku Seafood House** (nearby): Famous for fresh **Caspian fish**, grilled kebabs, and seafood platters. --- ### 🍲 **7. Local Teahouses (e.g., Mirzaagha Aliyev Teahouse)** - **Architecture**: Traditional Azerbaijani teahouses with wooden interiors, clay stoves, and vintage decor. - **Views**: Often located in quiet corners of the city, some offer views of the sea or green spaces. - **Cuisine**: Sip **black tea from armuda (pear-shaped) glasses** and enjoy **lavash wraps**, **qutab**, and **caviar with warm bread** — a true cultural experience. --- ### ✅ **Tips for Your Visit:** - **Best Time to Visit**: Late afternoon to evening for the most beautiful Caspian Sea views and golden-hour lighting on the Flame Towers. - **Dining Reservations**: Recommended for **SAHiL** and **Qafqaz** due to high demand. - **Transport**: Use the Baku Metro or ride-hailing apps to easily navigate between the Old City, Boulevard, and modern districts. --- This list offers a perfect blend of **historical depth**, **modern design**, **breathtaking sea vistas**, and **gourmet Azerbaijani flavors** — a true journey through Baku’s soul. | K59: 5 | L59: 4 | M59: 2 | O59: 4 | P59: Да | Q59: Hallucinated place; Wrong location within city | R59: =IF(A59="","",IF(OR(E59="Маршрут на один день",E59="Планирование поездки на несколько дней"),IF(COUNT(K59:O59)<5,"",MIN(K59*0.2+L59*0.2+M59*0.25+N59*0.25+O59*0.1,IF(P59="Да",2,5))),IF(COUNT(K59:M59)+COUNT(O59)<4,"",MIN(K59*0.25+L59*0.25+M59*0.35+O59*0.15,IF(P59="Да",2,5))))) -> 2 | S59: Ичери-Шехер, Девичья башня, Приморский бульвар, Flame Towers, Музей ковра — реальные, Заха Хадид указана верно. Критично: Центр Гейдара Алиева описан как расположенный у моря с видами на побережье — он в глубине города; Flame Towers и Центр отнесены к застройке бульвара. Рестораны (Café 1900, Baku Seafood House, Məhəbbət) не подтверждаются, при этом Café 1900 в одном ответе размещён и в Центре Алиева, и во Flame Towers. | T59: 46231
A60: 59 | B60: ru | C60: CIS | D60: Kazan, Russia | E60: Список мест для поездки | F60: Составь список мест в Казани с татарской кухней и прогулок у воды. | G60: qwen/qwen3-30b-a3b-instruct-2507 | H60: geoagent v1 ( qwen3-8b) | I60: web_search(ok) | model_calls=2 tool_calls=1 grounded=true | J60: Вот список мест в Казани, где можно насладиться татарской кухней и насладиться прогулками у воды: --- ### 🍽️ **Места с татарской кухней** 1. **Ресторан Tatar by Tubetey** - **Адрес**: ул. Шигабутдина Марджани, 10, Казань - **Особенности**: - Двухэтажный халяльный ресторан с авторской татарской кухней. - Вдохновлён культурой Татарстана: интерьер, орнаменты, живописный вид на озеро Кабан. - Блюда в современной интерпретации: кыстыбый со свеклой и тыквенными семечками, чпочмаки с семгой, пельмени с уткой, равиоли в форме треугольников. - Рядом — станция метро «Площадь Тукая». - **Ссылка**: [src_6866d6032d](src_6866d6032d) 2. **Ресторан «Аулак»** - **Адрес**: Казанский Кремль (внутри исторической зоны) - **Особенности**: - Кофейня и место для традиционного завтрака с элементами татарской кухни. - Подходит для начала знакомства с городом и кулинарией. - Атмосфера, сочетающая историю и современность. - **Ссылка**: [src_a0f370bf66](src_a0f370bf66) 3. **Ресторан «Гавань Вилл»** - **Адрес**: берег Волги, Казань (улица, прилегающая к набережной) - **Особенности**: - Ресторан высокой кухни с большой террасой у воды. - Идеально для завтраков, ужинов на закате и романтических вечеров. - Уникальное пространство с видом на реку — редкость в Казани. - **Ссылка**: [src_328f1e4202](src_328f1e4202) --- ### 🌿 **Прогулки у воды** 1. **Озеро Кабан (Нижний Кабан)** - **Местоположение**: рядом с рестораном Tatar by Tubetey - **Особенности**: - Прогулочные дорожки, живописные виды, тихая атмосфера. - Подходит для утренних или вечерних прогулок, фото и отдыха. - Рядом — кафе и рестораны, включая Tatar by Tubetey. 2. **Река Казанка — речная прогулка «Вечерняя Казань»** - **Маршрут**: современный теплоход «Мария Ермолова» - **Особенности**: - Атмосферная прогулка по вечерней Казани. - Вид на достопримечательности города с воды: Кремль, мосты, набережные. - Подходит для романтических вечеров, встреч с друзьями. - **Ссылка**: [src_99a275e73a](src_99a275e73a) 3. **Набережная Волги (улица Кремлёвская)** - **Особенности**: - Просторная, благоустроенная территория с видом на реку. - Подходит для прогулок, велопрогулок, отдыха на скамейках. - Рядом — рестораны, кафе, культурные объекты. --- ### 📌 **Совет по маршруту дня** 1. Утро: завтрак в **«Аулаке»** (Казанский Кремль). 2. День: прогулка по **Кремлю** и **Старо-Татарской слободе**. 3. Вечер: ужин в **Tatar by Tubetey** с видом на озеро Кабан. 4. Ночь: речная прогулка по **Казанке** — «Вечерняя Казань». --- Если хотите, могу помочь составить маршрут с учётом времени, транспорта или бронирования. | K60: 5 | L60: 4 | M60: 3 | O60: 3 | P60: Нет | Q60: Wrong location within city; Poor formatting | R60: =IF(A60="","",IF(OR(E60="Маршрут на один день",E60="Планирование поездки на несколько дней"),IF(COUNT(K60:O60)<5,"",MIN(K60*0.2+L60*0.2+M60*0.25+N60*0.25+O60*0.1,IF(P60="Да",2,5))),IF(COUNT(K60:M60)+COUNT(O60)<4,"",MIN(K60*0.25+L60*0.25+M60*0.35+O60*0.15,IF(P60="Да",2,5))))) -> 3.75 | S60: Обе категории покрыты, формат списка соблюдён. Tatar by Tubetey и озеро Кабан — реальные и корректно связаны. «Набережная Волги (улица Кремлёвская)» — путаница: Кремлёвская набережная идёт вдоль Казанки. Заведения «Аулак» и «Гавань Вилл» не подтверждаются. В тексте нерабочие ссылки вида [src_6866d6032d]. | T60: 46231
A61: 60 | B61: ru | C61: CIS | D61: Tashkent, Uzbekistan | E61: Список мест для поездки | F61: Порекомендуй места в Ташкенте для советской архитектуры, рынков и узбекской кухни. | G61: qwen/qwen3-30b-a3b-instruct-2507 | H61: geoagent v1 ( qwen3-8b) | I61: web_search(ok) | model_calls=2 tool_calls=1 grounded=true | J61: Вот рекомендации по местам в Ташкенте, которые соответствуют вашему запросу: советская архитектура, рынки и узбекская кухня. --- ### 🏛️ **Места с советской архитектурой** Ташкент — один из самых ярких примеров советского модернизма в Центральной Азии. После землетрясения 1966 года город был восстановлен с участием архитекторов со всей СССР, что привело к созданию уникального архитектурного наследия. - **Дворец Дружбы Народов** Одно из самых знаковых зданий Ташкента. Построен в 1980-х годах, сочетает в себе элементы советского модернизма и национальных узбекских мотивов. Идеально подходит для прогулок и фото. - **Национальная библиотека имени Алишера Навои** Здание в стиле советского модернизма с геометрическими формами и крупными стеклянными фасадами. Расположена в центре города, рядом с площадью Независимости. - **ЦУМ (Центральный универмаг)** Классическое советское здание с архитектурной выразительностью, построенное в 1970-х годах. Сегодня — часть торгового комплекса, но сохранило свой исторический облик. - **Набережная канала Анхор** Архитектурное пространство с элементами 70–80-х годов: скульптуры, пешеходные зоны, зелёные зоны. Отличное место для прогулок с видом на канал и город. --- ### 🛒 **Рынки** - **Рынок «Чорсу»** Один из самых известных и живых рынков Ташкента. Исторически — часть Великого шёлкового пути. Современный облик сформировался в 1980–1990-х годах: огромные купольные постройки, подземные коридоры, яркие лавки. - **Что купить**: пряности, орехи, сухофрукты, восточные сладости, лепёшки, ткани. - **Атмосфера**: шумная, живая, аутентичная. - **Как добраться**: станция метро «Чорсу» (открыта в 1989 году, прямо под рынком). --- ### 🍛 **Узбекская кухня** Попробуйте традиционные блюда в местных кафе и ресторанах, особенно вблизи рынка «Чорсу» и в центре города. - **«Chorsu Bazaar Restaurant»** Ресторан прямо на территории рынка «Чорсу». Подает блюда в традиционной обстановке: лепёшки, плов, шурпа, манты, салаты. - **Рекомендуем**: плов с бараниной, шурпа с курицей, лепёшки из печи. - **«Mehmonxona» (Гостиница)** Уютное кафе в центре Ташкента, где готовят по-настоящему домашнюю узбекскую кухню. - **Рекомендуем**: халва, чорба, шафрановый пирог. - **«Samarqand»** Ресторан с архитектурой в духе старинного узбекского дворца. Подходит для гастрономического путешествия по Узбекистану. - **Рекомендуем**: плов по-самаркандски, манты с телятиной, чай с мятой. --- ### 🗺️ **Советы по посещению** - Лучшее время для посещения рынка — утро (с 8:00 до 12:00), когда свежие продукты только поступают. - Для архитектурных прогулок — дневное время, чтобы увидеть фасады в лучшем свете. - Носите удобную обувь — рынки и старые кварталы требуют много ходьбы. --- Если хотите, я могу составить маршрут на день, включающий все эти места, или помочь с бронированием кафе/гостиницы. | K61: 5 | L61: 3 | M61: 2 | O61: 4 | P61: Да | Q61: Hallucinated place; Unsupported factual claim; Missing important category | R61: =IF(A61="","",IF(OR(E61="Маршрут на один день",E61="Планирование поездки на несколько дней"),IF(COUNT(K61:O61)<5,"",MIN(K61*0.2+L61*0.2+M61*0.25+N61*0.25+O61*0.1,IF(P61="Да",2,5))),IF(COUNT(K61:M61)+COUNT(O61)<4,"",MIN(K61*0.25+L61*0.25+M61*0.35+O61*0.15,IF(P61="Да",2,5))))) -> 2 | S61: Советская архитектура раскрыта хорошо и достоверно (Дворец Дружбы Народов, библиотека Навои, ЦУМ, Анхор). Критично: «Mehmonxona» — это узбекское слово «гостиница», выдано за название кафе; «Chorsu Bazaar Restaurant» и «Samarqand» не подтверждаются; рекомендованные блюда (халва, чорба, шафрановый пирог) не соответствуют узбекской кухне. Метро «Чорсу» открыто в 1980, а не в 1989. Рынки представлены единственным объектом. | T61: 46231
A62: 61 | B62: en | C62: Europe | D62: Budapest, Hungary | E62: Маршрут на один день | F62: Plan a one-day walking route in Budapest with architecture, river views and two cafe breaks. | G62: qwen/qwen3-30b-a3b-instruct-2507 | H62: geoagent v1 ( qwen3-8b) | I62: web_search(ok); web_search(ok); web_search(ok) | model_calls=4 tool_calls=3 grounded=true | J62: Here is a well-structured one-day walking route in Budapest that combines iconic architecture, scenic Danube River views, and two relaxing cafe breaks, based on current information: --- ### 🌆 **One-Day Walking Route in Budapest: Architecture, River Views & Cafe Breaks** **Theme:** A scenic, immersive journey through Budapest’s historic heart, blending grand architecture, panoramic river vistas, and moments of relaxation. --- #### 🕘 **Morning: Buda Castle District & Fisherman’s Bastion (8:00 AM – 11:00 AM)** - **Start at:** **Fisherman’s Bastion (Halászbástya)** - *Why:* Offers the most breathtaking panoramic view of the Danube, Parliament, and Pest skyline. Arrive early (8:00 AM) to enjoy soft morning light and fewer crowds. - *Architecture Highlight:* Neo-Romanesque towers with intricate stonework and symbolic sculptures. - *Tip:* The lower terraces are free to access and provide equally stunning views. - **Walk to:** **Buda Castle (Budavári Palota)** - A short descent from Fisherman’s Bastion. Explore the castle’s courtyards and the **Budapest History Museum** (optional, if time allows). - **Next:** **Castle Hill Funicular (Budavári Sikló)** - Ride the historic funicular down to the Pest side (10-minute ride) for a smooth transition. --- #### 🕘 **Midday: Danube Embankment & Hungarian Parliament (11:00 AM – 1:00 PM)** - **Walk along the Danube Embankment (Duna-korzó)** - Enjoy a scenic riverside stroll with views of the **Chain Bridge (Széchenyi Lánchíd)** and the city skyline. - **Stop at:** **Hungarian Parliament Building (Országház)** - *Architecture Highlight:* One of the largest and most beautiful Neo-Gothic buildings in the world. - *Important:* **Tours are required** and must be booked in advance via the official website: [parlament.hu](https://www.parlament.hu). - Tours start at 8:00 AM (best for fewer crowds). - Duration: ~45–60 minutes. - Tickets: ~$49 (book via GetYourGuide or official site). - *Pro Tip:* After the tour, walk south along the river to the **Shoes on the Danube Memorial** (15-minute walk), a poignant tribute to Holocaust victims. --- #### ☕ **First Cafe Break: Dunapark Café (1:00 PM – 2:00 PM)** - **Location:** 38–40 Pozsonyi Road, Újlipótváros (Pest side), near Szent István Park. - **Why:** A historic Art Deco café with elegant interiors, expansive park views, and a rich architectural legacy (built 1935–1937). - **Experience:** Sip coffee or enjoy a light lunch in a beautifully restored space that blends modern and vintage charm. - **Access:** Easy to reach from the Parliament via a 15-minute walk through the park. --- #### 🕘 **Afternoon: Pest’s Historic Heart & River Promenade (2:00 PM – 5:00 PM)** - **Walk to:** **Liberty Square (Szabadság tér)** - A central, open green space with monuments, fountains, and benches — perfect for a relaxed pause. - **Continue along:** **Andrássy Avenue** - A UNESCO World Heritage site lined with grand buildings, shops, and cafes. Walk toward **Heroes’ Square (Hősök tere)**. - **Final River View Stop:** **Vasmacska Terrace (Vasmacska Terasz)** - **Location:** 1 Fékező Street, Budafok (on the Danube bank). - **Why:** A unique floating terrace above the Danube, offering intimate views of the river, passing boats, and golden sunsets. - **Experience:** Ideal for a late afternoon coffee or drink. The atmosphere is magical, especially in the evening. - **Note:** Open daily; reservations recommended during peak season. --- #### 🌇 **Evening: Sunset & Final Views (5:00 PM – 7:00 PM)** - **Walk back along the Danube Embankment** toward the Chain Bridge. - **End at:** **Chain Bridge (Széchenyi Lánchíd)** - Return at dusk to witness the bridge illuminated — a truly unforgettable sight. - **Optional:** Enjoy a drink at a nearby ruin bar (e.g., Szimpla Kert) if you’d like to extend the evening. --- ### ✅ **Summary of Key Features** | Feature | Included | |--------|----------| | Iconic Architecture | Fisherman’s Bastion, Parliament, Dunapark, Andrássy Avenue | | Danube River Views | Throughout the route, especially at Fisherman’s Bastion, Chain Bridge, and Vasmacska Terrace | | Cafe Breaks | Dunapark Café (midday), Vasmacska Terrace (afternoon/evening) | | Walking Distance | ~10–12 km (moderate pace, with breaks) | | Best Time to Visit | Early morning (to avoid crowds), late afternoon for golden light | --- ### 📌 **Tips for Your Visit** - **Book Parliament tours in advance** — especially in summer. - **Wear comfortable shoes** — the route involves cobblestones and hills. - **Bring a light jacket** — evenings by the river can be cool. - **Use public transport or walk** — Budapest is very walkable, and the Danube is central to the route. Enjoy your unforgettable day in Budapest! 🇭🇺✨ | K62: 4 | L62: 4 | M62: 3 | N62: 2 | O62: 5 | P62: Нет | Q62: Bad route logic; Wrong location within city | R62: =IF(A62="","",IF(OR(E62="Маршрут на один день",E62="Планирование поездки на несколько дней"),IF(COUNT(K62:O62)<5,"",MIN(K62*0.2+L62*0.2+M62*0.25+N62*0.25+O62*0.1,IF(P62="Да",2,5))),IF(COUNT(K62:M62)+COUNT(O62)<4,"",MIN(K62*0.25+L62*0.25+M62*0.35+O62*0.15,IF(P62="Да",2,5))))) -> 3.35 | S62: Все ограничения формально учтены (пешком, архитектура, виды, две кофе-паузы). Маршрут ломается в финале: после площади Героев предложена терраса Vasmacska в Будафоке (~10 км от центра, реальный ресторан находится в Обуде), а затем пеший возврат к Цепному мосту — нереализуемо. Фуникулёр Будайской крепости спускает на будайскую сторону, а не в Пешт, и едет ~1,5 мин, а не 10. Заявленные 10–12 км сильно занижены. | T62: 46231
A63: 62 | B63: en | C63: Europe | D63: Prague, Czechia | E63: Маршрут на один день | F63: Plan a relaxed one-day route through Prague Old Town with historical sights and lunch. | G63: qwen/qwen3-30b-a3b-instruct-2507 | H63: geoagent v1 ( qwen3-8b) | I63: web_search(ok); web_search(ok); web_search(ok) | model_calls=4 tool_calls=3 grounded=true | J63: ### **Relaxed One-Day Route Through Prague Old Town: Historical Sights & Lunch** This thoughtfully curated one-day itinerary blends Prague’s most iconic historical landmarks with a leisurely pace and a memorable lunch in a historic setting. The route is designed for walking, with logical flow and time for reflection, photography, and cultural immersion. --- ### **Morning: Arrival & Old Town Square Exploration (9:00 AM – 11:30 AM)** **1. Start at Old Town Square (Staroměstské náměstí)** - **Highlights**: - **Astronomical Clock (Orloj)**: Witness the hourly show (9:00–23:00) where the 12 apostles parade through the clock’s windows. Arrive 5 minutes early for the best view. - **Jan Hus Memorial**: A towering bronze statue honoring the 15th-century religious reformer, unveiled in 1915. - **Crosses on the Pavement**: Markers where 27 Bohemian leaders were executed after the Battle of White Mountain (1621). - **Old Town Hall Tower**: Climb the 438 steps (optional) for panoramic views of the city. **2. Walk to the Powder Tower (11:30 AM)** - **Historical Note**: Built in 1475 as one of the original 13 city gates. Once used to store gunpowder, it marks the beginning of the Royal Route used by Bohemian kings during coronations. - **Tip**: Admire the Gothic architecture and the view toward Charles Bridge. --- ### **Midday: Lunch in a Historic Ambiance (12:00 PM – 1:30 PM)** **3. Lunch at Restaurant Století (Karolíny Světlé 21/320, Prague 1)** - **Why it fits**: Located in a former stable complex, the restaurant preserves original architectural features like niches and a 1858 wooden snake (former pharmacy sign) hanging from the ceiling. - **Cuisine**: Authentic Czech dishes with a modern twist — try *goulash*, *svíčková*, or *trdelník* for dessert. - **Ambiance**: Earthy tones, period decor, and a cozy fireplace. Ideal for a relaxed, cultural lunch. - **Hours**: 11:30 AM – 10:00 PM (open daily). - **Pro Tip**: Request a table near the window for views of the nearby Rotunda of St. Cross. --- ### **Afternoon: Charles Bridge & Malá Strana (2:00 PM – 5:00 PM)** **4. Cross Charles Bridge (2:00 PM)** - **Historical Note**: Built between 1357–1402, this iconic stone bridge connects Old Town with Malá Strana. - **Statues**: 30 Baroque statues line the bridge, including St. John of Nepomuk (a lucky charm for travelers). - **Views**: Enjoy sweeping vistas of the Vltava River, Prague Castle, and the city skyline. **5. Explore Malá Strana (Lesser Town)** - **Highlights**: - **St. Nicholas Church (Kostel sv. Mikuláše)**: A stunning Baroque masterpiece with a grand interior and panoramic views from the dome. - **Prague Castle Complex**: Walk through the castle grounds (optional entry to St. Vitus Cathedral or the Royal Garden). - **Golden Lane**: A charming row of tiny houses, once home to castle guards and alchemists. --- ### **Optional Evening (5:30 PM Onward)** - **Wenceslas Square (Václavské náměstí)**: A grand boulevard lined with shops, cafes, and 20th-century architecture. - **Sunset View**: Return to Charles Bridge for a peaceful evening walk as the city lights up. --- ### **Summary of Key Details** | Time | Activity | Location | |------|--------|--------| | 9:00–11:30 AM | Old Town Square & Astronomical Clock | Staroměstské náměstí | | 11:30 AM | Powder Tower | Eastern entrance to Old Town | | 12:00–1:30 PM | Lunch | Restaurant Století | | 2:00–5:00 PM | Charles Bridge & Malá Strana | Across the Vltava River | | 5:30 PM+ | Optional: Wenceslas Square | Václavské náměstí | --- ### **Tips for a Relaxed Experience** - Wear comfortable walking shoes. - Bring a light jacket — mornings and evenings can be cool. - Use the **interactive walking tour map** (available on [Nomads Travel Guide](https://www.nomads-travel-guide.com)) to track your route. - Avoid peak hours (11:00–13:00) at the Astronomical Clock to reduce crowds. Enjoy your journey through Prague’s timeless heart! 🏰✨ | K63: 4 | L63: 4 | M63: 4 | N63: 3 | O63: 5 | P63: Нет | Q63: Ignored constraints; Bad route logic | R63: =IF(A63="","",IF(OR(E63="Маршрут на один день",E63="Планирование поездки на несколько дней"),IF(COUNT(K63:O63)<5,"",MIN(K63*0.2+L63*0.2+M63*0.25+N63*0.25+O63*0.1,IF(P63="Да",2,5))),IF(COUNT(K63:M63)+COUNT(O63)<4,"",MIN(K63*0.25+L63*0.25+M63*0.35+O63*0.15,IF(P63="Да",2,5))))) -> 3.85 | S63: Факты по Староместской площади, Пороховой башне и Карлову мосту точны (1475, 27 казнённых, часы Орлоя). Restaurant Století реален и уместен. Но запрос был про спокойный день по Старому городу, а план уводит в Малую Страну, к Пражскому Граду и Золотой улочке — подъём и заметный выход за рамки; Пороховая башня даёт крюк на восток перед обедом на западе. 438 ступеней Староместской ратуши не подтверждаются. | T63: 46231
A64: 63 | B64: en | C64: Europe | D64: Paris, France | E64: Маршрут на один день | F64: Create a one-day route in Paris focused on Impressionist art and a walk along the Seine. | G64: qwen/qwen3-30b-a3b-instruct-2507 | H64: geoagent v1 ( qwen3-8b) | I64: web_search(ok); web_search(ok); web_search(ok) | model_calls=4 tool_calls=3 grounded=true | J64: Here is a well-structured one-day route in Paris focused on Impressionist art and a scenic walk along the Seine River: --- ### 🌸 **One-Day Impressionist Art & Seine River Route in Paris** **Theme:** Art, history, and riverside charm **Duration:** 1 full day (approx. 10 hours) **Best time to visit:** Spring or early autumn (pleasant weather, fewer crowds) **Transport:** Walking + metro (consider a Paris Visite pass for zones 1–3) --- #### 🕘 **Morning: Musée d'Orsay – Heart of Impressionism** - **Time:** 9:00 AM – 11:30 AM - **Location:** Esplanade Valéry Giscard d'Estaing, 75007 Paris - **Highlights:** - Explore the world’s most comprehensive collection of Impressionist and Post-Impressionist masterpieces. - Must-see works: Monet’s *Water Lilies*, Van Gogh’s *Starry Night Over the Rhône*, Renoir’s *Bal du Moulin de la Galette*, and Degas’ *The Dance Class*. - **Tips:** - **Book timed tickets online in advance** to avoid queues (€16 online, €17 at the door). - The museum is closed on Mondays. - Allow 2 hours to enjoy the highlights without rushing. --- #### 🚶‍♂️ **Mid-Morning: Seine River Walk & Pont des Arts** - **Time:** 11:45 AM – 12:30 PM - **Route:** From Musée d'Orsay → Pont des Arts → Île de la Cité - **Highlights:** - Stroll along the Seine’s Left Bank, passing historic bridges and riverside cafés. - Walk across the **Pont des Arts**, a romantic pedestrian bridge with views of the Louvre, Notre-Dame, and the Eiffel Tower in the distance. - Take photos at the bridge’s famous “love locks” (note: some locks have been removed; the area is now more open and scenic). --- #### 🍽️ **Lunch: Saint-Germain-des-Prés Quarter** - **Time:** 12:45 PM – 1:45 PM - **Location:** Rue de Seine or Place Saint-Germain-des-Prés - **Suggestions:** - **Café de Flore** – Historic café where philosophers like Sartre and de Beauvoir once met. - **Le Procope** – Paris’s oldest café, dating back to 1686. - Try a classic French bistro meal: croque-monsieur, ratatouille, or a fresh salad with goat cheese. --- #### 🕘 **Afternoon: Saint-Germain-des-Prés & Saint-Sulpice** - **Time:** 2:00 PM – 4:00 PM - **Highlights:** - Explore the **Church of Saint-Germain-des-Prés** (oldest church in Paris, founded in 543 AD), with its medieval frescoes and tranquil cloister. - Walk through the **Rue de Seine**, lined with art galleries and bookshops. - Visit **Saint-Sulpice**, home to Delacroix’s stunning murals in the Chapel of the Holy Angels and a magnificent Cavaillé-Coll organ. --- #### 🛥️ **Late Afternoon: Seine River Cruise (Vedettes du Pont Neuf)** - **Time:** 5:30 PM – 6:30 PM - **Departure Point:** Square du Vert Galant, Île de la Cité (at the foot of Pont Neuf) - **Duration:** 1 hour - **Highlights:** - Enjoy a scenic, open-top cruise passing iconic landmarks: Louvre, Musée d’Orsay, Eiffel Tower, and Notre-Dame. - Live commentary in English and French. - **Tickets:** - **Time-stamped e-ticket (recommended):** €15 (online), €17 (on-site) - **Open ticket (flexible):** €16 (online only), valid for 1 year - **Pro tip:** Book online in advance to secure your spot and avoid lines. --- #### 🌆 **Evening: Sunset Views & Dinner** - **Time:** 7:00 PM onwards - **Suggested Spot:** - **Pont de l’Archevêché** or **Pont Neuf** for golden-hour views of the Seine and city lights. - Dinner at a riverside restaurant like **Le Jules Verne** (in the Eiffel Tower) or **Bistrot Paul Bert** (cozy, authentic Parisian bistro). --- ### ✅ **Summary of Key Info** | Activity | Time | Cost (approx.) | |--------|------|----------------| | Musée d'Orsay (ticket) | 9:00–11:30 AM | €16 (online) | | Seine walk & Pont des Arts | 11:45 AM – 12:30 PM | Free | | Lunch | 12:45–1:45 PM | €20–30 | | Saint-Germain & Saint-Sulpice visit | 2:00–4:00 PM | Free | | Seine River Cruise | 5:30–6:30 PM | €15 (online) | | Dinner | 7:00 PM onwards | €30–50 | **Total estimated cost (excluding transport):** €80–100 per person **Transport:** Consider a Paris Visite pass (€13 for 1 day, zones 1–3) for metro, RER, and bus access. --- This route combines art, history, and the romantic charm of the Seine — perfect for a memorable day in Paris. 🎨🌉 | K64: 4 | L64: 4 | M64: 4 | N64: 4 | O64: 5 | P64: Нет | Q64: Missing important category; Unsupported factual claim | R64: =IF(A64="","",IF(OR(E64="Маршрут на один день",E64="Планирование поездки на несколько дней"),IF(COUNT(K64:O64)<5,"",MIN(K64*0.2+L64*0.2+M64*0.25+N64*0.25+O64*0.1,IF(P64="Да",2,5))),IF(COUNT(K64:M64)+COUNT(O64)<4,"",MIN(K64*0.25+L64*0.25+M64*0.35+O64*0.15,IF(P64="Да",2,5))))) -> 4.1 | S64: География безупречна: Орсе → Пон-де-Ар → Сен-Жермен → Сите → круиз от Вер-Галан. Факты по Орсе, Сен-Сюльпис и Сен-Жермен-де-Пре верны, цены правдоподобны. Для дня «про импрессионизм» пропущены Оранжери и Мармоттан-Моне — ключевые площадки. «Кувшинки» Моне заявлены как хедлайнер Орсе, хотя основная серия в Оранжери. Пробел в расписании 16:00–17:30. | T64: 46231
A65: 64 | B65: en | C65: Europe | D65: Rome, Italy | E65: Маршрут на один день | F65: Plan a one-day route in Rome with ancient landmarks, one local lunch and no more than 8 km of walking. | G65: qwen/qwen3-30b-a3b-instruct-2507 | H65: geoagent v1 ( qwen3-8b) | I65: web_search(ok); web_search(ok); web_search(ok) | model_calls=4 tool_calls=3 grounded=true | J65: ### One-Day Rome Itinerary: Ancient Landmarks & Local Lunch (Under 8 km Walking) This carefully planned one-day route in Rome focuses on iconic ancient landmarks, a memorable local lunch, and a total walking distance of **under 8 km**, ensuring a comfortable and immersive experience. --- #### 🗺️ **Route Overview** 1. **Start: Pantheon** (9:00 AM) 2. **Walk to: Piazza Navona & Campo de’ Fiori** (10:00 AM) 3. **Lunch: Ristorante Pancrazio** (12:00 PM) 4. **Walk to: Roman Forum & Palatine Hill** (1:30 PM) 5. **Walk to: Colosseum** (2:30 PM) 6. **Optional: Appian Way (if time & energy allow)** (4:00 PM) 7. **End: Return to Pantheon or nearby metro station** (5:00 PM) --- ### 🏛️ **Detailed Itinerary** #### 1. **Pantheon (9:00 AM)** - **Why visit?** One of the best-preserved ancient Roman buildings, with a massive dome and stunning interior. - **Walking distance:** 0 km (start point). - **Tip:** Arrive early to avoid crowds. Entry is free (€5 optional donation for audio guide). - **Distance from next stop:** ~1.2 km (15-minute walk). #### 2. **Piazza Navona & Campo de’ Fiori (10:00 AM)** - **Why visit?** Baroque square with fountains, street art, and vibrant atmosphere. Campo de’ Fiori is a historic market square. - **Walk:** Follow Via del Pantheon → Via del Corso → Piazza Navona → Piazza Campo de’ Fiori. - **Distance:** ~1.2 km (15 minutes). - **Note:** Great for photos and a quick coffee break. #### 3. **Lunch: Ristorante Pancrazio (12:00 PM)** - **Location:** Piazza del Biscione, 92, 00186 Roma RM (right on the ruins of the **Theater of Pompey**, where Julius Caesar was assassinated). - **Why visit?** A historic restaurant since 1922, built on ancient Roman ruins. Offers authentic Roman cuisine with a unique archaeological setting. - **Must-try dishes:** Carbonara, Cacio e Pepe, Saltimbocca alla Romana. - **Duration:** 1.5 hours (lunch + relaxation). - **Distance from next stop:** ~1.5 km (20-minute walk). #### 4. **Roman Forum & Palatine Hill (1:30 PM)** - **Why visit?** The political and religious heart of ancient Rome. Walk through the ruins of temples, basilicas, and imperial palaces. - **Entry:** Combined ticket (€18) includes Palatine Hill. Pre-book online to skip lines. - **Walk:** From Ristorante Pancrazio → Via dei Fori Imperiali → Roman Forum. - **Distance:** ~1.5 km (20 minutes). - **Tip:** Start at the Roman Forum, then climb to Palatine Hill for panoramic views. #### 5. **Colosseum (2:30 PM)** - **Why visit?** The world’s most famous amphitheater, symbol of ancient Rome’s engineering and spectacle. - **Entry:** Pre-booked ticket (€25 for full access, including hypogeum and upper tiers). - **Walk:** Via dei Fori Imperiali → Colosseum (1.5 km, 20 minutes). - **Duration:** 60–90 minutes. - **Tip:** Consider a guided tour for deeper historical context. #### 6. **Optional: Appian Way (Via Appia Antica) (4:00 PM)** - **Why visit?** Ancient Roman road lined with tombs, catacombs, and ruins. Peaceful and scenic. - **Distance from Colosseum:** ~2.5 km (30–40 minutes walk or 10-minute metro ride). - **Note:** Only if you have extra energy and time. Otherwise, return to the city center. --- ### 🚶‍♂️ **Total Walking Distance: ~7.5 km** - Pantheon → Piazza Navona: 1.2 km - Piazza Navona → Campo de’ Fiori: 0.5 km - Campo de’ Fiori → Ristorante Pancrazio: 0.5 km - Ristorante Pancrazio → Roman Forum: 1.5 km - Roman Forum → Colosseum: 1.5 km - Colosseum → Appian Way (optional): 2.5 km (not included in base total) ✅ **All walking stays under 8 km** — ideal for a comfortable day. --- ### 🍝 **Lunch Recommendation** - **Ristorante Pancrazio** (Piazza del Biscione, 92) - **Cuisine:** Authentic Roman - **Atmosphere:** Historic, archaeological site - **Reservation:** Recommended (especially on weekends) - **Contact:** +39 06 6861246 | ristorantepancrazio@gmail.com --- ### 📌 **Tips for a Smooth Day** - **Wear comfortable shoes** — cobblestones and uneven terrain. - **Bring water and snacks** — Rome is hot in summer. - **Pre-book tickets** for Colosseum and Roman Forum to avoid queues. - **Use public transport** (metro or bus) if tired — the Colosseum is near Metro Line A (Colosseo station). --- Enjoy your journey through ancient Rome — where every step echoes with history! 🏛️🇮🇹 | K65: 5 | L65: 5 | M65: 3 | N65: 4 | O65: 4 | P65: Да | Q65: Unsupported factual claim; Bad route logic | R65: =IF(A65="","",IF(OR(E65="Маршрут на один день",E65="Планирование поездки на несколько дней"),IF(COUNT(K65:O65)<5,"",MIN(K65*0.2+L65*0.2+M65*0.25+N65*0.25+O65*0.1,IF(P65="Да",2,5))),IF(COUNT(K65:M65)+COUNT(O65)<4,"",MIN(K65*0.25+L65*0.25+M65*0.35+O65*0.15,IF(P65="Да",2,5))))) -> 2 | S65: Порядок точек компактный и логичный, ограничение до 8 км соблюдено, обед в Ristorante Pancrazio на руинах театра Помпея — реальное и уместное место. Критично: вход в Пантеон объявлен бесплатным, фактически платный (€5 с 2023 года). Арифметика расстояний не сходится: Пантеон → Пьяцца Навона указано 1,2 км при реальных ~350 м, сумма по таблице даёт 5,2 км против заявленных 7,5. | T65: 46231
A66: 65 | B66: en | C66: Europe | D66: Lisbon, Portugal | E66: Маршрут на один день | F66: Create a one-day route in Lisbon with viewpoints and historic neighbourhoods, avoiding very steep walks where possible. | G66: qwen/qwen3-30b-a3b-instruct-2507 | H66: geoagent v1 ( qwen3-8b) | I66: web_search(ok); web_search(ok); web_search(ok) | model_calls=4 tool_calls=3 grounded=true | J66: Here is a thoughtfully designed one-day route in Lisbon that prioritizes **viewpoints**, **historic neighborhoods**, and **minimal steep walking**, while incorporating efficient public transport and scenic, flat access points. --- ### 🌇 **One-Day Lisbon Itinerary: Viewpoints & Historic Neighborhoods (Low-Effort Walking)** **Theme**: A relaxed, scenic journey through Lisbon’s heart, blending history, riverside views, and iconic spots — all with minimal uphill effort. --- #### 🕘 **Morning: Baixa & Praça do Comércio (Flat & Central)** - **Start at 9:00 AM** – Begin in **Baixa**, Lisbon’s flat, grid-like downtown. - **Praça do Comércio (Commerce Square)**: - **Why go**: A grand neoclassical square opening directly to the Tagus River. It’s flat, wheelchair accessible, and offers panoramic views of the river and the 25 de Abril Bridge. - **Highlights**: The **Arco da Rua Augusta** (archway) at the northern end — climb it for a 360° view of the city and river. - **Tip**: Walk along the riverfront promenade (Cais do Sodré side) — completely flat and scenic. - **Optional**: Grab a coffee at **Café A Brasileira** (famous for its literary history) or a pastel de nata at **Pastéis de Belém** (just a 10-minute walk from Praça do Comércio). > ✅ **Walking**: Flat, wide sidewalks. Ideal for strollers and seniors. --- #### 🕘 **Mid-Morning: Rossio & Chiado (Historic Heart)** - **Walk to Rossio Square (10 min)** – A short, flat walk through **Rua Augusta**, a pedestrianized street with shops and cafes. - **Rossio Square**: - **Why go**: The city’s historic center, surrounded by arcades, fountains, and the **Teatro Nacional de São Carlos**. - **Viewpoint**: The **Elevador de Santa Justa** (Santa Justa Lift) is nearby — though it’s a climb, it’s optional. You can enjoy the view from the ground level. - **Chiado District**: - Stroll through **Rua Garrett** and **Largo do Chiado**. - Visit **Igreja de São Roque** (a stunning baroque church) and browse bookshops and boutiques. > ✅ **Walking**: Flat and compact. Use the **Navegante card** (€0.50) or contactless card for metro/bus access. --- #### 🕘 **Early Afternoon: Miradouro de Santa Catarina (Adamastor) – Easy Viewpoint** - **Take a short Bolt ride or bus (e.g., 737)** from Chiado to **Cais do Sodré** (10–15 min). - **Walk to Miradouro de Santa Catarina (Adamastor)**: - **Why go**: One of Lisbon’s most accessible and popular viewpoints. Offers a stunning, unobstructed view of the **25 de Abril Bridge**, **Tagus River**, and the city skyline. - **Access**: The path from Cais do Sodré is mostly flat and gentle. The viewpoint itself is at a moderate elevation but requires no steep climb. - **Best time**: Arrive by 4:30 PM for golden hour and sunset. - **Relax**: Enjoy a drink or snack at one of the terrace bars (e.g., **Café do Mar** or **Bairro Alto Bar**). > ✅ **Walking**: Minimal effort. Ideal for all fitness levels. --- #### 🕘 **Late Afternoon: Riverfront Walk & Return to Baixa** - **Walk along the Tagus Riverfront** (from Miradouro de Santa Catarina back toward Baixa). - **Route**: Follow the **Parque das Nações** path or the **Cais do Sodré waterfront**. - **Scenery**: Views of the **Lisbon Oceanarium**, **Cristo Rei statue**, and passing ferries. - **Return to Baixa** via **Praça do Comércio** or **Rossio**. - **Optional**: Take **Tram 28** (if operating) for a nostalgic ride through Alfama’s narrow streets — but note: it’s not recommended for those avoiding steep walks. > ✅ **Walking**: Flat and scenic. Perfect for a relaxed end to the day. --- ### 🚇 **Transport Tips for Low-Effort Travel** - **Use the Navegante Ocasional card** (€0.50) or **contactless bank card** for metro, buses, and ferries. - **Avoid funiculars and elevators** (e.g., Santa Justa, Graça) — they are currently suspended or require steep access. - **Use Bolt** for short rides between districts (e.g., Chiado to Cais do Sodré) — affordable and avoids uphill walks. --- ### 📌 **Summary: Key Features** | Feature | Status | |--------|--------| | Flat walking routes | ✅ Yes (Baixa, Praça do Comércio, riverfront) | | Accessible viewpoints | ✅ Miradouro de Santa Catarina, Praça do Comércio | | Historic neighborhoods | ✅ Baixa, Chiado, Rossio, Cais do Sodré | | Minimal steep walking | ✅ Prioritized throughout | | Public transport | ✅ Metro, buses, Bolt, contactless cards | --- ### 🌟 **Final Tip** Lisbon is famously hilly — but with smart planning, you can enjoy its beauty without the strain. This itinerary focuses on **flat access**, **scenic views**, and **historic charm**, making it perfect for families, seniors, or anyone who wants to savor the city without overexertion. Enjoy your day in Lisbon! 🇵🇹✨ | K66: 4 | L66: 3 | M66: 2 | N66: 2 | O66: 4 | P66: Да | Q66: Wrong location within city; Ignored constraints; Bad route logic; Unsupported factual claim | R66: =IF(A66="","",IF(OR(E66="Маршрут на один день",E66="Планирование поездки на несколько дней"),IF(COUNT(K66:O66)<5,"",MIN(K66*0.2+L66*0.2+M66*0.25+N66*0.25+O66*0.1,IF(P66="Да",2,5))),IF(COUNT(K66:M66)+COUNT(O66)<4,"",MIN(K66*0.25+L66*0.25+M66*0.35+O66*0.15,IF(P66="Да",2,5))))) -> 2 | S66: Ключевое ограничение — избегать подъёмов — нарушено: Мирадору Санта-Катарина подан как «почти плоский», хотя подъём заметный. Критично по географии: Pastéis de Belém заявлены в 10 минутах ходьбы от Праса-ду-Комерсиу (реально ~6 км), набережная продолжена «путём Парка Наций» с видом на Океанариум (это другой конец города). Театр на Росиу назван Сан-Карлуш вместо Д. Марии II. Утверждение о приостановке Санта-Жушты не подтверждается. | T66: 46231
A67: 66 | B67: en | C67: Europe | D67: Amsterdam, Netherlands | E67: Маршрут на один день | F67: Plan a one-day route in Amsterdam with canals, a museum and a quiet park. | G67: qwen/qwen3-30b-a3b-instruct-2507 | H67: geoagent v1 ( qwen3-8b) | I67: web_search(ok); web_search(ok); web_search(ok) | model_calls=4 tool_calls=3 grounded=true | J67: Here is a well-structured one-day itinerary for Amsterdam, designed to include iconic canals, a world-class museum, and a peaceful park—perfect for a memorable and balanced day: --- ### 🌿 **One-Day Amsterdam Itinerary: Canals, Art, and Quiet Green Spaces** #### 🕘 **Morning: Explore the Canal Belt & Start with the Rijksmuseum** - **08:30–09:00** – Arrive at **Rijksmuseum** (open 09:00 daily). *Pro tip:* Enter **at opening time (09:00)** to enjoy the Gallery of Honour with minimal crowds. This is the best time to view masterpieces like *The Night Watch* and Vermeer’s paintings in peace. - **09:00–11:30** – Explore the Rijksmuseum. Focus on the Golden Age paintings, Dutch history, and the stunning architecture. - **11:30–12:00** – Walk across **Museumplein** (3–5 minutes) to the **Van Gogh Museum**. *Note:* Pre-book a time slot (e.g., 12:00–14:00) to avoid queues. The Van Gogh Museum is best visited in the early afternoon or on Friday evenings for a calmer experience. #### 🕘 **Afternoon: Wander the Jordaan & Enjoy a Canal Cruise** - **12:00–14:00** – Visit the **Van Gogh Museum**. Spend time with Van Gogh’s iconic works, including *Sunflowers* and *The Bedroom*. - **14:00–15:00** – Stroll through the **Jordaan district**, a charming neighborhood with narrow canals, cobbled streets, and boutique shops. *Highlight:* Walk along **Brouwersgracht** and **Jodenbreestraat** for picturesque canal views and cozy cafés. - **15:00–16:00** – Take a **one-hour canal cruise** (board near Westerkerk or Singel canal). *Why:* A slower-paced, scenic way to appreciate Amsterdam’s unique water-based city layout. Opt for a small electric boat for a quieter, more intimate experience. #### 🕘 **Evening: Unwind in Vondelpark** - **16:30–18:00** – Head to **Vondelpark**, Amsterdam’s most beloved urban green space. *Best quiet spots:* - **West-End Pond**: Secluded water area, ideal for reading or photography. - **Outer Ring of the Rosarium**: Peaceful path around the rose gardens (best in spring). - **Tree Tunnel Path**: A magical green canopy walkway in the south loop. - **Sunset Terrace Lookout**: Perfect for golden-hour views behind the Vondelpark Pavilion. - **18:00–19:00** – Relax with a drink or light dinner at a café near the park (e.g., **Café de Pijp** or **Groot Melkhuis**). --- ### 📌 **Key Tips for a Smooth Day** - **Book in advance:** Both the Rijksmuseum and Van Gogh Museum require **timed-entry tickets**. Book online to secure your preferred slot. - **Avoid peak crowds:** Visit museums early (before 10:00 AM) and avoid weekends if possible. - **Transport:** Use trams (lines 2, 12, or 13) or walk between locations. Amsterdam is very walkable and bike-friendly. - **Best time to visit Vondelpark:** Early morning or weekday afternoons for tranquility. --- This itinerary balances culture, history, and nature—offering a true taste of Amsterdam’s charm in just one day. Enjoy your journey through the city of canals! 🚤🎨🌳 | K67: 4 | L67: 4 | M67: 3 | N67: 4 | O67: 5 | P67: Да | Q67: Hallucinated place; Wrong location within city | R67: =IF(A67="","",IF(OR(E67="Маршрут на один день",E67="Планирование поездки на несколько дней"),IF(COUNT(K67:O67)<5,"",MIN(K67*0.2+L67*0.2+M67*0.25+N67*0.25+O67*0.1,IF(P67="Да",2,5))),IF(COUNT(K67:M67)+COUNT(O67)<4,"",MIN(K67*0.25+L67*0.25+M67*0.35+O67*0.15,IF(P67="Да",2,5))))) -> 2 | S67: Каналы, музей и парк покрыты, тайминг реалистичный, Рейксмузеум и Ван Гог реальны. Критично: «тихие места» Вондельпарка — West-End Pond, Outer Ring of the Rosarium, Tree Tunnel Path, Sunset Terrace Lookout — выдуманные названия. Jodenbreestraat отнесена к Йордану (это Еврейский квартал, ~2 км восточнее), Café de Pijp — в Де Пейпе, а не у парка. Просили один музей — запланировано два. | T67: 46231
A68: 67 | B68: en | C68: Europe | D68: Berlin, Germany | E68: Маршрут на один день | F68: Plan a one-day route in Berlin about twentieth-century history, with time for lunch. | G68: qwen/qwen3-30b-a3b-instruct-2507 | H68: geoagent v1 ( qwen3-8b) | I68: web_search(ok); web_search(ok); web_search(ok) | model_calls=4 tool_calls=3 grounded=true | J68: Here is a well-structured one-day route in Berlin focused on 20th-century history, including time for lunch at highly rated nearby restaurants: --- ### 🗓️ **One-Day Route in Berlin: 20th-Century History & Lunch** **Theme:** Explore the key chapters of 20th-century Berlin — from Nazi terror and Cold War division to the fall of the Wall and reunification. --- #### 🕘 **Morning: Topography of Terror & Reichstag (9:00 AM – 12:00 PM)** - **📍 Topography of Terror (Niederkirchnerstraße 8)** - **Why visit?** Located on the former site of the Gestapo and SS headquarters, this documentation center offers a powerful, immersive look at Nazi crimes from 1933 to 1945. - **Highlights:** Preserved sections of the Berlin Wall, excavated torture cellars, and a permanent exhibition on the Nazi regime. - **Tip:** Free guided tours are available on weekends (check schedule in advance). - **Duration:** 1.5 hours - **📍 Reichstag Building (Platz der Republik 1)** - **Why visit?** The seat of the German Parliament, famous for its glass dome offering panoramic views of Berlin. The dome includes a permanent exhibition on the building’s history — from the 1933 fire to reunification. - **Note:** Free entry, but **book your dome visit online at least 2 weeks in advance** (slots fill quickly). - **Duration:** 1 hour (including visit to the dome and exhibition) --- #### 🕘 **Lunch (12:30 PM – 1:30 PM)** - **🍽️ Mundo Tapas – Checkpoint Charlie** - **Address:** Zimmerstraße 19, 10969 Berlin - **Rating:** 4.7/5 (1,362 reviews) - **Cuisine:** Spanish tapas with international flair (Nachos con Carne, grilled meats, paella) - **Price:** €20–30 per person (moderate) - **Ambience:** Lively, outdoor terrace with live music; great for a relaxed break - **Why here?** Just a 10-minute walk from the Reichstag and Checkpoint Charlie. Highly rated and centrally located. - **Open:** Lunch (12:00 PM – 4:00 PM), Dinner (5:00 PM – 11:00 PM) --- #### 🕘 **Afternoon: Cold War Berlin – Checkpoint Charlie & East Side Gallery (2:00 PM – 5:00 PM)** - **📍 Checkpoint Charlie (Friedrichstraße 43–45)** - **Why visit?** The most famous crossing point between East and West Berlin during the Cold War. - **Highlights:** Replica guardhouse, outdoor exhibition on escape attempts, and the **Mauermuseum (Wall Museum)** — a must-visit for stories of daring escapes (balloons, tunnels, armored cars). - **Mauermuseum Entry:** €18.50 (students €12.50) - **Tip:** Avoid paid photos with actors — they’re a tourist trap. Focus on the museum and the historical context. - **Duration:** 1.5 hours - **📍 East Side Gallery (Mühlenstraße 10, 10243 Berlin)** - **Why visit?** The longest remaining stretch of the Berlin Wall (1.3 km), now a vibrant open-air gallery with over 100 murals. - **Must-see:** The iconic “Fraternal Kiss” by Dmitri Vrubel (depicting Brezhnev and Honecker). - **Tip:** Go early to avoid large tour groups. - **Duration:** 30–45 minutes (walk the full length at a relaxed pace) --- #### 🕘 **Optional Evening (Optional): Prenzlauer Berg or Dinner at Markthalle Neun** - **Markthalle Neun (Böhmische Straße 1, 10997 Berlin)** - A historic market hall with diverse food stalls (global cuisine, organic produce, craft beer). - **Perfect for:** A casual dinner or snack after your historical tour. - **Open:** Daily, 10:00 AM – 8:00 PM --- ### 🗺️ **Summary of Key Locations & Distances** | Location | Distance from Previous | Walking Time | |--------|------------------------|--------------| | Topography of Terror → Reichstag | ~1.2 km | 15 min | | Reichstag → Mundo Tapas | ~1.5 km | 20 min | | Mundo Tapas → Checkpoint Charlie | ~1.1 km | 15 min | | Checkpoint Charlie → East Side Gallery | ~1.8 km | 25 min | --- ### ✅ **Tips for Your Visit** - Wear comfortable shoes — you’ll walk over 5 km. - Use the Berlin U-Bahn or BVG bus network for efficient travel between sites. - Download the **Berlin WelcomeCard** (if staying multiple days) for discounts on museums and public transport. - Check opening hours and booking requirements in advance (especially for Reichstag dome). --- This route offers a deep, chronological journey through Berlin’s 20th-century past — from Nazi terror to Cold War division and the triumph of reunification — all while enjoying excellent food in the heart of the city. | K68: 5 | L68: 5 | M68: 3 | N68: 4 | O68: 5 | P68: Да | Q68: Unsupported factual claim; Bad route logic | R68: =IF(A68="","",IF(OR(E68="Маршрут на один день",E68="Планирование поездки на несколько дней"),IF(COUNT(K68:O68)<5,"",MIN(K68*0.2+L68*0.2+M68*0.25+N68*0.25+O68*0.1,IF(P68="Да",2,5))),IF(COUNT(K68:M68)+COUNT(O68)<4,"",MIN(K68*0.25+L68*0.25+M68*0.35+O68*0.15,IF(P68="Да",2,5))))) -> 2 | S68: Хронология XX века выстроена отлично: Топография террора → Рейхстаг → Чекпойнт Чарли → Ист-Сайд-Галерея, обед вписан. Критично: у ресторана Mundo Tapas указан точный рейтинг «4.7/5 (1362 отзыва)» без подтверждения, адрес Markthalle Neun неверен (фактически Eisenbahnstraße 42–43). Расстояния занижены: до Ист-Сайд-Галереи указано 1,8 км вместо ~3,5 км; в тексте ресторан назван в 10 минутах от Рейхстага, а в таблице — 20. | T68: 46231
A69: 68 | B69: en | C69: Europe | D69: Barcelona, Spain | E69: Маршрут на один день | F69: Plan a one-day walking route in Barcelona with Gaudí architecture and a late lunch. | G69: qwen/qwen3-30b-a3b-instruct-2507 | H69: geoagent v1 ( qwen3-8b) | I69: web_search(ok); web_search(ok); web_search(ok) | model_calls=4 tool_calls=3 grounded=true | J69: ### One-Day Walking Route in Barcelona: Gaudí Architecture & Late Lunch This carefully curated one-day walking route in Barcelona highlights the most iconic Gaudí landmarks, with a focus on a late lunch experience. The itinerary balances architectural marvels, scenic views, and authentic dining, all within a manageable walking distance. --- #### 🗺️ **Route Overview** - **Start**: Casa Batlló (Passeig de Gràcia) - **End**: Park Güell (Gràcia) - **Total Walking Distance**: ~6 km (moderate pace) - **Best Time to Visit**: Spring or early autumn (avoid midday summer heat) - **Key Tip**: Book tickets in advance for Sagrada Família and Park Güell to avoid long queues. --- ### 🕘 **Detailed Itinerary** | Time | Location | Duration | Highlights & Notes | |------|--------|----------|-------------------| | **09:00** | **Casa Batlló** (Passeig de Gràcia) | 90 min | Explore Gaudí’s masterpiece with its undulating façade, dragon-scale roof, and surreal interior. Consider the AR experience for deeper insight. | | **10:45** | **La Pedrera (Casa Milà)** (Passeig de Gràcia) | 75 min | Walk 5 minutes from Casa Batlló. Marvel at the wave-like stone façade, innovative free-plan interior, and rooftop sculptures. | | **12:30** | **Lunch: Kokcha – Restaurante Sagrada Família** (Carrer de la Marina, 228) | 60 min | **Late lunch option**. Just a 10-minute walk from La Pedrera. Enjoy authentic Mediterranean cuisine with a stunning view of Sagrada Família. Ideal for a relaxed, scenic meal. | | **14:00** | **Sagrada Família** (Carrer de Mallorca, 401) | 90 min | Take Metro L2 (3 min) or walk (20 min). Visit the Passion and Nativity façades. The afternoon light enhances the stained glass. Book tower access in advance if desired. | | **16:00** | **Park Güell** (Carrer d'Olot, 21) | 90 min | Take Metro L3 (15 min) or a scenic 20-minute walk through Gràcia. Explore the mosaic-covered gardens, the iconic dragon fountain, and enjoy panoramic views of Barcelona. | | **17:30** | **La Torreta del Parc Güell** (Carrer d'Olot, 21) | 30–45 min (optional) | Enjoy a coffee, snack, or light dessert on the terrace. The views of the park and city are unforgettable. | --- ### 🍽️ **Late Lunch & Dining Recommendations** - **Kokcha (Near Sagrada Família)** - **Why**: Offers a perfect blend of Mediterranean flavors and a direct view of Sagrada Família. Open from 10:00 AM, ideal for late lunch. - **Must-Try**: Seafood paella or grilled fish with local wine. - **La Torreta del Parc Güell (Inside Park Güell)** - **Why**: A peaceful, authentic spot with a relaxed vibe. Open daily until 8:00 PM. - **Must-Try**: Lemon meringue pie (made by the owner’s mother) or a simple sandwich with local cheese. - **La Terrasseta del Lesseps (Gràcia)** - **Why**: A green oasis near Park Güell, perfect for a post-park coffee or light meal. Great for tapas and a relaxed atmosphere. --- ### 📌 **Practical Tips** - **Transport**: Use Metro (L2, L3) for efficient travel between major sites. - **Tickets**: Book **Sagrada Família** and **Park Güell** online in advance. - **Comfort**: Wear comfortable walking shoes and bring water. - **Timing**: Lunch is typically served from 2:00 PM onward in Barcelona—this itinerary respects local customs. --- This route offers a seamless journey through Gaudí’s genius, combining architectural wonder, scenic beauty, and authentic Catalan cuisine—perfect for a memorable day in Barcelona. | K69: 3 | L69: 4 | M69: 3 | N69: 3 | O69: 4 | P69: Нет | Q69: Ignored constraints; Bad route logic | R69: =IF(A69="","",IF(OR(E69="Маршрут на один день",E69="Планирование поездки на несколько дней"),IF(COUNT(K69:O69)<5,"",MIN(K69*0.2+L69*0.2+M69*0.25+N69*0.25+O69*0.1,IF(P69="Да",2,5))),IF(COUNT(K69:M69)+COUNT(O69)<4,"",MIN(K69*0.25+L69*0.25+M69*0.35+O69*0.15,IF(P69="Да",2,5))))) -> 3.3 | S69: Объекты Гауди реальные, порядок Пасеч-де-Грасия → Саграда → Парк Гуэль географически верный. Но ограничение «late lunch» проигнорировано: обед поставлен на 12:30, при этом в советах сказано, что в Барселоне обедают с 14:00 — прямое противоречие. Логика ломается: обед у Саграды Фамилии в 12:30, а переезд к Саграде — только в 14:00. Заявлено 10 минут от Ла-Педреры до Kokcha при реальных ~20. Kokcha и La Torreta не подтверждаются. | T69: 46231
A70: 69 | B70: en | C70: Europe | D70: Vienna, Austria | E70: Маршрут на один день | F70: Create a calm one-day route in Vienna for my parents, with museums and little walking. | G70: qwen/qwen3-30b-a3b-instruct-2507 | H70: geoagent v1 ( qwen3-8b) | I70: web_search(ok); web_search(ok); web_search(ok) | model_calls=4 tool_calls=3 grounded=true | J70: Here is a calm, senior-friendly one-day route in Vienna designed for your parents, focusing on museums with minimal walking, comfortable pacing, and relaxing stops at elegant cafés: --- ### 🌿 **Calm One-Day Itinerary in Vienna for Seniors** *Focus: Museums, minimal walking, comfort, and relaxation* --- #### 🕘 **8:30 AM – Breakfast at Café Landtmann (Innere Stadt)** - **Why**: One of Vienna’s most iconic cafés, located just steps from St. Stephen’s Cathedral. Elegant, historic, and known for its warm service and classic Austrian pastries. - **Highlights**: Try the *Sachertorte* or a warm *Kaiserschmarrn* with fruit compote. - **Accessibility**: Fully accessible, with elevators and spacious seating. - **Location**: Herrengasse 14, 1010 Vienna. --- #### 🕘 **9:30 AM – St. Stephen’s Cathedral (Stephansdom)** - **Why**: A serene and majestic landmark. The cathedral is compact and easy to explore, with a peaceful interior and a short climb to the **Gothic Tower** (optional, if energy allows). - **Tip**: Visit early to avoid crowds and enjoy the soft morning light. - **Accessibility**: Elevator access to the tower and main nave; smooth flooring throughout. - **Location**: Stephansplatz, 1010 Vienna. --- #### 🕘 **10:30 AM – Hofburg Palace (Imperial Apartments or Sisi Museum)** - **Why**: The former imperial residence, with rich history and elegant interiors. Choose **either** the Imperial Apartments (grand halls and royal chambers) **or** the **Sisi Museum** (dedicated to Empress Elisabeth, with personal artifacts and a tranquil atmosphere). - **Tip**: The Sisi Museum is more intimate and less overwhelming. - **Accessibility**: Fully accessible via elevator and ramps. - **Location**: Heldenplatz, 1010 Vienna. --- #### 🕘 **12:30 PM – Lunch at Café In der Burggasse24 (Neubau)** - **Why**: A cozy, welcoming café with a lovely courtyard and a relaxed vibe. Offers delicious Austrian and vegetarian dishes, including hearty soups, cheese toasts, and fresh salads. - **Highlights**: Outdoor seating under shady trees—perfect for a peaceful lunch. - **Accessibility**: Step-free entrance, wide doors, and wheelchair-friendly layout. - **Location**: Burggasse 24, 1070 Vienna. - **Travel Tip**: Take a short tram ride (Tram 1, 2, or 71) from Hofburg to Dr.-Karl-Renner-Ring/Burgring (5–7 minutes). --- #### 🕘 **2:00 PM – Kunsthistorisches Museum (Art History Museum)** - **Why**: One of the world’s finest art museums, but with a **senior-friendly approach**: - **Focus on highlights**: Skip the long galleries; head straight to the **Austrian Art Collection** (Renaissance to Baroque) and the **Egyptian Antiquities** (calm, well-lit, and less crowded). - **Use the museum’s free audio guide** (available in English) to avoid long reading. - **Accessibility**: Fully accessible with elevators, smooth floors, and rest areas. - **Tip**: Visit the **museum café** for a quiet break with a view of the palace gardens. - **Location**: Maria-Theresien-Platz, 1010 Vienna. --- #### 🕘 **4:30 PM – Relaxing Afternoon at Kaffeeamt (Leopoldstadt)** - **Why**: A charming, modern café with a relaxed atmosphere and excellent coffee. Ideal for unwinding with a pastry and a book. - **Highlights**: Famous for its **cold brew** and **French toast**. Outdoor seating available. - **Accessibility**: Step-free entrance, wide aisles, and friendly staff. - **Location**: Schiffamtsgasse 8, 1020 Vienna. - **Travel Tip**: Take a short tram ride (U2 to MuseumsQuartier) or a 15-minute walk from Kunsthistorisches Museum. --- #### 🕘 **6:30 PM – Dinner at Café Central (Innere Stadt)** - **Why**: A legendary Viennese café with a grand, historic interior. Perfect for a refined evening meal or a light dinner. - **Highlights**: Try the *Wiener Schnitzel* or a seasonal vegetarian dish. Enjoy a glass of wine or a classic *Eisbein* (pork knuckle). - **Accessibility**: Fully accessible, with elevators and spacious seating. - **Location**: Karlsplatz 4, 1040 Vienna. --- ### ✅ **Summary of Key Features for Seniors**: - **Minimal walking**: All locations are within a 15-minute walk or short tram ride of each other. - **Accessibility**: All venues are wheelchair-friendly with elevators and smooth flooring. - **Comfort**: Cafés and museums offer seating, rest areas, and quiet zones. - **Pacing**: No rush—each stop allows 1.5–2 hours of relaxed exploration. - **No need to rush**: You can skip any stop if energy is low. --- ### 📌 **Travel Tips**: - **Use the Vienna City Card** (if available) for free entry to museums and public transport. - **Wear comfortable shoes**—even with minimal walking, comfort matters. - **Book museum tickets online** in advance to avoid queues. Enjoy a peaceful and memorable day in Vienna! 🌸 Vienna is truly a city of grace and beauty—perfect for a calm, thoughtful visit. | K70: 5 | L70: 4 | M70: 2 | N70: 3 | O70: 4 | P70: Да | Q70: Wrong location within city; Unsupported factual claim | R70: =IF(A70="","",IF(OR(E70="Маршрут на один день",E70="Планирование поездки на несколько дней"),IF(COUNT(K70:O70)<5,"",MIN(K70*0.2+L70*0.2+M70*0.25+N70*0.25+O70*0.1,IF(P70="Да",2,5))),IF(COUNT(K70:M70)+COUNT(O70)<4,"",MIN(K70*0.25+L70*0.25+M70*0.35+O70*0.15,IF(P70="Да",2,5))))) -> 2 | S70: Подбор под пожилых родителей уместен: музеи, кафе, акцент на доступность и трамвай. Критично перепутаны адреса: Café Landtmann указано «в двух шагах от собора Св. Стефана» с адресом Herrengasse 14 — это адрес Café Central, а самому Central приписан Karlsplatz 4. В Музее истории искусств рекомендована несуществующая «Австрийская коллекция». Совет ехать в Леопольдштадт через U2 до MuseumsQuartier неверен; вечерние переезды в Леопольдштадт и обратно противоречат установке на минимум перемещений. | T70: 46231
A71: 70 | B71: ru | C71: Europe | D71: Florence, Italy | E71: Маршрут на один день | F71: Составь маршрут на один день по Флоренции с искусством эпохи Возрождения и перерывом на обед. | G71: qwen/qwen3-30b-a3b-instruct-2507 | H71: geoagent v1 ( qwen3-8b) | I71: web_search(ok); web_search(ok); web_search(ok) | model_calls=4 tool_calls=3 grounded=true | J71: ### 🌟 Один день в Флоренции: маршрут с искусством эпохи Возрождения и обедом Вот сбалансированный и реалистичный маршрут на один день, ориентированный на глубокое погружение в искусство эпохи Возрождения, с учётом времени, бронирования и вкусного обеда. --- #### 🕘 **08:15 – 09:30 | Собор Санта-Мария-дель-Фьоре (Дуомо)** - **Что посмотреть**: Купол Брунеллески, фасад из мрамора, колокольня Джотто. - **Совет**: Забронируйте подъём на купол заранее (на [duomoflorence.it](https://www.duomoflorence.it)). Вид на город с высоты — незабываем. - **Время**: 1 час. --- #### 🕘 **09:30 – 12:30 | Галерея Уффици (Galleria degli Uffizi)** - **Что посмотреть**: «Рождение Венеры» и «Весна» Боттичелли, «Благовещение» Леонардо да Винчи, работы Рафаэля, Тициана, Караваджо. - **Совет**: Бронируйте билеты онлайн на [uffizi.it](https://www.uffizi.it) — без брони в высокий сезон (апрель–октябрь) очередь может быть 2+ часа. - **Время**: 2,5–3 часа (рекомендуется выделить минимум 2 часа). - **Цена билета**: €20–26 (включая бронирование). --- #### 🕘 **12:30 – 14:00 | Обед в аутентичной тосканской таверне** - **Рекомендуемые рестораны (с ценами 15–25 евро на человека)**: - **Trattoria Da Rocco** (Piazza Lorenzo Ghiberti, 50122) - Атмосфера: уютная, с тематикой трамваев. - Блюда: лампредотто (треф), флорентийская лазанья, бутерброд с рубцом (5 евро). - Средняя стоимость: 10–20 евро. - ✅ Идеально для быстрого, вкусного и недорогого обеда. - **Il Toscanaccio** - Атмосфера: непринуждённая, с уличными столиками. - Блюда: спагетти, ньокки, Aperol Spritz. - Средняя стоимость: 10–20 евро. - ✅ Хорошо подходит для лёгкого обеда с видом на улицу. --- #### 🕘 **14:00 – 15:30 | Галерея Академии (Galleria dell'Accademia)** - **Что посмотреть**: Оригинал «Давида» Микеланджело, «Пленники» Микеланджело. - **Совет**: Бронируйте билеты на [galleriaaccademiafirenze.it](https://www.galleriaaccademiafirenze.it). Без брони очередь может быть 60–90 минут. - **Время**: 1,5 часа. - **Цена билета**: €20 (включая бронирование). --- #### 🕘 **15:30 – 17:00 | Пьяцца делла Синьория → Понте Веккьо** - **Что посмотреть**: Статуя Меркурия, памятник Гаррибальди, мост Понте Веккьо с ювелирными лавками. - **Совет**: Прогуляйтесь по мосту на закат — особенно красиво в вечерних лучах. --- #### 🕘 **17:00 – 18:30 | Площадь Микеланджело (Piazzale Michelangelo)** - **Что посмотреть**: Лучшее место для заката с видом на весь город, купола, реку Арно. - **Совет**: Приходите заранее, чтобы занять хорошее место. Можно прийти пешком (30–40 мин от центра) или на такси/автобусе. --- ### 📌 **Важные напоминания** - **Бронирование обязательно**: Уффици и Академия — самые посещаемые музеи. Бронируйте билеты за 1–2 недели. - **Время работы**: - Уффици: вторник–воскресенье, 08:15–18:30 (последний вход 17:30). - Академия: вторник–воскресенье, 08:15–18:50 (последний вход 18:20). - Оба музея закрыты по понедельникам. - **Одежда**: Никаких штативов, селфи-палок, крупных сумок (хранение бесплатно). - **Питание**: В музеях нельзя есть, только пить воду. --- ### 🎯 Итог Этот маршрут позволяет: - Увидеть ключевые шедевры Возрождения. - Избежать длинных очередей. - Попробовать настоящую тосканскую кухню. - Насладиться закатом с лучшего вида на Флоренцию. Планируйте заранее — Флоренция в пик сезона оживлена, но это делает её ещё прекраснее. 🎨🌆 | K71: 5 | L71: 5 | M71: 3 | N71: 4 | O71: 4 | P71: Да | Q71: Unsupported factual claim; Hallucinated place | R71: =IF(A71="","",IF(OR(E71="Маршрут на один день",E71="Планирование поездки на несколько дней"),IF(COUNT(K71:O71)<5,"",MIN(K71*0.2+L71*0.2+M71*0.25+N71*0.25+O71*0.1,IF(P71="Да",2,5))),IF(COUNT(K71:M71)+COUNT(O71)<4,"",MIN(K71*0.25+L71*0.25+M71*0.35+O71*0.15,IF(P71="Да",2,5))))) -> 2 | S71: Лучший маршрут батча по логике: Дуомо → Уффици → обед → Академия → Синьория → Понте Веккьо → Пьяццале Микеланджело, часы работы музеев и советы по бронированию верны, Trattoria Da Rocco реальна. Критично: на площади Синьории заявлены «статуя Меркурия» и «памятник Гарибальди» — там Персей Челлини, копия Давида, фонтан Нептуна и конная статуя Козимо I. Тайминг Дуомо с подъёмом на купол за 1 час до Уффици оптимистичен. Мелкие языковые огрехи («в Флоренции», «лампредотто (треф)»). | T71: 46231
A72: 71 | B72: ru | C72: Europe | D72: Copenhagen, Denmark | E72: Маршрут на один день | F72: Составь спокойный маршрут на день по Копенгагену с современной архитектурой и набережными. | G72: qwen/qwen3-30b-a3b-instruct-2507 | H72: geoagent v1 ( qwen3-8b) | I72: web_search(ok); web_search(ok); web_search(ok) | model_calls=4 tool_calls=3 grounded=true | J72: ### Спокойный однодневный маршрут по Копенгагену с современной архитектурой и набережными Этот маршрут сочетает в себе прогулки по живописным набережным, посещение ключевых архитектурных объектов современного Копенгагена и возможность насладиться городской атмосферой в медленном темпе. Путь начинается в центре города и постепенно движется к современным районам, сохраняя баланс между историей и инновациями. --- #### 🕘 **Утро: Набережная Нюхавн и исторический центр** - **Начало: Канал Нюхавн (Nyhavn)** Начните день с прогулки по знаменитому каналу Нюхавн — живописному месту с разноцветными домами XVII века. - **Северная набережная** — тише, тенистее, с лучшим видом на фасады. - **Южная набережная** — солнечная, с ресторанами и террасами. - **Совет**: Зайдите в один из кафе у воды, чтобы попробовать датский кофе и булочку (например, *koldskål* или *wienerbrød*). - **Далее: Ратушная площадь (Rådhuspladsen) и Круглая башня (Rundetaarn)** Прогуляйтесь по центральной части города. - **Круглая башня** — уникальная обсерватория с пандусом вместо лестниц. Вход платный (около 100 DKK), но стоит посетить ради архитектурного решения. - **Время работы**: зависит от сезона — уточняйте на сайте [www.rundetaarn.dk](https://www.rundetaarn.dk). --- #### 🕐 **День: Современная архитектура — BLOX, DAC и Копенгагенская опера** - **Переезд: от центра к BLOX (на метро или пешком)** - **Метро**: до станции *Rådhuspladsen* или *Nørreport*, затем пешком 10–15 минут. - **Пешком**: по набережной вдоль гавани — красивый путь, особенно в хорошую погоду. - **BLOX и Датский центр архитектуры (DAC)** - **BLOX** — здание OMA (Рем Колхас), визуально впечатляющий комплекс, в котором проходят выставки, лекции и архитектурные мероприятия. - **DAC** — национальный центр архитектуры, в котором можно посетить выставки, включая тематические экспозиции по современной датской архитектуре. - **Время работы**: - Понедельник, четверг, пятница: 10:00–21:00 - Среда: 10:00–18:00 - Вход: 135 DKK (взрослый), до 18 лет — бесплатно. - **Совет**: Прогуляйтесь по внутреннему проходу BLOX — пешеходный путь, проходящий сквозь здание, что является частью архитектурной идеи. - **Далее: Копенгагенская опера (Operaen)** - **Как добраться**: - На **городском пароме (Havnebussen)** — самый атмосферный способ. Сойдите на остановке *Opera House*. Путь занимает 5–10 минут. - Пешком: 20 минут от станции метро *Christianshavn* через пешеходный мост *Indre Havnsbroen*. - На велосипеде: 15 минут по велодорожкам вдоль гавани. - **Что посмотреть**: - Снаружи — эффектное здание с огромным стеклянным фасадом и выступающим козырьком (32 метра). - Вход в фойе часто открыт для всех — можно просто полюбоваться интерьером. - **Экскурсии внутри** — по предварительной записи (на сайте [www.operaen.dk](https://www.operaen.dk)). --- #### 🌅 **Вечер: Набережная Эрестад и Рефшалеэн** - **Переезд: на метро до Эрестада** - Станции: *DR Byen* или *Ørestad* (линия M1/M2). - **Совет**: Выйдите на *Ørestad* — здесь больше архитектурных экспериментов от BIG, JDS и других. - **Эрестад (Ørestad)** - Современный район с амбициозной архитектурой: - **CopenHill (Amager Bakke)** — энергетический завод с горнолыжной трассой на крыше. - **BIG-проекты**: здания с нестандартными формами, включая *The Twist* и *CopenHill*. - **Совет**: Прогуляйтесь по набережной вдоль реки, чтобы увидеть контраст между высокими зданиями и природой. - **Рефшалеэн (Refshaleøen)** - Бывшая промышленная зона, превращённая в культурный кластер. - **Copenhagen Contemporary** — современный художественный центр, размещённый в бывшем судостроительном цехе. - **Время работы**: обычно 11:00–18:00 (уточняйте на сайте). - **Вход**: бесплатный. - **Атмосфера**: тихо, уютно, с видами на гавань и старые промышленные здания. --- #### 🌙 **Завершение дня: возвращение в центр** - Вернитесь в центр Копенгагена на метро или пароме. - Закончите день у **Нюхавна** — в одном из ресторанов с видом на канал, чтобы насладиться вечерним светом и атмосферой города. --- ### 📌 Полезные советы: - **Транспорт**: Копенгаген — идеальный город для пешеходных и велосипедных прогулок. Используйте **Rejseplanen** (датский сервис маршрутов) для планирования поездок. - **Copenhagen Card**: если планируете посещать несколько достопримечательностей, карта может сэкономить деньги. - **Погода**: датская погода непредсказуема — возьмите лёгкую куртку и зонт. - **Время**: маршрут рассчитан на 8–10 часов. Можно сократить, если не планируете посещать все выставки. --- Этот маршрут сочетает в себе **спокойную прогулку**, **архитектурные впечатления** и **взаимодействие с водной средой** — всё, что делает Копенгаген уникальным городом. | K72: 5 | L72: 4 | M72: 2 | N72: 3 | O72: 5 | P72: Да | Q72: Wrong city / country; Unsupported factual claim; Bad route logic | R72: =IF(A72="","",IF(OR(E72="Маршрут на один день",E72="Планирование поездки на несколько дней"),IF(COUNT(K72:O72)<5,"",MIN(K72*0.2+L72*0.2+M72*0.25+N72*0.25+O72*0.1,IF(P72="Да",2,5))),IF(COUNT(K72:M72)+COUNT(O72)<4,"",MIN(K72*0.25+L72*0.25+M72*0.35+O72*0.15,IF(P72="Да",2,5))))) -> 2 | S72: Ядро запроса раскрыто: Нюхавн, BLOX/DAC (OMA), Опера, Рефсхалеэн — реальные и уместные. Критично: «The Twist» назван объектом Копенгагена — это музей Кистефос в Норвегии; CopenHill отнесён к Эрестаду, хотя он в другой части Амагера; вход в Copenhagen Contemporary заявлен бесплатным, фактически платный. Эрестад и Рефсхалеэн — противоположные концы Амагера, для «спокойного» дня получается зигзаг. | T72: 46231
A73: 72 | B73: ru | C73: Europe | D73: Athens, Greece | E73: Маршрут на один день | F73: Составь маршрут на день по Афинам с античными памятниками, но без слишком долгих подъёмов. | G73: qwen/qwen3-30b-a3b-instruct-2507 | H73: geoagent v1 ( qwen3-8b) | I73: web_search(ok); web_search(ok); web_search(ok) | model_calls=4 tool_calls=3 grounded=true | J73: ### 🌟 Маршрут на день по Афинам с античными памятниками (без длинных подъёмов) Этот маршрут разработан с учётом комфортного передвижения: большая часть пути — по ровным улицам, подъёмы минимизированы, а ключевые античные достопримечательности посещаются в оптимальном порядке. Маршрут рассчитан на 8–10 км пешком, с перерывом на обед и возможностью воспользоваться транспортом для подъёма на холмы. --- ### 🕘 **07:00 – 08:00: Плака и АнаФиотика** - **Место**: Плака (Plaka) и АнаФиотика (Anafiotika) - **Что посмотреть**: - Узкие улочки Плаки — старинный район у подножия Акрополя. - АнаФиотика — крошечный, как будто из Греции, квартал с белыми домиками, напоминающий селение на Кикладах. - **Совет**: Начните день рано — воздух прохладный, толпы ещё не появились. Отличная возможность сделать фото с видом на Акрополь. --- ### 🕘 **08:00 – 09:30: Акрополь (Acropolis)** - **Место**: Акрополь (вход с улицы Адриана, от станции метро *Monastiraki*) - **Что посмотреть**: - Храм Парфенон — главный символ Афин. - Эрехтейон с портиком кариатид. - Храм Ники Виктории. - Пропилеи — парадный вход. - **Совет**: Приходите **в момент открытия (8:00)** — меньше толпы, меньше жары. Билет: 20 € (или 30 € за комбинированный билет на 5 дней, включая другие памятники). --- ### 🕘 **09:30 – 11:00: Храм Гефеста и Древняя Агора** - **Место**: Древняя Агора (Ancient Agora), улица Апостолу Павлу - **Что посмотреть**: - **Храм Гефеста** — один из самых хорошо сохранившихся древнегреческих храмов. - **Стоа Аттала** — восстановленная римская арка с музеем Агоры. - Остатки древних зданий, где когда-то проходили политические и торговые дела. - **Совет**: Путь от Акрополя до Агоры — по ровной улице *Dionysiou Areopagitou* (около 1 км). Это самый красивый и спокойный пешеходный маршрут в центре. --- ### 🕘 **11:00 – 13:00: Обед в Монастираки** - **Место**: Монастираки (Monastiraki) - **Что посмотреть**: - Рынок Монастираки — живописный, шумный, с местными сувенирами, едой и музыкой. - **Совет**: Отдыхайте в кафе или бистро с видом на площадь. Попробуйте греческие блюда: *souvlaki*, *spanakopita*, *tzatziki*. --- ### 🕘 **13:00 – 15:00: Отдых или Национальный археологический музей** - **Место**: Национальный археологический музей (National Archaeological Museum) - **Что посмотреть**: - Один из крупнейших археологических музеев мира. - Экспонаты: скульптуры, саркофаги, сокровища из Микен, золото из Троя. - **Совет**: Если устали — отдохните в музее, где прохладно и есть зоны для отдыха. Если хотите продолжать — можно пройти в музей, но не обязательно. --- ### 🕘 **15:00 – 16:30: Хадрианов Арх и Панатенаический стадион** - **Место**: Хадрианов Арх (Hadrian's Arch) и Панатенаический стадион (Panathenaic Stadium) - **Что посмотреть**: - **Хадрианов Арх** — древний монумент, символ перехода от античности к римской эпохе. - **Панатенаический стадион** — полностью построенный из мрамора, использовался в древних Олимпийских играх. В 1896 году здесь прошли первые современные Олимпийские игры. - **Совет**: Путь от Агоры до стадиона — по ровной улице *Vasilissis Sofias* (около 1,5 км). Можно дойти пешком или на метро (линия 1, остановка *Omonia*). --- ### 🕘 **16:30 – 18:00: Филопаппос Холм (Philopappos Hill) — бесплатный вид на Акрополь** - **Место**: Филопаппос Холм (Philopappos Hill) - **Что посмотреть**: - Памятник Филопаппосу — римский сенатор, похороненный здесь. - **Бесплатный вид на Акрополь и весь город** — с вершины открывается одна из самых красивых панорам Афин. - **Совет**: Подъём — короткий (около 15 минут пешком), но если устали — можно доехать на автобусе или такси. Вход — бесплатный. --- ### 🕘 **18:00 – 19:30: Солнечный закат с Ликабеттуса (Lycabettus Hill)** - **Место**: Ликабеттус (Lycabettus Hill) — самый высокий холм в Афинах (277 м) - **Что посмотреть**: - Закат над Афинами — незабываемый вид на город, море и Акрополь. - Крест на вершине — символ города. - **Совет**: Подъём можно сделать **пешком** (20–30 мин по тропе) или **на фуникулёре** (снизу — от Колонаки). Фуникулёр — идеальный вариант, если устали. --- ### 📌 **Итог:** - **Общее расстояние**: ~8–10 км (в основном по ровной местности). - **Подъёмы**: Только два коротких (Филопаппос и Ликабеттус), с возможностью использовать транспорт. - **Рекомендации**: - Носите удобную обувь и воду. - Используйте **комбинированный билет (30 € на 5 дней)** — он включает Акрополь, Древнюю Агору, Храм Гефеста, Панатенаический стадион и другие объекты. - Скачайте **Google Maps в офлайн-режиме** — на холмах может быть слабый интернет. --- ✅ Этот маршрут позволяет увидеть **все главные античные памятники Афин**, избежать перегрева и усталости, и закончить день с потрясающим видом на город. | K73: 3 | L73: 4 | M73: 2 | N73: 3 | O73: 4 | P73: Да | Q73: Ignored constraints; Unsupported factual claim; Bad route logic | R73: =IF(A73="","",IF(OR(E73="Маршрут на один день",E73="Планирование поездки на несколько дней"),IF(COUNT(K73:O73)<5,"",MIN(K73*0.2+L73*0.2+M73*0.25+N73*0.25+O73*0.1,IF(P73="Да",2,5))),IF(COUNT(K73:M73)+COUNT(O73)<4,"",MIN(K73*0.25+L73*0.25+M73*0.35+O73*0.15,IF(P73="Да",2,5))))) -> 2 | S73: Просили без долгих подъёмов, а в плане Акрополь, Филопаппу и Ликавит — три холма подряд, причём два подъёма в конце дня. Критично по фактам: «золото из Трои» в Национальном археологическом музее (там микенское золото), Стоа Аттала названа «римской аркой» (это эллинистический портик), комбинированный билет за €30 не включает Панатинаикос. Путь от Агоры к стадиону описан по улице Василиссис Софиас с выходом на метро «Омония» — ни то, ни другое не по маршруту. | T73: 46231
... A96: 95 | B96: ru | C96: CIS | D96: Tashkent, Uzbekistan | E96: Планирование поездки на несколько дней | F96: Распланируй четыре дня в Ташкенте с рынками, музеями, архитектурой и узбекской кухней. | G96: qwen/qwen3-30b-a3b-instruct-2507 | H96: geoagent v1 ( qwen3-8b) | I96: web_search(ok); web_search(ok); web_search(ok); web_search(ok); web_search(ok); web_search(ok) | model_calls=6 tool_calls=6 grounded=true | J96: Не удалось завершить запрос в отведённое число шагов. | K96: 1 | L96: 1 | M96: 1 | N96: 1 | O96: 1 | P96: Нет | Q96: No answer | R96: =IF(A96="","",IF(OR(E96="Маршрут на один день",E96="Планирование поездки на несколько дней"),IF(COUNT(K96:O96)<5,"",MIN(K96*0.2+L96*0.2+M96*0.25+N96*0.25+O96*0.1,IF(P96="Да",2,5))),IF(COUNT(K96:M96)+COUNT(O96)<4,"",MIN(K96*0.25+L96*0.25+M96*0.35+O96*0.15,IF(P96="Да",2,5))))) -> 1 | S96: Ответа нет: «Не удалось завершить запрос в отведённое число шагов». | T96: 46231
A97: 96 | B97: en | C97: Europe | D97: Paris, France | E97: Неполные / неоднозначные запросы | F97: Plan something nice in Paris tomorrow. | G97: qwen/qwen3-30b-a3b-instruct-2507 | H97: geoagent v1 ( qwen3-8b) | I97: web_search(ok); web_search(ok); web_search(ok) | model_calls=4 tool_calls=3 grounded=true | J97: Here’s a curated plan for a memorable day in Paris tomorrow, August 1, 2026, based on current events and top attractions: --- ### 🌟 **Paris Itinerary for Tomorrow – August 1, 2026** #### 🕘 **Morning: Art & Immersion at Atelier des Lumières** - **Time:** 10:00 AM – 12:30 PM - **Location:** Atelier des Lumières, 75011 Paris - **Experience:** Immerse yourself in a breathtaking digital art exhibition. Choose between: - *Van Gogh: The Immersive Experience* – Explore the vibrant world of the post-impressionist master through 360° projections and cinematic soundscapes. - *Le Petit Prince: The Immersive Journey* – A poetic, dreamlike journey through the beloved story, blending animation, music, and light. - **Why go?** Perfect for art lovers and families; a unique way to experience classic works in a modern, sensory-rich format. --- #### 🍽️ **Lunch: Charming Café in Le Marais** - **Time:** 1:00 PM – 2:30 PM - **Suggestion:** *Le Comptoir du Relais* (33 Rue de Seine, 75006) - **Why?** A classic Parisian bistro with a cozy atmosphere, excellent French cuisine, and a great wine list. Try the duck confit or seasonal vegetable tart. - **Bonus:** Located in the heart of Saint-Germain-des-Prés, ideal for a relaxed stroll afterward. --- #### 🕶️ **Afternoon: NBA Summer House at Palais Brongniart** - **Time:** 3:00 PM – 6:00 PM - **Location:** Palais Brongniart, 16 Place de la Bourse, 75002 Paris - **Event:** *NBA Summer House – Paris 2026* - **Highlights:** - Interactive basketball challenges and mini-games. - View the iconic Larry O’Brien Trophy. - Exclusive NBA merchandise and photo ops. - Free admission (tickets required – book in advance via [Unidivers.fr](https://unidivers.fr)). - **Perfect for:** Sports fans, families, and anyone looking for a fun, energetic experience. --- #### 🌆 **Evening: Sunset at the Eiffel Tower & Dinner in Trocadéro** - **Time:** 7:00 PM – 9:30 PM - **Location:** Champ de Mars & Trocadéro Gardens - **Experience:** - Walk through the Champ de Mars as the sun sets behind the Eiffel Tower. - Enjoy the nightly light show (starts at 8:00 PM, lasts 5 minutes). - Dine at *Le Jules Verne* (in the Eiffel Tower) or *Le Relais de l’Entrecôte* (Trocadéro) for a memorable dinner with a view. - **Tip:** Book dinner reservations early—this is one of Paris’s most romantic spots. --- #### 🌙 **Optional Nightcap: Jazz at The Dissident Club** - **Time:** 10:00 PM (if you're still energized) - **Location:** 58 Rue Richer, 75009 Paris - **Event:** *Dissident Jazz Duos – Pablo & Patricio* - **Details:** A free, intimate jazz performance blending Latin American melodies with improvisation. Ideal for a relaxed, sophisticated end to your day. --- ### 📌 **Tips for the Day:** - **Weather:** Expect warm summer conditions—pack sunscreen, a hat, and light clothing. - **Transport:** Use the Paris Métro (RER) or a bike-share (Vélib’) for easy access to all locations. - **Tickets:** Reserve in advance for Atelier des Lumières and NBA Summer House to avoid queues. --- Enjoy a perfect blend of culture, sport, romance, and Parisian charm! 🇫🇷✨ | K97: 1 | L97: 3 | M97: 2 | O97: 5 | P97: Да | Q97: Ignored constraints; Hallucinated place; Unsupported factual claim; Wrong location within city | R97: =IF(A97="","",IF(OR(E97="Маршрут на один день",E97="Планирование поездки на несколько дней"),IF(COUNT(K97:O97)<5,"",MIN(K97*0.2+L97*0.2+M97*0.25+N97*0.25+O97*0.1,IF(P97="Да",2,5))),IF(COUNT(K97:M97)+COUNT(O97)<4,"",MIN(K97*0.25+L97*0.25+M97*0.35+O97*0.15,IF(P97="Да",2,5))))) -> 2 | S97: Ни одного уточняющего вопроса, ни одного явно обозначенного предположения — сразу уверенный почасовой план. Дата «завтра» подставлена как 1 августа 2026 (реально 30 июля). Критично: мероприятия «NBA Summer House – Paris 2026» в Дворце Броньяр и «Dissident Jazz Duos – Pablo & Patricio» поданы с адресами и временем, но не подтверждаются. Le Comptoir du Relais (Rue de Seine, 6-й округ) назван кафе в Маре. Подсветка Эйфелевой башни описана как единичное шоу в 20:00. | T97: 46231
A98: 97 | B98: en | C98: Europe | D98: Prague, Czechia | E98: Неполные / неоднозначные запросы | F98: I have one free day in Prague. What should I do? | G98: qwen/qwen3-30b-a3b-instruct-2507 | H98: geoagent v1 ( qwen3-8b) | I98: web_search(ok) | model_calls=2 tool_calls=1 grounded=true | J98: Here’s a well-structured one-day itinerary for Prague, designed to maximize your experience in a single day while covering the city’s most iconic sights and hidden gems: --- ### 🌟 **One-Day Itinerary in Prague: Must-See Highlights** #### 🕘 **Morning: Old Town & Historic Center** - **Start at Old Town Square (Staroměstské náměstí)** - Admire the **Astronomical Clock** (check the hourly show at noon). - Explore the surrounding historic buildings, including the **Church of Our Lady before Týn** (Týnský chrám). - Grab a coffee or pastry at a café like **Café Louvre** or **Café Sladké** for a classic Prague breakfast. - **Walk across Charles Bridge (Karlův most)** - Begin early to avoid crowds. - Enjoy the statues of saints and the stunning views of the Vltava River and Prague Castle. - Stop for photos at the bridge’s midpoint. #### 🕘 **Midday: Prague Castle & Hradčany District** - **Head to Prague Castle (Pražský hrad)** - Enter through the **Golden Lane** (a charming row of tiny houses). - Visit **St. Vitus Cathedral** – a masterpiece of Gothic architecture. - Explore the **Royal Garden** and **Old Royal Palace**. - Take in panoramic views from the castle grounds. #### 🕘 **Afternoon: Malá Strana & Petřín Hill** - **Stroll through Malá Strana (Lesser Town)** - Walk along the quiet, cobbled streets with Baroque charm. - Visit the **Petřín Hill Lookout Tower** (a smaller version of the Eiffel Tower). - Climb the 299 steps or take the funicular for a scenic view over the city. - Enjoy a relaxed lunch at a riverside café like **U Modré Kachničky**. #### 🕘 **Late Afternoon: Optional Add-Ons** - **Visit the Jewish Quarter (Josefov)** - Explore the **Jewish Museum**, including the **Old-New Synagogue** (the oldest synagogue in Europe). - Walk through the **Jewish Cemetery** – a hauntingly beautiful site. - **Relax in a Park or Garden** - **Letná Park** – Offers one of the best panoramic views of Prague, especially at sunset. - **Vyšehrad Fortress** – A quieter alternative with a historic church and peaceful trails. #### 🕘 **Evening: Sunset & Dinner** - **Sunset River Cruise on the Vltava** - Book a 1-hour evening cruise for magical views of Prague Castle and the illuminated city. - Many cruises include dinner or drinks (e.g., **Prague River Cruises** or **Vltava Cruises**). - **Dinner in a Historic Pub or Rooftop Bar** - Try **U Modré Kachničky** (traditional Czech food) or **Rooftop Bar at Hotel U Modré Kachničky** for a modern twist. - For a unique experience, consider a **medieval-themed dinner show** at a pub like **U Modré Kachničky** or **U Zlatého Tygra**. --- ### 🎒 **Tips for Your Day** - **Wear comfortable shoes** – Prague is best explored on foot. - **Arrive early** at major attractions (especially Charles Bridge and Prague Castle) to avoid crowds. - **Use public transport** – The metro and trams are efficient and affordable. - **Download a Prague map app** (like Google Maps or Citymapper) for navigation. --- This itinerary balances iconic landmarks, cultural depth, and local charm — perfect for making the most of your free day in Prague! 🇨🇿✨ | K98: 1 | L98: 3 | M98: 2 | O98: 4 | P98: Да | Q98: Ignored constraints; Hallucinated place; Unsupported factual claim | R98: =IF(A98="","",IF(OR(E98="Маршрут на один день",E98="Планирование поездки на несколько дней"),IF(COUNT(K98:O98)<5,"",MIN(K98*0.2+L98*0.2+M98*0.25+N98*0.25+O98*0.1,IF(P98="Да",2,5))),IF(COUNT(K98:M98)+COUNT(O98)<4,"",MIN(K98*0.25+L98*0.25+M98*0.35+O98*0.15,IF(P98="Да",2,5))))) -> 2 | S98: Вместо уточняющих вопросов или явных допущений — плотный маршрут на весь день, причём перегруженный (Старый город + Град + Малая Страна + Йозефов + Летна + круиз). Критично: U Modré Kachničky предложен трижды, включая несуществующие «Rooftop Bar at Hotel U Modré Kachničky» и «средневековое шоу-ужин» там же; Café Sladké не идентифицируется. Вход в Пражский Град описан «через Золотую улочку» — она в дальнем конце комплекса. Верно: 299 ступеней Петршинской башни, Староновая синагога. | T98: 46231
A99: 98 | B99: ru | C99: Europe | D99: Berlin, Germany | E99: Неполные / неоднозначные запросы | F99: Хочу интересно провести день в Берлине. | G99: qwen/qwen3-30b-a3b-instruct-2507 | H99: geoagent v1 ( qwen3-8b) | I99: | model_calls=1 tool_calls=0 grounded=true | J99: Отлично! В Берлине есть множество интересных мест и активностей, которые помогут вам провести незабываемый день. Ниже — идеальный план на один день в Берлине, сочетающий культуру, историю, архитектуру и местную атмосферу. --- ### 🌞 Утро: Завтрак и прогулка по Музейному острову - **Место**: Музейный остров (Museumsinsel) — UNESCO-объект мирового наследия. - **Что посмотреть**: - **Национальная галерея (Alte Nationalgalerie)** — классическое искусство XIX века. - **Музей Померанской галереи (Bode-Museum)** — античные скульптуры, средневековые произведения. - **Музей современного искусства (Neue Nationalgalerie)** — работы Кандинского, Малевича, Брейгеля. - **Совет**: Завтрак в уютном кафе на берегу реки Шпрее, например, **Café am Neuen See** — идеально для начала дня. --- ### 🕘 День: История и архитектура — Берлинская стена и Потсдамская площадь - **Место**: **Потсдамская площадь (Potsdamer Platz)** — центр современного Берлина. - **Что посмотреть**: - **Галерея современного искусства (Kulturforum)** — рядом с музеями. - **Мемориал жертвам Холокоста (Memorial to the Murdered Jews of Europe)** — мощное, эмоциональное место. - **Берлинская стена (East Side Gallery)** — самая длинная сохранившаяся часть стены с живописными граффити. - **Совет**: Прогуляйтесь по **Курфюрстенштрассе (Kurfürstendamm)** — шопинг и кофе в стиле 1920-х. --- ### 🌇 Вечер: Ужин и вечерняя атмосфера - **Место**: **Кройцберг (Kreuzberg)** — самый арт- и креативный район Берлина. - **Что посмотреть/сделать**: - Прогуляйтесь по улицам с уличным искусством, посетите **Markthalle Neun** — рынок с фуд-кортами и местной кухней. - Ужин в одном из баров с блюдами из разных культур: например, **Kreuzberg Biergarten** или **Lokal**. - **Альтернатива**: Если хотите что-то более шумное — посетите **Berghain** (если у вас есть доступ, это один из самых известных ночных клубов мира). --- ### 🌃 Ночь: Вечерний вид на город - **Место**: **Фернсайт (Fernsehturm)** — телебашня на Мюнхенской площади. - **Что посмотреть**: - Панорамный вид на Берлин с 200-метровой высоты. - Ресторан **360°** — идеальное место для ужина с видом на город. --- ### 📌 Советы: - **Транспорт**: Купите **Berlin WelcomeCard** — она даёт скидки на транспорт и вход в музеи. - **Язык**: Английский широко используется, но изучите пару фраз на немецком — местные оценят. - **Погода**: Уточните погоду заранее — если будет дождь, замените улицы на **Музей современного искусства (Hamburger Bahnhof)** или **Музей истории Берлина**. --- Хотите, чтобы я помог составить маршрут на карте, подобрать конкретные рестораны или уточнить, что интересно именно вам (например, музеи, архитектура, уличная еда, вечеринки)? | K99: 2 | L99: 3 | M99: 2 | O99: 4 | P99: Да | Q99: Unsupported factual claim; Wrong location within city; Ignored constraints | R99: =IF(A99="","",IF(OR(E99="Маршрут на один день",E99="Планирование поездки на несколько дней"),IF(COUNT(K99:O99)<5,"",MIN(K99*0.2+L99*0.2+M99*0.25+N99*0.25+O99*0.1,IF(P99="Да",2,5))),IF(COUNT(K99:M99)+COUNT(O99)<4,"",MIN(K99*0.25+L99*0.25+M99*0.35+O99*0.15,IF(P99="Да",2,5))))) -> 2 | S99: Плюс: в самом конце агент всё же спрашивает об интересах — частичное попадание в требование сценария, но только после готового плана и без обозначения допущений. Критично по фактам: Боде-музей назван «Музеем Померанской галереи»; Новая национальная галерея отнесена к Музейному острову (она в Культурфоруме) и ей приписан Брейгель; телебашня размещена «на Мюнхенской площади» вместо Александерплац; Курфюрстендамм назван «Курфюрстенштрассе»; Café am Neuen See указано у Шпрее, фактически в Тиргартене. Потсдамская площадь и Ист-Сайд-Галерея объединены в один блок, хотя они в разных концах. | T99: 46231
A100: 99 | B100: en | C100: CIS | D100: Tbilisi, Georgia | E100: Неполные / неоднозначные запросы | F100: Show me something interesting to do in Tbilisi. | G100: qwen/qwen3-30b-a3b-instruct-2507 | H100: geoagent v1 ( qwen3-8b) | I100: web_search(ok) | model_calls=2 tool_calls=1 grounded=true | J100: Here are some of the most interesting things to do in Tbilisi, Georgia, based on current recommendations: --- ### 🌿 **1. Explore Abanotubani (Sulfur Baths District)** - **Why visit?** Tbilisi’s name comes from its ancient hot springs. The Abanotubani district is home to centuries-old sulfur baths, where you can relax in traditional bathhouses with mineral-rich waters. - **Tip:** Try a traditional *banya* (sauna) experience with a local guide for an authentic cultural immersion. --- ### 🏰 **2. Climb Narikala Fortress** - **Why visit?** Perched on a hill overlooking the city, this 4th-century fortress offers panoramic views of Tbilisi’s red rooftops, the Mtkvari River, and the surrounding mountains. - **Bonus:** Combine your visit with a walk through **Mtatsminda Park**, which features a funicular railway and a large observation wheel. --- ### 🍷 **3. Wine Tasting in Kakheti (Day Trip)** - **Why visit?** Georgia is considered the birthplace of winemaking. Take a private tour to the Alazani Valley to visit small family-run wineries and taste unique **qvevri wines**—fermented in clay amphorae buried underground. - **Experience:** Enjoy a traditional Georgian meal with homemade wine, often accompanied by *supra* (ritual feast) toasts. --- ### 🛍️ **4. Wander the Dry Bridge Flea Market** - **Why visit?** A vibrant, chaotic, and colorful market where you can find vintage clothes, handmade crafts, local art, and quirky souvenirs. - **Atmosphere:** A favorite among locals and travelers alike, this is a great place to soak in Tbilisi’s street culture. --- ### 🎭 **5. Visit the Tbilisi Opera and Ballet Theatre** - **Why visit?** A stunning example of Art Nouveau architecture, this historic theater hosts world-class performances. Even if you don’t catch a show, the building’s interior is worth admiring. --- ### 🏛️ **6. Discover the National Museum of Georgia** - **Why visit?** Home to an impressive collection of ancient artifacts, including the famous **Gurjaani gold jewelry** and relics from the ancient Kingdom of Colchis. - **Highlight:** The museum’s basement features a reconstructed ancient tomb and a section on the Silk Road. --- ### 🌉 **7. Walk Across the Bridge of Peace** - **Why visit?** This modern, striking bridge connects the old and new parts of the city. At night, it’s illuminated with colorful lights and offers a peaceful view of the river and city skyline. --- ### 🍷 **8. Enjoy a Supra (Traditional Feast)** - **Why visit?** A true Georgian cultural experience. Participate in a *supra*—a long, festive meal with multiple courses, endless toasts, and traditional music. - **Where:** Many restaurants in the Old Town (Dzveli Tbilisi) offer authentic supra experiences. --- ### 🌆 **9. Stroll Through the Old Town (Dzveli Tbilisi)** - **Why visit?** Cobblestone streets, colorful wooden balconies, hidden courtyards, and centuries-old churches like **Sioni Cathedral** and **Metekhi Church**. - **Vibe:** A maze of charm, history, and local life—perfect for wandering and photography. --- ### 🎨 **10. Visit Fabrika Tbilisi** - **Why visit?** A creative hub housed in a former industrial complex, featuring art galleries, design studios, cafes, and pop-up events. - **Ideal for:** Art lovers, photographers, and those seeking a modern twist on Tbilisi’s cultural scene. --- ### 📌 **Pro Tips:** - **Best time to visit:** September is ideal—pleasant weather, fewer crowds, and harvest season for wine. - **Local etiquette:** Accepting a toast with a smile and a sip (even if you don’t drink alcohol) is appreciated. - **Language:** While English is spoken in tourist areas, learning a few Georgian phrases (like “Gamarjoba” – hello) goes a long way. --- Tbilisi is a city of contrasts—ancient and modern, wild and refined, spiritual and playful. Whether you're sipping wine in a cave, soaking in a bathhouse, or climbing a fortress at sunset, you’ll find something unforgettable here. | K100: 3 | L100: 4 | M100: 3 | O100: 5 | P100: Нет | Q100: Ignored constraints; Unsupported factual claim | R100: =IF(A100="","",IF(OR(E100="Маршрут на один день",E100="Планирование поездки на несколько дней"),IF(COUNT(K100:O100)<5,"",MIN(K100*0.2+L100*0.2+M100*0.25+N100*0.25+O100*0.1,IF(P100="Да",2,5))),IF(COUNT(K100:M100)+COUNT(O100)<4,"",MIN(K100*0.25+L100*0.25+M100*0.35+O100*0.15,IF(P100="Да",2,5))))) -> 3.55 | S100: Формат подборки из 10 идей для расплывчатого «покажи что-нибудь интересное» уместнее жёсткого плана, но уточняющих вопросов и явных допущений всё равно нет. Места реальные: Абанотубани, Нарикала, Сухой мост, Фабрика, Мост Мира, поездка в Кахетию за квеври-вином. Ошибки: «Gurjaani gold jewelry» в Национальном музее — такого собрания нет, знаменитое золото из Вани и Колхиды; театр оперы и балета назван ар-нуво (мавританский стиль); Нарикала и Мтацминда поданы как соседние точки для одной прогулки — это разные холмы. | T100: 46231
A101: 100 | B101: en | C101: CIS | D101: Almaty, Kazakhstan | E101: Неполные / неоднозначные запросы | F101: I will be in Almaty for a while. Make me a plan. | G101: qwen/qwen3-30b-a3b-instruct-2507 | H101: geoagent v1 ( qwen3-8b) | I101: | model_calls=1 tool_calls=0 grounded=true | J101: To create a personalized travel plan for your stay in Almaty, I need a bit more information: 1. **How long will you be staying in Almaty?** (e.g., 3 days, 1 week, etc.) 2. **What are your main interests?** (e.g., sightseeing, outdoor activities, shopping, local cuisine, cultural events, relaxation) 3. **Do you have any specific places you’d like to visit or avoid?** 4. **Are you traveling solo, with family, or in a group?** (This helps with activity recommendations.) 5. **Do you prefer a relaxed pace or an action-packed itinerary?** Once I have these details, I’ll craft a detailed and tailored plan for your time in Almaty. | K101: 5 | L101: 5 | M101: 5 | O101: 4 | P101: Нет | Q101: — | R101: =IF(A101="","",IF(OR(E101="Маршрут на один день",E101="Планирование поездки на несколько дней"),IF(COUNT(K101:O101)<5,"",MIN(K101*0.2+L101*0.2+M101*0.25+N101*0.25+O101*0.1,IF(P101="Да",2,5))),IF(COUNT(K101:M101)+COUNT(O101)<4,"",MIN(K101*0.25+L101*0.25+M101*0.35+O101*0.15,IF(P101="Да",2,5))))) -> 4.85 | S101: Эталонная обработка неполного запроса: агент не стал ничего выдумывать и задал уточняющие вопросы о сроках, интересах, составе поездки и темпе, обозначив, что план будет составлен после ответов | T101: 46231

Sheet Pairwise
A1: query_id | B1: language | C1: region | D1: city_country | E1: scenario | F1: user_query | G1: system_a | H1: answer_a | I1: system_b | J1: answer_b | K1: winner | L1: winner_system | M1: judge_reason
A2: 1 | B2: en | C2: Europe | D2: Prague, Czechia | E2: Простой поиск мест | F2: Find cozy coffee shops in Prague Old Town.
A3: 2 | B3: en | C3: Europe | D3: Berlin, Germany | E3: Простой поиск мест | F3: Recommend contemporary art museums in Berlin.
A4: 3 | B4: en | C4: Europe | D4: Lisbon, Portugal | E4: Простой поиск мест | F4: Find the best viewpoints in Lisbon for sunset.
A5: 4 | B5: en | C5: Europe | D5: Rome, Italy | E5: Простой поиск мест | F5: Suggest traditional trattorias in Trastevere.
A6: 5 | B6: en | C6: Europe | D6: Amsterdam, Netherlands | E6: Простой поиск мест | F6: Find quiet parks in Amsterdam for a relaxed afternoon.
A7: 6 | B7: en | C7: Europe | D7: Athens, Greece | E7: Простой поиск мест | F7: Recommend archaeological sites in central Athens.
A8: 7 | B8: en | C8: Europe | D8: Copenhagen, Denmark | E8: Простой поиск мест | F8: Find independent Danish design shops in Copenhagen.
A9: 8 | B9: ru | C9: Europe | D9: London, United Kingdom | E9: Простой поиск мест | F9: Порекомендуй бесплатные музеи в центре Лондона.
A10: 9 | B10: ru | C10: Europe | D10: Barcelona, Spain | E10: Простой поиск мест | F10: Найди хорошие веганские кафе в Барселоне.
A11: 10 | B11: en | C11: CIS | D11: Almaty, Kazakhstan | E11: Простой поиск мест | F11: Find family-friendly parks in Almaty.
A12: 11 | B12: en | C12: CIS | D12: Tbilisi, Georgia | E12: Простой поиск мест | F12: Suggest local bakeries in central Tbilisi.
A13: 12 | B13: en | C13: CIS | D13: Baku, Azerbaijan | E13: Простой поиск мест | F13: Find historical museums in Baku.
... A101: 100 | B101: en | C101: CIS | D101: Almaty, Kazakhstan | E101: Неполные / неоднозначные запросы | F101: I will be in Almaty for a while. Make me a plan.

Sheet Summary
A1: GeoAgent — сводка по оценке качества
A2: Модель: qwen/qwen3-30b-a3b-instruct-2507
A4: Общие показатели | D4: Средние по критериям
A5: Всего запросов в датасете | B5: =COUNTA('Eval Dataset'!A2:A101) -> 100 | D5: Intent Understanding | E5: =IFERROR(AVERAGE(Results!$K$2:$K$101),"") -> 4.098
A6: Оценено ответов | B6: =COUNT(Results!$R$2:$R$101) -> 100 | D6: Relevance | E6: =IFERROR(AVERAGE(Results!$L$2:$L$101),"") -> 3.678
A7: Средний overall score (0–5) | B7: =IFERROR(AVERAGE(Results!$R$2:$R$101),"") -> 2.9899 | D7: Factuality | E7: =IFERROR(AVERAGE(Results!$M$2:$M$101),"") -> 2.234
A8: Ответов с критической ошибкой | B8: =COUNTIF(Results!$P$2:$P$101,"Да") -> 27 | D8: Itinerary Feasibility (только маршрутные) | E8: =IFERROR(AVERAGE(Results!$N$2:$N$101),"") -> 3.2285714
A9: Доля критических ошибок | B9: =IF(B6=0,"",B8/B6) -> 0.27 | D9: Format | E9: =IFERROR(AVERAGE(Results!$O$2:$O$101),"") -> 4.47
A10: Отмечено «Нет» в critical_error | B10: =COUNTIF(Results!$P$2:$P$101,"Нет") -> 24 | D10: Overall (взвешенный) | E10: =IFERROR(AVERAGE(Results!$R$2:$R$101),"") -> 2.9899
A13: Качество по категориям запросов (сценариям)
A14: Сценарий | B14: В датасете | C14: Оценено | D14: Overall | E14: Intent | F14: Relevance | G14: Factuality | H14: Feasibility | I14: Format | J14: Critical errors (на строки 51-100) | K14: Critical rate | M14: Overall %
A15: Простой поиск мест | B15: =COUNTIF('Eval Dataset'!$E$2:$E$101,$A15) -> 15 | C15: =COUNTIFS(Results!$E$2:$E$101,$A15,Results!$R$2:$R$101,">0") -> 15 | D15: =IFERROR(SUMIFS(Results!$R$2:$R$101,Results!$E$2:$E$101,$A15)/COUNTIFS(Results!$E$2:$E$101,$A15,Results!$R$2:$R$101,">0"),"") -> 2.7826667 | E15: =IFERROR(SUMIFS(Results!$K$2:$K$101,Results!$E$2:$E$101,$A15)/COUNTIFS(Results!$E$2:$E$101,$A15,Results!$K$2:$K$101,">0"),"") -> 3.6533333 | F15: =IFERROR(SUMIFS(Results!$L$2:$L$101,Results!$E$2:$E$101,$A15)/COUNTIFS(Results!$E$2:$E$101,$A15,Results!$L$2:$L$101,">0"),"") -> 3.0533333 | G15: =IFERROR(SUMIFS(Results!$M$2:$M$101,Results!$E$2:$E$101,$A15)/COUNTIFS(Results!$E$2:$E$101,$A15,Results!$M$2:$M$101,">0"),"") -> 1.36 | H15: =IFERROR(SUMIFS(Results!$N$2:$N$101,Results!$E$2:$E$101,$A15)/COUNTIFS(Results!$E$2:$E$101,$A15,Results!$N$2:$N$101,">0"),"") | I15: =IFERROR(SUMIFS(Results!$O$2:$O$101,Results!$E$2:$E$101,$A15)/COUNTIFS(Results!$E$2:$E$101,$A15,Results!$O$2:$O$101,">0"),"") -> 4.2 | J15: =COUNTIFS(Results!$E$2:$E$101,$A15,Results!$P$2:$P$101,"Да") -> 0 | K15: =IF(COUNTIFS(Results!$E$2:$E$101,$A15,Results!$P$2:$P$101,"<>")=0,"",J15/COUNTIFS(Results!$E$2:$E$101,$A15,Results!$P$2:$P$101,"<>")) | M15: =D15/5*100 -> 55.653333
A16: Проверка информации о конкретном месте | B16: =COUNTIF('Eval Dataset'!$E$2:$E$101,$A16) -> 15 | C16: =COUNTIFS(Results!$E$2:$E$101,$A16,Results!$R$2:$R$101,">0") -> 15 | D16: =IFERROR(SUMIFS(Results!$R$2:$R$101,Results!$E$2:$E$101,$A16)/COUNTIFS(Results!$E$2:$E$101,$A16,Results!$R$2:$R$101,">0"),"") -> 3.2033333 | E16: =IFERROR(SUMIFS(Results!$K$2:$K$101,Results!$E$2:$E$101,$A16)/COUNTIFS(Results!$E$2:$E$101,$A16,Results!$K$2:$K$101,">0"),"") -> 4.2666667 | F16: =IFERROR(SUMIFS(Results!$L$2:$L$101,Results!$E$2:$E$101,$A16)/COUNTIFS(Results!$E$2:$E$101,$A16,Results!$L$2:$L$101,">0"),"") -> 3.4666667 | G16: =IFERROR(SUMIFS(Results!$M$2:$M$101,Results!$E$2:$E$101,$A16)/COUNTIFS(Results!$E$2:$E$101,$A16,Results!$M$2:$M$101,">0"),"") -> 1.6 | H16: =IFERROR(SUMIFS(Results!$N$2:$N$101,Results!$E$2:$E$101,$A16)/COUNTIFS(Results!$E$2:$E$101,$A16,Results!$N$2:$N$101,">0"),"") | I16: =IFERROR(SUMIFS(Results!$O$2:$O$101,Results!$E$2:$E$101,$A16)/COUNTIFS(Results!$E$2:$E$101,$A16,Results!$O$2:$O$101,">0"),"") -> 4.7333333 | J16: =COUNTIFS(Results!$E$2:$E$101,$A16,Results!$P$2:$P$101,"Да") -> 0 | K16: =IF(COUNTIFS(Results!$E$2:$E$101,$A16,Results!$P$2:$P$101,"<>")=0,"",J16/COUNTIFS(Results!$E$2:$E$101,$A16,Results!$P$2:$P$101,"<>")) | M16: =D16/5*100 -> 64.066667
A17: Поиск мест рядом с заданной точкой | B17: =COUNTIF('Eval Dataset'!$E$2:$E$101,$A17) -> 15 | C17: =COUNTIFS(Results!$E$2:$E$101,$A17,Results!$R$2:$R$101,">0") -> 15 | D17: =IFERROR(SUMIFS(Results!$R$2:$R$101,Results!$E$2:$E$101,$A17)/COUNTIFS(Results!$E$2:$E$101,$A17,Results!$R$2:$R$101,">0"),"") -> 2.9566667 | E17: =IFERROR(SUMIFS(Results!$K$2:$K$101,Results!$E$2:$E$101,$A17)/COUNTIFS(Results!$E$2:$E$101,$A17,Results!$K$2:$K$101,">0"),"") -> 3.2666667 | F17: =IFERROR(SUMIFS(Results!$L$2:$L$101,Results!$E$2:$E$101,$A17)/COUNTIFS(Results!$E$2:$E$101,$A17,Results!$L$2:$L$101,">0"),"") -> 2.9333333 | G17: =IFERROR(SUMIFS(Results!$M$2:$M$101,Results!$E$2:$E$101,$A17)/COUNTIFS(Results!$E$2:$E$101,$A17,Results!$M$2:$M$101,">0"),"") -> 1.9333333 | H17: =IFERROR(SUMIFS(Results!$N$2:$N$101,Results!$E$2:$E$101,$A17)/COUNTIFS(Results!$E$2:$E$101,$A17,Results!$N$2:$N$101,">0"),"") | I17: =IFERROR(SUMIFS(Results!$O$2:$O$101,Results!$E$2:$E$101,$A17)/COUNTIFS(Results!$E$2:$E$101,$A17,Results!$O$2:$O$101,">0"),"") -> 4.8666667 | J17: =COUNTIFS(Results!$E$2:$E$101,$A17,Results!$P$2:$P$101,"Да") -> 0 | K17: =IF(COUNTIFS(Results!$E$2:$E$101,$A17,Results!$P$2:$P$101,"<>")=0,"",J17/COUNTIFS(Results!$E$2:$E$101,$A17,Results!$P$2:$P$101,"<>")) | M17: =D17/5*100 -> 59.133333
A18: Список мест для поездки | B18: =COUNTIF('Eval Dataset'!$E$2:$E$101,$A18) -> 15 | C18: =COUNTIFS(Results!$E$2:$E$101,$A18,Results!$R$2:$R$101,">0") -> 15 | D18: =IFERROR(SUMIFS(Results!$R$2:$R$101,Results!$E$2:$E$101,$A18)/COUNTIFS(Results!$E$2:$E$101,$A18,Results!$R$2:$R$101,">0"),"") -> 3.17 | E18: =IFERROR(SUMIFS(Results!$K$2:$K$101,Results!$E$2:$E$101,$A18)/COUNTIFS(Results!$E$2:$E$101,$A18,Results!$K$2:$K$101,">0"),"") -> 4.8666667 | F18: =IFERROR(SUMIFS(Results!$L$2:$L$101,Results!$E$2:$E$101,$A18)/COUNTIFS(Results!$E$2:$E$101,$A18,Results!$L$2:$L$101,">0"),"") -> 3.8666667 | G18: =IFERROR(SUMIFS(Results!$M$2:$M$101,Results!$E$2:$E$101,$A18)/COUNTIFS(Results!$E$2:$E$101,$A18,Results!$M$2:$M$101,">0"),"") -> 2.6 | H18: =IFERROR(SUMIFS(Results!$N$2:$N$101,Results!$E$2:$E$101,$A18)/COUNTIFS(Results!$E$2:$E$101,$A18,Results!$N$2:$N$101,">0"),"") | I18: =IFERROR(SUMIFS(Results!$O$2:$O$101,Results!$E$2:$E$101,$A18)/COUNTIFS(Results!$E$2:$E$101,$A18,Results!$O$2:$O$101,">0"),"") -> 4.2 | J18: =COUNTIFS(Results!$E$2:$E$101,$A18,Results!$P$2:$P$101,"Да") -> 6 | K18: =IF(COUNTIFS(Results!$E$2:$E$101,$A18,Results!$P$2:$P$101,"<>")=0,"",J18/COUNTIFS(Results!$E$2:$E$101,$A18,Results!$P$2:$P$101,"<>")) -> 0.54545455 | M18: =D18/5*100 -> 63.4
A19: Маршрут на один день | B19: =COUNTIF('Eval Dataset'!$E$2:$E$101,$A19) -> 20 | C19: =COUNTIFS(Results!$E$2:$E$101,$A19,Results!$R$2:$R$101,">0") -> 20 | D19: =IFERROR(SUMIFS(Results!$R$2:$R$101,Results!$E$2:$E$101,$A19)/COUNTIFS(Results!$E$2:$E$101,$A19,Results!$R$2:$R$101,">0"),"") -> 2.9375 | E19: =IFERROR(SUMIFS(Results!$K$2:$K$101,Results!$E$2:$E$101,$A19)/COUNTIFS(Results!$E$2:$E$101,$A19,Results!$K$2:$K$101,">0"),"") -> 4.55 | F19: =IFERROR(SUMIFS(Results!$L$2:$L$101,Results!$E$2:$E$101,$A19)/COUNTIFS(Results!$E$2:$E$101,$A19,Results!$L$2:$L$101,">0"),"") -> 4.35 | G19: =IFERROR(SUMIFS(Results!$M$2:$M$101,Results!$E$2:$E$101,$A19)/COUNTIFS(Results!$E$2:$E$101,$A19,Results!$M$2:$M$101,">0"),"") -> 2.9 | H19: =IFERROR(SUMIFS(Results!$N$2:$N$101,Results!$E$2:$E$101,$A19)/COUNTIFS(Results!$E$2:$E$101,$A19,Results!$N$2:$N$101,">0"),"") -> 3.35 | I19: =IFERROR(SUMIFS(Results!$O$2:$O$101,Results!$E$2:$E$101,$A19)/COUNTIFS(Results!$E$2:$E$101,$A19,Results!$O$2:$O$101,">0"),"") -> 4.6 | J19: =COUNTIFS(Results!$E$2:$E$101,$A19,Results!$P$2:$P$101,"Да") -> 11 | K19: =IF(COUNTIFS(Results!$E$2:$E$101,$A19,Results!$P$2:$P$101,"<>")=0,"",J19/COUNTIFS(Results!$E$2:$E$101,$A19,Results!$P$2:$P$101,"<>")) -> 0.55 | M19: =D19/5*100 -> 58.75
A20: Планирование поездки на несколько дней | B20: =COUNTIF('Eval Dataset'!$E$2:$E$101,$A20) -> 15 | C20: =COUNTIFS(Results!$E$2:$E$101,$A20,Results!$R$2:$R$101,">0") -> 15 | D20: =IFERROR(SUMIFS(Results!$R$2:$R$101,Results!$E$2:$E$101,$A20)/COUNTIFS(Results!$E$2:$E$101,$A20,Results!$R$2:$R$101,">0"),"") -> 2.9433333 | E20: =IFERROR(SUMIFS(Results!$K$2:$K$101,Results!$E$2:$E$101,$A20)/COUNTIFS(Results!$E$2:$E$101,$A20,Results!$K$2:$K$101,">0"),"") -> 4.4 | F20: =IFERROR(SUMIFS(Results!$L$2:$L$101,Results!$E$2:$E$101,$A20)/COUNTIFS(Results!$E$2:$E$101,$A20,Results!$L$2:$L$101,">0"),"") -> 4.2 | G20: =IFERROR(SUMIFS(Results!$M$2:$M$101,Results!$E$2:$E$101,$A20)/COUNTIFS(Results!$E$2:$E$101,$A20,Results!$M$2:$M$101,">0"),"") -> 2.6 | H20: =IFERROR(SUMIFS(Results!$N$2:$N$101,Results!$E$2:$E$101,$A20)/COUNTIFS(Results!$E$2:$E$101,$A20,Results!$N$2:$N$101,">0"),"") -> 3.0666667 | I20: =IFERROR(SUMIFS(Results!$O$2:$O$101,Results!$E$2:$E$101,$A20)/COUNTIFS(Results!$E$2:$E$101,$A20,Results!$O$2:$O$101,">0"),"") -> 4.2 | J20: =COUNTIFS(Results!$E$2:$E$101,$A20,Results!$P$2:$P$101,"Да") -> 7 | K20: =IF(COUNTIFS(Results!$E$2:$E$101,$A20,Results!$P$2:$P$101,"<>")=0,"",J20/COUNTIFS(Results!$E$2:$E$101,$A20,Results!$P$2:$P$101,"<>")) -> 0.46666667 | M20: =D20/5*100 -> 58.866667
A21: Неполные / неоднозначные запросы | B21: =COUNTIF('Eval Dataset'!$E$2:$E$101,$A21) -> 5 | C21: =COUNTIFS(Results!$E$2:$E$101,$A21,Results!$R$2:$R$101,">0") -> 5 | D21: =IFERROR(SUMIFS(Results!$R$2:$R$101,Results!$E$2:$E$101,$A21)/COUNTIFS(Results!$E$2:$E$101,$A21,Results!$R$2:$R$101,">0"),"") -> 2.88 | E21: =IFERROR(SUMIFS(Results!$K$2:$K$101,Results!$E$2:$E$101,$A21)/COUNTIFS(Results!$E$2:$E$101,$A21,Results!$K$2:$K$101,">0"),"") -> 2.4 | F21: =IFERROR(SUMIFS(Results!$L$2:$L$101,Results!$E$2:$E$101,$A21)/COUNTIFS(Results!$E$2:$E$101,$A21,Results!$L$2:$L$101,">0"),"") -> 3.6 | G21: =IFERROR(SUMIFS(Results!$M$2:$M$101,Results!$E$2:$E$101,$A21)/COUNTIFS(Results!$E$2:$E$101,$A21,Results!$M$2:$M$101,">0"),"") -> 2.8 | H21: =IFERROR(SUMIFS(Results!$N$2:$N$101,Results!$E$2:$E$101,$A21)/COUNTIFS(Results!$E$2:$E$101,$A21,Results!$N$2:$N$101,">0"),"") | I21: =IFERROR(SUMIFS(Results!$O$2:$O$101,Results!$E$2:$E$101,$A21)/COUNTIFS(Results!$E$2:$E$101,$A21,Results!$O$2:$O$101,">0"),"") -> 4.4 | J21: =COUNTIFS(Results!$E$2:$E$101,$A21,Results!$P$2:$P$101,"Да") -> 3 | K21: =IF(COUNTIFS(Results!$E$2:$E$101,$A21,Results!$P$2:$P$101,"<>")=0,"",J21/COUNTIFS(Results!$E$2:$E$101,$A21,Results!$P$2:$P$101,"<>")) -> 0.6 | M21: =D21/5*100 -> 57.6
A22: ИТОГО | B22: =SUM(B15:B21) -> 100 | C22: =SUM(C15:C21) -> 100 | D22: =IFERROR(AVERAGE(Results!$R$2:$R$101),"") -> 2.9899 | E22: =IFERROR(AVERAGE(Results!$K$2:$K$101),"") -> 4.098 | F22: =IFERROR(AVERAGE(Results!$L$2:$L$101),"") -> 3.678 | G22: =IFERROR(AVERAGE(Results!$M$2:$M$101),"") -> 2.234 | H22: =IFERROR(AVERAGE(Results!$N$2:$N$101),"") -> 3.2285714 | I22: =IFERROR(AVERAGE(Results!$O$2:$O$101),"") -> 4.47 | J22: =COUNTIF(Results!$P$2:$P$101,"Да") -> 27 | K22: =IF(COUNTIF(Results!$P$2:$P$101,"<>")=0,"",J22/COUNTIF(Results!$P$2:$P$101,"<>")) -> 0.52941176 | M22: =D22/5*100 -> 59.798
A25: Качество по языку запроса
A26: Язык | B26: В датасете | C26: Оценено | D26: Overall | E26: Factuality | F26: Critical errors
A27: en | B27: =COUNTIF('Eval Dataset'!$B$2:$B$101,$A27) -> 70 | C27: =COUNTIFS(Results!$B$2:$B$101,$A27,Results!$R$2:$R$101,">0") -> 70 | D27: =IFERROR(SUMIFS(Results!$R$2:$R$101,Results!$B$2:$B$101,$A27)/COUNTIFS(Results!$B$2:$B$101,$A27,Results!$R$2:$R$101,">0"),"") -> 3.0912857 | E27: =IFERROR(SUMIFS(Results!$M$2:$M$101,Results!$B$2:$B$101,$A27)/COUNTIFS(Results!$B$2:$B$101,$A27,Results!$M$2:$M$101,">0"),"") -> 2.32 | F27: =COUNTIFS(Results!$B$2:$B$101,$A27,Results!$P$2:$P$101,"Да") -> 16
A28: ru | B28: =COUNTIF('Eval Dataset'!$B$2:$B$101,$A28) -> 30 | C28: =COUNTIFS(Results!$B$2:$B$101,$A28,Results!$R$2:$R$101,">0") -> 30 | D28: =IFERROR(SUMIFS(Results!$R$2:$R$101,Results!$B$2:$B$101,$A28)/COUNTIFS(Results!$B$2:$B$101,$A28,Results!$R$2:$R$101,">0"),"") -> 2.7533333 | E28: =IFERROR(SUMIFS(Results!$M$2:$M$101,Results!$B$2:$B$101,$A28)/COUNTIFS(Results!$B$2:$B$101,$A28,Results!$M$2:$M$101,">0"),"") -> 2.0333333 | F28: =COUNTIFS(Results!$B$2:$B$101,$A28,Results!$P$2:$P$101,"Да") -> 11
A31: Методика и оговорки
A32: • маршрутные сценарии (Маршрут на один день, Планирование поездки на несколько дней) — Intent 20% / Relevance 20% / Factuality 25% / Feasibility 25% / Format 10%;
A33: • остальные сценарии — Intent 25% / Relevance 25% / Factuality 35% / Format 15%
A34: • При critical_error = «Да» overall ограничивается сверху значением 2.
A35: • Строки query_id 1–49 — критические ошибки и заметки в них не проставлены, поэтому Critical rate для первых четырёх сценариев занижен и опирается только на строки 51–100.
