Workbook

Sheet Eval Dataset
A1: query_id | B1: language | C1: region | D1: city_country | E1: scenario | F1: request
A2: 1 | B2: en | C2: Europe | D2: Prague, Czechia | E2: Простой поиск мест | F2: Find cozy coffee shops in Prague Old Town.
A3: 2 | B3: en | C3: Europe | D3: Berlin, Germany | E3: Простой поиск мест | F3: Recommend contemporary art museums in Berlin.
A4: 3 | B4: en | C4: Europe | D4: Lisbon, Portugal | E4: Простой поиск мест | F4: Find the best viewpoints in Lisbon for sunset.
A5: 4 | B5: en | C5: Europe | D5: Rome, Italy | E5: Простой поиск мест | F5: Suggest traditional trattorias in Trastevere.
A6: 5 | B6: en | C6: Europe | D6: Amsterdam, Netherlands | E6: Простой поиск мест | F6: Find quiet parks in Amsterdam for a relaxed afternoon.
A7: 6 | B7: en | C7: Europe | D7: Athens, Greece | E7: Простой поиск мест | F7: Recommend archaeological sites in central Athens.
A8: 7 | B8: en | C8: Europe | D8: Copenhagen, Denmark | E8: Простой поиск мест | F8: Find independent Danish design shops in Copenhagen.
A9: 8 | B9: ru | C9: Europe | D9: London, United Kingdom | E9: Простой поиск мест | F9: Порекомендуй бесплатные музеи в центре Лондона.
A10: 9 | B10: ru | C10: Europe | D10: Barcelona, Spain | E10: Простой поиск мест | F10: Найди хорошие веганские кафе в Барселоне.
A11: 10 | B11: en | C11: CIS | D11: Almaty, Kazakhstan | E11: Простой поиск мест | F11: Find family-friendly parks in Almaty.
A12: 11 | B12: en | C12: CIS | D12: Tbilisi, Georgia | E12: Простой поиск мест | F12: Suggest local bakeries in central Tbilisi.
A13: 12 | B13: en | C13: CIS | D13: Baku, Azerbaijan | E13: Простой поиск мест | F13: Find historical museums in Baku.
... A161: 160 | B161: en | C161: Europe | D161: Berlin, Germany | E161: Неполные / неоднозначные запросы | F161: Is it better to spend your time in Berlin in a cultural way, exploring various attractions, or in a chaotic manner without a specific plan?

Sheet Results
A1: query_id | B1: request | C1: answer | D1: answer_with_tools | E1: gate_passed | F1: gate reason | G1: intent | H1: usefulness | I1: factuality | J1: format | K1: constraint adherence | L1: novelty | M1: completeness | N1: overall
A2: 1 | B2: Find cozy coffee shops in Prague Old Town. | C2: Вот несколько уютных кофеен в районе Старого города Праги: ### ☕ Týnská 9 **Адрес:** Týnská 626/9, Praha 1 (всего ~100 метров от Староместской площади) Описание: Тихое кафе в самом сердце Старого города — настоящая оазис тишины. Уютное пространство с арочными сводами, разноцветными скатертями и волшебным двориком с колодцем и плющом. Вечером вас встретят светящиеся гирлянды, а днём — красочные цветы. Идеальное место для чтения, работы за ноутбуком или спокойной беседы. **Часы работы:** ежедневно с 10:00 до 22:00 --- ### ☕ Café Revoluční **Адрес:** Soukenická / Revoluční 1084/14, Nové Město (110 00 Praha) Описание: Кофейня с выбором кофе, домашней выпечкой и бранчем. Интерьер выполнен в тёплых тонах с использованием дерева, мягких цветов и приятного освещения — здесь действительно хочется остаться подольше. Не является сетью и не ориентирована на туристов. **Часы работы:** сегодня, 10 августа, с 07:30 до 18:30 **Телефон:** +420 725 722 887 --- ### ☕ Coffe cube, stánek s nápoji **Адрес:** náměstí Republiky 656/8c stánek **Часы работы:** пн–сб 08:00–19:00 **Статус:** открыто сейчас --- ### ☕ Coffe café, kavárna **Адрес:** Štěpánská 626/63 **Часы работы:** пн–сб 08:00–20:00 **Статус:** открыто сейчас --- *Информация о часах работы актуальна на 10 августа 2026 года.* | D2: Tool result (places_search): {"places":[{"ref":"plc_b244d44328","id":"70000001007533319","name":"Coffe cube, stánek s nápoji","address":"Praha, náměstí Republiky 656/8c stánek","categories":["Fresh bary / Stánky s nealko koktejly / horkými nápoji"],"phones":[],"rating":null,"review_count":null,"hours_text":"пн–сб 08:00–19:00","open_24h":null,"is_open_now":true,"accessibility":[],"distance_m":363},{"ref":"plc_031e84751d","id":"70000001024458517","name":"Coffe café, kavárna","address":"Praha, Štěpánská 626/63","categories":["Kavárny"],"phones":[],"rating":null,"review_count":null,"hours_text":"пн–сб 08:00–20:00","open_24h":null,"is_open_now":true,"accessibility":[],"distance_m":900}],"area":null,"truncated":false,"anchor":"plc_c28e29a276","resolved":[],"returned_count":2} Tool result (web_search): {"query":"cozy coffee shops Prague Old Town","results":[{"ref":"src_979c90a20b","title":"Týnská 9 | Silent café in Prague Old Town","domain":"tynska9.com","snippet":"Týnská 9 | Silent café in Prague Old Town --\n...\nTýnská 9\n...\nCafé & Bar\n...\n## In the Heart of\n...\nYou can find us just 100 meters far from the Old Town Square, the very centre of Prague.\n...\nWe are the right place where you can have Prague's local beer, near-made ciders or fine Moravian wine.\n...\n## Are you looking for a quiet place, where you can contemplate with a book, have a game of chess with a friend, do some work on your laptop, or just have a nice chat? Týnská 9 is exactly that.\n...\nOn a little back street, almost on the Old Town Square, is a magical place, an oasis of silence. A yard with a well and ivy climbing up the walls. In the yard, there is a cosy little café. It has an arched ceiling and the tables are covered with colourful tablecloths. If you come here after dark, you will be greeted by floating fairy lights. If you arrive in daylight, you will see a colourful scenery made up of flowers. This is where our family and friends work. We work here because we like meeting and talking to people, and we like to offer them something nice to drink and to eat. If you come over, you might bump into someone sharing photographs from their journey, or witness one of the art shows that regularly take place there. We kindly invite you to come and enjoy the atmosphere of this unique space.\n...\nOpen daily from 10 am to 10 pm\n...\nThe choice of Dacaffé was a result of years and years of hanging around various cafés in Prague and pretending to understand the coffee.\n...\n, it seems that we learned something - our guests love Dacaffé, Prague's supplier of coffee:\n...\n- www.tynska9.cz\n- info[at]tynska9.cz\n- +420 727 937 998\n- Týnská 9, Praha 1, 110 00, Czech Republic","published_date":null},{"_omitted_items":8},{"ref":"src_cd225fd3cb","title":"Café Revolučni | Výběrová kavárna Praha 1 – Domácí dezerty, pekárna & brunch","domain":"caferevolucni.cz","snippet":"Café Revolučni | Výběrov\n...\nPraha 1 – Domácí dezerty\n...\nAre you looking for a café in Prague 1 where you can have a truly great coffee, a homemade dessert, or a brunch you'll still be thinking about next week? Then you've come to the right place.Café Revoluční stands on the corner of Revoluční Street in Nové Město. We are not a chain. We are not a tourist trap. We are a café, bistro, and homemade bakery all in one. A place where every day, from morning, things are baked, cooked, and prepared with care. This page will show you exactly what you'll find here and why guests are happy to keep coming back.Café Revoluční was created as a place that emphasizes three things: quality of ingredients, design of the space, and a human approach. No semi-finished products, no industrial bread, no coffee from inferior beans.\n...\nThe address Revoluční 1084/14 is not just a number. It is a place in the heart of Prague's historic center, a few minutes' walk from náměstí Republiky (Republic Square), Josefov, and the riverfront. The interior was designed by two architects: Petra Šmejkalová and Andrea Šetinová, and the result speaks for itself. Warm wood, soft colors, pleasant lighting, seating that truly invites you to stay. Coming here in the morning with a laptop, meeting a friend for brunch, or having an afternoon dessert with coffee — every scenario works here.\n...\nBrunch in Prague\n...\n— why ours is differentWe serve brunch every day, all\n...\n, in the heart of Prague 1\n...\nfind the same full menu\n...\n3 in the afternoon\n...\neven if you'\n...\nhad a late\n...\nof this — and none of it gets in\n...\na birthday brunch\n...\na café in the heart\n...\na distribution warehouse\n...\nRevoluční 1084/14 110 00, Nové Město\n...\nAdressRevoluční 1084/14110 00, Nové MěstoContact 725 722 887 info@","published_date":null}]} Tool result (places_search): {"places":[],"area":null,"truncated":false,"anchor":null,"resolved":[{"client_id":"candidate_1","input_name":"Týnská 9","status":"resolved","place":{"ref":"plc_30924460b3","id":"12948484583879079","name":"Týnská 626/9","address":"Praha, Týnská 626/9","categories":[],"phones":[],"rating":null,"review_count":null,"hours_text":null,"open_24h":null,"is_open_now":null,"accessibility":[],"distance_m":null},"options":[],"error":null},{"client_id":"candidate_2","input_name":"Café Revoluční","status":"resolved","place":{"ref":"plc_612c61115b","id":"AZu43AFUay0ke1FsDdUqfQ","name":"Café Revoluční","address":"Soukenická, 110 00 Praha","categories":["restaurant","czech"],"phones":["+420 725 722 887"],"rating":null,"review_count":null,"hours_text":"Next 7 days: Aug 10–14 07:30–18:30; Aug 15 08:00–18:30; Aug 16 08:00–18:00","open_24h":false,"is_open_now":true,"accessibility":[],"distance_m":null},"options":[],"error":null},{"client_id":"candidate_3","input_name":"Coffe cube, stánek s nápoji","status":"resolved","place":{"ref":"plc_b244d44328","id":"70000001007533319","name":"Coffe cube, stánek s nápoji","address":"Praha, náměstí Republiky 656/8c stánek","categories":["Fresh bary / Stánky s nealko koktejly / horkými nápoji"],"phones":[],"rating":null,"review_count":null,"hours_text":"пн–сб 08:00–19:00","open_24h":null,"is_open_now":true,"accessibility":[],"distance_m":null},"options":[],"error":null},{"client_id":"candidate_4","input_name":"Coffe café, kavárna","status":"resolved","place":{"ref":"plc_031e84751d","id":"70000001024458517","name":"Coffe café, kavárna","address":"Praha, Štěpánská 626/63","categories":["Kavárny"],"phones":[],"rating":null,"review_count":null,"hours_text":"пн–сб 08:00–20:00","open_24h":null,"is_open_now":true,"accessibility":[],"distance_m":null},"options":[],"error":null}],"returned_count":4,"warnings":["2GIS place search returned no matches; retrying with TomTom."]} Final answer: Вот несколько уютных кофеен в районе Старого города Праги: ### ☕ Týnská 9 **Адрес:** Týnská 626/9, Praha 1 (всего ~100 метров от Староместской площади) Описание: Тихое кафе в самом сердце Старого города — настоящая оазис тишины. Уютное пространство с арочными сводами, разноцветными скатертями и волшебным двориком с колодцем и плющом. Вечером вас встретят светящиеся гирлянды, а днём — красочные цветы. Идеальное место для чтения, работы за ноутбуком или спокойной беседы. **Часы работы:** ежедневно с 10:00 до 22:00 --- ### ☕ Café Revoluční **Адрес:** Soukenická / Revoluční 1084/14, Nové Město (110 00 Praha) Описание: Кофейня с выбором кофе, домашней выпечкой и бранчем. Интерьер выполнен в тёплых тонах с использованием дерева, мягких цветов и приятного освещения — здесь действительно хочется остаться подольше. Не является сетью и не ориентирована на туристов. **Часы работы:** сегодня, 10 августа, с 07:30 до 18:30 **Телефон:** +420 725 722 887 --- ### ☕ Coffe cube, stánek s nápoji **Адрес:** náměstí Republiky 656/8c stánek **Часы работы:** пн–сб 08:00–19:00 **Статус:** открыто сейчас --- ### ☕ Coffe café, kavárna **Адрес:** Štěpánská 626/63 **Часы работы:** пн–сб 08:00–20:00 **Статус:** открыто сейчас --- *Информация о часах работы актуальна на 10 августа 2026 года.* | E2: FAIL | F2: Language missmatch | G2: 0 | H2: 0 | I2: 0 | K2: 0 | L2: 0 | M2: 0 | N2: =IF($E2="","",IF($E2="FAIL","FAIL",ROUND(G2*15%+H2*15%+I2*25%+J2*10%+K2*20%+M2*5%+L2*10%,2))) -> FAIL
A3: 2 | B3: Recommend contemporary art museums in Berlin. | C3: Вот основные музеи современного искусства в Берлине: ### 1. KW Institute for Contemporary Art - **Адрес:** Auguststraße 69, 10117 Berlin - **Телефон:** +49 30 2434590 - **Часы работы:** Сегодня (10 августа) 11:00–19:00; 11 августа закрыто; 12 августа 11:00–19:00; 13 августа 11:00–21:00; 14–16 августа 11:00–19:00 - **Открыто сейчас:** ✅ Да - **Описание:** Транснациональный институт, глубоко укоренённый в местном контексте. Не имеет постоянной коллекции, что обеспечивает гибкость и открытость. Специализируется на актуальных выставках и программах, отвечающих на вопросы современности. ### 2. Hamburger Bahnhof – Nationalgalerie der Gegenwart - **Адрес:** Invalidenstraße 50, 10557 Berlin - **Телефон:** +49 30 266424242 - **Часы работы:** Сегодня (10 августа) закрыто; 11–12 августа 10:00–18:00; 13 августа 10:00–20:00; 14–16 августа 10:00–18:00 - **Открыто сейчас:** ❌ Нет - **Описание:** Главный музей современного искусства Берлина. Расположен в здании бывшей железнодорожной станции XIX века. Представляет коллекции, специальные выставки и событийные форматы. Входной билет: 16,00 € (льготный 8,00 €), дети до 18 лет бесплатно. ### 3. Berlinische Galerie - **Адрес:** Alte Jakobstraße 124, 10969 Berlin - **Телефон:** +49 30 78902600 - **Часы работы:** Сегодня (10 августа) 10:00–18:00; 11 августа закрыто; 12 августа 10:00–18:00; 13 августа 10:00–20:00; 14–16 августа 10:00–18:00 - **Открыто сейчас:** ✅ Да - **Описание:** Музей современного искусства Берлина с серьёзным международным охватом программ. ### 4. Neue Nationalgalerie - **Адрес:** Potsdamer Straße 50, 10785 Berlin - **Телефон:** +49 30 266424242 - **Часы работы:** Сегодня (10 августа) закрыто; 11–12 августа 10:00–18:00; 13 августа 10:00–20:00; 14–16 августа 10:00–18:00 - **Открыто сейчас:** ❌ Нет - **Описание:** Часть Национальной галереи, специализирующаяся на искусстве XX–XXI веков. ### 5. Gropius Bau - **Адрес:** Niederkirchnerstraße 7, 10963 Berlin - **Телефон:** +49 30 254860 - **Описание:** Выставочная площадка с международным охватом программ современного искусства. ### 6. Sammlung Boros - **Адрес:** Reinhardtstraße 20, 10117 Berlin - **Телефон:** +49 30 27594065 - **Часы работы:** Сегодня (10 августа) закрыто; 13–16 августа 10:00–20:00 - **Описание:** Частная коллекция современного искусства, расположенная в бывшем бункере времён Второй мировой войны. --- **Примечание:** Сегодня (10 августа) открыты KW Institute for Contemporary Art и Berlinische Galerie. Остальные музеи откроются завтра (11 августа). *Источники:,* | D3: Tool result (places_search): {"places":[{"ref":"plc_130d1074d6","id":"62FqLZ8XAB0g5PifIo8huA","name":"Bode-Museum","address":"Am Kupfergraben 1, 10117 Berlin","categories":["museum"],"phones":["+49 30 266424242"],"rating":null,"review_count":null,"hours_text":"Next 7 days: Aug 10 closed; Aug 11–16 10:00–18:00","open_24h":false,"is_open_now":false,"accessibility":[],"distance_m":null},{"ref":"plc_9ba49d8728","id":"B4qfD2jyfhPan3KGAgbUuw","name":"New National Gallery","address":"Reichpietschufer 46, 10785 Berlin","categories":["museum"],"phones":["+49 30 2662651"],"rating":null,"review_count":null,"hours_text":null,"open_24h":null,"is_open_now":null,"accessibility":[],"distance_m":null},{"ref":"plc_86d205e6aa","id":"N097s3JWBtbnHGybIVMLgA","name":"Museum of Technology","address":"Tempelhofer Ufer 31, 10963 Berlin","categories":["museum"],"phones":["+49 30 4397340"],"rating":null,"review_count":null,"hours_text":null,"open_24h":null,"is_open_now":null,"accessibility":[],"distance_m":null},{"ref":"plc_289475b302","id":"K75k5d46RUzo1gxUMouREQ","name":"Sammlung Boros","address":"Reinhardtstraße 20, 10117 Berlin","categories":["museum"],"phones":["+49 30 27594065"],"rating":null,"review_count":null,"hours_text":"Next 7 days: Aug 10–12 closed; Aug 13–16 10:00–20:00","open_24h":false,"is_open_now":false,"accessibility":[],"distance_m":null},{"ref":"plc_f2f1c2539f","id":"N36mrtM_3kl4_SialxosTA","name":"Pergamon Museum","address":"Bodestraße 1, 10178 Berlin","categories":["museum"],"phones":["+49 30 266424242"],"rating":null,"review_count":null,"hours_text":"Next 7 days: Aug 10 closed; Aug 11–12 10:00–18:00; Aug 13 10:00–20:00; Aug 14–16 10:00–18:00","open_24h":false,"is_open_now":false,"accessibility":[],"distance_m":null},{"ref":"plc_fc63da8d00","id":"psdgFQ03O6jc1PgPKIx2Kg","name":"Altes Museum","address":"Am Lustgarten, 10178 Berlin","categories":["museum"],"phones":["+49 30 266424242"],"rating":null,"review_count":null,"hours_text":"Next 7 days: Aug 10 closed; Aug 11–16 10:00–18:00","open_24h":false,"is_open_now":false,"accessibility":[],"distance_m":null},{"ref":"plc_8fae6ed365","id":"QkGpHypwq0M7O02MGMMlVQ","name":"Neues Museum","address":"Bodestraße, 10178 Berlin","categories":["museum"],"phones":["+49 30 266424242"],"rating":null,"review_count":null,"hours_text":"Next 7 days: Aug 10 closed; Aug 11–16 10:00–18:00","open_24h":false,"is_open_now":false,"accessibility":[],"distance_m":null},{"ref":"plc_ddffa824dd","id":"Oz2lhDov2tODfrR82vN_ew","name":"Topography of Terror","address":"Niederkirchnerstraße 8, 10963 Berlin","categories":["museum"],"phones":["+49 30 25486703"],"rating":null,"review_count":null,"hours_text":"Next 7 days: Aug 10–16 10:00–20:00","open_24h":false,"is_open_now":true,"accessibility":[],"distance_m":null},{"ref":"plc_8bf1611d5b","id":"f8sdALrHhP-5Vljtu8sr7Q","name":"Classic Remise Berlin","address":"Wiebestraße 37, 10553 Berlin","categories":["museum"],"phones":["+49 30 3640780"],"rating":null,"review_count":null,"hours_text":"Next 7 days: Aug 10–15 08:00–20:00; Aug 16 10:00–20:00","open_24h":false,"is_open_now":true,"accessibility":[],"distance_m":null},{"ref":"plc_7d21835e86","id":"C9n4hK9bi6FHZCjjv_nc7A","name":"Deutsches Historisches Museum","address":"Unter den Linden 2, 10117 Berlin","categories":["museum"],"phones":["+49 30 203040"],"rating":null,"review_count":null,"hours_text":"Next 7 days: Aug 10–12 10:00–18:00; Aug 13 10:00–20:00; Aug 14–16 10:00–18:00","open_24h":false,"is_open_now":true,"accessibility":[],"distance_m":null}],"area":{"ref":"plc_5655f612cc","name":"Berlin","address":"Berlin, Deutschland"},"truncated":true,"anchor":null,"resolved":[],"returned_count":10,"warnings":["2GIS does not cover the requested locality; using TomTom."]} Tool result (web_search): {"query":"contemporary art museums in Berlin","results":[{"ref":"src_e4315ac44c","title":"KW Institute for Contemporary Art","domain":"www.kw-berlin.de","snippet":"KW Institute for Contemporary Art\n...\nKW Institute for Contemporary Art engages with the central questions of our time through the production, presentation, and discussion of art. Attuned to the evolving needs of Berlin’s artists and practitioners, KW occupies a unique position as a transnational institution deeply rooted in our local context. Without a permanent collection, flexibility and openness lie at the heart of what makes KW special, as well as creating dynamic and timely programming that resonates with our times and audience. Who we are\n...\nSupport KW and Berlin Biennale\n...\nKW Friends is a non-profit organisation in support of KW Institute for Contemporary Art and the Berlin Biennale for Contemporary Art. Become a Friend and discover our art-community!","published_date":null},{"_omitted_items":8},{"ref":"src_7809a395bb","title":"Museumsportal Berlin - Museum – Hamburger Bahnhof – Nationalgalerie der Gegenwart","domain":"www.museumsportal-berlin.de","snippet":"Museumsportal Berlin - Museum – Hamburger Bahnhof – Nationalgalerie der Gegenwart\n...\nenstraße\n...\nMuseum für Gegenwart\n...\nBerlin, Invaliden\n...\n50,\n...\nThe Hamburger Bahnhof - Nationalgalerie der Gegenwart is Berlin's museum for contemporary art, which presents collections, special exhibitions and event formats. It is the largest building of the Nationalgalerie, whose extensive holdings can also be found in the Alte Nationalgalerie, the Neue Nationalgalerie, the Museum Berggruen and the Scharf-Gerstenberg Collection. \n\nAs one of Berlin's major railway terminus stations of the 19th century, it has always been a place of arrival, departure and transition. This history still characterises the museum in the centre of Berlin today. Today, art and society meet here. Art as an expression of human experience opens up new perspectives on our present and invites debate. Art creates spaces for dialogue and encounters - everyone brings something of their own, and together a polyphonic space is created.\n...\n### Location,\n\n Invalidenstraße 50-51, 10557 Berlin \n\nThird-party OpenStreetMap cookies By loading the map, you accept OpenStreetMaps' privacy policy of OpenStreetMap.\n...\nEmail,\n...\n### Prices,\n\n Admission price 16,00 € \n\nHamburger Bahnhof Nationalgalerie der Gegenwart + temporary exhibitions\n\n Reduced price 8,00 € \n\nChildren and young people up to the age of 18 are admitted free of charge.\n...\nNationalgalerie\n...\nNationalgalerie\n...\nNationalgalerie\n...\nNationalgalerie\n...\nHamburger Bahnhof – National\n...\nHamburger Bahnhof – National\n...\nHamburger Bahnhof – National\n...\nHamburger Bahnhof – Nationalgalerie\n...\nHamburger Bahnhof – Nationalgalerie\n...\nHamburger Bahnhof – National\n...\nHamburger Bahnhof – Nationalgalerie der Gegenwart\n...\nHamburger Bahnhof – Nationalgalerie","published_date":null}]} Tool result (web_search): {"query":"best contemporary art museums Berlin list","results":[{"ref":"src_8477b7eaf5","title":"Art museums | visitBerlin.de","domain":"www.visitberlin.de","snippet":"The old masters, important Modernist works and contemporary art: In Berlin's art museums you can wander through all eras of art history.\n...\nPay a visit to Nefertiti in the Neues Museum(New Museum) a…","published_date":null},{"_omitted_items":8},{"ref":"src_15cd75a207","title":"Berlin Contemporary Art Map – Galleries & Artist-Run Spaces | 1 Cubic Meter","domain":"1cubicmeter.com","snippet":"On the institutional side, Berlin carries real weight. Hamburger Bahnhof, KW Institute for Contemporary Art, the Berlinische Galerie, and Gropius Bau all run programs with serious international reach…","published_date":null}]} Tool result (places_search): {"places":[],"area":null,"truncated":false,"anchor":null,"resolved":[{"client_id":"kw_institute","input_name":"KW Institute for Contemporary Art","status":"resolved","place":{"ref":"plc_b7ca608b38","id":"g-qiS25EQD4MPWRMaai6_w","name":"KW Institute for Contemporary Art","address":"Auguststraße 69, 10117 Berlin","categories":["museum"],"phones":["+49 30 2434590"],"rating":null,"review_count":null,"hours_text":"Next 7 days: Aug 10 11:00–19:00; Aug 11 closed; Aug 12 11:00–19:00; Aug 13 11:00–21:00; Aug 14–16 11:00–19:00","open_24h":false,"is_open_now":true,"accessibility":[],"distance_m":null},"options":[],"error":null},{"client_id":"hamburger_bahnhof","input_name":"Hamburger Bahnhof – Nationalgalerie der Gegenwart","status":"resolved","place":{"ref":"plc_70818d6680","id":"nEK1GUAVbZ3Qkbuq7Xf3Aw","name":"Hamburger Bahnhof-Nationalgalerie der Gegenwart","address":"Invalidenstraße 50, 10557 Berlin","categories":["museum"],"phones":["+49 30 266424242"],"rating":null,"review_count":null,"hours_text":"Next 7 days: Aug 10 closed; Aug 11–12 10:00–18:00; Aug 13 10:00–20:00; Aug 14 10:00–18:00; Aug 15–16 11:00–18:00","open_24h":false,"is_open_now":false,"accessibility":[],"distance_m":null},"options":[],"error":null},{"client_id":"berlinische_galerie","input_name":"Berlinische Galerie","status":"resolved","place":{"ref":"plc_7b0c73b08b","id":"Wc5e36L9ytb8zTCQGG5LVg","name":"Berlinische Galerie","address":"Alte Jakobstraße 124, 10969 Berlin","categories":["museum"],"phones":["+49 30 78902600"],"rating":null,"review_count":null,"hours_text":"Next 7 days: Aug 10 10:00–18:00; Aug 11 closed; Aug 12 10:00–18:00; Aug 13 10:00–20:00; Aug 14–16 10:00–18:00","open_24h":false,"is_open_now":true,"accessibility":[],"distance_m":null},"options":[],"error":null},{"client_id":"gropius_bau","input_name":"Gropius Bau","status":"resolved","place":{"ref":"plc_e9bc9536ef","id":"43CtefL5_ArV9s2FvBgsjQ","name":"Gropius-Bau","address":"Niederkirchnerstraße 7, 10963 Berlin","categories":["restaurant"],"phones":["+49 30 254860"],"rating":null,"review_count":null,"hours_text":null,"open_24h":null,"is_open_now":null,"accessibility":[],"distance_m":null},"options":[],"error":null},{"client_id":"neue_nationalgalerie","input_name":"Neue Nationalgalerie","status":"resolved","place":{"ref":"plc_0089f2f30f","id":"7bHZidh3Mef8hhSMoro3JA","name":"Neue Nationalgalerie","address":"Potsdamer Straße 50, 10785 Berlin","categories":["museum"],"phones":["+49 30 266424242"],"rating":null,"review_count":null,"hours_text":"Next 7 days: Aug 10 closed; Aug 11–12 10:00–18:00; Aug 13 10:00–20:00; Aug 14–16 10:00–18:00","open_24h":false,"is_open_now":false,"accessibility":[],"distance_m":null},"options":[],"error":null}],"returned_count":5,"warnings":["2GIS does not cover the requested locality; using TomTom."]} Final answer: Вот основные музеи современного искусства в Берлине: ### 1. KW Institute for Contemporary Art - **Адрес:** Auguststraße 69, 10117 Berlin - **Телефон:** +49 30 2434590 - **Часы работы:** Сегодня (10 августа) 11:00–19:00; 11 августа закрыто; 12 августа 11:00–19:00; 13 августа 11:00–21:00; 14–16 августа 11:00–19:00 - **Открыто сейчас:** ✅ Да - **Описание:** Транснациональный институт, глубоко укоренённый в местном контексте. Не имеет постоянной коллекции, что обеспечивает гибкость и открытость. Специализируется на актуальных выставках и программах, отвечающих на вопросы современности. ### 2. Hamburger Bahnhof – Nationalgalerie der Gegenwart - **Адрес:** Invalidenstraße 50, 10557 Berlin - **Телефон:** +49 30 266424242 - **Часы работы:** Сегодня (10 августа) закрыто; 11–12 августа 10:00–18:00; 13 августа 10:00–20:00; 14–16 августа 10:00–18:00 - **Открыто сейчас:** ❌ Нет - **Описание:** Главный музей современного искусства Берлина. Расположен в здании бывшей железнодорожной станции XIX века. Представляет коллекции, специальные выставки и событийные форматы. Входной билет: 16,00 € (льготный 8,00 €), дети до 18 лет бесплатно. ### 3. Berlinische Galerie - **Адрес:** Alte Jakobstraße 124, 10969 Berlin - **Телефон:** +49 30 78902600 - **Часы работы:** Сегодня (10 августа) 10:00–18:00; 11 августа закрыто; 12 августа 10:00–18:00; 13 августа 10:00–20:00; 14–16 августа 10:00–18:00 - **Открыто сейчас:** ✅ Да - **Описание:** Музей современного искусства Берлина с серьёзным международным охватом программ. ### 4. Neue Nationalgalerie - **Адрес:** Potsdamer Straße 50, 10785 Berlin - **Телефон:** +49 30 266424242 - **Часы работы:** Сегодня (10 августа) закрыто; 11–12 августа 10:00–18:00; 13 августа 10:00–20:00; 14–16 августа 10:00–18:00 - **Открыто сейчас:** ❌ Нет - **Описание:** Часть Национальной галереи, специализирующаяся на искусстве XX–XXI веков. ### 5. Gropius Bau - **Адрес:** Niederkirchnerstraße 7, 10963 Berlin - **Телефон:** +49 30 254860 - **Описание:** Выставочная площадка с международным охватом программ современного искусства. ### 6. Sammlung Boros - **Адрес:** Reinhardtstraße 20, 10117 Berlin - **Телефон:** +49 30 27594065 - **Часы работы:** Сегодня (10 августа) закрыто; 13–16 августа 10:00–20:00 - **Описание:** Частная коллекция современного искусства, расположенная в бывшем бункере времён Второй мировой войны. --- **Примечание:** Сегодня (10 августа) открыты KW Institute for Contemporary Art и Berlinische Galerie. Остальные музеи откроются завтра (11 августа). *Источники:,* | E3: PASS | G3: 5 | H3: 4 | I3: 4 | J3: 5 | K3: 5 | L3: 4 | M3: 5 | N3: =IF($E3="","",IF($E3="FAIL","FAIL",ROUND(G3*15%+H3*15%+I3*25%+J3*10%+K3*20%+M3*5%+L3*10%,2))) -> 4.5
A4: 3 | B4: Find the best viewpoints in Lisbon for sunset. | C4: Based on my research, here are the **best viewpoints in Lisbon for watching the sunset**: --- ## 🌅 Top Sunset Viewpoints in Lisbon ### 1. **Miradouro da Senhora do Monte** ⭐ Highest Point - **Location:** Graça hill, northern edge of the old city - **Why it's special:** The highest viewpoint in Lisbon, offering the most complete panorama — terracotta rooftops, São Jorge Castle, and the Tagus River stretching into the distance - **Atmosphere:** Magical golden hour light, but busier than sunrise; arrive early and bring a light layer (the exposed hilltop can be breezy) - **Access:** Free ### 2. **Miradouro de Santa Catarina** - **Why it's special:** Expansive terrace with far-reaching views across the Tagus River - **Atmosphere:** Lively and social — often filled with youthful chatter, street musicians, and clinking glasses from nearby bars - **Best for:** Those who enjoy a vibrant, communal sunset experience ### 3. **Parque Eduardo VII (Northwestern Observation Deck)** - **Why it's special:** A sloped park that feels like you're descending toward the water; position yourself at the northwestern observation deck for a dramatic vista straight down the green lawn toward the Marquês de Pombal monument and the Tagus River - **Best for:** A scenic, open-air setting with sweeping views ### 4. **Ribeira das Naus** - **Location:** Riverside promenade (former shipyard area) - **Why it's special:** Watch the sun set *behind* the iconic 25th of April Bridge from ground level by the water - **Atmosphere:** Relaxed — people relax on wide steps, bike along the path, or sunbathe at the sandy beach area - **Best for:** A riverside sunset with bridge silhouettes ### 5. **MAAT Rooftop** - **Location:** Museum of Art, Architecture and Technology (MAAT), riverside landmark - **Why it's special:** Smooth, curving architecture with direct views of the river and 25th of April Bridge - **Bonus:** Completely free to the public — no museum ticket required - **Best for:** Modern architecture lovers and unobstructed river views ### 6. **Miradouro da Graça (Sophia de Mello Breyner Andresen)** - **Location:** Rua dos Lagares, 1100 Lisboa - **Why it's special:** Lower than Senhora do Monte but more social, with a café and kiosk on-site - **Atmosphere:** Relaxed and accessible, great for lingering with a drink - **Access:** Open 24 hours ### 7. **Castelo de São Jorge Viewpoint** - **Why it's special:** Lisbon's most iconic miradouro, built at the end of the 18th century with supporting walls dating back to the 14th century. Offers a monumental panoramic view dominating the entire landscape, with cannons pointing toward the river - **Atmosphere:** Historic and dramatic, with shade from indigenous trees - **Note:** Requires a climb up to the castle --- ## 💡 Tips for Sunset Viewing - **Arrive early** — popular spots fill up quickly during golden hour - **Bring a light layer** — especially for elevated viewpoints like Senhora do Monte, which can be cooler and windier - **Sunset timing in August:** Around 20:30–21:00 local time in Lisbon - **Free options:** Most miradouros are free; MAAT rooftop is also free Would you like help planning a route between any of these viewpoints or getting directions to a specific one? | D4: Tool result (places_search): {"places":[{"ref":"plc_78018ac931","id":"9q_IQFmptX82bByHEJwVgQ","name":"Telecabine Lisboa","address":"Passeio das Tágides, 1990 Lisboa","categories":["scenic/panoramic view"],"phones":["+351 21 895 6143"],"rating":null,"review_count":null,"hours_text":"Next 7 days: Aug 10–16 11:00–18:00","open_24h":false,"is_open_now":false,"accessibility":[],"distance_m":null},{"ref":"plc_b2169efd51","id":"6yxYqEmR5XDUevE_sAKbFg","name":"Jacarandás do Restelo","address":"Avenida do Restelo, 1400 Lisboa","categories":["scenic/panoramic view"],"phones":[],"rating":null,"review_count":null,"hours_text":"Open 24 hours for the next 7 days","open_24h":true,"is_open_now":true,"accessibility":[],"distance_m":null},{"ref":"plc_16566ae328","id":"HwYybqVO7fol8QVF7J57uw","name":"Miradouro dos Barros","address":"Rua Damasceno Monteiro, 1170 Lisboa","categories":["scenic/panoramic view"],"phones":[],"rating":null,"review_count":null,"hours_text":"Open 24 hours for the next 7 days","open_24h":true,"is_open_now":true,"accessibility":[],"distance_m":null},{"ref":"plc_0a631f6f2b","id":"EI1tXdWFYEaooNb7cQSNRA","name":"Miradouro do Chão do Loureiro","address":"Calçada do Marquês de Tancos, 1100 Lisboa","categories":["scenic/panoramic view"],"phones":[],"rating":null,"review_count":null,"hours_text":null,"open_24h":null,"is_open_now":null,"accessibility":[],"distance_m":null},{"ref":"plc_b6abf394a1","id":"P89rdmELWnB7-FePmHNiow","name":"Zona de Spotters","address":"Avenida Santos e Castro, 1750 Lisboa","categories":["scenic/panoramic view"],"phones":[],"rating":null,"review_count":null,"hours_text":"Open 24 hours for the next 7 days","open_24h":true,"is_open_now":true,"accessibility":[],"distance_m":null},{"ref":"plc_55541d3af3","id":"TBBTY_4hXEsjmhUo1QsMSg","name":"Miradouro do Jardim do Torel","address":"Travessa da Cruz do Torel, 1150 Lisboa","categories":["scenic/panoramic view"],"phones":[],"rating":null,"review_count":null,"hours_text":"Next 7 days: Aug 10–16 08:00–20:00","open_24h":false,"is_open_now":true,"accessibility":[],"distance_m":null},{"ref":"plc_ce4c3f0535","id":"pJ0bcpEYkdwZTIO4dXHcCw","name":"Miradouro do Bairro do Alvito","address":"Estrada do Clube de Ténis, 1300 Lisboa","categories":["scenic/panoramic view"],"phones":[],"rating":null,"review_count":null,"hours_text":"Open 24 hours for the next 7 days","open_24h":true,"is_open_now":true,"accessibility":[],"distance_m":null},{"ref":"plc_7ad6ea9d4b","id":"AbitAsQ4q4uAmW8R1qY94w","name":"Miradouro do Arboreto","address":"Estacada do Arboreto, 1990 Lisboa","categories":["scenic/panoramic view"],"phones":[],"rating":null,"review_count":null,"hours_text":"Open 24 hours for the next 7 days","open_24h":true,"is_open_now":true,"accessibility":[],"distance_m":null},{"ref":"plc_1d6fe4d932","id":"-QqUy3HvBNzhmxiGNoFqUg","name":"Miradouro dos Moinhos de Santana","address":"Rua Tristão Vaz, 1400 Lisboa","categories":["scenic/panoramic view"],"phones":["+351 915 225 592"],"rating":null,"review_count":null,"hours_text":"Next 7 days: Aug 10–16 09:00–18:00","open_24h":false,"is_open_now":false,"accessibility":[],"distance_m":null},{"ref":"plc_44f1f0a8c5","id":"8Sy3KR3XJXubdLjXXZ9Gzw","name":"Miradouro da Graça (Sophia de Mello Breyner Andresen)","address":"Rua dos Lagares, 1100 Lisboa","categories":["scenic/panoramic view"],"phones":["+351 21 031 2899"],"rating":null,"review_count":null,"hours_text":"Open 24 hours for the next 7 days","open_24h":true,"is_open_now":true,"accessibility":[],"distance_m":null}],"area":{"ref":"plc_904cc2fb84","name":"Lisboa","address":"Lisboa, Portugal Continental, Portugal"},"truncated":true,"anchor":null,"resolved":[],"returned_count":10,"warnings":["2GIS does not cover the requested locality; using TomTom.","TomTom supplied neither opening hours nor a phone number for 1 results; their current operation could not be verified from this response."]} Tool result (web_search): {"query":"best viewpoints in Lisbon for sunset 2026","results":[{"ref":"src_85e6939ec0","title":"8 sunset spots in Lisbon for the best golden hour views","domain":"www.getyourguide.com","snippet":"Since Lisbon is a city of hills, there are numerous elevated viewpoints like Miradouro da Senhora do Monte that make for top-tier sunset spots. Prefer a sunset from down by the water? Riverfront destinations like the Ribeira das Naus promenade are where to go. Covering locations above the city as well as those down on the water, this guide on where to watch the sunset in Lisbon points you in the right direction.\n...\nIf you think the higher the better with sunset viewing, then you have to visit Miradouro da Senhora do Monte — the highest point in the city. At this popular lookout point at the Chapel of Our Lady of the Mountain, you’ll see a sea of terracotta rooftops all the way to São Jorge Castle and the Tagus River as the sun goes down.\n...\nOften buzzing with youthful chatter, music from street performers, and the sound of clinking beer glasses, the expansive terrace at the Miradouro de Santa Catarina makes for one of the best places to watch the sunset in Lisbon with its far-reaching views across the Tagus River.\n...\nWith its sloped design, the well-manicured Parque Eduardo VII seems like it’s delivering you right to the water. For a spectacular sunset view, position yourself at the observation deck at the park’s northwestern section to look straight down the green lawn to the Marquês de Pombal monument and the Tagus River.\n...\nOnce a shipyard, Ribeira das Naus is a riverfront promenade where you’ll find people relaxing on the wide steps, biking up and down the path, and sunbathing at the sandy beach area. Sunset is a special time here since you can watch the sun go down behind the 25th of April Bridge in the distance.\n...\nof Art, Architecture, and Technology (MAAT) is an eye-catching riverside landmark with its smooth, curving design, and one of its coolest features is a rooftop accessible to pedestrians. Better still, it’s free to the public — no museum ticket necessary. With its direct views of the river and 25th of April Bridge, it’s one of","published_date":"2026-07-13"},{"_omitted_items":8},{"ref":"src_b02c9d8d2b","title":"Miradouro de São Jorge | Visit Lisboa","domain":"www.visitlisboa.com","snippet":"## Miradouro de São Jorge\n...\nLet the most iconic miradouro in Lisbon cast its spell over you. Earn the right to the best view in the city after tackling the steep climb up to the castle.\n...\nLisbon’s most iconic viewing point, or miradouro, is inside the Castelo de São Jorge and has a monumental panoramic view of the city and river, dominating the whole surrounding landscape. It was built at the end of the 18th century, but its supporting walls date from the 14th. Much of it was totally rebuilt in 1940 in a massive preservation exercise. The miradouro is inside the castle and is an ideal place to rest after wandering up the streets to reach it. Its cannons point towards the river in an eternal challenge to whoever dares to invade this proud city. With endless shade offered by magnificent examples of indigenous trees, this is an obligatory place to stop and contemplate Lisbon.","published_date":null}]} Tool result (web_search): {"query":"Miradouro da Senhora do Monte sunset Lisbon best view 2026","results":[{"ref":"src_6dec0faa5c","title":"Miradouro da Senhora do Monte: Best Time + Route · Love Lisbon","domain":"lovelisbon.com","snippet":"- One of Lisbon’s biggest panoramas — rooftops, river, and the whole city layout.\n- Best at sunrise for calm; magical at sunset for warm light (but busier).\n- Plan it as ‘up first, down later’ so the hill feels satisfying, not exhausting.\n- Pair it with Graça’s streets and Alfama’s lanes for a perfect old-Lisbon day.\n- Bring a light layer — the hill can catch a cooler breeze.\n- Choose one viewpoint per day and linger (this one is a great pick).\n...\nIf you want Senhora do Monte to feel peaceful, sunrise is the move. You’ll get softer light, quieter streets, and that rare feeling of having Lisbon to yourself.\n...\nIf you want romance, sunset is beautiful — just expect more people. The trick is to arrive early, bring a light layer, and treat it as the evening anchor rather than one stop in a rushed list.\n...\n- Calmest: sunrise (or early morning).\n- Most cinematic: golden hour into sunset (busier, but gorgeous).\n- Best habit: show up early and stay a little after the sun drops.\n...\nMiradouro da Senhora do Monte sits at the top of the Graça hill, on the northern edge of the old city — it’s one of the highest of Lisbon’s named viewpoints, which is exactly why the panorama is so complete. From the terrace, beside a small chapel, you look back across the entire historic city: the castle on its hill in the foreground, the rooftops of Mouraria and Baixa below, and the Tagus stretching wide behind it all.\n...\n. The nearby Miradouro da Graça is lower and more social, with a café and a kiosk\n...\nBecause it’s exposed at the top of the hill, it can be breezy and cooler than the streets below; bring a light layer, especially for sunrise or after sunset. The classic mistake is treating it as a quick tram stop — the reward is in lingering, so build it into a slower plan rather than a dash. And as with anywhere a crowd gathers at sunset, keep an eye on your belongings. Treat any kiosk or vendor specifics as worth confirming on the day, since they change.","published_date":"2026-02-10"},{"_omitted_items":3},{"ref":"src_3f72d17222","title":"Miradouro da Senhora do Monte - Like A Local Guide","domain":"likealocalguide.com","snippet":"Miradouro da Senhora do Monte - Like A Local Guide\n\n# Miradouro da Senhora do Monte\n\nGraça • ★ 4.7 • $\n\nThe highest of Lisbon’s viewpoints, offering castle, rooftops and river in one sweep at sunset. Up in Graca, this free-to-enjoy lookout is a local favourite for golden hour. Bring a drink and settle in as the light softens over the city.","published_date":"2026-07-03"}]} Final answer: Based on my research, here are the **best viewpoints in Lisbon for watching the sunset**: --- ## 🌅 Top Sunset Viewpoints in Lisbon ### 1. **Miradouro da Senhora do Monte** ⭐ Highest Point - **Location:** Graça hill, northern edge of the old city - **Why it's special:** The highest viewpoint in Lisbon, offering the most complete panorama — terracotta rooftops, São Jorge Castle, and the Tagus River stretching into the distance - **Atmosphere:** Magical golden hour light, but busier than sunrise; arrive early and bring a light layer (the exposed hilltop can be breezy) - **Access:** Free ### 2. **Miradouro de Santa Catarina** - **Why it's special:** Expansive terrace with far-reaching views across the Tagus River - **Atmosphere:** Lively and social — often filled with youthful chatter, street musicians, and clinking glasses from nearby bars - **Best for:** Those who enjoy a vibrant, communal sunset experience ### 3. **Parque Eduardo VII (Northwestern Observation Deck)** - **Why it's special:** A sloped park that feels like you're descending toward the water; position yourself at the northwestern observation deck for a dramatic vista straight down the green lawn toward the Marquês de Pombal monument and the Tagus River - **Best for:** A scenic, open-air setting with sweeping views ### 4. **Ribeira das Naus** - **Location:** Riverside promenade (former shipyard area) - **Why it's special:** Watch the sun set *behind* the iconic 25th of April Bridge from ground level by the water - **Atmosphere:** Relaxed — people relax on wide steps, bike along the path, or sunbathe at the sandy beach area - **Best for:** A riverside sunset with bridge silhouettes ### 5. **MAAT Rooftop** - **Location:** Museum of Art, Architecture and Technology (MAAT), riverside landmark - **Why it's special:** Smooth, curving architecture with direct views of the river and 25th of April Bridge - **Bonus:** Completely free to the public — no museum ticket required - **Best for:** Modern architecture lovers and unobstructed river views ### 6. **Miradouro da Graça (Sophia de Mello Breyner Andresen)** - **Location:** Rua dos Lagares, 1100 Lisboa - **Why it's special:** Lower than Senhora do Monte but more social, with a café and kiosk on-site - **Atmosphere:** Relaxed and accessible, great for lingering with a drink - **Access:** Open 24 hours ### 7. **Castelo de São Jorge Viewpoint** - **Why it's special:** Lisbon's most iconic miradouro, built at the end of the 18th century with supporting walls dating back to the 14th century. Offers a monumental panoramic view dominating the entire landscape, with cannons pointing toward the river - **Atmosphere:** Historic and dramatic, with shade from indigenous trees - **Note:** Requires a climb up to the castle --- ## 💡 Tips for Sunset Viewing - **Arrive early** — popular spots fill up quickly during golden hour - **Bring a light layer** — especially for elevated viewpoints like Senhora do Monte, which can be cooler and windier - **Sunset timing in August:** Around 20:30–21:00 local time in Lisbon - **Free options:** Most miradouros are free; MAAT rooftop is also free Would you like help planning a route between any of these viewpoints or getting directions to a specific one? | E4: PASS | G4: 5 | H4: 4 | I4: 3 | J4: 5 | K4: 5 | L4: 4 | M4: 5 | N4: =IF($E4="","",IF($E4="FAIL","FAIL",ROUND(G4*15%+H4*15%+I4*25%+J4*10%+K4*20%+M4*5%+L4*10%,2))) -> 4.25
A5: 4 | B5: Suggest traditional trattorias in Trastevere. | C5: Based on my search, here are two well-known traditional trattorias in Trastevere, Rome: --- ### 🍝 **Checco Er Carettiere** - **Address:** Via Benedetta 10, 00153 Roma - **Phone:** +39 06 580 0985 - **History:** A historic family-run trattoria that opened in 1935, making it one of the oldest restaurants in the neighborhood. The establishment has been passed down through generations of the Checco family. - **Hours (Aug 10–16):** 12:00–15:00, 19:00–24:00 - **Currently open:** ✅ Yes --- ### 🍝 **Trattoria da Lucia** - **Address:** Vicolo del Mattonato 2, 00153 Roma - **Phone:** +39 06 580 3601 - **History:** A beloved traditional trattoria operating since 1938, located in a charming alley (vicolo) in the heart of Trastevere. It is recommended by numerous international Rome guides. - **Hours:** - Aug 10–11: Closed - Aug 12: 19:30–23:00 - Aug 13–16: 12:30–15:00, 19:30–23:00 - **Currently open:** ❌ No (closed today) --- Both trattorias are deeply rooted in Trastevere's culinary tradition, offering authentic Roman cuisine in historic settings. If you're planning a visit today, **Checco Er Carettiere** is currently open. *Sources:,* | D5: Tool result (places_search): {"places":[],"area":{"ref":"plc_23ea44258d","name":"Roma","address":"Roma, Lazio, Italia"},"truncated":false,"anchor":null,"resolved":[],"returned_count":0,"warnings":["2GIS does not cover the requested locality; using TomTom."]} Tool result (web_search): {"query":"traditional trattorias in Trastevere Rome","results":[{"ref":"src_9878e9adb3","title":"History of Checco er Carettiere | Trastevere Restaurant","domain":"www.checcoercarettiere.it","snippet":"generations of Checco Er Carettiere restaurant in Trastevere.\n...\nThe story of Checco Er Carettiere began back in the 1930s. In fact, Checco’s Tavern opened in 1935, when Francesco and his wife Diomi…","published_date":"2020-02-10"},{"_omitted_items":3},{"ref":"src_526f4f7522","title":"Roma, Trattoria da Lucia a Trastevere dal 1938 - Luciano Pignataro Wine Blog","domain":"www.lucianopignataro.it","snippet":"Diciamo subito che da Lucia a Trastevere, al vicolo del Mattonato, non siete di sicuro nella versione junk food quanto piuttosto in un localino consigliato da tante guide di Roma di tutto il mondo, R…","published_date":"2019-10-26"}]} Tool result (places_search): {"places":[],"area":null,"truncated":false,"anchor":null,"resolved":[{"client_id":"checco","input_name":"Checco Er Carettiere","status":"resolved","place":{"ref":"plc_42e1ddd191","id":"zW69GBRG1f_D3ePURDOwjA","name":"Checco Er Carettiere","address":"Via Benedetta 10, 00153 Roma","categories":["restaurant","italian"],"phones":["+39 06 580 0985"],"rating":null,"review_count":null,"hours_text":"Next 7 days: Aug 10–16 12:00–15:00, 19:00–24:00","open_24h":false,"is_open_now":true,"accessibility":[],"distance_m":null},"options":[],"error":null},{"client_id":"lucia","input_name":"Trattoria da Lucia","status":"resolved","place":{"ref":"plc_07dba703a0","id":"jRYouEGWKw54tdIRCEQFGw","name":"Trattoria Da Lucia","address":"Vicolo del Mattonato 2, 00153 Roma","categories":["restaurant","italian"],"phones":["+39 06 580 3601"],"rating":null,"review_count":null,"hours_text":"Next 7 days: Aug 10–11 closed; Aug 12 19:30–23:00; Aug 13–16 12:30–15:00, 19:30–23:00","open_24h":false,"is_open_now":false,"accessibility":[],"distance_m":null},"options":[],"error":null}],"returned_count":2,"warnings":["2GIS does not cover the requested locality; using TomTom."]} Final answer: Based on my search, here are two well-known traditional trattorias in Trastevere, Rome: --- ### 🍝 **Checco Er Carettiere** - **Address:** Via Benedetta 10, 00153 Roma - **Phone:** +39 06 580 0985 - **History:** A historic family-run trattoria that opened in 1935, making it one of the oldest restaurants in the neighborhood. The establishment has been passed down through generations of the Checco family. - **Hours (Aug 10–16):** 12:00–15:00, 19:00–24:00 - **Currently open:** ✅ Yes --- ### 🍝 **Trattoria da Lucia** - **Address:** Vicolo del Mattonato 2, 00153 Roma - **Phone:** +39 06 580 3601 - **History:** A beloved traditional trattoria operating since 1938, located in a charming alley (vicolo) in the heart of Trastevere. It is recommended by numerous international Rome guides. - **Hours:** - Aug 10–11: Closed - Aug 12: 19:30–23:00 - Aug 13–16: 12:30–15:00, 19:30–23:00 - **Currently open:** ❌ No (closed today) --- Both trattorias are deeply rooted in Trastevere's culinary tradition, offering authentic Roman cuisine in historic settings. If you're planning a visit today, **Checco Er Carettiere** is currently open. *Sources:,* | E5: PASS | G5: 5 | H5: 4 | I5: 4 | J5: 4 | K5: 5 | L5: 5 | M5: 5 | N5: =IF($E5="","",IF($E5="FAIL","FAIL",ROUND(G5*15%+H5*15%+I5*25%+J5*10%+K5*20%+M5*5%+L5*10%,2))) -> 4.5
A6: 5 | B6: Find quiet parks in Amsterdam for a relaxed afternoon. | C6: Вот несколько тихих парков Амстердама, которые отлично подойдут для расслабленного дня: ### 🌿 **Flevopark** **Адрес:** Kramatweg, 1095 KC Amsterdam Один из самых уютных и малолюдных парков Амстердама, расположенный в районе Ост (Amsterdam-East). Парк достаточно просторный, чтобы всегда найти тихое место, даже в солнечные дни. Здесь есть мирные лесные тропинки и скрытые скамейки у воды. По сравнению с Вонделпаком, здесь значительно меньше туристов. В выходные здесь царит расслабленная атмосфера — люди берут пледы, еду и напитки, но всё остаётся спокойным и не хаотичным. *Источник:* --- ### 🌳 **Oosterpark** **Адрес:** Populierenweg 43A, 1092 EN Amsterdam Муниципальный парк в восточном районе Амстердама, расположенный на небольшом расстоянии от центра, но далеко за пределами туристических маршрутов. Название буквально означает «Восточный парк» — и это полностью отражает его суть: зелёный оазис вдали от суеты. *Источник:* --- ### 🍃 **Sarphatipark** **Район:** Де Пип (De Pijp), рядом с рынком Альберт Кейп Небольшой, но очень уютный городской парк, который называют тихой зелёной гаванью в шумном городе. Парк окружён величественными зданиями и любим местными жителями. Здесь гуляют с собаками, играют дети, а друзья устраивают пикники или просто сидят на траве с кофе. Это не туристическое место, поэтому здесь царит спокойная атмосфера. *Лучшее время для тишины — утро; днём парк становится более оживлённым, но всё ещё спокойным.* *Источник:* --- Все три парка открыты для посещения и отлично подходят для неспешных прогулок, чтения или пикника. Если хотите максимально уединения, рекомендую **Flevopark** или **Oosterpark** — они находятся дальше от туристических зон. | D6: Tool result (places_search): {"places":[{"ref":"plc_4fa267c67e","id":"TFVQCme_1Sna4gU9N0HeaQ","name":"Bloompark","address":"Sarphatistraat 219, 1018 GJ Amsterdam","categories":["park recreation area","park"],"phones":[],"rating":null,"review_count":null,"hours_text":"Open 24 hours for the next 7 days","open_24h":true,"is_open_now":true,"accessibility":[],"distance_m":null},{"ref":"plc_d303d55317","id":"DvEf2G29WovvGggYTNCtkw","name":"Piet Wiedijkpark","address":"Johan Braakensiekhof 1, 1068 KL Amsterdam","categories":["park recreation area","park"],"phones":[],"rating":null,"review_count":null,"hours_text":"Open 24 hours for the next 7 days","open_24h":true,"is_open_now":true,"accessibility":[],"distance_m":null},{"ref":"plc_5431c06cbb","id":"viLdfZgubj08glwr9ikvfw","name":"Workout Spot","address":"Saskia van Uilenburgkade 5, 6181 NA Amsterdam","categories":["park recreation area","park"],"phones":[],"rating":null,"review_count":null,"hours_text":"Open 24 hours for the next 7 days","open_24h":true,"is_open_now":true,"accessibility":[],"distance_m":null},{"ref":"plc_78be201137","id":"pPG8de3RCuSycPzjvDmfQQ","name":"Tuingroep Wijkergouw","address":"Wijkergouw 30, 1023 NX Amsterdam","categories":["park recreation area","park"],"phones":["+31 20 490 4567"],"rating":null,"review_count":null,"hours_text":"Next 7 days: Aug 10–16 09:00–20:00","open_24h":false,"is_open_now":true,"accessibility":[],"distance_m":null},{"ref":"plc_3a9fb20dcf","id":"YZQ2i9YGiljw8gR_r6S0Rg","name":"Domela Nieuwenhuisplantsoen","address":"Domela Nieuwenhuisplantsoen, 1013 SR Amsterdam","categories":["park recreation area","park"],"phones":[],"rating":null,"review_count":null,"hours_text":"Open 24 hours for the next 7 days","open_24h":true,"is_open_now":true,"accessibility":[],"distance_m":null},{"ref":"plc_a118624c5c","id":"FiV-zYpK7aNaR3XWFojRPw","name":"Schinkel Beach","address":"Helicopterstraat, 1059 CC Amsterdam","categories":["park recreation area","park"],"phones":[],"rating":null,"review_count":null,"hours_text":"Open 24 hours for the next 7 days","open_24h":true,"is_open_now":true,"accessibility":[],"distance_m":null},{"ref":"plc_bbcc6b2d9a","id":"bwySMGPuhodIdBa2MYIEbw","name":"Recreatiegebied de Steltloper","address":"Ertskade 266, 1019 EZ Amsterdam","categories":["park recreation area","park"],"phones":[],"rating":null,"review_count":null,"hours_text":"Next 7 days: Aug 10–16 09:00–20:00","open_24h":false,"is_open_now":true,"accessibility":[],"distance_m":null},{"ref":"plc_cc12dd1a38","id":"eIGIpV4zXazmihzaOu-IyA","name":"Stadspark Osdorp","address":"Wolbrantskerkweg, 1069 DA Amsterdam","categories":["park recreation area","park"],"phones":["+31 20 624 1111"],"rating":null,"review_count":null,"hours_text":"Open 24 hours for the next 7 days","open_24h":true,"is_open_now":true,"accessibility":[],"distance_m":null},{"ref":"plc_e48c4911bc","id":"ipmrw8LPwcb7faS4lu--dg","name":"National Holocaust Names Monument","address":"Nieuwe Herengracht, 1018 DN Amsterdam","categories":["park recreation area","park"],"phones":[],"rating":null,"review_count":null,"hours_text":"Next 7 days: Aug 10–16 08:00–20:00","open_24h":false,"is_open_now":true,"accessibility":[],"distance_m":null},{"ref":"plc_9d1b59f141","id":"Us53VgV5Mnt3VgWsfHypZw","name":"Nature Playground the Natureluur Sloterpark","address":"President Allendelaan, 1064 GW Amsterdam","categories":["park recreation area","park"],"phones":["+31 20 411 5177"],"rating":null,"review_count":null,"hours_text":"Next 7 days: Aug 10–14 09:00–18:00; Aug 15–16 12:00–17:00","open_24h":false,"is_open_now":true,"accessibility":[],"distance_m":null}],"area":{"ref":"plc_1717ef6890","name":"Amsterdam","address":"Amsterdam, Noord-Holland, Nederland"},"truncated":true,"anchor":null,"resolved":[],"returned_count":10,"warnings":["2GIS does not cover the requested locality; using TomTom.","TomTom did not provide enough schedule or time-zone data to verify the current opening status of 15 result(s); those results were omitted."]} Tool result (web_search): {"query":"quiet parks Amsterdam relaxed afternoon peaceful","results":[{"ref":"src_bf9793f230","title":"What to Do in Sarphati park: Tips for a Visit - Amsterdam Now","domain":"www.amsterdam-now.com","snippet":"Amsterdam is the city of canals, museums, and lively terraces, but also of many tourists. Sometimes you just want to escape the crowds for a while. Sarphati park is the perfect peaceful spot to catch your breath. The park is located right in the middle of De Pijp, the friendliest neighbourhood in Amsterdam.This city park may be small in size, but in meaning. It is surrounded by stately buildings and lies just a stone’s throw from the Albert Cuyp Market. Locals walk their dogs, children play, and friends relax with a picnic or just coffee on a plaid in the grass.\n...\n• Have a picnic on the grass. Pick up some treats from the nearby Albert Cuyp Market.• Walk along the pond and admire the centuries-old trees.• Exercise. Runners often use the park as a green route.• Let the kids have fun in the playground.• Take photographs. Especially in spring, the park blooms beautifully.\n...\nof Samuel Sar\n...\n• Location: In De Pijp, close to the Albert Cuyp Market.• Getting there: Easily reached by tram.• Best time to visit: Morning for peace and quiet, afternoon for liveliness.\n...\nIf you truly want to get to know Amsterdam, you should also visit its city parks. Sarphati park isn’t a tourist hotspot, but it is much loved by locals and other Amsterdammers. A quiet, green haven in a bustling city.","published_date":"2025-07-11"},{"_omitted_items":3},{"ref":"src_894c6e5b9d","title":"The unexpected green haven of Flevopark in Amsterdam - Things to do in Amsterdam","domain":"www.tipsamsterdam.co.uk","snippet":"Flevopark in Amsterdam is one of those places where you can completely forget the bustle of the city. This green park lies in Amsterdam-East, right behind the Indische Buurt, and feels like a hidden oasis. Whether you want to exercise, relax with friends or simply unwind, Flevopark will surprise you with its versatility. In this article I’ll share my favourite spots, tips and activities in the park, so you’ll see why Flevopark is the hotspot for young adults who love nature, sport and sociability.\n...\nall enjoying it in their\n...\nWhat makes Flevopark special is its relaxed atmosphere. The park is big enough to always find a quiet spot, even on sunny days. At the same time, there’s plenty going on. On the large lawn near the main entrance, groups of friends often picnic or play frisbee. Further in, you’ll find peaceful woodland paths and hidden benches by the water. At weekends the park takes on an almost festival-like feel. People bring blankets, food and drinks to enjoy the sun. Yet it never feels chaotic or overwhelming. The wide lanes, ponds and open water create space and calm. You could easily spend an afternoon here without getting bored.\n...\nFlevopark\n...\nalways take my\n...\nI go for a walk\n...\n’ll discover\n...\nother city parks\n...\n- End your day at Brouwerij ’t IJ or the Flevopark Tearoom with a drink and a view.\n- Bring swim gear if the Flevoparkbad is open. It’s one of the nicest outdoor pools in Amsterdam.\n- Come early in the morning for peace and the best photos. The light is soft and the park almost empty.\n...\nFlevopark is one of Amsterdam’s most versatile and surprising parks. You’ll find everything here: space, nature, sport, relaxation and good food & drink. The vibe is laid-back and unpretentious, without the crowds of the Vondelpark. Whether you want to exercise, relax or meet new people, Flevopark has it all. Its location in Amsterdam-East makes it easy to reach.","published_date":"2025-08-21"}]} Tool result (web_search): {"query":"best quiet peaceful parks Amsterdam not crowded","results":[{"ref":"src_ba099fa3fc","title":"Oosterpark Amsterdam: Complete Visitor Guide | Nomado Travel","domain":"www.nomadotravel.app","snippet":"Oosterpark is a municipal park in the Oost (east) district of Amsterdam, a short distance from the city centre but firmly outside the tourist orbit. The name means, simply, Eastern Park, and it does …","published_date":"2026-06-04"},{"_omitted_items":3},{"ref":"src_894c6e5b9d","title":"The unexpected green haven of Flevopark in Amsterdam - Things to do in Amsterdam","domain":"www.tipsamsterdam.co.uk","snippet":"Flevopark in Amsterdam is one of those places where you can completely forget the bustle of the city. This green park lies in Amsterdam-East, right behind the Indische Buurt, and feels like a hidden …","published_date":"2025-08-21"}]} Tool result (places_search): {"places":[],"area":null,"truncated":false,"anchor":null,"resolved":[{"client_id":"candidate_1","input_name":"Sarphatipark","status":"ambiguous","place":null,"options":[{"ref":"plc_86f61c3e88","id":"jKM67fZlSveNvwC8QPFK3Q","name":"Natuurspeelpark Sarphatipark","address":"Sarphatipark 100, 1073 CV Amsterdam","categories":["leisure center"],"phones":[],"rating":null,"review_count":null,"hours_text":null,"open_24h":null,"is_open_now":null,"accessibility":[],"distance_m":null},{"ref":"plc_9fa0db6d78","id":"3HyBrVwZvks-IymtZBxkEg","name":"Speeltuin Sarphatipark","address":"Sarphatipark 11, 1072 PA Amsterdam","categories":["leisure center"],"phones":[],"rating":null,"review_count":null,"hours_text":"Open 24 hours for the next 7 days","open_24h":true,"is_open_now":true,"accessibility":[],"distance_m":null},{"ref":"plc_b1284f0ad8","id":"7yrx6zTGSW4IIlgXh4oC7A","name":"PostNL Sarphatipark","address":"Sarphatipark 135, 1073 CX Amsterdam","categories":["courier drop box"],"phones":[],"rating":null,"review_count":null,"hours_text":null,"open_24h":null,"is_open_now":null,"accessibility":[],"distance_m":null}],"error":null},{"client_id":"candidate_2","input_name":"Flevopark","status":"resolved","place":{"ref":"plc_0b83624821","id":"GXQDjDO-5s9jY_0BUTprNw","name":"Flevopark","address":"Kramatweg, 1095 KC Amsterdam","categories":["park recreation area","park"],"phones":[],"rating":null,"review_count":null,"hours_text":null,"open_24h":null,"is_open_now":null,"accessibility":[],"distance_m":null},"options":[],"error":null},{"client_id":"candidate_3","input_name":"Oosterpark","status":"resolved","place":{"ref":"plc_7120e3ea24","id":"azxNFLagZ5td6kD5ddM_Mw","name":"Oosterpark","address":"Populierenweg 43A, 1092 EN Amsterdam","categories":["sports center"],"phones":["+31 6 10480297"],"rating":null,"review_count":null,"hours_text":null,"open_24h":null,"is_open_now":null,"accessibility":[],"distance_m":null},"options":[],"error":null}],"returned_count":2,"warnings":["2GIS does not cover the requested locality; using TomTom.","TomTom supplied neither opening hours nor a phone number for 3 results; their current operation could not be verified from this response.","TomTom supplied neither opening hours nor a phone number for 1 results; their current operation could not be verified from this response."]} Final answer: Вот несколько тихих парков Амстердама, которые отлично подойдут для расслабленного дня: ### 🌿 **Flevopark** **Адрес:** Kramatweg, 1095 KC Amsterdam Один из самых уютных и малолюдных парков Амстердама, расположенный в районе Ост (Amsterdam-East). Парк достаточно просторный, чтобы всегда найти тихое место, даже в солнечные дни. Здесь есть мирные лесные тропинки и скрытые скамейки у воды. По сравнению с Вонделпаком, здесь значительно меньше туристов. В выходные здесь царит расслабленная атмосфера — люди берут пледы, еду и напитки, но всё остаётся спокойным и не хаотичным. *Источник:* --- ### 🌳 **Oosterpark** **Адрес:** Populierenweg 43A, 1092 EN Amsterdam Муниципальный парк в восточном районе Амстердама, расположенный на небольшом расстоянии от центра, но далеко за пределами туристических маршрутов. Название буквально означает «Восточный парк» — и это полностью отражает его суть: зелёный оазис вдали от суеты. *Источник:* --- ### 🍃 **Sarphatipark** **Район:** Де Пип (De Pijp), рядом с рынком Альберт Кейп Небольшой, но очень уютный городской парк, который называют тихой зелёной гаванью в шумном городе. Парк окружён величественными зданиями и любим местными жителями. Здесь гуляют с собаками, играют дети, а друзья устраивают пикники или просто сидят на траве с кофе. Это не туристическое место, поэтому здесь царит спокойная атмосфера. *Лучшее время для тишины — утро; днём парк становится более оживлённым, но всё ещё спокойным.* *Источник:* --- Все три парка открыты для посещения и отлично подходят для неспешных прогулок, чтения или пикника. Если хотите максимально уединения, рекомендую **Flevopark** или **Oosterpark** — они находятся дальше от туристических зон. | E6: FAIL | F6: Language missmatch | N6: =IF($E6="","",IF($E6="FAIL","FAIL",ROUND(G6*15%+H6*15%+I6*25%+J6*10%+K6*20%+M6*5%+L6*10%,2))) -> FAIL
A7: 6 | B7: Recommend archaeological sites in central Athens. | C7: Based on the available information, here are the main archaeological sites in central Athens: ### 1. **Acropolis of Athens** The iconic "high city" overlooking modern Athens, inhabited since the Bronze Age. This UNESCO World Heritage Site is the most famous archaeological landmark in Greece, featuring the Parthenon, Erechtheion, Propylaea, and the Temple of Athena Nike. ### 2. **Ancient Agora of Athens** The heart of ancient Athenian public life, containing the well-preserved **Temple of Hephaestus** (also known as Theseion) on top of Agoraios Kolonos hill — one of the best-preserved ancient temples in all of Greece. ### 3. **Kerameikos Archaeological Site** Located on the northwest edge of the ancient city, straddling the banks of the Eridanos River. This 11-acre site was once the largest deme of ancient Athens and is known as one of the most atmospheric and least crowded archaeological sites in the city. It lies between Ermou, Peireos, and Asomaton Streets. ### 4. **Roman Agora** A major public marketplace built during the Roman period, adjacent to the Ancient Agora. ### 5. **Tower of the Winds (Aeolian Tower)** An ancient clock tower in the Roman Agora area, notable for its architectural and astronomical significance. ### 6. **Hadrian's Library** A ancient structure built by the Roman Emperor Hadrian, located near the Acropolis. ### 7. **Lycabettus Hill** A prominent hill in central Athens offering panoramic views of the city and its archaeological surroundings. --- **Note:** The local mapping service (2GIS) does not cover Athens, so detailed addresses, opening hours, and phone numbers are not available through the place database. For visiting information, it is recommended to consult the official Greek Ministry of Culture website (odysseus.culture.gr) or the Athens Tourism Authority (athenstourism.org). | D7: Tool result (places_search): {"places":[],"area":{"ref":"plc_210a919c65","name":"Αθήνα","address":"Αθήνα, Κεντρικός Τομέας Αθηνών, Αττική, Ελλάδα"},"truncated":false,"anchor":null,"resolved":[],"returned_count":0,"warnings":["2GIS does not cover the requested locality; using TomTom."]} Tool result (web_search): {"query":"archaeological sites central Athens Greece","results":[{"ref":"src_554c8c906d","title":"Ministry of Culture and Sports | Kerameikos","domain":"odysseus.culture.gr","snippet":"The archaeological site of the Kerameikos, between Ermou, Peireos, and Asomaton Streets, is a small part of the ancient Attic Deme of Kerameon, one of the largest demes of ancient Athens, located on …","published_date":null},{"_omitted_items":6},{"ref":"src_32ef4628d3","title":"Ministry of Culture and Sports | Temple of Hephaistos","domain":"odysseus.culture.gr","snippet":"On top of Agoraios Kolonos hill, which is delimiting the Ancient Agora of Athens to the west, stands the temple of Hephaestus, broadly known as ?Thisio?. It is one of the best preserved ancient templ…","published_date":null}]} Tool result (web_search): {"query":"top archaeological sites central Athens visiting guide","results":[{"ref":"src_9a28ec532b","title":"Athens Historical Sites & Museums Guide (2026)","domain":"www.athenstourism.org","snippet":"3,4\n...\nKerameikos is one of Athens’ most atmospheric and least crowded archaeological sites. Straddling the banks of the Eridanos River on the northwest edge of the ancient city, this 11-acre landsc…","published_date":"2026-04-14"},{"_omitted_items":8},{"ref":"src_c7bd91a5bd","title":"A guide to the Acropolis of Athens - Lonely Planet","domain":"www.lonelyplanet.com","snippet":"Overlooking modern-day Athens, the mighty Acropolis is a powerful reminder of the city's ancient history. Inhabited since the Bronze Age, this \"high city\" served various purposes, from housing Greece…","published_date":"2024-07-22"}]} Tool result (places_search): {"places":[],"area":null,"truncated":false,"anchor":null,"resolved":[{"client_id":"candidate_1","input_name":"Acropolis of Athens","status":"not_found","place":null,"options":[],"error":null},{"client_id":"candidate_2","input_name":"Ancient Agora of Athens","status":"not_found","place":null,"options":[],"error":null},{"client_id":"candidate_3","input_name":"Kerameikos Archaeological Site","status":"not_found","place":null,"options":[],"error":null},{"client_id":"candidate_4","input_name":"Temple of Hephaestus","status":"not_found","place":null,"options":[],"error":null},{"client_id":"candidate_5","input_name":"Roman Agora","status":"not_found","place":null,"options":[],"error":null},{"client_id":"candidate_6","input_name":"Tower of the Winds","status":"not_found","place":null,"options":[],"error":null},{"client_id":"candidate_7","input_name":"Hadrian's Library","status":"not_found","place":null,"options":[],"error":null},{"client_id":"candidate_8","input_name":"Lycabettus Hill","status":"not_found","place":null,"options":[],"error":null}],"returned_count":0,"warnings":["2GIS does not cover the requested locality; using TomTom."]} Final answer: Based on the available information, here are the main archaeological sites in central Athens: ### 1. **Acropolis of Athens** The iconic "high city" overlooking modern Athens, inhabited since the Bronze Age. This UNESCO World Heritage Site is the most famous archaeological landmark in Greece, featuring the Parthenon, Erechtheion, Propylaea, and the Temple of Athena Nike. ### 2. **Ancient Agora of Athens** The heart of ancient Athenian public life, containing the well-preserved **Temple of Hephaestus** (also known as Theseion) on top of Agoraios Kolonos hill — one of the best-preserved ancient temples in all of Greece. ### 3. **Kerameikos Archaeological Site** Located on the northwest edge of the ancient city, straddling the banks of the Eridanos River. This 11-acre site was once the largest deme of ancient Athens and is known as one of the most atmospheric and least crowded archaeological sites in the city. It lies between Ermou, Peireos, and Asomaton Streets. ### 4. **Roman Agora** A major public marketplace built during the Roman period, adjacent to the Ancient Agora. ### 5. **Tower of the Winds (Aeolian Tower)** An ancient clock tower in the Roman Agora area, notable for its architectural and astronomical significance. ### 6. **Hadrian's Library** A ancient structure built by the Roman Emperor Hadrian, located near the Acropolis. ### 7. **Lycabettus Hill** A prominent hill in central Athens offering panoramic views of the city and its archaeological surroundings. --- **Note:** The local mapping service (2GIS) does not cover Athens, so detailed addresses, opening hours, and phone numbers are not available through the place database. For visiting information, it is recommended to consult the official Greek Ministry of Culture website (odysseus.culture.gr) or the Athens Tourism Authority (athenstourism.org). | E7: PASS | G7: 4 | H7: 3 | I7: 4 | J7: 4 | K7: 3 | L7: 3 | M7: 4 | N7: =IF($E7="","",IF($E7="FAIL","FAIL",ROUND(G7*15%+H7*15%+I7*25%+J7*10%+K7*20%+M7*5%+L7*10%,2))) -> 3.55
A8: 7 | B8: Find independent Danish design shops in Copenhagen. | C8: Based on my search, here are independent Danish design shops in Copenhagen: --- ## Designkollektivet A collaborative design shop bringing together multiple independent designers under one roof. The collective includes ceramicists, jewellery designers, glassmakers, textile designers, architects, and leather-crafters, offering unique handmade products in jewellery, accessories, interior design, and arts & crafts. **Locations:** - **Jægersborggade 5, 2200 København N** — Currently open (11:00–17:30) - **Stefansgade 12, 2200 København N** --- ## Frama Studio Store A creative studio and store nestled in a historic space from 1878 (former St. Pauls Apotek) in the Nyboder area. Frama operates across various creative fields and produces Danish interior design products. **Address:** Fredericiagade 57, 1310 København K **Phone:** +45 31 40 60 30 **Hours:** Closed today (Aug 10–11); Opens Aug 12–14 at 10:00–17:00 --- ## Paustian A well-known Danish design concept store offering furniture, lighting, and accessories from top Scandinavian designers. **Locations:** - **Niels Hemmingsens Gade 24, 1153 København K** — Currently open (11:00–18:00) - Phone: +45 39 16 65 65 - **Kattegatvej 38, 2150 Nordhavn** — Closed today - Phone: +45 46 76 03 12 - **Kalkbrænderiløbskaj 2, 2100 København Ø** --- *Sources:,,* | D8: Tool result (places_search): {"places":[],"area":{"ref":"plc_e41db6a2ba","name":"København","address":"København, Danmark"},"truncated":false,"anchor":null,"resolved":[],"returned_count":0,"warnings":["2GIS does not cover the requested locality; using TomTom."]} Tool result (web_search): {"query":"independent Danish design shops Copenhagen","results":[{"ref":"src_537b26a5d1","title":"OUR COLLECTIVE – Designkollektivet","domain":"designkollektivet.dk","snippet":"OUR COLLECTIVE – Designkollektivet\n...\nIn our shop you will find a broad selection of unique products. We have come together across a variety of products, skills and backgrounds to create a platform for synergy, inspiration and community. In our shop you will find unique products, made by hand and with a love of design, quality and aesthetics. Each designer brings something special to the shop and inspires you with ingenious and beautiful products.\n...\nThe Design Collective consists of Ceramicist Kristina Vildersbøll, the Jewllery Designers Lind&James, the Glassmakers Jette Bøge & Sally Xenia (Blæs) Tekstile designer Kristine Skov Cancar (StricktlyKnit), Architect Kaja Skytte and leather-crafter Maria Solon (Solon Handmade).\n...\nOur style is characterized by a minimalistic and timeless design in good materials and great quality craftmanship. We have a broad catalogue of products within the range of a lifestyle shop, such as jewellery, accessories, interior design and arts and craft products. At the Design Collective our core values are curiosity, community, honesty, engagement and drive. The energy between us is important. We are more than just a shop – we are a community were friendships grow while we exchange ideas, inspire each other and share our knowledge and skills.","published_date":null},{"_omitted_items":8},{"ref":"src_d3774f7f0b","title":"Tiensuu Studio\n – Tiensuu Studio","domain":"www.tiensuustudio.com","snippet":"Tiensuu Studio is more than an interior design studio, it is a perspective on the world, rooted in the raw nature of Bornholm and shaped by a strong sense of story and design.\n...\nFrom Bornholm, we work on projects across Denmark and internationally, combining interior design, sourcing, and curated solutions for private homes, businesses, and creative spaces. In our store and webshop, you'll find furniture, wallpapers and paints, each selected for its coherence and character.\n...\nWe work as one unified entity — studio, showroom and shop. From Bornholm to Copenhagen and out into the world, we create coherence between what we design and what we curate.\n...\nIn our shop in Rønne on Bornholm, you'll find a curated selection of interior treasures, from antique vessels and patinated furniture to textiles, ceramics and objects with personality. In Copenhagen, you'll find us at Designhuset, Frederiksgade 1, where we present beautiful furniture and interior in collaboration with Swedish Jakobsdals.","published_date":null}]} Tool result (web_search): {"query":"best independent Danish design shops stores Copenhagen","results":[{"ref":"src_99e98ec7c1","title":"Danish interior design stores","domain":"www.visitcopenhagen.com","snippet":"On a quiet street in the royal quarter around Nyboder, Frama Studio Store lies nestled in the old space of St. Pauls Apotek, dating back to 1878. Frama operates in various creative fields and produce…","published_date":null},{"_omitted_items":8},{"ref":"src_5dca37d813","title":"Paustian Concept Stores","domain":"www.paustianweekly.com","snippet":"* * [English**](https://uk.paustian.com/)\n* [Danish**](https://paustian.com/)\n...\n# Paustian Concept Stores\nWith a full range of furniture, lighting and accessories, Paustian offers some of the very …","published_date":"2019-01-23"}]} Tool result (places_search): {"places":[],"area":null,"truncated":false,"anchor":null,"resolved":[{"client_id":"candidate_1","input_name":"Designkollektivet","status":"ambiguous","place":null,"options":[{"ref":"plc_9c9e023686","id":"SCcDwgjDFVk_QNL1SVQVWQ","name":"Designkollektivet","address":"Jægersborggade 5, 2200 København N","categories":["hobby/free time","shop"],"phones":[],"rating":null,"review_count":null,"hours_text":"Next 7 days: Aug 10–11 11:00–17:30; Aug 12 closed; Aug 13–14 11:00–17:30; Aug 15 11:00–16:00; Aug 16 closed","open_24h":false,"is_open_now":true,"accessibility":[],"distance_m":null},{"ref":"plc_3989ea256d","id":"v-Ay9AK6WahLVfPXCuxePg","name":"Designkollektivet","address":"Stefansgade 12, 2200 København N","categories":["gifts, cards, novelties souvenirs","shop"],"phones":[],"rating":null,"review_count":null,"hours_text":null,"open_24h":null,"is_open_now":null,"accessibility":[],"distance_m":null}],"error":null},{"client_id":"candidate_2","input_name":"Tiensuu Studio","status":"not_found","place":null,"options":[],"error":null},{"client_id":"candidate_3","input_name":"Frama Studio Store","status":"resolved","place":{"ref":"plc_9ed51682fc","id":"ND3mgdHNm3COpJRnpPVyPw","name":"Frama Studio Store","address":"Fredericiagade 57, 1310 København K","categories":["shop","furniture/home furnishings"],"phones":["+45 31 40 60 30"],"rating":null,"review_count":null,"hours_text":"Next 7 days: Aug 10–11 closed; Aug 12–14 10:00–17:00; Aug 15 10:00–15:00; Aug 16 closed","open_24h":false,"is_open_now":false,"accessibility":[],"distance_m":null},"options":[],"error":null},{"client_id":"candidate_4","input_name":"Paustian","status":"ambiguous","place":null,"options":[{"ref":"plc_0d4cf23a0c","id":"nvvoUPd5y7pgwQkwZc_GSA","name":"Paustian","address":"Kattegatvej 38, 2150 Nordhavn","categories":["shop","furniture/home furnishings"],"phones":["+45 46 76 03 12"],"rating":null,"review_count":null,"hours_text":"Next 7 days: Aug 10–13 07:30–15:45; Aug 14 07:30–14:00; Aug 15–16 closed","open_24h":false,"is_open_now":false,"accessibility":[],"distance_m":null},{"ref":"plc_67a6c8f6de","id":"0jVcdc_AWbFHlFN9MH1bEA","name":"Paustian","address":"Niels Hemmingsens Gade 24, 1153 København K","categories":["shop","furniture/home furnishings"],"phones":["+45 39 16 65 65"],"rating":null,"review_count":null,"hours_text":"Next 7 days: Aug 10–14 11:00–18:00; Aug 15 11:00–17:00; Aug 16 closed","open_24h":false,"is_open_now":true,"accessibility":[],"distance_m":null},{"ref":"plc_a66733bb0b","id":"aG7GCENMlfIJMLlZXRYxQA","name":"Paustian","address":"Kalkbrænderiløbskaj 2, 2100 København Ø","categories":["shop","furniture/home furnishings"],"phones":["+45 39 16 65 65"],"rating":null,"review_count":null,"hours_text":null,"open_24h":null,"is_open_now":null,"accessibility":[],"distance_m":null}],"error":null}],"returned_count":1,"warnings":["2GIS does not cover the requested locality; using TomTom.","TomTom supplied neither opening hours nor a phone number for 1 results; their current operation could not be verified from this response."]} Final answer: Based on my search, here are independent Danish design shops in Copenhagen: --- ## Designkollektivet A collaborative design shop bringing together multiple independent designers under one roof. The collective includes ceramicists, jewellery designers, glassmakers, textile designers, architects, and leather-crafters, offering unique handmade products in jewellery, accessories, interior design, and arts & crafts. **Locations:** - **Jægersborggade 5, 2200 København N** — Currently open (11:00–17:30) - **Stefansgade 12, 2200 København N** --- ## Frama Studio Store A creative studio and store nestled in a historic space from 1878 (former St. Pauls Apotek) in the Nyboder area. Frama operates across various creative fields and produces Danish interior design products. **Address:** Fredericiagade 57, 1310 København K **Phone:** +45 31 40 60 30 **Hours:** Closed today (Aug 10–11); Opens Aug 12–14 at 10:00–17:00 --- ## Paustian A well-known Danish design concept store offering furniture, lighting, and accessories from top Scandinavian designers. **Locations:** - **Niels Hemmingsens Gade 24, 1153 København K** — Currently open (11:00–18:00) - Phone: +45 39 16 65 65 - **Kattegatvej 38, 2150 Nordhavn** — Closed today - Phone: +45 46 76 03 12 - **Kalkbrænderiløbskaj 2, 2100 København Ø** --- *Sources:,,* | E8: PASS | G8: 4 | H8: 3 | I8: 3 | J8: 4 | K8: 3 | L8: 4 | M8: 4 | N8: =IF($E8="","",IF($E8="FAIL","FAIL",ROUND(G8*15%+H8*15%+I8*25%+J8*10%+K8*20%+M8*5%+L8*10%,2))) -> 3.4
A9: 8 | B9: Порекомендуй бесплатные музеи в центре Лондона. | C9: Вот список бесплатных музеев в центре Лондона, основанный на актуальных данных: ### Крупные национальные музеи (полностью бесплатные) **1. British Museum (Британский музей)** - Адрес: 1 Montague Place, Bloomsbury, London, WC1E 7JW - Один из крупнейших и самых известных музеев мира с коллекцией искусства и цивилизаций со всего мира **2. Tate Modern** - Адрес: Bankside, South Bank, London, SE1 9JF - Телефон: +44 20 7887 8888 - Современное искусство мирового уровня **3. Natural History Museum (Музей естественной истории)** - Район: South Kensington - Коллекция природных наук, знаменитые экспонаты динозавров **4. Science Museum (Музей науки)** - Район: South Kensington - Интерактивные экспозиции, посвящённые науке и технологиям **5. Victoria and Albert Museum (V&A)** - Район: South Kensington - Искусство и дизайн, одна из крупнейших коллекций в мире ### Специализированные музеи **6. Bank of England Museum (Музей Банка Англии)** - Адрес: Bartholomew Lane, London EC2R 8AH - Бесплатный вход, бронирование не требуется - Открыт: Пн–Пт 10:00–17:00 (последний вход в 16:30), третьи четверги до 20:00 **7. Sir John Soane's Museum (Музей сэра Джона Соуна)** - Район: Holborn - Сохранён в первоначальном виде с 1837 года - Открыт: Ср–Вс 10:00–17:00 **8. Hunterian Museum (Хантерианский музей)** - Район: Holborn - Медицинская и анатомическая коллекция **9. Grant Museum of Zoology (Музей зоологии Гранта)** - Адрес: 2 Malet Place, Bloomsbury, London, WC1E 7LE - Телефон: +44 20 7679 2884 - Зоологическая коллекция **10. London Mithraeum Bloomberg SPACE** - Адрес: 12 Walbrook, Saint Paul's, London, EC4N 8AA - Телефон: +44 20 7330 7500 - Восстановленный храм бога Митры ### Другие бесплатные музеи в центре - **Alexander Fleming Laboratory Museum** — Paddington - **British Optical Association Museum** — Charing Cross - **Charterhouse** — Smithfield - **Faraday Museum** — Mayfair - **Library and Museum of Freemasonry** — Holborn - **London Archives** — Clerkenwell - **Museum of Anaesthesia** — Marylebone - **Museum of the Order of St. John** — Clerkenwell - **Petrie Museum of Egyptian Archaeology** — Bloomsbury - **St Bartholomew's Hospital Museum** — Smithfield > **Примечание:** Вход в основные залы большинства перечисленных музеев бесплатный, однако за специальные выставки может взиматься плата. Некоторые музеи рекомендуют предварительное бронирование. | D9: Tool result (web_search): {"query":"бесплатные музеи в центре Лондона","results":[{"ref":"src_86ea9e9b07","title":"Tate Modern | Tate","domain":"www.tate.org.uk","snippet":"See some of the world’s most exciting modern and contemporary art at Tate Modern. Enjoy innovative works that have shaped art as we know it. Our gallery is free to visit. On display are paintings, sculptures and large-scale installations from artists around the world including Pablo Picasso, Yayoi Kusama and Henri Matisse. Explore the iconic Turbine Hall alongside our underground Tanks, a striking space dedicated to live performances and video.\n...\nMembers enjoy unlimited free entry to exhibitions with no need to book.\n...\nTate ModernBanksideLondon SE1 9TG\n...\nEntry to the collection is free for everyone. Booking is recommended for exhibitions.\n...\n- Members and Supporters enjoy free exhibition entry – no need to book, just turn up with your card\n- Visitors with a disability pay a concessionary rate, and entrance for companions is free\n- Visitors aged 16–25 can join Tate Collective to access £5 exhibition tickets\n- Up to four children aged 11 and under go free per parent or guardian\n- £5 family child tickets are available for children aged 12–18 years","published_date":null},{"_omitted_items":8},{"ref":"src_a30f840475","title":"Plan your visit | Bank of England","domain":"www.bankofengland.co.uk","snippet":"Plan your free visit to our museum\n...\nFree, no booking needed\n...\nOur museum is free to visit, with no booking or tickets required. We are open Monday to Friday, 10am to 5pm (last entry 4.30pm), and until 8pm (last entry 7.30pm) every third Thursday of the month. We are closed on Bank holidays and weekends.\n...\nOur museum is free to visit. You do not need to book a ticket to visit.\n...\nYes, you may bring a group. It is free to visit. If your group is larger than 15, please notify us in advance by pre-booking your self-guided tour slot. Learn more on our Schools or Groups page.\n...\nYou can find us in the same building as the Bank of England. Our museum entrance is on Bartholomew Lane, London EC2R 8AH.\n...\nIf you are facing the Bank of England’s main entrance on Threadneedle Street, we are around the corner on the right.\n...\n- Bank (Central, Northern, and Waterloo & City lines, and Docklands Light Railway (DLR))\n- Cannon Street (District and Circle lines)\n- Mansion House (District and Circle lines)\n- Monument (District and Circle lines)\n- Moorgate (Northern, and Hammersmith & City lines)","published_date":null}]} Tool result (web_search): {"query":"free museums in central London","results":[{"ref":"src_7a55a488f7","title":"Free Museums In London: The Definitive Guide - Londonist","domain":"londonist.com","snippet":"## Free museums in central London\n...\n### Alexander Fleming Laboratory Museum, Paddington\n...\nVisit the very laboratory in which Alexander Fleming discovered penicillin — thus changing the trajectory of the medical world for good. The room is set up as Fleming would've had it (famously he'd left the place untidy, as he went off on his hols, only to return to find the breakthrough growing on a dish). Other bits and pieces include the first microscope Fleming owned as a student, and the 'mould medallions' the scientist handed out to celebs including Winston Churchill and Marlene Dietrich. Alex, you shouldn't have...\n...\n### Bank of England Museum, Bank\n...\n### British Museum, Bloomsbury\n...\n### British Optical Association Museum, Charing Cross\n...\n### Charterhouse, Smithfield\n...\n### Faraday Museum, Mayfair\n...\n### Grant Museum of Zoology, Fitzrovia\n...\n### Hunterian Museum, Holborn\n...\n### Islington Museum, Clerkenwell\n...\n### Library and Museum of Freemasonry, Holborn\n...\n### London Archives, Clerkenwell\n...\n### London Mithraeum Bloomberg SPACE, Bank\n...\n### Museum of Anaesthesia, Marylebone\n...\n### Museum of Comedy, Bloomsbury\n...\n### Museum of the Order of St. John, Clerkenwell\n...\n### Petrie Museum of Egyptian Archaeology, Bloomsbury\n...\n### Royal College of Nursing Museum, Marylebone\n...\n### Sir John Soane's Museum, Holborn\n...\n### St Bartholomew's Hospital Museum, Smithfield\n...\n### St Bride's Crypt, Blackfriars\n...\nLibrary, Bloomsbury\n...\n## Free museums in north London\n...\n### Barnet Museum, High Barnet\n...\n### British Library (\n...\nures Gallery), St Pancras\n...\n### Bruce Castle Museum,\n...\n### Royal College of Physicians\n...\n### Wellcome Collection, Euston\n...\nEast Storehouse,\n...\nWalthamstow\n...\n### Natural History Museum, South Kensington\n...\n### Science Museum, South Kensington\n...\n### Twickenham\n...\n, Twickenham\n...\n### Victoria and Albert Museum (V&A), South Kensington\n...\n### Wimbledon Museum, Wimbledon\n...\nmill Museum, Wimbledon Common","published_date":"2026-08-07"},{"_omitted_items":8},{"ref":"src_c54015be4e","title":"Homepage | Sir John Soane's Museum","domain":"www.soane.org","snippet":"## Welcome to Sir John Soane's Museum\n...\nDiscover the extraordinary house and museum of Sir John Soane, one of the greatest English architects, who built and lived in it two centuries ago. The museum has been kept as it was at the time of his death in 1837, and displays his vast collection of antiquities, furniture, sculptures, architectural models and paintings.\n...\nWe're open Wednesday to Sunday, 10 to 5. Entry is free and you can visit by walking in on the day. Joining a highlights tour, or visiting as a group of eight or more, requires advanced booking.\n...\nSir John Soane’s Museum is the smallest of the National Museums and we now welcome more visitors than ever before; free of charge, to learn, enjoy and be inspired by the story of Sir John Soane, his house and collection. Your support is vital in ensuring that this continues.","published_date":null}]} Tool result (places_search): {"places":[],"area":null,"truncated":false,"anchor":null,"resolved":[{"client_id":"candidate_1","input_name":"British Museum","status":"resolved","place":{"ref":"plc_796665c38b","id":"zV9iyvswDn_jUwVNq9_v8Q","name":"British Museum","address":"1 Montague Place, Bloomsbury, London, WC1E 7JW","categories":["open parking area","coach parking area"],"phones":[],"rating":null,"review_count":null,"hours_text":null,"open_24h":null,"is_open_now":null,"accessibility":[],"distance_m":null},"options":[],"error":null},{"client_id":"candidate_2","input_name":"Tate Modern","status":"resolved","place":{"ref":"plc_f36b95e987","id":"hB4pAA1aNAtbSdMWfyF9Hw","name":"Tate Modern","address":"Bankside, South Bank, London, SE1 9JF","categories":["important tourist attraction","building"],"phones":["+44 20 7887 8888"],"rating":null,"review_count":null,"hours_text":null,"open_24h":null,"is_open_now":null,"accessibility":[],"distance_m":null},"options":[],"error":null},{"_omitted_items":6},{"client_id":"candidate_9","input_name":"Grant Museum of Zoology","status":"resolved","place":{"ref":"plc_ca1b4cb2cb","id":"DMk8NQtXZ8T1Znt06SnwjQ","name":"Grant Museum of Zoology","address":"2 Malet Place, Bloomsbury, London, WC1E 7LE","categories":["important tourist attraction"],"phones":["+44 20 7679 2884"],"rating":null,"review_count":null,"hours_text":"Next 7 days: Aug 10 closed; Aug 11–14 13:00–17:00; Aug 15 11:00–17:00; Aug 16 closed","open_24h":false,"is_open_now":false,"accessibility":[],"distance_m":null},"options":[],"error":null},{"client_id":"candidate_10","input_name":"London Mithraeum Bloomberg SPACE","status":"resolved","place":{"ref":"plc_b127645f9a","id":"FCBAt0XAli8RpMAYOXJMNQ","name":"London Mithraeum Bloomberg Space","address":"12 Walbrook, Saint Paul's, London, EC4N 8AA","categories":["important tourist attraction"],"phones":["+44 20 7330 7500"],"rating":null,"review_count":null,"hours_text":"Next 7 days: Aug 10 closed; Aug 11–15 10:00–18:00; Aug 16 12:00–17:00","open_24h":false,"is_open_now":false,"accessibility":[],"distance_m":null},"options":[],"error":null}],"returned_count":8,"warnings":["2GIS does not cover the requested locality; using TomTom.","TomTom supplied neither opening hours nor a phone number for 1 results; their current operation could not be verified from this response."]} Final answer: Вот список бесплатных музеев в центре Лондона, основанный на актуальных данных: ### Крупные национальные музеи (полностью бесплатные) **1. British Museum (Британский музей)** - Адрес: 1 Montague Place, Bloomsbury, London, WC1E 7JW - Один из крупнейших и самых известных музеев мира с коллекцией искусства и цивилизаций со всего мира **2. Tate Modern** - Адрес: Bankside, South Bank, London, SE1 9JF - Телефон: +44 20 7887 8888 - Современное искусство мирового уровня **3. Natural History Museum (Музей естественной истории)** - Район: South Kensington - Коллекция природных наук, знаменитые экспонаты динозавров **4. Science Museum (Музей науки)** - Район: South Kensington - Интерактивные экспозиции, посвящённые науке и технологиям **5. Victoria and Albert Museum (V&A)** - Район: South Kensington - Искусство и дизайн, одна из крупнейших коллекций в мире ### Специализированные музеи **6. Bank of England Museum (Музей Банка Англии)** - Адрес: Bartholomew Lane, London EC2R 8AH - Бесплатный вход, бронирование не требуется - Открыт: Пн–Пт 10:00–17:00 (последний вход в 16:30), третьи четверги до 20:00 **7. Sir John Soane's Museum (Музей сэра Джона Соуна)** - Район: Holborn - Сохранён в первоначальном виде с 1837 года - Открыт: Ср–Вс 10:00–17:00 **8. Hunterian Museum (Хантерианский музей)** - Район: Holborn - Медицинская и анатомическая коллекция **9. Grant Museum of Zoology (Музей зоологии Гранта)** - Адрес: 2 Malet Place, Bloomsbury, London, WC1E 7LE - Телефон: +44 20 7679 2884 - Зоологическая коллекция **10. London Mithraeum Bloomberg SPACE** - Адрес: 12 Walbrook, Saint Paul's, London, EC4N 8AA - Телефон: +44 20 7330 7500 - Восстановленный храм бога Митры ### Другие бесплатные музеи в центре - **Alexander Fleming Laboratory Museum** — Paddington - **British Optical Association Museum** — Charing Cross - **Charterhouse** — Smithfield - **Faraday Museum** — Mayfair - **Library and Museum of Freemasonry** — Holborn - **London Archives** — Clerkenwell - **Museum of Anaesthesia** — Marylebone - **Museum of the Order of St. John** — Clerkenwell - **Petrie Museum of Egyptian Archaeology** — Bloomsbury - **St Bartholomew's Hospital Museum** — Smithfield > **Примечание:** Вход в основные залы большинства перечисленных музеев бесплатный, однако за специальные выставки может взиматься плата. Некоторые музеи рекомендуют предварительное бронирование. | E9: PASS | G9: 4 | H9: 4 | I9: 4 | J9: 5 | K9: 4 | L9: 5 | M9: 5 | N9: =IF($E9="","",IF($E9="FAIL","FAIL",ROUND(G9*15%+H9*15%+I9*25%+J9*10%+K9*20%+M9*5%+L9*10%,2))) -> 4.25
A10: 9 | B10: Найди хорошие веганские кафе в Барселоне. | C10: Вот список популярных веганских кафе и ресторанов в Барселоне, основанный на актуальных данных: ### 🥑 Бранч и Кофейни * **Little Fern** * **Адрес:** 168 Carrer de Pere IV, Barcelona, 08005. * **Особенности:** Популярное место для завтраков и бранча. Предлагает асаи-боулы, панкейки с кимчи, фафаль-рап и авторские латте. Есть веганское молоко. * **Часы работы:** Пн–Пт 08:30–16:00, Сб–Вс 09:00–16:00. * **Удобства:** Открытая терраса, доступность для инвалидных колясок. * **MIAM** * **Адрес:** Carrer de València 423, L'Eixample, Barcelona, 08013. * **Особенности:** Уютное кафе с кофе и чаем. Предлагают тосты с авокадо и другие блюда, которые можно адаптировать под веганство. * **Часы работы:** Ежедневно 09:00–16:00. * **Удобства:** Бесплатный Wi-Fi, открытая терраса. * **GAIA's GARDEN** * **Адрес:** Carrer de Còrsega, 551, Barcelona, 08025. * **Особенности:** Полностью веганское и безглютеновое кафе. Специализируется на здоровой еде: смузи, боулы и specialty coffee. * **Часы работы:** Пн 08:00–18:00; Вт–Пт 08:00–16:00; Сб–Вс 10:00–17:00. * **Equilibrium Cafe** * **Адрес:** Gran Via de Les Corts Catalanes 677, Eixample Dreta. * **Особенности:** Кафе полного веганского меню. Идеально для завтрака: панкейки, английский завтрак и другие классические блюда в веганской интерпретации. ### 🍕 Рестораны и Тапас * **Blu Bar** * **Адрес:** Rambla del Poblenou, 11, Poblenou. * **Особенности:** Очень популярное место, где подают тапас, сэндвичи, пиццу и напитки. Отличный выбор для ужина или легкого перекуса. * **La Perra Verde** * **Адрес:** Carrer del Torrent de l'Olla, 12, Gràcia. * **Особенности:** Веганский бар с тапасами. Атмосферное место в районе Грасия. * **Mad Mad Vegan** * **Адрес:** Carrer d’Aribau 65, Eixample Esquerra. * **Особенности:** Сеть, известная своими бургерами, тако и другими фаст-фуд блюдами в веганском исполнении. * **Veggie Garden** * **Адрес:** Carrer dels Àngels 3, Raval. * **Особенности:** Ресторан веганской кухни в центре города. * **Vida Cafe** * **Адрес:** Carrer de Feliu i Codina, 24, Horta. * **Особенности:** Дружелюбное соседское кафе с полностью веганским меню, включая обеденные предложения. Эти заведения охватывают разные районы Барселоны — от Эшампле и Грасии до Поблену и Равала. Если вас интересует конкретный район или тип кухни, уточните запрос, и я помогу сузить выбор. | D10: Tool result (web_search): {"query":"best vegan cafes in Barcelona","results":[{"ref":"src_87702009a4","title":"Little Fern - Barcelona Restaurant - HappyCow","domain":"www.happycow.net","snippet":"Little Fern - Barcelona Restaurant - HappyCow\n...\nCaffè latte al caramello #Veganuary at Little Fern in Barcelona\n...\nAcai bowl #Veganuary at Little Fern in Barcelona\n...\nKimchi pancake #Veganuary at Little Fern in Barcelona\n...\nKimchi pancakes at Little Fern in Barcelona\n...\nLittle Fern in Barcelona\n...\nLittle Fern in Barcelona\n...\nLittle Fern in Barcelona\n...\nLittle Fern in Barcelona\n...\nLittle Fern in Barcelona\n...\n# Little Fern\n...\n4.5 stars - View reviews\n...\nVegan-friendly\n...\nA vegetarian breakfast and brunch café that offers sweet and savoury dishes, speciality coffee, signature lattes, cold-pressed juices, and breakfast cocktails. Vegan options are labelled, such as açaí bowl, kimchi pancakes, and falafel wrap. Planted-based milk is available for drinks. Open Mon-Fri 08:30-16:00, Sat-Sun 09:00-16:00.\n...\n168 Carrer de Pere IV, Barcelona, Spain, 08005\n...\n- Outdoor seating\n...\n- Wheelchair accessible\n...\n168 Carrer de Pere IV, Barcelona, Spain, 08005","published_date":null},{"_omitted_items":7},{"ref":"src_6d89885422","title":"MIAM - Barcelona Coffee & Tea - HappyCow","domain":"www.happycow.net","snippet":"MIAM - Barcelona Coffee & Tea - HappyCow\n...\nCafe offering plant-based milk for drinks and several veganizable dishes such as avocado toast. Open Mon-Sun 09:00-16:00.\n...\nCarrer de València 423, L'Eixample, Barcelona, Spain, 08013\n...\nCarrer de València 423, L'Eixample, Barcelona, Spain, 08013\n...\n- Outdoor seating\n...\n- Accepts credit cards\n...\n- Free Wi-Fi\n...\n### Nearby Listings\n...\n#### Kala Brunch\n...\n#### Matcha Crew\n...\n#### Hula Poke\n...\n#### Brunch and Cake\n...\n#### Si et ve gana\n...\n### Vegan News","published_date":null}]} Tool result (web_search): {"query":"best vegan cafes in Barcelona","results":[{"ref":"src_87702009a4","title":"Little Fern - Barcelona Restaurant - HappyCow","domain":"www.happycow.net","snippet":"Little Fern - Barcelona Restaurant - HappyCow\n...\nCaffè latte al caramello #Veganuary at Little Fern in Barcelona\n...\nAcai bowl #Veganuary at Little Fern in Barcelona\n...\nKimchi pancake #Veganuary at Little Fern in Barcelona\n...\nKimchi pancakes at Little Fern in Barcelona\n...\nLittle Fern in Barcelona\n...\nLittle Fern in Barcelona\n...\nLittle Fern in Barcelona\n...\nLittle Fern in Barcelona\n...\nLittle Fern in Barcelona\n...\n# Little Fern\n...\n4.5 stars - View reviews\n...\nVegan-friendly\n...\nA vegetarian breakfast and brunch café that offers sweet and savoury dishes, speciality coffee, signature lattes, cold-pressed juices, and breakfast cocktails. Vegan options are labelled, such as açaí bowl, kimchi pancakes, and falafel wrap. Planted-based milk is available for drinks. Open Mon-Fri 08:30-16:00, Sat-Sun 09:00-16:00.\n...\n168 Carrer de Pere IV, Barcelona, Spain, 08005\n...\n- Outdoor seating\n...\n- Wheelchair accessible\n...\n168 Carrer de Pere IV, Barcelona, Spain, 08005","published_date":null},{"_omitted_items":7},{"ref":"src_6d89885422","title":"MIAM - Barcelona Coffee & Tea - HappyCow","domain":"www.happycow.net","snippet":"MIAM - Barcelona Coffee & Tea - HappyCow\n...\nCafe offering plant-based milk for drinks and several veganizable dishes such as avocado toast. Open Mon-Sun 09:00-16:00.\n...\nCarrer de València 423, L'Eixample, Barcelona, Spain, 08013\n...\nCarrer de València 423, L'Eixample, Barcelona, Spain, 08013\n...\n- Outdoor seating\n...\n- Accepts credit cards\n...\n- Free Wi-Fi\n...\n### Nearby Listings\n...\n#### Kala Brunch\n...\n#### Matcha Crew\n...\n#### Hula Poke\n...\n#### Brunch and Cake\n...\n#### Si et ve gana\n...\n### Vegan News","published_date":null}]} Tool result (web_search): {"query":"vegan cafe Barcelona list recommended","results":[{"ref":"src_7c02a2f937","title":"GAIA's GARDEN - Barcelona Restaurant - HappyCow","domain":"www.happycow.net","snippet":"GAIA's GARDEN - Barcelona Restaurant - HappyCow\n...\n# GAIA's GARDEN\n...\nGluten-free\n...\nA fully gluten-free & fully vegan café offering açaí bowls, freshly house-made smoothies, and specialty coffee. Focused on healthy, wholesome options. Open Mon 08:00-18:00, Tue-Fri 08:00-16:00, Sat-Sun 10:00-17:00.\n...\nCarrer de Còrsega, 551, Barcelona, Spain, 08025\n...\nCarrer de Còrsega, 551, Barcelona, Spain, 08025\n...\n### Nearby Listings\n...\n#### Fargo Café\n...\n#### Kurz & Gut - Gaudi\n...\n#### Oakberry - Sardenya\n...\n#### Cafeteria Tokio Barcelona\n...\n#### Corgi Café","published_date":null},{"_omitted_items":8},{"ref":"src_bf6b43c15f","title":"Best Vegetarian & Vegan Restaurants in Barcelona (2026)","domain":"www.barcelonafoodexperience.com","snippet":"## best vegan restaurants and cafes\n...\nde les Cort\n...\nria Bar- Some say it’s the best place for vegan\n...\nused to be called BarCeloneta, but\n...\na rebranding and\n...\nlocation to the Born. Carrer\n...\nFlassaders, 15 (Born).\n...\n, Vegan Kebabs\n...\n8 (Grácia).\n...\nBotanic- In\n...\nyou remember Mama’s Cafe in Gràcia (\n...\nclosed some time\n...\na brunch restaurant that has now opened in\n...\nyou can book a table,\n...\nis always appreciated when it comes to brunch\n...\nvegan falafel benedict with\n...\nC/ de Torrijos 26 (Gràcia).\n...\nbar in Barcelona\n...\n17 (La\n...\nMad Mad Vegan\n...\nfirst started in Madrid and then\n...\nto hungry patrons\n...\nThey do burgers, tacos,\n...\nand a whole lot more. Carrer d’Aribau 65 (Eixample Esquerra).\n...\nVeggie Garden\n...\nCarrer dels Àngels 3 (Raval)\n...\n2 (Eix\n...\nquerra).\n...\nquerra).\n...\nEquilibrium Cafe- A breakfast and brunch place with pancakes, a full English breakfast, and more, all vegan, of course. Gran Via de Les Corts Catalanes 677 (Eixample Dreta).\n...\nDesoriente\n...\n(Pob\n...\nEixample Esquerra).\n...\nBlu Bar- A very popular vegan restaurant serving tapas, sandwiches, pizzas, and drinks. Rambla del Poblenou, 11 (Poblenou).\n...\nVrutal\n...\n. Rambla del Poblenou,\n...\n16,\n...\n4 (Pob\n...\nou) and Carrer de la Diputació 200 (Eixample Esquerra).\n...\nMacrobiotic Zen\n...\nPaella,\n...\nC/ de Munt\n...\n12 (Eixample Esquerra).\n...\nLa Perra Verde\n...\nvegan tapas in a pet-\n...\nCarrer del Torrent de l'Olla,\n...\n12 (Gràcia).\n...\nVida Cafe- A friendly neighborhood cafe with an all vegan menu, including a lunch deal. Carrer de Feliu i Codina, 24 (Horta).\n...\n6 (G","published_date":"2026-02-07"}]} Final answer: Вот список популярных веганских кафе и ресторанов в Барселоне, основанный на актуальных данных: ### 🥑 Бранч и Кофейни * **Little Fern** * **Адрес:** 168 Carrer de Pere IV, Barcelona, 08005. * **Особенности:** Популярное место для завтраков и бранча. Предлагает асаи-боулы, панкейки с кимчи, фафаль-рап и авторские латте. Есть веганское молоко. * **Часы работы:** Пн–Пт 08:30–16:00, Сб–Вс 09:00–16:00. * **Удобства:** Открытая терраса, доступность для инвалидных колясок. * **MIAM** * **Адрес:** Carrer de València 423, L'Eixample, Barcelona, 08013. * **Особенности:** Уютное кафе с кофе и чаем. Предлагают тосты с авокадо и другие блюда, которые можно адаптировать под веганство. * **Часы работы:** Ежедневно 09:00–16:00. * **Удобства:** Бесплатный Wi-Fi, открытая терраса. * **GAIA's GARDEN** * **Адрес:** Carrer de Còrsega, 551, Barcelona, 08025. * **Особенности:** Полностью веганское и безглютеновое кафе. Специализируется на здоровой еде: смузи, боулы и specialty coffee. * **Часы работы:** Пн 08:00–18:00; Вт–Пт 08:00–16:00; Сб–Вс 10:00–17:00. * **Equilibrium Cafe** * **Адрес:** Gran Via de Les Corts Catalanes 677, Eixample Dreta. * **Особенности:** Кафе полного веганского меню. Идеально для завтрака: панкейки, английский завтрак и другие классические блюда в веганской интерпретации. ### 🍕 Рестораны и Тапас * **Blu Bar** * **Адрес:** Rambla del Poblenou, 11, Poblenou. * **Особенности:** Очень популярное место, где подают тапас, сэндвичи, пиццу и напитки. Отличный выбор для ужина или легкого перекуса. * **La Perra Verde** * **Адрес:** Carrer del Torrent de l'Olla, 12, Gràcia. * **Особенности:** Веганский бар с тапасами. Атмосферное место в районе Грасия. * **Mad Mad Vegan** * **Адрес:** Carrer d’Aribau 65, Eixample Esquerra. * **Особенности:** Сеть, известная своими бургерами, тако и другими фаст-фуд блюдами в веганском исполнении. * **Veggie Garden** * **Адрес:** Carrer dels Àngels 3, Raval. * **Особенности:** Ресторан веганской кухни в центре города. * **Vida Cafe** * **Адрес:** Carrer de Feliu i Codina, 24, Horta. * **Особенности:** Дружелюбное соседское кафе с полностью веганским меню, включая обеденные предложения. Эти заведения охватывают разные районы Барселоны — от Эшампле и Грасии до Поблену и Равала. Если вас интересует конкретный район или тип кухни, уточните запрос, и я помогу сузить выбор. | E10: PASS | G10: 3 | H10: 3 | I10: 3 | J10: 4 | K10: 2 | L10: 4 | M10: 4 | N10: =IF($E10="","",IF($E10="FAIL","FAIL",ROUND(G10*15%+H10*15%+I10*25%+J10*10%+K10*20%+M10*5%+L10*10%,2))) -> 3.05
A11: 10 | B11: Find family-friendly parks in Almaty. | C11: Вот подборка семейных парков в Алматы, подходящих для отдыха с детьми: ### 🎡 **Alem Park, парк семейного отдыха** - **Адрес:** улица Жунисова, 340/42 - **Часы работы:** ежедневно 10:00–23:00 - **Рейтинг:** 4.8 (3703 отзыва) - **Особенности:** парк развлечений, верёвочный парк, каток ### 🎢 **Fantasy World Almaty, парк развлечений** - **Адрес:** проспект Абая, 50а/1 - **Часы работы:** пн–пт 12:00–21:00; сб–вс 11:00–21:00 - **Рейтинг:** 4.9 (4175 отзывов) - **Особенности:** аттракционы, парк развлечений ### 🏔️ **Кок-Тобе, парк отдыха** - **Адрес:** Алматы, Сооружение - **Часы работы:** пн–пт 10:00–23:00; сб–вс 10:00–24:00 - **Рейтинг:** 4.9 (4081 отзыв) - **Особенности:** парк отдыха на горе с панорамными видами ### 🌳 **Центральный Парк Отдыха г. Алматы** - **Адрес:** улица Гоголя, 1 - **Часы работы:** ежедневно 11:00–21:00 - **Рейтинг:** 4.9 (4904 отзыва) ### 🌿 **Парк им. 28 гвардейцев-панфиловцев** - **Адрес:** Алматы - **Часы работы:** круглосуточно - **Рейтинг:** 5.0 (3930 отзывов) ### 🌺 **Главный Ботанический сад** - **Адрес:** улица Тимирязева, 36д к2 - **Часы работы:** ежедневно 09:00–15:00, 15:30–20:00 (санитарный день — первый понедельник месяца) - **Рейтинг:** 4.9 (4660 отзывов) ### 🌲 **Роща им. Баума** - **Адрес:** Алматы, Роща им. Баума - **Рейтинг:** 4.7 (2289 отзывов) Наиболее подходящими для семейного отдыха с детьми являются **Alem Park** (специализированный парк семейного отдыха с верёвочным парком и катком) и **Fantasy World** (парк аттракционов). | D11: Tool result (places_search): {"places":[{"ref":"plc_062118adea","id":"70000001035014267","name":"Friendly, лаундж-бар","address":"Алматы, проспект Достык, 89г","categories":["Рестораны","Кафе","Доставка еды","Бары"],"phones":[],"rating":4.9,"review_count":2442,"hours_text":"пн–чт 11:00–04:00; пт–сб 11:00–06:00; вс 11:00–04:00","open_24h":false,"is_open_now":true,"accessibility":[],"distance_m":null},{"ref":"plc_aea9beaabb","id":"70000001069398135","name":"Family, хостел","address":"Алматы, улица Васнецова, 29Б","categories":["Хостелы"],"phones":[],"rating":4.9,"review_count":97,"hours_text":"ежедневно 07:00–24:00","open_24h":false,"is_open_now":true,"accessibility":[],"distance_m":null},{"ref":"plc_45a697a741","id":"70000001115643563","name":"Family, магазин одежды","address":"Алматы, Саина улица, 16а","categories":["Мужская одежда","Женская одежда","Детская одежда","Обувные магазины"],"phones":[],"rating":5.0,"review_count":2,"hours_text":"ежедневно 09:00–22:00","open_24h":false,"is_open_now":true,"accessibility":[],"distance_m":null},{"ref":"plc_b29da0b9a5","id":"70000001064539033","name":"Family, строящийся жилой комплекс","address":"Алматы, улица Котельникова, 2","categories":["Новостройки"],"phones":[],"rating":3.1,"review_count":5,"hours_text":"ежедневно 10:00–19:00","open_24h":false,"is_open_now":false,"accessibility":[],"distance_m":null},{"ref":"plc_c4d1f2e8ff","id":"70000001068999476","name":"Family, продуктовый магазин","address":"Алматы, микрорайон Атырау, 11 к1","categories":["Продуктовые магазины"],"phones":[],"rating":4.1,"review_count":18,"hours_text":"пн–чт 08:00–00:30; пт–сб 08:00–01:00; вс 08:00–00:30","open_24h":false,"is_open_now":true,"accessibility":[],"distance_m":null},{"ref":"plc_851c961a83","id":"70000001061300648","name":"Family, салон красоты","address":"Алматы, улица Розыбакиева, 57","categories":["Парикмахерские услуги","Ногтевой сервис","Оформление бровей и ресниц","Косметолог"],"phones":[],"rating":4.6,"review_count":71,"hours_text":"ежедневно 09:00–21:00","open_24h":false,"is_open_now":true,"accessibility":[],"distance_m":null},{"ref":"plc_770a343bce","id":"70030076362896815","name":"проспект Улугбека, 57/8","address":"Алматы, проспект Улугбека, 57/8","categories":["Парки"],"phones":[],"rating":4.6,"review_count":298,"hours_text":null,"open_24h":null,"is_open_now":null,"accessibility":[],"distance_m":null}],"area":{"ref":"plc_c23dbfe41e","name":"Алматы","address":"Алматы, Казахстан"},"truncated":false,"anchor":null,"resolved":[],"returned_count":7} Tool result (places_search): {"places":[{"ref":"plc_edff10f269","id":"70000001017272265","name":"Кок-Тобе, парк отдыха","address":"Алматы, Сооружение","categories":["Парки"],"phones":[],"rating":4.9,"review_count":4081,"hours_text":"пн–пт 10:00–23:00; сб–вс 10:00–24:00","open_24h":false,"is_open_now":true,"accessibility":[],"distance_m":null},{"ref":"plc_4eaba027cb","id":"9429940000895897","name":"Центральный Парк Отдыха г. Алматы","address":"Алматы, улица Гоголя, 1","categories":["Парки"],"phones":[],"rating":4.9,"review_count":4904,"hours_text":"ежедневно 11:00–21:00","open_24h":false,"is_open_now":true,"accessibility":[],"distance_m":null},{"ref":"plc_f6142ba164","id":"9429940000798123","name":"Fantasy World Almaty, парк развлечений","address":"Алматы, проспект Абая, 50а/1","categories":["Парки","Аттракционы"],"phones":[],"rating":4.9,"review_count":4175,"hours_text":"пн–пт 12:00–21:00; сб–вс 11:00–21:00","open_24h":false,"is_open_now":true,"accessibility":[],"distance_m":null},{"ref":"plc_b5e5238262","id":"70000001114849933","name":"Flow Park","address":"Алматы, Объект","categories":["Парки"],"phones":[],"rating":4.9,"review_count":599,"hours_text":null,"open_24h":null,"is_open_now":null,"accessibility":[],"distance_m":null},{"ref":"plc_9aa76c0bf2","id":"70000001033029108","name":"Парк Первого Президента Республики Казахстан","address":"Алматы, Объект","categories":["Парки"],"phones":[],"rating":4.9,"review_count":2807,"hours_text":"ежедневно 05:00–23:00","open_24h":false,"is_open_now":true,"accessibility":[],"distance_m":null},{"ref":"plc_8947b55236","id":"70000001017515451","name":"Главный Ботанический сад","address":"Алматы, улица Тимирязева, 36д к2","categories":["Парки","Ботанический сад"],"phones":[],"rating":4.9,"review_count":4660,"hours_text":"ежедневно 09:00–15:00, 15:30–20:00; санитарный день: первый пн месяца","open_24h":false,"is_open_now":true,"accessibility":[],"distance_m":null},{"ref":"plc_0e1a2afda3","id":"70000001064318703","name":"Alem Park, парк семейного отдыха","address":"Алматы, улица Жунисова, 340/42","categories":["Парки","Аттракционы","Верёвочные парки","Каток"],"phones":[],"rating":4.8,"review_count":3703,"hours_text":"ежедневно 10:00–23:00","open_24h":false,"is_open_now":true,"accessibility":[],"distance_m":null},{"ref":"plc_d72fb494b0","id":"70000001113485529","name":"Парк им. 28 гвардейцев-панфиловцев","address":"Алматы, Сооружение","categories":["Парки"],"phones":[],"rating":5.0,"review_count":3930,"hours_text":"круглосуточно","open_24h":true,"is_open_now":true,"accessibility":[],"distance_m":null},{"ref":"plc_700f14910c","id":"9430098953552028","name":"Терренкур","address":"Алматы, Терренкур","categories":[],"phones":[],"rating":4.9,"review_count":1421,"hours_text":null,"open_24h":null,"is_open_now":null,"accessibility":[],"distance_m":null},{"ref":"plc_6c017f4770","id":"9430098914574557","name":"Роща им. Баума","address":"Алматы, Роща им. Баума","categories":["Парки"],"phones":[],"rating":4.7,"review_count":2289,"hours_text":null,"open_24h":null,"is_open_now":null,"accessibility":[],"distance_m":null}],"area":{"ref":"plc_c23dbfe41e","name":"Алматы","address":"Алматы, Казахстан"},"truncated":true,"anchor":null,"resolved":[],"returned_count":10} Final answer: Вот подборка семейных парков в Алматы, подходящих для отдыха с детьми: ### 🎡 **Alem Park, парк семейного отдыха** - **Адрес:** улица Жунисова, 340/42 - **Часы работы:** ежедневно 10:00–23:00 - **Рейтинг:** 4.8 (3703 отзыва) - **Особенности:** парк развлечений, верёвочный парк, каток ### 🎢 **Fantasy World Almaty, парк развлечений** - **Адрес:** проспект Абая, 50а/1 - **Часы работы:** пн–пт 12:00–21:00; сб–вс 11:00–21:00 - **Рейтинг:** 4.9 (4175 отзывов) - **Особенности:** аттракционы, парк развлечений ### 🏔️ **Кок-Тобе, парк отдыха** - **Адрес:** Алматы, Сооружение - **Часы работы:** пн–пт 10:00–23:00; сб–вс 10:00–24:00 - **Рейтинг:** 4.9 (4081 отзыв) - **Особенности:** парк отдыха на горе с панорамными видами ### 🌳 **Центральный Парк Отдыха г. Алматы** - **Адрес:** улица Гоголя, 1 - **Часы работы:** ежедневно 11:00–21:00 - **Рейтинг:** 4.9 (4904 отзыва) ### 🌿 **Парк им. 28 гвардейцев-панфиловцев** - **Адрес:** Алматы - **Часы работы:** круглосуточно - **Рейтинг:** 5.0 (3930 отзывов) ### 🌺 **Главный Ботанический сад** - **Адрес:** улица Тимирязева, 36д к2 - **Часы работы:** ежедневно 09:00–15:00, 15:30–20:00 (санитарный день — первый понедельник месяца) - **Рейтинг:** 4.9 (4660 отзывов) ### 🌲 **Роща им. Баума** - **Адрес:** Алматы, Роща им. Баума - **Рейтинг:** 4.7 (2289 отзывов) Наиболее подходящими для семейного отдыха с детьми являются **Alem Park** (специализированный парк семейного отдыха с верёвочным парком и катком) и **Fantasy World** (парк аттракционов). | E11: FAIL | F11: Language missmatch | N11: =IF($E11="","",IF($E11="FAIL","FAIL",ROUND(G11*15%+H11*15%+I11*25%+J11*10%+K11*20%+M11*5%+L11*10%,2))) -> FAIL
A12: 11 | B12: Suggest local bakeries in central Tbilisi. | C12: Based on recent reviews and local guides, here are some highly regarded local bakeries in central Tbilisi: * **Leila's Tone** * **Location:** 1/21 Mose Gogiberidze St, Tbilisi. * **Highlights:** Known for its high-quality bread and pastries. It is a popular spot for locals and visitors alike, often praised for its fresh, traditional Georgian bread and modern pastries. * **Source:** [Culinary Backstreets](https://culinarybackstreets.com/stories/tbilisi/hitting-the-right-tone) * **Dedas Puri** * **Location:** 16-20 Zaza Panaskerteli-Tsisvili St, Tbilisi. * **Highlights:** A 24-hour bakery, making it a convenient option for late-night cravings or early morning bread. It is known for serving fresh *puri* (Georgian bread) around the clock. * **Source:** [Culinary Backstreets](https://culinarybackstreets.com/stories/tbilisi/hitting-the-right-tone) * **The Baker's Tale** * **Location:** Beneath Sioni Church, off Lezelidze St, Tbilisi. * **Highlights:** This unique bakery is located in an underground space beneath the historic Sioni Church. It is famous for its traditional baking methods and the expertise of its baker, who has been baking for decades. * **Source:** [Tasting Georgia](https://app.ckbk.com) * **QooQy Bakery** * **Location:** Inside Bazari Orbeliani market, Tbilisi. * **Highlights:** A small, charming bakery within the famous Orbeliani Market. It is particularly noted for its vegan options, including soft pretzels, apple galettes, and nut bars, as well as its cookies and coffee. * **Source:** [Georgia Today](https://georgiatoday.ge), [HappyCow](https://www.happycow.net) * **The Bakery (Lily Vanilli)** * **Location:** 20 Irakli Abashidze St, Vake, Tbilisi. * **Highlights:** While Vake is a distinct district, this location is well-known for its seasonal cakes, eclairs, and high-quality coffee. It offers a more modern, international bakery experience. * **Source:** [Lily Vanilli](https://lilyvanilli.com) Please note that addresses and opening hours may change, so it is advisable to verify details before visiting. | D12: Tool result (places_search): {"places":[],"area":{"ref":"plc_474036408b","name":"თბილისი","address":"თბილისი, საქართველო"},"truncated":false,"anchor":null,"resolved":[],"returned_count":0,"warnings":["2GIS does not cover the requested locality; using TomTom."]} Tool result (web_search): {"query":"local bakeries in central Tbilisi","results":[{"ref":"src_c4f882cc08","title":"The Bakery - Tbilisi","domain":"lilyvanilli.com","snippet":"The Bakery - Tbilisi - Lily Vanilli\n\n# The Bakery – Tbilisi\n\nLily Vanilli has opened in Tbilisi. The cafe in Vake is open everyday serving Allpress coffee, brunch and seasonal cakes, eclairs and pastries, including delicious dairy free options. The bespoke wedding and celebration cake service is available all year round, creating beautiful modern cakes for any occasion.\n\nVisit us at: 20 Irakli Abashidze Street 0179 Tbilisi, Georgia\n\nHours 09:00 – 21:00\n\n+995 577 72 80 02\n\nGet in touch about your order\n\nლონდონის შემდეგ ლილი ვანილიმ თავის , #მაღაზია და#კაფე გახსნა თბილისში ! სადაც მზადდება( )ძალიანგემრიელი#საუზმე,#ლანჩი სხვადასხვა სეზონური, ნამცხვრები განსაკუთრებული ცომეული და ასევე მსოფლიოში ერთ ერთი საუკეთესო, და იშვიათი ყავა#AllPress Coffee, .ახალი ზელანდიიდანამ ყველაფერთანერთად#ლილივანილი განთქმულია თავის არაჩვეულებრივი და ყველასგანგანსხვავებული#საქორწილო და#სადღესასწაულო ტორტებით რომლის შეკვეთაც . შესაძლებელია მთელი წლის განმავლობაში .\n\nგვესტუმრეთ – ი. აბაშიძის 20, ვაკ, თბილისი. 0179 ან\n\nდაგვიკავშირდით: hello@lilyvanilli.com ტელ: 577728002\n\n## Cakes\n\n## Classes\n\n## About","published_date":"2018-12-08"},{"_omitted_items":8},{"ref":"src_87376eea06","title":"Two of My Favourite Tbilisi Bakeries from Tasting Georgia: A Food and Wine Journey in the Caucasus by Carla Capalbo","domain":"app.ckbk.com","snippet":"Two of My Favourite Tbilisi Bakeries from Tasting Georgia: A Food and Wine Journey in the Caucasus by Carla Capalbo\n...\nThe Baker’s Tale 1: Sasha Jabidze Alexandre ‘Sasha’ Jabidze has been baking bread for 63 years, 22 of which in a large underground space beneath Sioni Church, off Lezelidze. He was born in Imereti near Terjola, on the border with Racha, in 1938.\n...\n“At school some kids had books but I studied the history and culture of baking bread,” he says, as he mixes the dough far below street level in central Tbilisi. He’s wearing a once-colourful T-shirt and is covered with a light dusting of flour. “In the Black ’90s, before I was given this space by the patriarch, I worked in a factory. But I preferred baking. In Soviet times each loaf had to weigh more than one kilo. Now it’s 600 grams so we use less flour but the price has remained the same,” he says with a shake of the head. “In those days the bread was circular, a shoti with two handles, whereas now it’s a half-shoti with just one. Each area of Georgia has its own shape.”","published_date":null}]} Tool result (web_search): {"query":"best local bakeries central Tbilisi Georgia","results":[{"ref":"src_3b3b7b27b6","title":"Hitting the Right Tone: Tbilisi's Best Bakeries","domain":"culinarybackstreets.com","snippet":"Home / Stories / Hitting the Right Tone: Tbilisi’s Best Bakeries \n\n# Hitting the Right Tone: Tbilisi’s Best Bakeries\n...\nHitting the Right Tone: Tbilisi’s Best Bakeries\n...\n#### Leila’s Tone\n...\n1/21…","published_date":"2024-02-20"},{"_omitted_items":8},{"ref":"src_ce9eb0c122","title":"'QooQy Bakery' – a Unique Experience of Tasty - Georgia Today","domain":"georgiatoday.ge","snippet":"We love sweets and we love coffee. There are a lot of others who love this combination too, and this was the inspiration behind creating a brand that would offer the best quality cookies to customers…","published_date":"2021-08-26"}]} Tool result (web_search): {"query":"Tbilisi best local bakeries addresses old town central","results":[{"ref":"src_3b3b7b27b6","title":"Tbilisi's Best Bakeries - Culinary Backstreets","domain":"culinarybackstreets.com","snippet":"Bakeries \n\n# Hitting the Right Tone\n...\nTbilisi’s Best\n...\n### Location &\n...\n#### Leila’s Tone\n\n1/21 Mose Gogiberidze St \n\nDirections \n\n#### St. Nino's Church\n\n9 Shota Chitadze St, T'bilisi, Georgia \n\nMonday - Sunday 08:30 - 18:30\n\n[(+995) 32 298 93 03 ](tel:%28+995%29 32 298 93 03)\n\nDirections \n\n#### Dedas Puri\n\n16-, 20 ზაზა ფანასკერტელ-ციციშვილის ქუჩა, თბილისი, Georgia \n\nMonday - Sunday 00:00 - 24:00\n\n[(+995) 558 23 54 12 ](tel:%28+995%29 558 23 54 12)\n\nDirections \n\n### Book our\n...\n```json\n{\n \"@context\": \"https://schema.org\",\n \"@type\": \"Article\",\n \"author\": [\n {\n \"@type\": \"Person\",\n \"name\": \"Rowan Twine\",\n \"url\": \"https://culinarybackstreets.com/search/results?author_filter[]=Rowan%20Twine\"\n }\n ],\n \"dateModified\": \"2024-02-20T04:00:06Z\",\n \"datePublished\": \"\",\n \"description\": \"Tbilisi is a city of bread. This staple food has a permanent residency on every kitchen sideboard and a space on every modern table, and has been consumed in Georgia since the beginning of the 6th millennium BC. The demand for fresh bread has produced bakeries throughout the city; multiple in each area and sometimes as many as three along one street. A Tibilsian walking down the street carrying puri (bread) tucked under their arm should really be as emblematic as the baguette-bearing Parisian. \",\n \"headline\": \"Hitting the Right Tone: Tbilisi’s Best Bakeries\",\n \"image\": \"https://culinarybackstreets.s3.us-east-2.amazonaws.com/culinarybackstreets/uploads/cb_Tbilisi_Tbilisi-Tone_RT_top.jpg\",\n \"publisher\": {\n \"@type\": \"Organization\",\n \"image\": \"https://culinarybackstreets.com/images/logo-culinary-backstreets.png\",\n \"logo\": \"https://culinarybackstreets.com/images/logo-culinary-backstreets.png\",\n \"name\": \"Culinary Backstreets\",\n \"url\": \"https://culinarybackstreets.com\"\n },\n \"url\": \"https://culinarybackstreets.com/stories/tbilisi/hitting-the-right-tone\"\n}","published_date":"2024-02-20"},{"_omitted_items":8},{"ref":"src_fc5b702e21","title":"QooQy Bakery - Tbilisi Bakery - HappyCow","domain":"www.happycow.net","snippet":"QooQy Bakery - Tbilisi Bakery - HappyCow\n\n \n\n \n\n \n\n \n\n \n\n \n\nLacto\n\nBakery\n\nEuropean\n\n Small bakery inside Bazari Orbeliani market that also serves coffee and tea. Offers many clearly labeled vegan options, some of which include soft pretzels, apple galettes, nut bars, roasted nuts, truffles, chocolates and more. Open Mon-Sun 12:00am-12:00am. \n\n### 2 Reviews\n\n#### Nica59 \n\nPoints +50\n\n13 Nov 2025\n\n#### Super leckere Dessert - Edit \n\n Cool, alles vegane ist angeschrieben, somit schnell bestellt und super lecker! Kennen uns auch am nächsten Tag noch! Sehr sympatisch. Updated from previous review on 2025-11-13 \n\n#### Guest\n\n \n\n#### M.P.v.O. \n\nPoints +1715\n\n23 Oct 2024\n\n#### Clearly labeled vegan items - Edit \n\n The bakery is nearby one of the metro entrances. All vegan items are clearly labeled. I had a pastry with Spinach and one with potato. \n\n \n\n \n\n \n\n \n\n##### For Members","published_date":null}]} Tool result (places_search): {"places":[],"area":null,"truncated":false,"anchor":null,"resolved":[{"client_id":"bakery_1","input_name":"Leila's Tone","status":"not_found","place":null,"options":[],"error":null},{"client_id":"bakery_2","input_name":"Dedas Puri","status":"not_found","place":null,"options":[],"error":null},{"client_id":"bakery_3","input_name":"The Baker's Tale","status":"not_found","place":null,"options":[],"error":null},{"client_id":"bakery_4","input_name":"QooQy Bakery","status":"not_found","place":null,"options":[],"error":null}],"returned_count":0,"warnings":["2GIS does not cover the requested locality; using TomTom."]} Final answer: Based on recent reviews and local guides, here are some highly regarded local bakeries in central Tbilisi: * **Leila's Tone** * **Location:** 1/21 Mose Gogiberidze St, Tbilisi. * **Highlights:** Known for its high-quality bread and pastries. It is a popular spot for locals and visitors alike, often praised for its fresh, traditional Georgian bread and modern pastries. * **Source:** [Culinary Backstreets](https://culinarybackstreets.com/stories/tbilisi/hitting-the-right-tone) * **Dedas Puri** * **Location:** 16-20 Zaza Panaskerteli-Tsisvili St, Tbilisi. * **Highlights:** A 24-hour bakery, making it a convenient option for late-night cravings or early morning bread. It is known for serving fresh *puri* (Georgian bread) around the clock. * **Source:** [Culinary Backstreets](https://culinarybackstreets.com/stories/tbilisi/hitting-the-right-tone) * **The Baker's Tale** * **Location:** Beneath Sioni Church, off Lezelidze St, Tbilisi. * **Highlights:** This unique bakery is located in an underground space beneath the historic Sioni Church. It is famous for its traditional baking methods and the expertise of its baker, who has been baking for decades. * **Source:** [Tasting Georgia](https://app.ckbk.com) * **QooQy Bakery** * **Location:** Inside Bazari Orbeliani market, Tbilisi. * **Highlights:** A small, charming bakery within the famous Orbeliani Market. It is particularly noted for its vegan options, including soft pretzels, apple galettes, and nut bars, as well as its cookies and coffee. * **Source:** [Georgia Today](https://georgiatoday.ge), [HappyCow](https://www.happycow.net) * **The Bakery (Lily Vanilli)** * **Location:** 20 Irakli Abashidze St, Vake, Tbilisi. * **Highlights:** While Vake is a distinct district, this location is well-known for its seasonal cakes, eclairs, and high-quality coffee. It offers a more modern, international bakery experience. * **Source:** [Lily Vanilli](https://lilyvanilli.com) Please note that addresses and opening hours may change, so it is advisable to verify details before visiting. | E12: PASS | G12: 3 | H12: 3 | I12: 3 | J12: 5 | K12: 2 | L12: 5 | M12: 4 | N12: =IF($E12="","",IF($E12="FAIL","FAIL",ROUND(G12*15%+H12*15%+I12*25%+J12*10%+K12*20%+M12*5%+L12*10%,2))) -> 3.25
A13: 12 | B13: Find historical museums in Baku. | C13: Based on the search results, here are the historical museums in Baku. The **National Museum of History of Azerbaijan** is the primary historical museum with verified location details. Other notable historical and cultural museums are listed below based on local sources. ### 1. National Museum of History of Azerbaijan This is the main historical museum of Azerbaijan, located in the former residence of oil magnate Haji Zeynalabdin Taghiyev. It covers the history of Azerbaijan from ancient times to the modern republic. * **Address:** Hacı Zeynalabdin Tağıyev Küçəsi 4, Baku * **Hours:** 09:00–18:00 (Closed on August 16) * **Source:** ### Other Notable Historical Museums in Baku The following museums are recognized as significant historical and cultural institutions in Baku. Please note that specific addresses for these locations were not available in the current database. * **Azerbaijan Carpet Museum** – Dedicated to traditional Azerbaijani carpet weaving, a UNESCO-recognized heritage. * **Museum of Archaeology and Ethnography** – Features archaeological finds and ethnographic exhibits from the region. * **Azerbaijan State Museum of History of Religion** – Focuses on the history of religion and religious tolerance in Azerbaijan. * **Azerbaijan State Theatre Museum** – Dedicated to the history of theatre in Azerbaijan. * **Nizami Museum of Azerbaijani Literature** – Commemorates the poet Nizami Ganjavi and the history of Azerbaijani literature. * **Institute of Manuscripts of Azerbaijan** – Houses a vast collection of ancient manuscripts and historical documents. * **Azerbaijan State Museum of Musical Culture** – Explores the musical heritage and instruments of Azerbaijan. * **Azerbaijan Medicine Museum** – Details the history of medicine and healthcare in the region. * **House-Museum of Azim Azimzade** – Dedicated to the famous artist Azim Azimzade. * **House-Museum of Jalil Mammadguluzadeh** – Dedicated to the writer and public figure Jalil Mammadguluzadeh. * **House-Museum of Bulbul** – Dedicated to the renowned singer Bulbul. * **Hasanbey Zardabi Natural History Museum** – Focuses on the natural history of the Caucasus. * **House-Museum of Leopold and Mstislav Rostropovich** – Dedicated to the famous cellist and his father. * **Azerbaijan Railway Museum** – Showcases the history of railways in Azerbaijan. * **Baku Museum of Miniature Books** – Features a unique collection of miniature books from around the world. * **House-Museum of Mammed Said Ordubadi** – Dedicated to the writer Mammed Said Ordubadi. * **House-Museum of Nariman Narimanov** – Dedicated to the political figure Nariman Narimanov. * **House-Museum of Samad Vurgun** – Dedicated to the poet Samad Vurgun. * **Uzeyir Hajibeyov's House Museum** – Dedicated to the composer Uzeyir Hajibeyov. * **House-Museum of Sattar Bahlulzade** – Dedicated to the artist Sattar Bahlulzade. * **ANAS House-Museum of Huseyn Javid** – Dedicated to the poet Huseyn Javid. **Sources:** * * * | D13: Tool result (places_search): {"places":[{"ref":"plc_659c1dc198","id":"70000001112816932","name":"Historical, otel","address":"Баку, Кичик Гала, 16","categories":["Гостиницы"],"phones":[],"rating":null,"review_count":null,"hours_text":"круглосуточно","open_24h":true,"is_open_now":true,"accessibility":[],"distance_m":null}],"area":{"ref":"plc_c37b314381","name":"Bakı","address":"Bakı, Azərbaycan"},"truncated":false,"anchor":null,"resolved":[],"returned_count":1} Tool result (places_search): {"places":[{"ref":"plc_19519ac183","id":"70000001037502820","name":"Museum İnn, restoran","address":"Баку, Беюк Гала 4-ый, 5","categories":["Рестораны"],"phones":[],"rating":3.8,"review_count":9,"hours_text":"ежедневно 10:00–24:00","open_24h":false,"is_open_now":true,"accessibility":[],"distance_m":null},{"ref":"plc_5093b22345","id":"70000001114964799","name":"Khan Museum, restoran","address":"Баку, Низами, 62Б","categories":["Рестораны"],"phones":[],"rating":null,"review_count":null,"hours_text":"ежедневно 10:00–23:00","open_24h":false,"is_open_now":true,"accessibility":[],"distance_m":null},{"ref":"plc_f1ae083568","id":"70000001038018344","name":"Shah Palace Luxury Museum, otel","address":"Баку, Бёюк Гала, 47","categories":["Гостиницы"],"phones":[],"rating":4.1,"review_count":11,"hours_text":"круглосуточно","open_24h":true,"is_open_now":true,"accessibility":[],"distance_m":null},{"ref":"plc_f8e77fdeab","id":"70000001106052289","name":"Coffee Museum, qəhvəxana","address":"Баку, Бести Багирова улица, 32-34","categories":["Точки кофе","Кофейни"],"phones":[],"rating":5.0,"review_count":1,"hours_text":"ежедневно 07:30–23:00","open_24h":false,"is_open_now":true,"accessibility":[],"distance_m":null}],"area":{"ref":"plc_c37b314381","name":"Bakı","address":"Bakı, Azərbaycan"},"truncated":false,"anchor":null,"resolved":[],"returned_count":4} Tool result (web_search): {"query":"historical museums in Baku Azerbaijan","results":[{"ref":"src_534e4ee08e","title":"National Museum of History of Azerbaijan","domain":"azhistorymuseum.gov.az","snippet":"Main page - National Museum of History of Azerbaijan\n\nBronze medal dedicated to the 20th Anniversary of Mingechevir\n\nGold medal of the 1st European Games\n\nThe first natural gold placer of Azerbaijan\n\nThe exhibition “Nizami and Azerbaijani Atabeks state”","published_date":null},{"_omitted_items":8},{"ref":"src_119b36c9f2","title":"UNESCO World Heritage - \"Icherisheher\" State Historical-Architectural Reserve Administration","domain":"icherisheher.gov.az","snippet":"Icherisheher is the ancient core of Baku, the historical heart of the capital of Azerbaijan. This unique urban complex has played an important role in the cultural, architectural and social life of the Caucasus for millennia, preserving the traces of different eras.\n...\nIn 2000, Icherisheher was inscribed on the UNESCO World Heritage List. This decision confirms that Icherisheher has an outstanding universal value not only for Azerbaijan, but for all of humanity. In 2003, Icherisheher was included in the UNESCO List of World Heritage in Danger due to the earthquake in Baku and the lack of a unified conservation and management policy. In accordance with the decree of the President of the Republic of Azerbaijan, Mr. Ilham Aliyev, dated February 10, 2005, the Administration of State Historical-Architectural Reserve “Icherisheher” was established. In 2009, the Master Plan for the Conservation of Icherisheher was approved by the Cabinet of Ministers, and in the same year, Icherisheher was removed from the UNESCO List of World Heritage in Danger.\n...\nto create a unique urban panorama.\n...\n, the elegant ornaments of the Palace of the Shir\n...\nhahs and the magnificence of the\n...\nhistorical value of I\n...\n## Open-air museum\n...\nAs a result of restoration and conservation work carried out by the Administration of State Historical-Architectural Reserve “Icherisheher” in accordance with UNESCO standards, Icherisheher, while preserving its originality, has become an open-air museum for visitors from all over the world.","published_date":null}]} Tool result (web_search): {"query":"list of museums in Baku Azerbaijan historical","results":[{"ref":"src_2339c04849","title":"List of museums in Baku","domain":"en.wikipedia.org","snippet":"List of museums in Baku\n...\nThis is a list of museums in Baku, the capital city of Azerbaijan.\n...\n| The name of museums | Picture | Established |\n| --- | --- | --- |\n| House-Museum of Abdulla Shaig | 1990 |\n| Museum of Archaeology and Ethnography | 1981 |\n| Azerbaijan State Museum of History of Religion | 1967 |\n| Azerbaijan State Agriculture Museum | 1924 |\n| House-Museum of Jalil Mammadguluzadeh | 1978 |\n| National Art Museum of Azerbaijan | 1936 |\n| House-Museum of Bulbul | 1976 |\n| National Museum of History of Azerbaijan | 1920 |\n| Hasanbey Zardabi Natural History Museum | 1930 |\n| House-Museum of Leopold and Mstislav Rostropovich | 1998 |\n| Azerbaijan Carpet Museum | 1967 |\n| Azerbaijan Railway Museum | 2019 |\n| Institute of Manuscripts of Azerbaijan | 1986 |\n| Baku Museum of Miniature Books | 2002 |\n| House-Museum of Mammed Said Ordubadi (Baku) | 1979 |\n| Nizami Museum of Azerbaijani Literature | 1939 |\n| House-Museum of Nariman Narimanov | 1977 |\n| Gobustan National Park | 1996 |\n| Rinay | 1989 |\n| House-Museum of Samad Vurgun | 1975 |\n| Uzeyir Hajibeyov's House Museum | 1975 |\n| House-Museum of Sattar Bahlulzade | 2014 |\n| House-Museum of Azim Azimzade | 1968 |\n| Azerbaijan State Theatre Museum | 1934 |\n| ANAS House-Museum of Huseyn Javid | 1981 |\n| Azerbaijan Medicine Museum | 1986 |\n| Azerbaijan State Museum of Musical Culture | 1967 |","published_date":null},{"_omitted_items":8},{"ref":"src_7fd9cbf582","title":"Top 6 Museums in Baku: A Cultural Guide for First-Time Visitors – Azerbaijan Traveller","domain":"azerbaijantraveller.com","snippet":"If you’re planning a trip to Azerbaijan, visiting museums in Baku is one of the best ways to understand the city’s rich history and vibrant culture. From ancient craftsmanship to modern art,\n...\nmuseums reflect the country’s unique position between East and West.\n...\nThis guide highlights the best museums in Baku to experience outside the Baku Old Town (Icherisheher). It is perfect for travelers interested in history, art, architecture, and authentic cultural experiences.\n...\n## 🏛️ Azerbaijan Carpet Museum\n...\nThe Azerbaijan Carpet Museum is one of the most famous cultural attractions in Baku. Dedicated to traditional Azerbaijani carpet weaving — a UNESCO-recognized heritage — the museum showcases regional styles, patterns, and techniques dating back centuries.\n...\n## 🏛️ National Museum of History of Azerbaijan\n...\nLocated in the former residence of oil magnate Haji Zeynalabdin Taghiyev, this museum is the best place to understand Azerbaijan’s historical journey from ancient civilizations to the modern republic.\n...\n## 🏛️ Heydar Aliyev Center\n...\nDesigned by world-renowned architect Zaha Hadid, the Heydar Aliyev Center is one of the most iconic buildings in Azerbaijan and a symbol of modern Baku. More than a museum, it functions as a cultural center hosting permanent and temporary exhibitions on history, art, and national identity.\n...\n## 🎨 Museum of Modern Art Baku\n...\nFocused on Azerbaijani modern and avant-garde art, this museum reflects the country’s creative evolution during the late Soviet and post-independence periods.\n...\n## 🎨 National Art Museum of Azerbaijan\n...\nAs the country’s largest art museum, it presents Azerbaijani, Russian, and European art collections inside historic oil-boom mansions. It’s one of the most refined cultural attractions in Baku.\n...\n## 📚Museum of Miniature Books\n...\nprivate museum features thousands of tiny books from across the world, a delight for book lovers and curious travelers alike.","published_date":"2026-01-10"}]} Tool result (places_search): {"places":[],"area":null,"truncated":false,"anchor":null,"resolved":[{"client_id":"candidate_1","input_name":"National Museum of History of Azerbaijan","status":"resolved","place":{"ref":"plc_156314926e","id":"yq24MgwpHhR3g_5xsohnFw","name":"National Museum Of History Of Azerbaijan","address":"Hacı Zeynalabdin Tağıyev Küçəsi 4 Bakı, Bakı","categories":["museum"],"phones":[],"rating":null,"review_count":null,"hours_text":"Next 7 days: Aug 10–15 09:00–18:00; Aug 16 closed","open_24h":false,"is_open_now":false,"accessibility":[],"distance_m":null},"options":[],"error":null},{"client_id":"candidate_2","input_name":"Azerbaijan Carpet Museum","status":"not_found","place":null,"options":[],"error":null},{"client_id":"candidate_3","input_name":"Museum of Archaeology and Ethnography","status":"not_found","place":null,"options":[],"error":null},{"client_id":"candidate_4","input_name":"Azerbaijan State Museum of History of Religion","status":"not_found","place":null,"options":[],"error":null},{"client_id":"candidate_5","input_name":"Azerbaijan Theatre Museum","status":"not_found","place":null,"options":[],"error":null},{"client_id":"candidate_6","input_name":"Nizami Museum of Azerbaijani Literature","status":"not_found","place":null,"options":[],"error":null},{"client_id":"candidate_7","input_name":"Institute of Manuscripts of Azerbaijan","status":"not_found","place":null,"options":[],"error":null},{"client_id":"candidate_8","input_name":"Azerbaijan State Museum of Musical Culture","status":"not_found","place":null,"options":[],"error":null},{"client_id":"candidate_9","input_name":"Azerbaijan Medicine Museum","status":"not_found","place":null,"options":[],"error":null},{"client_id":"candidate_10","input_name":"House-Museum of Azim Azimzade","status":"not_found","place":null,"options":[],"error":null}],"returned_count":1,"warnings":["2GIS place search returned no matches; retrying with TomTom."]} Final answer: Based on the search results, here are the historical museums in Baku. The **National Museum of History of Azerbaijan** is the primary historical museum with verified location details. Other notable historical and cultural museums are listed below based on local sources. ### 1. National Museum of History of Azerbaijan This is the main historical museum of Azerbaijan, located in the former residence of oil magnate Haji Zeynalabdin Taghiyev. It covers the history of Azerbaijan from ancient times to the modern republic. * **Address:** Hacı Zeynalabdin Tağıyev Küçəsi 4, Baku * **Hours:** 09:00–18:00 (Closed on August 16) * **Source:** ### Other Notable Historical Museums in Baku The following museums are recognized as significant historical and cultural institutions in Baku. Please note that specific addresses for these locations were not available in the current database. * **Azerbaijan Carpet Museum** – Dedicated to traditional Azerbaijani carpet weaving, a UNESCO-recognized heritage. * **Museum of Archaeology and Ethnography** – Features archaeological finds and ethnographic exhibits from the region. * **Azerbaijan State Museum of History of Religion** – Focuses on the history of religion and religious tolerance in Azerbaijan. * **Azerbaijan State Theatre Museum** – Dedicated to the history of theatre in Azerbaijan. * **Nizami Museum of Azerbaijani Literature** – Commemorates the poet Nizami Ganjavi and the history of Azerbaijani literature. * **Institute of Manuscripts of Azerbaijan** – Houses a vast collection of ancient manuscripts and historical documents. * **Azerbaijan State Museum of Musical Culture** – Explores the musical heritage and instruments of Azerbaijan. * **Azerbaijan Medicine Museum** – Details the history of medicine and healthcare in the region. * **House-Museum of Azim Azimzade** – Dedicated to the famous artist Azim Azimzade. * **House-Museum of Jalil Mammadguluzadeh** – Dedicated to the writer and public figure Jalil Mammadguluzadeh. * **House-Museum of Bulbul** – Dedicated to the renowned singer Bulbul. * **Hasanbey Zardabi Natural History Museum** – Focuses on the natural history of the Caucasus. * **House-Museum of Leopold and Mstislav Rostropovich** – Dedicated to the famous cellist and his father. * **Azerbaijan Railway Museum** – Showcases the history of railways in Azerbaijan. * **Baku Museum of Miniature Books** – Features a unique collection of miniature books from around the world. * **House-Museum of Mammed Said Ordubadi** – Dedicated to the writer Mammed Said Ordubadi. * **House-Museum of Nariman Narimanov** – Dedicated to the political figure Nariman Narimanov. * **House-Museum of Samad Vurgun** – Dedicated to the poet Samad Vurgun. * **Uzeyir Hajibeyov's House Museum** – Dedicated to the composer Uzeyir Hajibeyov. * **House-Museum of Sattar Bahlulzade** – Dedicated to the artist Sattar Bahlulzade. * **ANAS House-Museum of Huseyn Javid** – Dedicated to the poet Huseyn Javid. **Sources:** * * * | E13: PASS | G13: 3 | H13: 3 | I13: 3 | J13: 3 | K13: 3 | L13: 4 | M13: 5 | N13: =IF($E13="","",IF($E13="FAIL","FAIL",ROUND(G13*15%+H13*15%+I13*25%+J13*10%+K13*20%+M13*5%+L13*10%,2))) -> 3.2
A14: 13 | B14: Recommend bookstores with cafes in Yerevan. | C14: Based on my search, I found **2 bookstores with cafes** in Yerevan: --- ### 1. **Common Ground** (ռեստորան-գրախանութ) - **Address:** Yerevan, Khachatur Abovyan street, 22/4 - **Type:** Restaurant-bookstore - **Hours:** Daily 18:00–23:00 ### 2. **Russian Book House** (Russian Book House, bookstore-cafe) - **Address:** Yerevan, Vardanants street, 15/4 - **Type:** Bookstore-cafe - **Hours:** Mon–Fri 10:00–19:00; Sat–Sun 11:00–18:00 --- Both locations combine book browsing with dining options. If you'd like more details about either place or need help with directions, let me know! | D14: Tool result (places_search): {"places":[{"ref":"plc_0375913af8","id":"2QFCVAnEl_zVt3l_CSG9Iw","name":"Luys Bookstore","address":"Մեսրոպ Մաշտոցի պողոտա 45 Երևան Մարզ, Երևան Մարզ","categories":["shop"],"phones":[],"rating":null,"review_count":null,"hours_text":null,"open_24h":null,"is_open_now":null,"accessibility":[],"distance_m":null},{"ref":"plc_da1c2b03ee","id":"pEinqY34vbFxGSHGMdp8ug","name":"Zangak Bookstore","address":"Խաչատուր Աբովյան փողոց 7 Երևան Մարզ, Երևան Մարզ","categories":["shop"],"phones":[],"rating":null,"review_count":null,"hours_text":null,"open_24h":null,"is_open_now":null,"accessibility":[],"distance_m":null}],"area":{"ref":"plc_b767569bab","name":"Երևան","address":"Երևան, Երևան Մարզ, Հայաստան"},"truncated":false,"anchor":null,"resolved":[],"returned_count":2,"warnings":["2GIS place search returned no matches; retrying with TomTom.","TomTom supplied neither opening hours nor a phone number for 2 results; their current operation could not be verified from this response."]} Tool result (places_search): {"places":[],"area":{"ref":"plc_b767569bab","name":"Երևան","address":"Երևան, Երևան Մարզ, Հայաստան"},"truncated":false,"anchor":null,"resolved":[],"returned_count":0,"warnings":["2GIS place search returned no matches; retrying with TomTom."]} Tool result (places_search): {"places":[{"ref":"plc_b33f06e6d7","id":"70000001084183625","name":"Zangak, գրախանութ","address":"Yerevan, Khachatur Abovyan street, 7","categories":["Bookstores","Gift wrapping service","Stationery / school supplies","Educational materials"],"phones":[],"rating":5.0,"review_count":1,"hours_text":"ежедневно 10:00–22:00","open_24h":false,"is_open_now":true,"accessibility":[],"distance_m":null},{"ref":"plc_c046a5c12c","id":"70000001084412318","name":"Epigraph, նկարչական պարագաների խանութ","address":"Yerevan, Mesrop Mashtotsi avenue, 43","categories":["Bookstores","Goods / Materials for arts","Stationery / school supplies"],"phones":[],"rating":5.0,"review_count":1,"hours_text":"ежедневно 09:00–22:00","open_24h":false,"is_open_now":true,"accessibility":[],"distance_m":null},{"ref":"plc_ea5609ea4f","id":"70000001084311259","name":"Bookinist, գրախանութ","address":"Yerevan, Mesrop Mashtotsi avenue, 20","categories":["Bookstores","Stationery / school supplies","Table games"],"phones":[],"rating":5.0,"review_count":3,"hours_text":"ежедневно 10:00–21:00","open_24h":false,"is_open_now":false,"accessibility":[],"distance_m":null},{"ref":"plc_ee8e0d0fe5","id":"70000001116070319","name":"Common Ground, ռեստորան-գրախանութ","address":"Yerevan, Khachatur Abovyan street, 22/4","categories":["Bookstores","Restaurants"],"phones":[],"rating":null,"review_count":null,"hours_text":"ежедневно 18:00–23:00","open_24h":false,"is_open_now":true,"accessibility":[],"distance_m":null},{"ref":"plc_0502d2c275","id":"70000001084532866","name":"Bookinist, գրախանութ","address":"Yerevan, Պապ թագավորի street, 2","categories":["Bookstores","Stationery / school supplies","Gift shops / home decoration"],"phones":[],"rating":5.0,"review_count":2,"hours_text":"ежедневно 10:00–22:00","open_24h":false,"is_open_now":true,"accessibility":[],"distance_m":null},{"ref":"plc_53736586ce","id":"70000001110448331","name":"National Gallery of Armenia, souvenir store","address":"Yerevan, Republic square street, 3","categories":["Bookstores","Gift shops / home decoration"],"phones":[],"rating":null,"review_count":null,"hours_text":"вт–сб 11:00–18:00; вс 11:00–17:00","open_24h":null,"is_open_now":false,"accessibility":[],"distance_m":null},{"ref":"plc_55237129b3","id":"70000001099382959","name":"Kanach kakach, bookshop","address":"Yerevan, Saryan street, 16/3","categories":["Bookstores"],"phones":[],"rating":5.0,"review_count":2,"hours_text":"пн–вт 12:00–20:00; чт–вс 12:00–20:00","open_24h":null,"is_open_now":false,"accessibility":[],"distance_m":null},{"ref":"plc_f8b0ff0b00","id":"70000001087493114","name":"Epigraph, նկարչական պարագաների խանութ","address":"Yerevan, Komitasi avenue, 65","categories":["Bookstores","Goods / Materials for arts","Stationery / school supplies"],"phones":[],"rating":5.0,"review_count":1,"hours_text":"пн–сб 10:00–21:00; вс 12:00–21:00","open_24h":false,"is_open_now":false,"accessibility":[],"distance_m":null},{"ref":"plc_eaa8056598","id":"70000001087693171","name":"Bookinist, գրախանութ","address":"Yerevan, Arshakunyats avenue, 34/3","categories":["Bookstores","Stationery / school supplies","Gift shops / home decoration"],"phones":[],"rating":null,"review_count":null,"hours_text":"ежедневно 10:00–22:00","open_24h":false,"is_open_now":true,"accessibility":[],"distance_m":null},{"ref":"plc_5264db84c0","id":"70000001090679824","name":"Russian Book House, bookstore-cafe","address":"Yerevan, Vardanants street, 15/4","categories":["Bookstores","Cafe / Restaurants"],"phones":[],"rating":null,"review_count":null,"hours_text":"пн–пт 10:00–19:00; сб–вс 11:00–18:00","open_24h":false,"is_open_now":false,"accessibility":[],"distance_m":null}],"area":{"ref":"plc_b767569bab","name":"Երևան","address":"Երևան, Երևան Մարզ, Հայաստան"},"truncated":true,"anchor":null,"resolved":[],"returned_count":10} Final answer: Based on my search, I found **2 bookstores with cafes** in Yerevan: --- ### 1. **Common Ground** (ռեստորան-գրախանութ) - **Address:** Yerevan, Khachatur Abovyan street, 22/4 - **Type:** Restaurant-bookstore - **Hours:** Daily 18:00–23:00 ### 2. **Russian Book House** (Russian Book House, bookstore-cafe) - **Address:** Yerevan, Vardanants street, 15/4 - **Type:** Bookstore-cafe - **Hours:** Mon–Fri 10:00–19:00; Sat–Sun 11:00–18:00 --- Both locations combine book browsing with dining options. If you'd like more details about either place or need help with directions, let me know! | E14: PASS | G14: 5 | H14: 4 | I14: 4 | J14: 5 | K14: 5 | L14: 5 | M14: 4 | N14: =IF($E14="","",IF($E14="FAIL","FAIL",ROUND(G14*15%+H14*15%+I14*25%+J14*10%+K14*20%+M14*5%+L14*10%,2))) -> 4.55
A15: 14 | B15: Найди красивые смотровые площадки в Москве. | C15: Вот список красивых смотровых площадок в Москве, которые можно посетить: ### 1. **Смотровая площадка «Солнце Москвы», колесо обозрения** - **Рейтинг:** 5.0 (1422 отзыва) - **Часы работы:** пн–чт 11:00–22:00; пт 11:00–23:00; сб–вс 10:00–23:00 - **Особенности:** Отличная возможность увидеть город с высоты, совмещённая с колесом обозрения. ### 2. **Смотровая площадка Воробьёвых гор** - **Рейтинг:** 4.8 (243 отзыва) - **Часы работы:** круглосуточно - **Особенности:** Классическая смотровая площадка с панорамным видом на Москву-реку и центр города. ### 3. **Panorama360, смотровая площадка** - **Рейтинг:** 4.8 (2035 отзывов) - **Адрес:** Пресненская набережная, 12 - **Часы работы:** пн–пт 11:00–22:00; сб–вс 10:00–22:00 - **Особенности:** Расположена на 89-м этаже «Москва-Сити», предлагает панорамный вид на город. ### 4. **Останкинская телебашня, смотровая площадка** - **Рейтинг:** 5.0 (1196 отзывов) - **Адрес:** улица Академика Королёва, 15 к1 - **Часы работы:** ежедневно 09:00–22:00 - **Особенности:** Одна из самых высоких точек Москвы, открывающая потрясающий вид на столицу. ### 5. **«#Вышетольколюбовь», смотровая площадка** - **Рейтинг:** 4.8 (550 отзывов) - **Адрес:** 1-й Красногвардейский проезд, 21 ст2 - **Часы работы:** пн–пт 12:00–23:00; сб–вс 10:00–23:00 - **Особенности:** Современная площадка с видом на реку и городскую застройку. ### 6. **ЦДМ, смотровая площадка** - **Рейтинг:** 4.4 (24 отзыва) - **Адрес:** Театральный проезд, 5 - **Часы работы:** пн–чт 10:00–21:30; пт–сб 10:00–22:30; вс 10:00–21:30 - **Особенности:** Расположена на крыше Центрального детского магазина, с видом на Красную площадь. ### 7. **Смотровая площадка Храма Христа Спасителя** - **Рейтинг:** 4.9 (20 отзывов) - **Адрес:** улица Волхонка, 15 - **Часы работы:** пн 13:00–19:00; вт–пт 10:00–19:00; сб 10:00–16:30; вс 12:00–18:00 - **Особенности:** Панорамный вид на храм и прилегающие районы. ### 8. **Billion City, смотровая площадка** - **Рейтинг:** 4.8 (23 отзыва) - **Адрес:** Пресненская набережная, 6 ст2 - **Часы работы:** ежедневно 10:00–21:00 - **Особенности:** Современная площадка с видом на «Москва-Сити». ### 9. **Смотровая площадка Казанского вокзала** - **Рейтинг:** 3.8 (4 отзыва) - **Адрес:** Комсомольская площадь, 2 - **Часы работы:** ежедневно 10:00–21:00 - **Особенности:** Небольшая площадка с видом на вокзал и прилегающие улицы. ### 10. **Ленинский проспект, 32а ст1** - **Рейтинг:** 4.6 (69 отзывов) - **Особенности:** Локация с видом на город. Эти площадки предлагают разнообразные виды на Москву, от панорамных до уютных локаций. | D15: Tool result (places_search): {"places":[{"ref":"plc_4cd4a9f054","id":"70000001052410383","name":"Солнце Москвы, колесо обозрения","address":"Москва, Солнце Москвы, колесо обозрения","categories":["Смотровые площадки","Организация праздников","Аттракционы","Экскурсии"],"phones":[],"rating":5.0,"review_count":1422,"hours_text":"пн–чт 11:00–22:00; пт 11:00–23:00; сб–вс 10:00–23:00","open_24h":false,"is_open_now":true,"accessibility":[],"distance_m":null},{"ref":"plc_a5e8fdc39f","id":"70000001097217949","name":"Смотровая площадка Воробьёвых гор","address":"Москва, Объект","categories":["Смотровые площадки"],"phones":[],"rating":4.8,"review_count":243,"hours_text":"круглосуточно","open_24h":true,"is_open_now":true,"accessibility":[],"distance_m":null},{"ref":"plc_7d7296911b","id":"70000001031381499","name":"Panorama360, смотровая площадка","address":"Москва, Пресненская набережная, 12","categories":["Смотровые площадки"],"phones":[],"rating":4.8,"review_count":2035,"hours_text":"пн–пт 11:00–22:00; сб–вс 10:00–22:00","open_24h":false,"is_open_now":true,"accessibility":[],"distance_m":null},{"ref":"plc_2bfa3372df","id":"4504127912850497","name":"Останкинская телебашня, смотровая площадка","address":"Москва, улица Академика Королёва, 15 к1","categories":["Смотровые площадки","Интересные здания"],"phones":[],"rating":5.0,"review_count":1196,"hours_text":"ежедневно 09:00–22:00","open_24h":false,"is_open_now":true,"accessibility":[],"distance_m":null},{"ref":"plc_5c028d37cb","id":"70000001029329887","name":"#Вышетольколюбовь, смотровая площадка","address":"Москва, 1-й Красногвардейский проезд, 21 ст2","categories":["Смотровые площадки"],"phones":[],"rating":4.8,"review_count":550,"hours_text":"пн–пт 12:00–23:00; сб–вс 10:00–23:00","open_24h":false,"is_open_now":true,"accessibility":[],"distance_m":null},{"ref":"plc_252d6957d6","id":"70000001055629056","name":"ЦДМ, смотровая площадка","address":"Москва, Театральный проезд, 5","categories":["Смотровые площадки"],"phones":[],"rating":4.4,"review_count":24,"hours_text":"пн–чт 10:00–21:30; пт–сб 10:00–22:30; вс 10:00–21:30","open_24h":false,"is_open_now":true,"accessibility":[],"distance_m":null},{"ref":"plc_0c7618125e","id":"70000001034355338","name":"Смотровая площадка, Храм Христа Спасителя","address":"Москва, улица Волхонка, 15","categories":["Смотровые площадки"],"phones":[],"rating":4.9,"review_count":20,"hours_text":"пн 13:00–19:00; вт–пт 10:00–19:00; сб 10:00–16:30; вс 12:00–18:00; зимний период: пн 13:00-18:00; вт-пт 10:00-18:00; сб 10:00-16:30; вс 12:00-18:00","open_24h":false,"is_open_now":false,"accessibility":[],"distance_m":null},{"ref":"plc_d830870d8b","id":"4504235291227144","name":"Ленинский проспект, 32а ст1","address":"Москва, Ленинский проспект, 32а ст1","categories":["Смотровые площадки"],"phones":[],"rating":4.6,"review_count":69,"hours_text":null,"open_24h":null,"is_open_now":null,"accessibility":[],"distance_m":null},{"ref":"plc_34c0241b1d","id":"70000001062893384","name":"Billion City, смотровая площадка","address":"Москва, Пресненская набережная, 6 ст2","categories":["Смотровые площадки"],"phones":[],"rating":4.8,"review_count":23,"hours_text":"ежедневно 10:00–21:00","open_24h":false,"is_open_now":true,"accessibility":[],"distance_m":null},{"ref":"plc_42c9aded7b","id":"70000001082521046","name":"Смотровая площадка Казанского вокзала","address":"Москва, Комсомольская площадь, 2","categories":["Смотровые площадки"],"phones":[],"rating":3.8,"review_count":4,"hours_text":"ежедневно 10:00–21:00","open_24h":false,"is_open_now":true,"accessibility":[],"distance_m":null}],"area":{"ref":"plc_c05673c3e9","name":"Москва","address":"Москва, Центральный федеральный округ, Россия"},"truncated":true,"anchor":null,"resolved":[],"returned_count":10} Final answer: Вот список красивых смотровых площадок в Москве, которые можно посетить: ### 1. **Смотровая площадка «Солнце Москвы», колесо обозрения** - **Рейтинг:** 5.0 (1422 отзыва) - **Часы работы:** пн–чт 11:00–22:00; пт 11:00–23:00; сб–вс 10:00–23:00 - **Особенности:** Отличная возможность увидеть город с высоты, совмещённая с колесом обозрения. ### 2. **Смотровая площадка Воробьёвых гор** - **Рейтинг:** 4.8 (243 отзыва) - **Часы работы:** круглосуточно - **Особенности:** Классическая смотровая площадка с панорамным видом на Москву-реку и центр города. ### 3. **Panorama360, смотровая площадка** - **Рейтинг:** 4.8 (2035 отзывов) - **Адрес:** Пресненская набережная, 12 - **Часы работы:** пн–пт 11:00–22:00; сб–вс 10:00–22:00 - **Особенности:** Расположена на 89-м этаже «Москва-Сити», предлагает панорамный вид на город. ### 4. **Останкинская телебашня, смотровая площадка** - **Рейтинг:** 5.0 (1196 отзывов) - **Адрес:** улица Академика Королёва, 15 к1 - **Часы работы:** ежедневно 09:00–22:00 - **Особенности:** Одна из самых высоких точек Москвы, открывающая потрясающий вид на столицу. ### 5. **«#Вышетольколюбовь», смотровая площадка** - **Рейтинг:** 4.8 (550 отзывов) - **Адрес:** 1-й Красногвардейский проезд, 21 ст2 - **Часы работы:** пн–пт 12:00–23:00; сб–вс 10:00–23:00 - **Особенности:** Современная площадка с видом на реку и городскую застройку. ### 6. **ЦДМ, смотровая площадка** - **Рейтинг:** 4.4 (24 отзыва) - **Адрес:** Театральный проезд, 5 - **Часы работы:** пн–чт 10:00–21:30; пт–сб 10:00–22:30; вс 10:00–21:30 - **Особенности:** Расположена на крыше Центрального детского магазина, с видом на Красную площадь. ### 7. **Смотровая площадка Храма Христа Спасителя** - **Рейтинг:** 4.9 (20 отзывов) - **Адрес:** улица Волхонка, 15 - **Часы работы:** пн 13:00–19:00; вт–пт 10:00–19:00; сб 10:00–16:30; вс 12:00–18:00 - **Особенности:** Панорамный вид на храм и прилегающие районы. ### 8. **Billion City, смотровая площадка** - **Рейтинг:** 4.8 (23 отзыва) - **Адрес:** Пресненская набережная, 6 ст2 - **Часы работы:** ежедневно 10:00–21:00 - **Особенности:** Современная площадка с видом на «Москва-Сити». ### 9. **Смотровая площадка Казанского вокзала** - **Рейтинг:** 3.8 (4 отзыва) - **Адрес:** Комсомольская площадь, 2 - **Часы работы:** ежедневно 10:00–21:00 - **Особенности:** Небольшая площадка с видом на вокзал и прилегающие улицы. ### 10. **Ленинский проспект, 32а ст1** - **Рейтинг:** 4.6 (69 отзывов) - **Особенности:** Локация с видом на город. Эти площадки предлагают разнообразные виды на Москву, от панорамных до уютных локаций. | E15: PASS | G15: 4 | H15: 3 | I15: 3 | J15: 5 | K15: 4 | L15: 5 | M15: 5 | N15: =IF($E15="","",IF($E15="FAIL","FAIL",ROUND(G15*15%+H15*15%+I15*25%+J15*10%+K15*20%+M15*5%+L15*10%,2))) -> 3.85
A16: 15 | B16: Посоветуй недорогие рестораны узбекской кухни в Ташкенте. | C16: На основе найденной информации, вот несколько недорогих ресторанов узбекской кухни в Ташкенте: ## Сеть «Beshqozon» (Бешқозон) — центры плова Это сеть бюджетных заведений, специализирующихся на узбекском плове и традиционных блюдах. Отличаются высокими рейтингами (4.9) и доступными ценами. - **Beshqozon Glinka** — ул. Глинки, 43 - **Beshqozon Ko'kcha** — ул. Шерози, 41/1 - **Beshqozon Sergeli** — массив Сергели-8, 3а - **Beshqozon Teleminora** — ул. Ифтихор, 1 Работают ежедневно с 09:00–10:00 до 23:00–03:00. ## Сеть «Kamolon Osh» (Камолон Ош) — центры плова Ещё одна популярная сеть с рейтингом 4.9: - **Kamolon Osh** — ул. Зульфияхоним, 10а - **Kamolon Osh** — микрорайон Бешагач, 6а Работают ежедневно с 10:30 до 24:00. ## Koʼkcha tansiq Taomlari - **Адрес:** ул. Гулобод, Маннон Уйгур, 26 - **Рейтинг:** 4.4 - **Цены:** от 1 000 до 100 000 сумов на человека - **Особенности:** по отзывам — «вкусная недорогая местная еда», быстрое обслуживание, приятная атмосфера ## Семейный ресторан «Shohona» - **Адрес:** проспект Мирзо Улугбека, 1 - **Цены:** от 50 000 до 100 000 сумов на человека - **Особенности:** разнообразное меню традиционных узбекских блюд, есть летняя терраса, парковка, обслуживание на вынос ## Другие варианты с высоким рейтингом - **Музей Плова** — ул. Катта Дархон, 55 (рейтинг 4.7) - **Caravan** — ул. Абдуллы Каххара, 22 (рейтинг 4.8) - **Bazar** — ул. Укчи, 3 (рейтинг 4.8, нео-ориентальная кухня) Цены в Ташкенте в целом доступные: в бюджетных заведениях (центры плова) обед может обойтись в 10 000–30 000 сумов, в ресторанах среднего уровня — 50 000–100 000 сумов на человека. | D16: Tool result (places_search): {"places":[{"ref":"plc_cabf94beeb","id":"70000001093567321","name":"Beshqozon Glinka, центр плова","address":"Ташкент, Глинки, 43","categories":["Кафе","Кофейни","Доставка еды"],"phones":[],"rating":4.9,"review_count":1552,"hours_text":"ежедневно 10:00–03:00","open_24h":false,"is_open_now":true,"accessibility":[],"distance_m":null},{"ref":"plc_efce0b4c55","id":"70000001054290971","name":"Beshqozon Ko'kcha, центр плова","address":"Ташкент, Шерози, 41/1","categories":["Кафе","Доставка еды"],"phones":[],"rating":4.9,"review_count":813,"hours_text":"ежедневно 10:00–03:00","open_24h":false,"is_open_now":true,"accessibility":[],"distance_m":null},{"ref":"plc_eec4a6bb11","id":"70000001064978231","name":"Kamolon Osh, центр плова","address":"Ташкент, улица Зульфияхоним, 10а","categories":["Кафе"],"phones":[],"rating":4.9,"review_count":150,"hours_text":"ежедневно 10:30–24:00","open_24h":false,"is_open_now":true,"accessibility":[],"distance_m":null},{"ref":"plc_4f0548f8fc","id":"70000001102452874","name":"Музей Плова, ресторан","address":"Ташкент, Катта Дархон, 55","categories":["Рестораны"],"phones":[],"rating":4.7,"review_count":210,"hours_text":"ежедневно 11:00–02:00","open_24h":false,"is_open_now":true,"accessibility":[],"distance_m":null},{"ref":"plc_b7c89ed9f2","id":"70000001063396297","name":"Sharshara, ресторан","address":"Ташкент, Массив Северный Алмазар, 10","categories":["Рестораны"],"phones":[],"rating":4.7,"review_count":114,"hours_text":"ежедневно 11:00–23:00","open_24h":false,"is_open_now":true,"accessibility":[],"distance_m":null},{"ref":"plc_5f32479c55","id":"70000001038034192","name":"Beshqozon Sergeli, центр плова","address":"Ташкент, Массив Сергели-8, 3а","categories":["Кафе","Доставка еды"],"phones":[],"rating":4.9,"review_count":170,"hours_text":"ежедневно 10:00–23:00","open_24h":false,"is_open_now":true,"accessibility":[],"distance_m":null},{"ref":"plc_f381203071","id":"70000001036727194","name":"Kamolon Osh, центр плова","address":"Ташкент, микрорайон Бешагач, 6а","categories":["Кафе"],"phones":[],"rating":4.9,"review_count":249,"hours_text":"ежедневно 10:30–24:00","open_24h":false,"is_open_now":true,"accessibility":[],"distance_m":null},{"ref":"plc_529466d91c","id":"70000001037837793","name":"Beshqozon Teleminora, центр плова","address":"Ташкент, Ифтихор, 1","categories":["Кафе","Доставка еды","Кофейни"],"phones":[],"rating":4.9,"review_count":3975,"hours_text":"ежедневно 09:00–23:00","open_24h":false,"is_open_now":true,"accessibility":[],"distance_m":null},{"ref":"plc_a0791a6e65","id":"70000001036447741","name":"Caravan, ресторан","address":"Ташкент, Абдуллы Каххара, 22","categories":["Доставка еды","Рестораны"],"phones":[],"rating":4.8,"review_count":360,"hours_text":"ежедневно 11:00–02:00","open_24h":false,"is_open_now":true,"accessibility":[],"distance_m":null},{"ref":"plc_3ee84a7639","id":"70000001109599927","name":"Bazar, нео-ориентальный ресторан","address":"Ташкент, Укчи, 3","categories":["Рестораны"],"phones":[],"rating":4.8,"review_count":56,"hours_text":"пн–чт 12:00–24:00; пт–сб 12:00–02:00; вс 12:00–24:00","open_24h":false,"is_open_now":true,"accessibility":[],"distance_m":null}],"area":{"ref":"plc_6e1d538ed3","name":"Tashkent","address":"Tashkent, Ўзбекистон"},"truncated":true,"anchor":null,"resolved":[],"returned_count":10} Tool result (web_search): {"query":"недорогие рестораны узбекской кухни Ташкент 2026","results":[{"ref":"src_3c57f54494","title":"Koʼkcha tansiq Taomlari, Tashkent - Restaurant menu, prices and reviews","domain":"restaurantguru.com","snippet":"Koʼkcha tansiq Taomlari, Tashkent - Restaurant menu, prices and reviews\n...\n# Koʼkcha tansiq Taomlari\n...\n#1428 of 5174 restaurants in Tashkent\n...\ncha tansiq Taom\n...\nAccording to the visitors' revi…","published_date":"2026-05-21"},{"_omitted_items":3},{"ref":"src_7bed008fc7","title":"Sim Sim, Tashkent - Restaurant menu, prices and reviews","domain":"restaurantguru.com","snippet":"Sim Sim, Tashkent - Restaurant menu, prices and reviews\n...\n#11 of 5174 restaurants in Tashkent\n...\nGreek and Russian cuisines are must-taste ones at this restaurant. The recipe for success of Sim Si…","published_date":"2026-06-11"}]} Tool result (web_search): {"query":"budget affordable Uzbek restaurants Tashkent cheap food 2026","results":[{"ref":"src_3c57f54494","title":"Koʼkcha tansiq Taomlari, Tashkent - Restaurant menu, prices and reviews","domain":"restaurantguru.com","snippet":"Koʼkcha tansiq Taomlari, Tashkent - Restaurant menu, prices and reviews\n...\nAccording to the visitors' reviews, Uzbek dishes here are quite nice and the menu is well-organized. The truth is that you will really like tasty soup. Most guests consider the staff cute. This restaurant is notable for its fast service. You will appreciate fair prices. Koʼkcha tansiq Taomlari is known for its peaceful atmosphere. Google users granted the rating of 4.4 to this place.\n...\nStrongly recommended. Great tasting inexpensive local food. No English, but Google Translate works just fine Meal type: Lunch Price per person: UZS 1–50,000\n...\nВкусно и сытно. Food: 5 Service: 3 Atmosphere: 2 Meal type: Dinner Price per person: UZS 50–100k\n...\nMiddle Eastern, Uzbek\n...\n$$$$ Price range per person UZS 1 - UZS 100,000\n...\nGulobod str, Mannon Uygur str 26\n...\nTashkent, Tashkent Province, Uzbekistan\n...\nGulobod str, Mannon Uygur str 26, Tashkent, Tashkent Province, Uzbekistan\n...\nUpdated on: May 21, 2026","published_date":"2026-05-21"},{"_omitted_items":3},{"ref":"src_7bffb149df","title":"Family restaurant \"Shohona\", Tashkent - Restaurant menu, prices and reviews","domain":"restaurantguru.com","snippet":"Family restaurant \"Shohona\", Tashkent - Restaurant menu, prices and reviews\n...\nFamily Restaurant \"Shohona\" offers a taste of Uzbekistan on Mirzo Ulugbek Avenue in Tashkent. Known for its diverse menu featuring traditional Uzbek dishes, the restaurant provides both dine-in and outdoor seating options. Whether you're stopping by for breakfast, brunch, lunch, or dinner, you'll find a variety of offerings, including alcohol and late-night snacks. There is also a catering service available, ensuring convenience for larger gatherings or events. Visitors have mixed opinions about \"Shohona,\" praising the food's flavor while indicating variability in service quality. Some mention a cozy atmosphere conducive to family dining, complete with high chairs and reservations for larger groups. Accessibility options include wheelchair-accessible seating, and there is free parking available in both street and lot locations. As payment options, debit cards and NFC mobile payments are accepted, though it is unclear whether credit cards are. Although service might sometimes miss promptness, guest experiences highlight consistent deliciousness in select dishes. The restaurant lacks recent updates from ownership regarding specific perks or changes. If you're visiting with children, the eatery is prepared to accommodate little ones, even offering space for birthday celebrations. It's best to visit with tempered expectations regarding service, while anticipating flavorsome cuisine that meets a variety of seating preferences.\n...\n$$$$ Price range per person UZS 50,000 - UZS 100,000\n...\nMirzo Ulugbek Avenue 1\n...\nTashkent, Tashkent Province, Uzbekistan\n...\nMirzo Ulugbek Avenue 1, Tashkent, Tashkent Province, Uzbekistan\n...\nOutdoor seating Takeaway Сredit cards accepted Parking Booking Delivery Wi-Fi\n...\n| --- | --- |\n...\n-11\n...\nfood delivery\n...\nUpdated on: May 02, 2026","published_date":"2026-05-02"}]} Final answer: На основе найденной информации, вот несколько недорогих ресторанов узбекской кухни в Ташкенте: ## Сеть «Beshqozon» (Бешқозон) — центры плова Это сеть бюджетных заведений, специализирующихся на узбекском плове и традиционных блюдах. Отличаются высокими рейтингами (4.9) и доступными ценами. - **Beshqozon Glinka** — ул. Глинки, 43 - **Beshqozon Ko'kcha** — ул. Шерози, 41/1 - **Beshqozon Sergeli** — массив Сергели-8, 3а - **Beshqozon Teleminora** — ул. Ифтихор, 1 Работают ежедневно с 09:00–10:00 до 23:00–03:00. ## Сеть «Kamolon Osh» (Камолон Ош) — центры плова Ещё одна популярная сеть с рейтингом 4.9: - **Kamolon Osh** — ул. Зульфияхоним, 10а - **Kamolon Osh** — микрорайон Бешагач, 6а Работают ежедневно с 10:30 до 24:00. ## Koʼkcha tansiq Taomlari - **Адрес:** ул. Гулобод, Маннон Уйгур, 26 - **Рейтинг:** 4.4 - **Цены:** от 1 000 до 100 000 сумов на человека - **Особенности:** по отзывам — «вкусная недорогая местная еда», быстрое обслуживание, приятная атмосфера ## Семейный ресторан «Shohona» - **Адрес:** проспект Мирзо Улугбека, 1 - **Цены:** от 50 000 до 100 000 сумов на человека - **Особенности:** разнообразное меню традиционных узбекских блюд, есть летняя терраса, парковка, обслуживание на вынос ## Другие варианты с высоким рейтингом - **Музей Плова** — ул. Катта Дархон, 55 (рейтинг 4.7) - **Caravan** — ул. Абдуллы Каххара, 22 (рейтинг 4.8) - **Bazar** — ул. Укчи, 3 (рейтинг 4.8, нео-ориентальная кухня) Цены в Ташкенте в целом доступные: в бюджетных заведениях (центры плова) обед может обойтись в 10 000–30 000 сумов, в ресторанах среднего уровня — 50 000–100 000 сумов на человека. | E16: PASS | G16: 4 | H16: 3 | I16: 2 | J16: 5 | K16: 3 | L16: 4 | M16: 4 | N16: =IF($E16="","",IF($E16="FAIL","FAIL",ROUND(G16*15%+H16*15%+I16*25%+J16*10%+K16*20%+M16*5%+L16*10%,2))) -> 3.25
A17: 16 | B17: Top good cafes in Moscow | C17: Based on my search, here are some of the top-rated cafes in Moscow: ## **Cafes with verified locations:** ### 1. **Scramble Cafe** - **Address:** Улица Спиридоновка, 24/1, Москва, 123001 - **Hours:** 08:00–23:00 daily - **Currently open:** Yes - **Notes:** Part of the Friends Forever group, known for excellent coffee, all-day breakfasts, waffles (including with red berries), and creative drinks like the "unicorn" coffee with rainbow colors. Reservations recommended, especially on weekends. ### 2. **SOS.CAFE** - **Address:** Мясницкая улица, 11, Москва, 101000 - **Phone:** +7 495 150-43-34 - **Notes:** Described as having pure American style. ## **Other highly recommended cafes (from web sources):** ### 3. **Upside Down Cake Cafe** - **Notes:** Known for the best cupcakes, cakes, and tarts (try the Velvet cupcake, lemon, orange, and fruit cakes, plus carrot cake). Offers breakfasts and all-day brunch, main dishes (meat, fish, burgers), and cocktails. Multiple branches in Moscow. ### 4. **Pushkin Patisserie** - **Notes:** Described as the most classic and renowned patisserie in Moscow. ### 5. **David Bowie Cafe** - **Notes:** Featured in top Moscow cafe lists. ### 6. **Conversation Cafe** - **Notes:** Also featured in top Moscow cafe recommendations. --- *Sources: Nextination (2025), Discover Moscow (2025)* Would you like more details about any of these cafes, or help with directions to a specific location? | D17: Tool result (places_search): {"places":[],"area":{"ref":"plc_c05673c3e9","name":"Москва","address":"Москва, Центральный федеральный округ, Россия"},"truncated":false,"anchor":null,"resolved":[],"returned_count":0} Tool result (places_search): {"places":[{"ref":"plc_09cca40ced","id":"70000001116561295","name":"Cafe","address":"Москва, Огородный проезд, 16/1 ст1","categories":["Кофейни"],"phones":[],"rating":null,"review_count":null,"hours_text":"пн–пт 08:00–21:00; сб–вс 10:00–18:00","open_24h":false,"is_open_now":true,"accessibility":[],"distance_m":null}],"area":{"ref":"plc_c05673c3e9","name":"Москва","address":"Москва, Центральный федеральный округ, Россия"},"truncated":true,"anchor":null,"resolved":[],"returned_count":1} Tool result (web_search): {"query":"best cafes in Moscow 2026","results":[{"ref":"src_1740e67dc3","title":"The 10 best Cafes in Moscow that you can't miss - Nextination","domain":"nextination.es","snippet":"Previously I have been writing about the different locations to see in Moscow, however today I bring you a different post and is to share with you the top ten cafes in Moscow, in my opinion. Top about what? I have to say that Moscow has a very rich culture of coffee in general and that it is difficult to find a place that does not have good coffee. Still, here I have compiled the 10 coffee places that I like most due either where they are located, the taste of coffee and/or the decoration of the site.\n...\nOne of my favorites\n...\nfor the coffee is Scramble.\n...\nbelongs to the Friends Forever group that have several other\n...\nall amazing.\n...\nbest brunches. The best thing\n...\nthey have breakfasts all day.\n...\nwaffles. One of my favorite dishes are the\n...\nwith waffles or waffles with red berries and hot\n...\n, you can not go without trying\n...\neven they have a «unicorn» coffee with\n...\ncolors of the rainbow.\n...\nat 8 in the morning included on\n...\n. You must\n...\nin advance, especially if you go on weekends.\n...\n# Upside Down Cake Cafe\n...\nmy favorite definitely and they also have breakfasts and all-day brunch.\n...\nbest cupcakes, cakes and tarts\n...\nYou have to try the\n...\nVelvet cupcake and the lemon, orange and fruit cakes, in addition to\n...\ncarrot cake.\n...\nyou will also find main dishes\n...\nmeat, fish\n...\nburgers or others\n...\nand cocktails.\n...\ns menu. I love\n...\nhave several branches in\n...\nalso perfect if you are going to spend the day at the Botanical Garden, since\n...\nthat I like\n...\nrest after a day of shopping.\n...\ncan not stop\n...\n# Pushkin Patisserie\n...\nmost classic and most renowned\n...\n# David Bowie Cafe\n...\n# Conversation Cafe\n...\n# SOS CAFE\n...\ncan not miss because it\n...\npurest American style\n...\nfind here several\n...\nfor one of","published_date":"2025-07-08"},{"_omitted_items":8},{"ref":"src_30632ebbcc","title":"Moscow's Top Coffee Shops for a Long Stroll The ... - Instagram","domain":"www.instagram.com","snippet":"and local roasters who master the art of roasting and extraction with remarkable precision.Лучшие кофейни Москвы для долгой прогулки Сайт «Дискавер Москва» опубликовал список кофеен, которые он называет лучшими в российской столице — мест, где можно согреться во время прогулки или восстановить силы в любое время года.В начале публикации «Дискавер Москва» отмечает, что Москва по праву заслужила звание «кофейной столицы». В каждом районе города можно найти особенную атмосферу, напитки из разных стран мира и местные обжарки, где мастера прекрасно знают своё дело.أفضل مقاهي موسكو لجولة طويلة في المدينة نشر موقع «اكتشف موسكو» قائمة تضم أفضل المقاهي في العاصمة الروسية لجولة طويلة في المدينة، حيث يمكن للزوار الاستمتاع بأجواء دافئة واستعادة النشاط في أي وقت من العام.يؤكد الموقع في مقدمته أن موسكو تستحق عن جدارة لقب «عاصمة القهوة»، فحيثما ذهبت في أحيائها ستجد مشروبات قهوة مختصة من مختلف أنحاء العالم، ومحامص محلية تتقن فن التحميص وتفاصيل الاستخلاص بإتقان.Read the full story at","published_date":"2025-10-12"}]} Tool result (places_search): {"places":[],"area":null,"truncated":false,"anchor":null,"resolved":[{"client_id":"scramble","input_name":"Scramble","status":"resolved","place":{"ref":"plc_f11d875153","id":"zxHY-L5EOEB0qXgx2poDkA","name":"Scramble Cafe","address":"Улица Спиридоновка, 24/1, Москва, 123001","categories":["restaurant","american"],"phones":[],"rating":null,"review_count":null,"hours_text":"Next 7 days: Aug 10–16 08:00–23:00","open_24h":false,"is_open_now":true,"accessibility":[],"distance_m":null},"options":[],"error":null},{"client_id":"upside_down_cake_cafe","input_name":"Upside Down Cake Cafe","status":"not_found","place":null,"options":[],"error":null},{"client_id":"pushkin_patisserie","input_name":"Pushkin Patisserie","status":"not_found","place":null,"options":[],"error":null},{"client_id":"david_bowie_cafe","input_name":"David Bowie Cafe","status":"not_found","place":null,"options":[],"error":null},{"client_id":"conversation_cafe","input_name":"Conversation Cafe","status":"not_found","place":null,"options":[],"error":null},{"client_id":"sos_cafe","input_name":"SOS CAFE","status":"resolved","place":{"ref":"plc_c3dc30214d","id":"NAjcAfhDYo1NO6cfNa4WGw","name":"SOS.CAFE","address":"Мясницкая улица, 11, Москва, 101000","categories":["restaurant","fast food"],"phones":["+7 495 150-43-34"],"rating":null,"review_count":null,"hours_text":null,"open_24h":null,"is_open_now":null,"accessibility":[],"distance_m":null},"options":[],"error":null}],"returned_count":2,"warnings":["2GIS place search returned no matches; retrying with TomTom."]} Final answer: Based on my search, here are some of the top-rated cafes in Moscow: ## **Cafes with verified locations:** ### 1. **Scramble Cafe** - **Address:** Улица Спиридоновка, 24/1, Москва, 123001 - **Hours:** 08:00–23:00 daily - **Currently open:** Yes - **Notes:** Part of the Friends Forever group, known for excellent coffee, all-day breakfasts, waffles (including with red berries), and creative drinks like the "unicorn" coffee with rainbow colors. Reservations recommended, especially on weekends. ### 2. **SOS.CAFE** - **Address:** Мясницкая улица, 11, Москва, 101000 - **Phone:** +7 495 150-43-34 - **Notes:** Described as having pure American style. ## **Other highly recommended cafes (from web sources):** ### 3. **Upside Down Cake Cafe** - **Notes:** Known for the best cupcakes, cakes, and tarts (try the Velvet cupcake, lemon, orange, and fruit cakes, plus carrot cake). Offers breakfasts and all-day brunch, main dishes (meat, fish, burgers), and cocktails. Multiple branches in Moscow. ### 4. **Pushkin Patisserie** - **Notes:** Described as the most classic and renowned patisserie in Moscow. ### 5. **David Bowie Cafe** - **Notes:** Featured in top Moscow cafe lists. ### 6. **Conversation Cafe** - **Notes:** Also featured in top Moscow cafe recommendations. --- *Sources: Nextination (2025), Discover Moscow (2025)* Would you like more details about any of these cafes, or help with directions to a specific location? | E17: PASS | G17: 4 | H17: 2 | I17: 2 | J17: 4 | K17: 4 | L17: 4 | M17: 3 | N17: =IF($E17="","",IF($E17="FAIL","FAIL",ROUND(G17*15%+H17*15%+I17*25%+J17*10%+K17*20%+M17*5%+L17*10%,2))) -> 3.15
A18: 17 | B18: Find me good schools in Minsk for students, who are talented in math and physics | E18: FAIL | F18: Wrong Geo | N18: =IF($E18="","",IF($E18="FAIL","FAIL",ROUND(G18*15%+H18*15%+I18*25%+J18*10%+K18*20%+M18*5%+L18*10%,2))) -> FAIL
A19: 18 | B19: Where can I buy yen in Bishkek? | E19: FAIL | F19: Empty | N19: =IF($E19="","",IF($E19="FAIL","FAIL",ROUND(G19*15%+H19*15%+I19*25%+J19*10%+K19*20%+M19*5%+L19*10%,2))) -> FAIL
A20: 19 | B20: Can you tell me which cities in Tajikistan have the best bars? | C20: Не удалось сформировать ответ по полученным данным. | D20: Tool result (places_search): {"places":[{"ref":"plc_4ed04ea690","id":"70000001102597680","name":"Bars, нуқтаи таъмири чархҳо ва аккумуляторҳои мошин","address":"Душанбе, проспект Джаббора Расулова, 29/1","categories":["Шины и диски","Автомобильные аккумуляторы"],"phones":[],"rating":null,"review_count":null,"hours_text":"пн–сб 08:00–12:00, 13:00–19:00","open_24h":null,"is_open_now":false,"accessibility":[],"distance_m":null},{"ref":"plc_8dad8addfc","id":"70000001102765633","name":"Bars, мағозаи қисмҳои эхтиётии автомобилӣ","address":"Душанбе","categories":["Автомобильные аккумуляторы"],"phones":[],"rating":null,"review_count":null,"hours_text":"ежедневно 09:00–18:00","open_24h":false,"is_open_now":false,"accessibility":[],"distance_m":null},{"ref":"plc_14f5ebc748","id":"70000001103644017","name":"Bars, мағозаи аккамуляторҳои автомобил","address":"Душанбе, махалля Кушониён, 1","categories":["Автомобильные аккумуляторы"],"phones":[],"rating":null,"review_count":null,"hours_text":"ежедневно 08:00–17:00","open_24h":false,"is_open_now":false,"accessibility":[],"distance_m":null},{"ref":"plc_d3b918c0c1","id":"70000001110068391","name":"Bars, акамуляторҳо ва балонҳо","address":"Душанбе","categories":["Автомобильные аккумуляторы","Шины и диски"],"phones":[],"rating":null,"review_count":null,"hours_text":"ежедневно 08:00–19:00","open_24h":false,"is_open_now":false,"accessibility":[],"distance_m":null},{"ref":"plc_00c8615743","id":"70000001100803897","name":"Bars consuling, ташкили лоиҳаҳои авесто гуруҳ","address":"Душанбе, улица Пулоди, 41","categories":["Бизнес-тренинги"],"phones":[],"rating":null,"review_count":null,"hours_text":"пн–пт 09:00–18:00","open_24h":null,"is_open_now":false,"accessibility":[],"distance_m":null}],"area":{"ref":"plc_a2dda20249","name":"Душанбе","address":"Душанбе, Ноҳияҳои тобеи ҷумҳурӣ, Тоҷикистон"},"truncated":false,"anchor":null,"resolved":[],"returned_count":5} Tool result (places_search): {"places":[{"ref":"plc_4ed04ea690","id":"70000001102597680","name":"Bars, нуқтаи таъмири чархҳо ва аккумуляторҳои мошин","address":"Душанбе, проспект Джаббора Расулова, 29/1","categories":["Шины и диски","Автомобильные аккумуляторы"],"phones":[],"rating":null,"review_count":null,"hours_text":"пн–сб 08:00–12:00, 13:00–19:00","open_24h":null,"is_open_now":false,"accessibility":[],"distance_m":null},{"ref":"plc_8dad8addfc","id":"70000001102765633","name":"Bars, мағозаи қисмҳои эхтиётии автомобилӣ","address":"Душанбе","categories":["Автомобильные аккумуляторы"],"phones":[],"rating":null,"review_count":null,"hours_text":"ежедневно 09:00–18:00","open_24h":false,"is_open_now":false,"accessibility":[],"distance_m":null},{"ref":"plc_14f5ebc748","id":"70000001103644017","name":"Bars, мағозаи аккамуляторҳои автомобил","address":"Душанбе, махалля Кушониён, 1","categories":["Автомобильные аккумуляторы"],"phones":[],"rating":null,"review_count":null,"hours_text":"ежедневно 08:00–17:00","open_24h":false,"is_open_now":false,"accessibility":[],"distance_m":null},{"ref":"plc_d3b918c0c1","id":"70000001110068391","name":"Bars, акамуляторҳо ва балонҳо","address":"Душанбе","categories":["Автомобильные аккумуляторы","Шины и диски"],"phones":[],"rating":null,"review_count":null,"hours_text":"ежедневно 08:00–19:00","open_24h":false,"is_open_now":false,"accessibility":[],"distance_m":null},{"ref":"plc_00c8615743","id":"70000001100803897","name":"Bars consuling, ташкили лоиҳаҳои авесто гуруҳ","address":"Душанбе, улица Пулоди, 41","categories":["Бизнес-тренинги"],"phones":[],"rating":null,"review_count":null,"hours_text":"пн–пт 09:00–18:00","open_24h":null,"is_open_now":false,"accessibility":[],"distance_m":null},{"ref":"plc_77df2420a9","id":"70030077110257018","name":"Барс","address":"Душанбе, Барс","categories":["Памятники и скульптуры"],"phones":[],"rating":null,"review_count":null,"hours_text":null,"open_24h":null,"is_open_now":null,"accessibility":[],"distance_m":null}],"area":{"ref":"plc_a2dda20249","name":"Душанбе","address":"Душанбе, Ноҳияҳои тобеи ҷумҳурӣ, Тоҷикистон"},"truncated":false,"anchor":null,"resolved":[],"returned_count":6} Tool result (places_search): {"places":[{"ref":"plc_798589642f","id":"70000001100536213","name":"Форель, ресторан","address":"Душанбе, проспект Хафиза Шерози, 3","categories":["Бары","Рестораны","Кафе"],"phones":[],"rating":4.5,"review_count":5,"hours_text":"ежедневно 09:00–23:00","open_24h":false,"is_open_now":false,"accessibility":[],"distance_m":null},{"ref":"plc_78dbe66745","id":"70000001100627757","name":"28 monkeys, гастробар","address":"Душанбе, проспект Рудаки, 66","categories":["Бары","Рестораны"],"phones":[],"rating":5.0,"review_count":7,"hours_text":"пн 12:00–01:00; вт–вс 09:00–01:00","open_24h":false,"is_open_now":true,"accessibility":[],"distance_m":null},{"ref":"plc_7a6da24438","id":"70000001100690154","name":"Gusht, тарабхона","address":"Душанбе, улица Мирзо Турсунзаде, 45","categories":["Бары","Рестораны","Банкетные залы"],"phones":[],"rating":4.7,"review_count":3,"hours_text":"ежедневно 11:00–24:00","open_24h":false,"is_open_now":true,"accessibility":[],"distance_m":null},{"ref":"plc_dfc67b56f6","id":"70000001116065415","name":"The Bar, бар","address":"Душанбе, проспект Исмоила Сомони, 26/1","categories":["Бары"],"phones":[],"rating":null,"review_count":null,"hours_text":null,"open_24h":null,"is_open_now":null,"accessibility":[],"distance_m":null},{"ref":"plc_2936f5bdf3","id":"70000001101224025","name":"Caf, қаҳвахона","address":"Душанбе, улица Шарифджона Хусейнзаде, 28","categories":["Бары","Рестораны"],"phones":[],"rating":5.0,"review_count":1,"hours_text":"ежедневно 07:00–24:00","open_24h":false,"is_open_now":true,"accessibility":[],"distance_m":null},{"ref":"plc_63fb0f8375","id":"70000001101569619","name":"Bundes bar, кафе-бар","address":"Душанбе, улица Бухоро, 23/25","categories":["Бары","Рестораны"],"phones":[],"rating":5.0,"review_count":3,"hours_text":"ежедневно 11:00–24:00","open_24h":false,"is_open_now":true,"accessibility":[],"distance_m":null},{"ref":"plc_9d72863ff1","id":"70000001101582246","name":"Public pub 2. 0, лаундж-кафе","address":"Душанбе, улица Бухоро, 32","categories":["Бары"],"phones":[],"rating":4.6,"review_count":3,"hours_text":"ежедневно 11:00–23:00","open_24h":false,"is_open_now":false,"accessibility":[],"distance_m":null},{"ref":"plc_65de526413","id":"70000001101774376","name":"Etno, рестобар","address":"Душанбе, улица Шота Руставели, 1","categories":["Бары","Кафе","Караоке-залы","Банкетные залы"],"phones":[],"rating":5.0,"review_count":1,"hours_text":"ежедневно 10:00–23:00","open_24h":false,"is_open_now":false,"accessibility":[],"distance_m":null},{"ref":"plc_97650f5edd","id":"70000001100858101","name":"Community Dushanbe, гастробар","address":"Душанбе, улица Дружбы народов, 47/1","categories":["Бары","Рестораны"],"phones":[],"rating":4.4,"review_count":3,"hours_text":"пн–чт 11:00–24:00; пт–сб 11:00–03:00; вс 11:00–24:00","open_24h":false,"is_open_now":true,"accessibility":[],"distance_m":null},{"ref":"plc_4de551d70b","id":"70000001105659751","name":"Сим-Сим, бар","address":"Душанбе","categories":["Бары"],"phones":[],"rating":null,"review_count":null,"hours_text":"ежедневно 10:00–23:00","open_24h":false,"is_open_now":false,"accessibility":[],"distance_m":null}],"area":{"ref":"plc_a2dda20249","name":"Душанбе","address":"Душанбе, Ноҳияҳои тобеи ҷумҳурӣ, Тоҷикистон"},"truncated":true,"anchor":null,"resolved":[],"returned_count":10} Final answer: Не удалось сформировать ответ по полученным данным. | E20: FAIL | F20: Empty | N20: =IF($E20="","",IF($E20="FAIL","FAIL",ROUND(G20*15%+H20*15%+I20*25%+J20*10%+K20*20%+M20*5%+L20*10%,2))) -> FAIL
A21: 20 | B21: What are the shopping centers in Brussels? | C21: В Брюсселе найден один торговый центр: **Woluwe Shopping Center** - Адрес: Woluwedal 70, 1200 Brussel - Телефон: +32 2 771 20 45 Обратите внимание: поиск выполнен с использованием данных TomTom, так как 2GIS не покрывает Брюссель. Возможно, в городе есть и другие торговые центры, которые не попали в результаты поиска. | D21: Tool result (places_search): {"places":[{"ref":"plc_b05656cd75","id":"DTsSL4OaQNs1DKvmE0JvBA","name":"Woluwe Shopping Center","address":"Woluwedal 70, 1200 Brussel","categories":["shopping center"],"phones":["+32 2 771 20 45"],"rating":null,"review_count":null,"hours_text":null,"open_24h":null,"is_open_now":null,"accessibility":[],"distance_m":null}],"area":{"ref":"plc_692e23a050","name":"Brussel","address":"Brussel, Brussel Hoofdstad, Brussel Hoofdstedelijk Gewest, België"},"truncated":true,"anchor":null,"resolved":[],"returned_count":1,"warnings":["2GIS does not cover the requested locality; using TomTom."]} Final answer: В Брюсселе найден один торговый центр: **Woluwe Shopping Center** - Адрес: Woluwedal 70, 1200 Brussel - Телефон: +32 2 771 20 45 Обратите внимание: поиск выполнен с использованием данных TomTom, так как 2GIS не покрывает Брюссель. Возможно, в городе есть и другие торговые центры, которые не попали в результаты поиска. | E21: FAIL | F21: Language missmatch | N21: =IF($E21="","",IF($E21="FAIL","FAIL",ROUND(G21*15%+H21*15%+I21*25%+J21*10%+K21*20%+M21*5%+L21*10%,2))) -> FAIL
A22: 21 | B22: Посоветуй необычные достопримечательности в Лихтенштейне | N22: =IF($E22="","",IF($E22="FAIL","FAIL",ROUND(G22*15%+H22*15%+I22*25%+J22*10%+K22*20%+M22*5%+L22*10%,2)))
A23: 22 | B23: Какие в Люксмебурге есть шоколадные фабрики? | C23: В Люксембурге есть несколько известных мастерских и производителей шоколада, которые занимаются производством продукции на месте (от зерна до плитки). Вот основные из них, найденные по запросу: 1. **Maison Oberweis** Это единственный производитель шоколада в Люксембурге, который использует концепцию «Bean to Bar» (от зерна до плитки). Они самостоятельно обжаривают и перерабатывают какао-бобы в своей производственной мастерской в Люксембурге, создавая шоколад ручной работы [1]. 2. **Chocolaterie Luxembourg** Это ремесленная шоколадная мастерская, которая также занимается производством. Их лаборатория и мастерская расположены в городе Дюделанж (Dudelange). Они создают шоколадные изделия ручной работы, используя традиционные методы [2]. *Примечание: Точные адреса производственных цехов этих компаний не были подтверждены картографическими сервисами, однако они работают в Люксембурге и Дюделанже соответственно.* [1] Chocolat Bean to Bar Oberweis [2] Chocolaterie Luxembourg - Artisan Chocolatier | D23: Tool result (places_search): {"places":[],"area":{"ref":"plc_6a06ccf073","name":"Luxembourg","address":"Luxembourg"},"truncated":false,"anchor":null,"resolved":[],"returned_count":0,"warnings":["2GIS does not cover the requested locality; using TomTom."]} Tool result (places_search): {"places":[{"ref":"plc_6f59003f73","id":"IJ7eCEqQ3YVZ5vZlO5aaDw","name":"Chocolate House","address":"20 Rue du Marché-aux-Herbes, L-1728 Luxembourg","categories":["western continental","restaurant"],"phones":[],"rating":null,"review_count":null,"hours_text":null,"open_24h":null,"is_open_now":null,"accessibility":[],"distance_m":null},{"ref":"plc_cfd05f5b2a","id":"kggBFuDjZjscyF4nWNDEIA","name":"Chocolate Company","address":"20 Rue du Marché-aux-Herbes, L-1728 Luxembourg","categories":["bar","nightlife"],"phones":[],"rating":null,"review_count":null,"hours_text":null,"open_24h":null,"is_open_now":null,"accessibility":[],"distance_m":null}],"area":{"ref":"plc_6a06ccf073","name":"Luxembourg","address":"Luxembourg"},"truncated":false,"anchor":null,"resolved":[],"returned_count":2,"warnings":["2GIS does not cover the requested locality; using TomTom.","TomTom supplied neither opening hours nor a phone number for 2 results; their current operation could not be verified from this response."]} Tool result (places_search): {"places":[],"area":{"ref":"plc_6a06ccf073","name":"Luxembourg","address":"Luxembourg"},"truncated":false,"anchor":null,"resolved":[],"returned_count":0,"warnings":["2GIS does not cover the requested locality; using TomTom."]} Tool result (web_search): {"query":"chocolate factory Luxembourg production","results":[{"ref":"src_cf7099062d","title":"Chocolat Bean to Bar Oberweis","domain":"www.oberweis.lu","snippet":"## Oberweis chocolate: discover the only chocolate made 100% in Luxembourg\n...\nMaison Oberweis is currently the only chocolatier in Luxembourg to craft its own chocolate using the “Bean to Bar” concept.\n...\nIn the heart of the plantations in Colombia, Tom Oberweis reveals, through an exceptional documentary, the secrets of cocoa transformation in his workshop in Luxembourg.\n...\nIn 2017, Tom and Jeff Oberweis traveled to South America to visit cocoa plantations. There, they discovered the extraordinary craftsmanship of small local producers, often passed down from generation to generation. This experience marked the beginning of a passionate journey at the heart of the “Bean to Bar” chocolate-making process. Bean-to-bar is not just a method of working; it is an artisanal commitment, transforming cocoa from raw beans into a finished chocolate bar in our production workshop.\n...\nMaison Oberweis is the only chocolatier in Luxembourg to process cocoa directly from the bean. More than just a technique, ‘Bean to Bar’ is a true philosophy: putting craftsmanship and the quality of raw materials back at the heart of chocolate making.\n...\nOberweis chocolate, crafted according to the Bean to Bar concept, is produced through a long process that requires outstanding human expertise and technical knowledge.\n...\nplantations dedicated to careful\n...\n- Roasting: beans are gently roasted to unlock\n...\n- Cracking:\n...\nshells are removed, leaving\n...\ncocoa nibs.\n...\n- Grinding and conching: nib\n...\nare ground into a silky cocoa mass, then con\n...\nto develop smoothness and deepen the\n...\n- Tempering and molding: the chocolate is carefully crystallized to achieve its shine, snap\n...\nAs a chocolate maker and roaster, we go beyond market prices to source cocoa beans, supporting small local producers and ensuring a truly exceptional tasting experience, elevated by our artisanal craftsmanship and love for innovation.","published_date":null},{"_omitted_items":3},{"ref":"src_9f58719fa5","title":"Chocolaterie Luxembourg - Artisan Chocolatier","domain":"www.chocolaterie-rg.lu","snippet":"Chocolaterie Luxembourg - Artisan Chocolatier\n...\n## L'Art du Chocolat Fait Main au Luxembourg\n...\nBienvenue dans notre univers cacao où nous sublimons des ingrédients de qualité pour créer de véritables œuvres gourmandes, vous invitant à un voyage gustatif exquis.\n...\nTransformation artisanale dans notre atelier luxembourgeois, où chaque geste respecte la noblesse de la fève.\n...\n### Chocolatiers Engagés\n...\nDans notre laboratoire à Dudelange, nous perpétuons l'art chocolatier avec des méthodes traditionnelles et des ingrédients d'exception. Chaque création est le fruit d'un savoir-faire transmis de génération en génération, dans le respect des producteurs et de l'environnement.\n...\n### L'Univers Chocolaté de Dudelange\n...\nNotre boutique de Dudelange vous invite à vivre une aventure chocolatée\n...\nartisanaux présentés\n...\nVous pouvez également retrouver nos chocolats à la Luxembourg House au 2 rue de l'Eau, Luxembourg-Ville, à côté du Palais Grand-Ducal","published_date":null}]} Tool result (places_search): {"places":[],"area":null,"truncated":false,"anchor":null,"resolved":[{"client_id":"oberweis","input_name":"Maison Oberweis","status":"not_found","place":null,"options":[],"error":null},{"client_id":"chocolaterie_luxembourg","input_name":"Chocolaterie Luxembourg","status":"not_found","place":null,"options":[],"error":null}],"returned_count":0,"warnings":["2GIS does not cover the requested locality; using TomTom."]} Final answer: В Люксембурге есть несколько известных мастерских и производителей шоколада, которые занимаются производством продукции на месте (от зерна до плитки). Вот основные из них, найденные по запросу: 1. **Maison Oberweis** Это единственный производитель шоколада в Люксембурге, который использует концепцию «Bean to Bar» (от зерна до плитки). Они самостоятельно обжаривают и перерабатывают какао-бобы в своей производственной мастерской в Люксембурге, создавая шоколад ручной работы [1]. 2. **Chocolaterie Luxembourg** Это ремесленная шоколадная мастерская, которая также занимается производством. Их лаборатория и мастерская расположены в городе Дюделанж (Dudelange). Они создают шоколадные изделия ручной работы, используя традиционные методы [2]. *Примечание: Точные адреса производственных цехов этих компаний не были подтверждены картографическими сервисами, однако они работают в Люксембурге и Дюделанже соответственно.* [1] Chocolat Bean to Bar Oberweis [2] Chocolaterie Luxembourg - Artisan Chocolatier | E23: PASS | F23: - | G23: 5 | H23: 4 | I23: 3 | J23: 4 | K23: 5 | L23: 5 | M23: 4 | N23: =IF($E23="","",IF($E23="FAIL","FAIL",ROUND(G23*15%+H23*15%+I23*25%+J23*10%+K23*20%+M23*5%+L23*10%,2))) -> 4.2
